Workbook

Sheet 00_Mat
A1: MATERIALES
A3: CODIGO | B3: MATERIALES CORRALON | C3: UNIDAD | D3: PRECIO CON IVA | E3: PRECIO SIN IVA | F3: DESCUENTO | G3: PRECIO CON DESCUENTO | I3: REFERENCIA | J3: FECHA
A4: ARG | B4: Arena a granel (1m3) | C4: m3 | D4: 29403 | E4: =D4/1.21 -> 24300 | I4: Su Corralon | J4: 45406
A5: AR | B5: Bolson de Arena (1m3) | C5: m3 | E5: 31040 | I5: Su Corralon | J5: 45824
A6: PIEG | B6: Piedra a granel (1m3) | C6: m3 | D6: 58995 | E6: =D6/1.21 -> 48756.198 | I6: Su Corralon | J6: 45406
A7: PIEP | B7: Bolson de Piedra partida (1m3) | C7: m3 | E7: 74566 | I7: Su Corralon | J7: 45824
A8: PIE | B8: Bolson de Piedra (1m3) | C8: m3 | D8: 60000 | E8: =D8/1.21 -> 49586.777 | I8: Su Corralon | J8: 45777
A9: CEM | B9: Bolsa Cemento "Loma Negra" 25 k (u) | C9: u | E9: 5050 | I9: Su Corralon | J9: 45890
A10: CEM-GROUT | B10: Sika Grout 25k (u) | C10: u | E10: 31900 | I10: Su Corralon | J10: 45890
A11: CAL | B11: Bolsa Cal "Cacique" 25 k (u) | C11: u | D11: 6500 | E11: =D11/1.21 -> 5371.9008 | I11: ML | J11: 45785
A12: PLASTICOR | B12: Bolsa Plasticor 40k (u) | C12: u | D12: 8500 | E12: =D12/1.21 -> 7024.7934 | I12: ML | J12: 45785
A13: CER | B13: Ceresita 20 k (u) | C13: u | D13: 45000 | E13: =D13/1.21 -> 37190.083 | I13: Su Corralon | J13: 45771
A14: LP18 | B14: Ladrillo Portante 18 (u) | C14: u | E14: 1377 | I14: Su Corralon | J14: 45824
A15: LP12 | B15: Ladrillo Portante 12 (u) | C15: u | E15: 1110.2 | I15: Su Corralon | J15: 45824
A16: LH18 | B16: Ladrillo Hueco 18 (u) | C16: u | E16: 598 | I16: Su Corralon | J16: 45478
A17: LH12 | B17: Ladrillo Hueco 12 (u) | C17: u | E17: 726 | I17: Su Corralon | J17: 45824
A18: LH8 | B18: Ladrillo Hueco 8 (u) | C18: u | E18: 568.7 | I18: Su Corralon | J18: 45824
A19: LCOM | B19: Ladrillo Comun | C19: u | E19: 190.61 | I19: Su Corralon | J19: 45824
A20: LCOMVIST | B20: Ladrillo Comun Vista | C20: u | D20: 240 | E20: =D20/1.21 -> 198.34711 | I20: Su Corralon | J20: 45771
A21: LPINT | B21: Pavimento Intertrabado | C21: m2 | E21: 37600 | I21: Su Corralon | J21: 45824
A22: LGB | B22: Garden Block 38x38x8cm (1m2) | C22: m2 | E22: 22500 | I22: ml | J22: 45877
A23: LDC | B23: Deck Liston Hormigon Cemento Piso Durmiente 100 X 12 Cms (1m2) | E23: 41000 | I23: ml | J23: 45877
A24: YES | B24: Bolsa Yeso Tuyango 30 k (u) | C24: u | D24: 13879 | E24: =D24/1.21 -> 11470.248 | I24: Su Corralon | J24: 45400
A25: ES | B25: Cascote / Escombro (m3) | C25: m3 | D25: 19360 | E25: =D25/1.21 -> 16000 | I25: Su Corralon | J25: 45412
A26: TOS8 | B26: Tosca | C26: m3 | E26: 30000 | I26: NICO | J26: 45498
A27: TOS30 | B27: Tosca | C27: m3 | E27: 9500 | I27: NICO | J27: 45498
A28: TN | B28: BOLSON Tierra negra | C28: m3 | E28: 33275 | I28: Su Corralon | J28: 45824
A29: TNF | B29: BOLSON Tierra negra fertil 10% compost | C29: m3 | E29: 86600 | I29: Su Corralon | J29: 45890
A30: TRA | B30: BOLSON Tierra negra abonada 40% compost | C30: m3 | E30: 94400 | I30: Su Corralon | J30: 45890
A31: CL2 | B31: Clavos 2" punta paris (k) | C31: k | E31: 3739.67 | I31: Naclelio | J31: 45496
A32: CL2.5 | B32: Clavos 2,5" punta paris (k) | C32: k | E32: 3739.67 | I32: Naclelio | J32: 45496
A33: AL | B33: Alambre Fardo (k) | C33: k | E33: 4326.45 | I33: Naclelio | J33: 45496
A34: ES24 | B34: Cascote / Escombro cada 24 m3 (m3) | C34: m3 | D34: 16500 | E34: =D34/1.21 -> 13636.364 | I34: Su Corralon | J34: 45412
A35: DISCO PORC | B35: Disco Amoladora para porcelanato. marca aliafor | E35: 20000 | I35: ML | J35: 45783
A36: DISCO | B36: Disco Ascerradora | C36: u | E36: 120000
A37: DIS | B37: Disco corte | C37: u | E37: 40000
A38: VI7 | B38: Vigueta pretensada de hormigon 7m | C38: u | E38: 34000 | I38: ML | J38: 45817
A39: VI6 | B39: Vigueta pretensada de hormigon 6m | C39: u | E39: 30111 | I39: Su Corralon | J39: 45824
A40: VI4 | B40: Vigueta pretensada de hormigon 4m | C40: u | E40: 26000 | I40: ML | J40: 11//9/25
A41: VI-EPS | B41: Ladrillos Telgopor 10cm | C41: u | E41: 3600 | I41: Su Corralon | J41: 45824
A42: P-pro | B42: Protex 215 x 1kg | C42: u | D42: =E42*1.21 -> 21780 | E42: 18000 | I42: Tecnolibertador | J42: 45776
A43: z-sell | B43: Adhesivo Zocalos Sellador Rellenador Atrim 420gr | C43: u | E43: 13000
A44: ME | B44: MECHA ROTOPERCUTORA | C44: u | E44: 5000
A45: EPS | B45: EPS aislante para techos 1x1 30mm 15 Kg Pack 5u | C45: u | E45: 60000 | I45: ML | J45: 45824
A46: GRO | B46: Sika Grout 22kg | C46: U | E46: 43000 | I46: ML | J46: 45902
A49: CODIGO | B49: MATERIALES ACERO | D49: PRECIO CON IVA | E49: PRECIO SIN IVA | I49: REFERENCIA | J49: FECHA
A50: M3,5 | B50: Malla Φ 3,5 (2 m x 5 m) (hierros cada 0,18 x 0,18 m) - menos de 50 u (u) | C50: u | D50: 23200 | E50: =D50/1.21 -> 19173.554 | I50: Mallas Ya | J50: 45399
A51: M5 | B51: Malla Φ 5 (2 m x 5 m) (hierros cada 0,18 x 0,18 m) - menos de 50 u (u) | C51: u | D51: 36200 | E51: =D51/1.21 -> 29917.355 | I51: Mallas Ya | J51: 45399
A52: M5,5 | B52: Malla Φ 5,5 (2 m x 5 m) (hierros cada 0,18 x 0,18 m) - menos de 50 u (u) | C52: u | D52: 41900 | E52: =D52/1.21 -> 34628.099 | I52: Mallas Ya | J52: 45399
A53: M3,5M | B53: Malla Φ 3,5 (2 m x 5 m) (hierros cada 0,18 x 0,18 m) - mas de 50 u (u) | C53: u | D53: 22600 | E53: =D53/1.21 -> 18677.686 | I53: Mallas Ya | J53: 45399
A54: M5M | B54: Malla Φ 5 (2 m x 5 m) (hierros cada 0,18 x 0,18 m) - mas de 50 u (u) | C54: u | D54: 35800 | E54: =D54/1.21 -> 29586.777 | I54: Mallas Ya | J54: 45399
A55: M5,5 | B55: Malla Φ 5,5 (2 m x 5 m) (hierros cada 0,18 x 0,18 m) | C55: u | D55: 36600 | E55: 37608 | I55: Su Corralon | J55: 45824
A56: M6 | B56: Malla Φ 6 (2 m x 5 m) (hierros cada 0,15 x 0,15 m) | C56: u | J56: 45798
A57: M8 | B57: Malla Φ 8 (2 m x 5 m) (hierros cada 0,15 x 0,15 m) | C57: u | E57: 50000
A58: M8-Q335 | B58: Malla Φ 8 Q335 (2,4 m x 6 m) (hierros cada 0,15 x 0,15 m) | C58: u | I58: Su Corralon | J58: 45768
A59: HADN6 | B59: Hierros ADN 420 Φ 6 | C59: u | E59: 5250 | I59: Su Corralon | J59: 45824
A60: HADN8 | B60: Hierros ADN 420 Φ 8 | C60: u | E60: 9050 | I60: Su Corralon | J60: 45824
A61: HADN10 | B61: Hierros ADN 420Φ 10 | C61: u | D61: 12100 | E61: =D61/1.21 -> 10000 | I61: Su Corralon | J61: 45767
A62: HADN12 | B62: Hierros ADN 420 Φ 12 | C62: u | E62: 20442.5 | I62: Su Corralon | J62: 45824
A63: HADN16 | B63: Hierros ADN 420 Φ 16 | C63: u | E63: 36603.12 | I63: Su Corralon | J63: 45824
A64: HADN20 | B64: Hierros ADN 420 Φ 20 | C64: u | D64: 48744.82 | E64: =D64/1.21 -> 40284.975 | I64: Mallas Ya | J64: 45399
A65: HADN25 | B65: Hierros ADN 420 Φ 25 | C65: u | D65: 83198.48 | E65: =D65/1.21 -> 68759.074 | I65: Mallas Ya | J65: 45399
A66: HADN6K | B66: Hierros ADN 420 Φ 6 (k) | C66: k | E66: 1347.48 | I66: Mallas Ya | J66: 45399
A67: HADN8K | B67: Hierros ADN 420 Φ 8 (k) | C67: k | E67: 1310.31 | I67: Mallas Ya | J67: 45399
A68: HADN10K | B68: Hierros ADN 420Φ 10 (k) | C68: k | E68: 1310.31 | I68: Mallas Ya | J68: 45399
A69: HADN12K | B69: Hierros ADN 420 Φ 12 (k) | C69: k | E69: 1301.01 | I69: Mallas Ya | J69: 45399
A70: HADN16K | B70: Hierros ADN 420 Φ 16 (k) | C70: k | E70: 1263.84 | I70: Mallas Ya | J70: 45399
A71: HADN20K | B71: Hierros ADN 420 Φ 20 (k) | C71: k | E71: 1263.84 | I71: Mallas Ya | J71: 45399
A72: HADN25K | B72: Hierros ADN 420 Φ 25 (k) | C72: k | E72: 1263.84 | I72: Mallas Ya | J72: 45399
A73: HADN6K | B73: Hierros ADN 420 Φ 6 (k) | C73: k | E73: 1455 | I73: Materiales Urquiza | J73: 45407
A74: HADN8K | B74: Hierros ADN 420 Φ 8 (k) | C74: k | E74: 1374 | I74: Materiales Urquiza | J74: 45407
A75: HADN10K | B75: Hierros ADN 420Φ 10 (k) | C75: k | E75: 1374 | I75: Materiales Urquiza | J75: 45407 | L75: BNA
A76: HADN12K | B76: Hierros ADN 420 Φ 12 (k) | C76: k | E76: 1374 | I76: Materiales Urquiza | J76: 45407 | L76: 940
A77: HADN16K | B77: Hierros ADN 420 Φ 16 (k) | C77: k | E77: 1322 | I77: Materiales Urquiza | J77: 45407 | L77: 940
A78: HADN20K | B78: Hierros ADN 420 Φ 20 (k) | C78: k | E78: 1322 | I78: Materiales Urquiza | J78: 45407
A79: HADN25K | B79: Hierros ADN 420 Φ 25 (k) | C79: k | E79: 1322 | I79: Materiales Urquiza | J79: 45407
A80: HL16 | B80: Hierros Liso Φ 16 - l=6 m | C80: m | E80: 20410 | I80: Materiales Urquiza | J80: 45407
A81: M-ELEC | B81: Malla electrosada (1x1) 250 | C81: m2 | E81: 30000 | I81: ml | J81: 45902
A82: C.E. 40X60 | B82: Cano estructural 40x60x1.6 (6mts) | C82: m | E82: 60000 | I82: ml | J82: 45902
C83: u | K83: PRECIO EN USD
K84: 398
A85: CODIGO | B85: MATERIALES PLOMERIA | D85: PRECIO CON IVA | E85: PRECIO SIN IVA | I85: REFERENCIA | J85: FECHA | K85: 317
A86: LAVAT | B86: Lavatorio DECA (SOBRE MESADA) | C86: u | E86: 200000 | I86: ML | J86: 45797
A87: INOD | B87: Inodoro FERRUM | C87: u | E87: 600000 | I87: ML | J87: 45799
A88: INOD-BID | B88: Indoro y Bidet completos FERRUM | C88: u | E88: 1000000 | I88: ML | J88: 45797
A89: PDP | B89: Pileta de patio AWADUCT | C89: u | E89: 12000 | I89: ML | J89: 45797
A90: GRIF-TOI | B90: Grfieria Lavatorio FV | C90: u | E90: 150000 | I90: ML | J90: 45797
A91: GRIF-COC | B91: Griferia mocomando cocina movible FV | C91: u | E91: 300000 | I91: ML | J91: 45797
A92: GRIF-CS | B92: Griferia CANILLA DE SERVICIO | C92: u | E92: 10000 | I92: ML | J92: 45877
A93: GRIF-DUCHA | B93: Grfieria Ducha FV | C93: u | E93: 360000 | I93: ML | J93: 45797
A94: GRIF-BID | B94: Grfieria Bide FV | C94: u | E94: 211000 | I94: ML | J94: 45797
A95: PDP-REJ | B95: Rejilla ATRIM Pileta Patio Reversible 12x12 Cuadrada Acero I | C95: u | E95: 26000 | I95: ML | J95: 45797
A96: INOD-DEP | B96: Deposito Capea Italiana Apoyo | C96: u | E96: 98608.68 | I96: Hokama | J96: 45496
A97: INOD | B97: Inodoro Capea Italiana Largo | C97: u | E97: 143129.81 | I97: Hokama | J97: 45496
... A99: PL-TRI | B99: Tritubo 40 mm (3 mm espesor) | C99: m | E99: 4487.71 | I99: Mercado Libre | J99: 45432
A100: PL-FAJA | B100: Faja Advertencia Blanca | C100: m | D100: 480 | E100: =D100/1.21 -> 396.69421 | I100: Mercado Libre | J100: 45432
A101: PL-CAM30 | B101: Tapa y Marco Hormigon para Camara Inspeccion 0,6 x 0,6 m | C101: u | D101: 32000 | E101: =D101/1.21 -> 26446.281 | I101: Darsie Web | J101: 45432
A102: PL-CAM60 | B102: Tapa y Marco Hormigon para Camara Inspeccion 0,6 x 0,6 m | C102: u | D102: 40000 | E102: =D102/1.21 -> 33057.851 | I102: Darsie Web | J102: 45432
A103: H-CAM60 | B103: Tapa y Marco SEMILLA DE MELON para Camara Inspeccion 0,6 x 0,6 m | E103: 150000 | I103: LUIS LUPINO | J103: 45893
A104: AF-TAN2000 | B104: Tanque De Agua Waterplast Vertical Tricapa 2000l | E104: 450000 | I104: ML | J104: 45819
...

Sheet 00_MO
A1: MANO DE OBRA
A3: CODIGO | B3: MATERIALES CORRALON | C3: UNIDAD | D3: PRECIO SIN IVA | E3: FECHA
A4: MO-CA | B4: Capataz | C4: u | D4: =60000*1.5 -> 90000 | E4: 45926
A5: MO-PU | B5: Puntero | C5: u | D5: =55000*1.5 -> 82500 | E5: 45926
A6: MO-OF | B6: Oficial | C6: u | D6: =50000*1.5 -> 75000 | E6: 45926
A7: MO-AY | B7: Ayudante | C7: u | D7: =40000*1.5 -> 60000 | E7: 45926
A8: MO-GER | B8: GERVACIO | C8: u | D8: 80000 | E8: 45926

Sheet 00_Eq
A1: EQUIPOS
A3: CODIGO | B3: MATERIALES CORRALON | C3: UNIDAD | D3: PRECIO SIN IVA | E3: FECHA
A4: E-MC | B4: Mini Cargadora | C4: u | D4: 420000 | E4: 45804
A5: E-MCM | B5: Mini Cargadora con martillo | C5: u | D5: 550000 | E5: 45804
A6: E-ME | B6: Mini Excavadora | C6: u | D6: 550000 | E6: 45804
A7: E-MP | B7: Motopison | C7: u | D7: 40000
A8: E-RP | B8: Retropala | C8: u | D8: 450000
A9: E-VC | B9: Vibrocompactador | C9: u | D9: 400000
A10: E-MN | B10: Motoniveladora | C10: u | D10: 600000
A11: E-CAMCH | B11: Camion Chasis | C11: u | D11: 150000
A12: E-REG | B12: Regador | C12: u | D12: 200000
A13: E-MAR | B13: Martillete | C13: u | D13: 60000
A14: E-ASC | B14: Ascerradora | C14: u | D14: 60000 | E14: 45890
A15: E-RET | B15: Retiro x camion | C15: u | D15: 250000 | E15: 45890
A16: E-MR | B16: Mini Retro | C16: u | D16: 480000 | E16: 45804
A17: MS-TM3 | B17: TOSCA x M3 | C17: m3 | D17: 30000 | E17: 45804
A18: MS-TCA | B18: TOSCA X CAMION | C18: m3 | D18: =D17*8 -> 240000 | E18: 45804
A19: MS-ER | B19: EXCAVACION Y RETIRO | C19: m3 | D19: 21000 | E19: 45804
A20: MS-TC | B20: TOSCA COMPACTADA | C20: m3 | D20: 25000 | E20: 45804
A21: MS-ARBOL | B21: RETIRO DE ARBOL | C21: u | D21: 570000 | E21: 45804
A22: E-CAM | B22: Camioneta | C22: u | D22: 100000
A23: E-TRAS | B23: TRASLADO DE MAQUINARIA | C23: u | D23: 300000
A24: E-VOL | B24: Volquete | C24: u | D24: 200000

Sheet 00_Sub
A1: SUBCONTRATOS
A3: CODIGO | B3: SUBCONTRATOS | C3: UNIDAD | D3: PRECIO SIN IVA
A4: SUB-PI | B4: Pintura Interior: 1Mano Enduido + Yeso, 1 Mano Enduido, 2 a 3 Manos de Pintura | C4: m2 | D4: 16000 | F4: 45789
A5: SUB-PIC | B5: Pintura Interior Cielorraso | C5: m2 | D5: 10000 | F5: 45789
A6: SUB-PET | B6: Pintura Exterior Tarquini | C6: m2 | D6: 12000 | F6: 45789
A7: SUB-PE | B7: Pintura Exterior | C7: m2 | D7: 10000
A8: SUB-PI | B8: Pintura Interior | C8: m2 | D8: 8000
A9: SUB-END | B9: Enduido | C9: m2 | D9: 8000
A10: SUB-PPS | B10: Pintura Puerta Simple Hoja | C10: u | D10: 25000
A11: SUB-PPD | B11: Pintura Puerta Doble Hoja | C11: u | D11: 50000
A12: SUB-CIE | B12: Instalacion de Cielorraso Durlock. Incluye Materiales. | C12: m2 | D12: 37000 | F12: 45791
A13: SUB-CIEDES | B13: Instalacion de Cielorraso Desmontable. Incluye Materiales. | C13: m2 | D13: 37000 | F13: 45791
A14: SUB-CIECO | B14: Instalacion de Cielorraso Durlock Cortineros. Incluye Materiales. | C14: m | D14: 45000 | F14: 45791
A15: SUB-CIECA | B15: Instalacion de Cajon Durlock. Incluye Materiales. | C15: m | D15: 20000 | F15: 45791
A16: SUB-CIEGL | B16: Instalacion de Cielorraso Durlock Garganta Led. Incluye Materiales. | C16: m | D16: 45000 | F16: 45791
A17: SUB-TAB | B17: Instalacion de Tabique Durlock. Incluye Materiales. | C17: m2 | D17: 48000 | F17: 45791
A18: SUB-BZ | B18: Instlacion Buña Z. Incluye Materiales. | C18: m | D18: 16000 | F18: 45791
A19: SUB-CAN | B19: Instalacion Cantonera. Incluye Materiales. | C19: m | D19: 16000 | F19: 45791
A20: SUB-E-BOC | B20: Boca. Incluye Materiales. | C20: boca | D20: 100000 | E20: MDO Y MAT | F20: 45800 | G20: CABEZA
A21: SUB-E-COL | B21: Colocacion de artefatcos | C21: u | D21: 7000 | E21: MDO | F21: 45800 | G21: CABEZA
A22: SUB-E-AAC | B22: Alimentacion aire acondicionado con split. | C22: u | D22: 100000 | E22: MDO Y MAT | F22: 45800 | G22: CABEZA
A23: SUB-E-TAB | B23: Instalacion de Tablero para 100 bocas (casa chica). Incluye alimentacion desde el pilar. | C23: u | D23: 100000 | E23: MDO | F23: 45800 | G23: CABEZA
A24: SUB-ZING | B24: Zinguero | C24: u | D24: 700000
A25: SUB-PIS | B25: Pisero | C25: m² | D25: 7000 | F25: 45800 | G25: CEFERINO
A26: SUB-COR | B26: CORDON | C26: m | D26: 10000 | F26: 45800 | G26: CEFERINO
A27: SUB-ELE-T | C27: TABLERO | D27: 1000000
A28: SUB-ELE-B | B28: Electricista | C28: boca | D28: 60000
A29: SUB-SIDING | B29: COLOCAcion de siding en pared | C29: m2 | D29: 18000
A30: SUB-REV-CH | B30: Revestimiento de chapa | C30: m2 | D30: 18000 | F30: 45902 | G30: HUGO
A32: CODIGO | B32: MOVIMIENTO DE SUELOS | C32: UNIDAD | D32: PRECIO SIN IVA
A33: MS-MC | B33: MINICARGADORA | C33: u | D33: 420000
A34: MS-MCM | B34: MINICARGADORA CON MARTILLO | C34: u | D34: 550000
A35: MS-MR | B35: MINIRETRO EXCAVADORA | C35: u | D35: 550000
A36: MS-T | B36: TRASLADO DE MAQUINARIA | C36: u | D36: 300000
A37: MS-RV | B37: RETIRO X VIAJE | C37: u | D37: 60000
A38: MS-TM3 | B38: TOSCA x M3 | C38: m3 | D38: 30000
A39: MS-TCA | B39: TOSCA X CAMION | C39: m3 | D39: =D38*8 -> 240000
A40: MS-ER | B40: EXCAVACION Y RETIRO | C40: m3 | D40: 21000
A41: MS-TC | B41: TOSCA COMPACTADA | C41: m3 | D41: 25000
A42: MS-ARBOL | B42: RETIRO DE ARBOL | C42: u | D42: 200000
A45: BQ | B45: BAÑO QUIMICO | C45: U | D45: 120000
A47: Perfracion | B47: Perforacion para bobas de 7.5 HP de 17m3/h materiales y mo | D47: 2800000 | F47: 14614.9 | G47: cac antes | H47: 2250000
F48: 1692950 | G48: cac ahora | H48: =F48*H47/F47 -> 2.6063384e+08

Sheet 00_JEF + ESTR
A1: JEFATURA DE OBRA (mes)
A3: Jefatura de Obra | B3: 2000000
A4: Jefe de Obra | B4: 1500000
A5: Gastos Estructura | B5: =SUM(B6:B9) -> 1620000
A6: Nafta Jefe de Obra | B6: 280000
A7: Nafta Nico | B7: 140000
A8: Guille | B8: 200000
A9: Herramientas | B9: 1000000
B11: =SUM(B5+B3) -> 3620000
A13: JEFATURA X 12 MESES | B13: =B3*12 -> 24000000
A14: G.E. X 12 MESES | B14: =B5*12 -> 19440000

Sheet 01_C&P
A1: CASA LUGONES
A3: PLANILLA COMPUTO Y PRESPUPUESTO
A5: ITEM | B5: DESCRIPCIÓN | C5: UNIDAD | D5: CANTIDAD | E5: SUBTOTAL 01: GASTOS DIRECTOS | O5: SUBTOTAL 02: GASTOS INDIRECTOS | R5: SUBTOTAL 03: BENEFICIOS | U5: TOTAL (NETO)
E6: V.UNITARIO | L6: V.GENERAL | O6: V. GENERAL | R6: V. GENERAL | U6: V. UNITARIO | X6: V.GENERAL
E7: MAT. | F7: M.O.: JORNALES | G7: M.O.: EQUIPOS | H7: M.O.: MATERIALES | I7: M.O.: SUBCONTRATOS | J7: M.O. | K7: GENERAL | L7: MAT. | M7: M.O | N7: GENERAL | O7: MAT. | P7: M.O. | Q7: GENERAL | R7: MAT. | S7: M.O. | T7: GENERAL | U7: MAT. | V7: M.O | W7: GENERAL | X7: MAT. | Y7: M.O | Z7: GENERAL
A8: 1- TAREAS PRELIMINARES
A9: 45658 | B9: OBRADOR | C9: mes | D9: 1 | E9: 800000 | F9: 400000 | H9: 200000 | I9: 0 | J9: =SUM(F9:I9) -> 600000 | K9: =SUM(E9,J9) -> 1400000 | L9: =$D9*E9 -> 800000 | M9: =$D9*(SUM(F9:I9)) -> 600000 | N9: =L9+M9 -> 1400000 | O9: =L9 -> 800000 | P9: =(P$110*M9)/M$110 -> 1014000 | Q9: =O9+P9 -> 1814000 | R9: =L9 -> 800000 | S9: =(S$110*P9)/P$110 -> 1368900 | T9: =R9+S9 -> 2168900 | U9: =E9 -> 800000 | V9: =Y9/D9 -> 1481149.8 | W9: =U9+V9 -> 2281149.8 | X9: =L9 -> 800000 | Y9: =(Y$110*S9)/S$110 -> 1481149.8 | Z9: =X9+Y9 -> 2281149.8
A10: 45689 | B10: CARTEL DE OBRA | C10: unid | D10: 1 | J10: =SUM(F10:I10) -> 0 | K10: =SUM(E10,J10) -> 0 | L10: =$D10*E10 -> 0 | M10: =$D10*(SUM(F10:I10)) -> 0 | N10: =L10+M10 -> 0 | O10: =L10 -> 0 | P10: =(P$110*M10)/M$110 -> 0 | Q10: =O10+P10 -> 0 | R10: =L10 -> 0 | S10: =(S$110*P10)/P$110 -> 0 | T10: =R10+S10 -> 0 | U10: =E10 | V10: =Y10/D10 -> 0 | W10: =U10+V10 -> 0 | X10: =L10 -> 0 | Y10: =(Y$110*S10)/S$110 -> 0 | Z10: =X10+Y10 -> 0
A11: 45717 | B11: BAÑO QUIMICO | C11: mes | D11: 12 | I11: 100000 | J11: =SUM(F11:I11) -> 100000 | K11: =SUM(E11,J11) -> 100000 | L11: =$D11*E11 -> 0 | M11: =$D11*(SUM(F11:I11)) -> 1200000 | N11: =L11+M11 -> 1200000 | O11: =L11 -> 0 | P11: =(P$110*M11)/M$110 -> 2028000 | Q11: =O11+P11 -> 2028000 | R11: =L11 -> 0 | S11: =(S$110*P11)/P$110 -> 2737800 | T11: =R11+S11 -> 2737800 | U11: =E11 | V11: =Y11/D11 -> 246858.3 | W11: =U11+V11 -> 246858.3 | X11: =L11 -> 0 | Y11: =(Y$110*S11)/S$110 -> 2962299.6 | Z11: =X11+Y11 -> 2962299.6
A12: 45748 | B12: INSTALACIONES PROVISORIAS | C12: unid | D12: 1 | J12: =SUM(F12:I12) -> 0 | K12: =SUM(E12,J12) -> 0 | L12: =$D12*E12 -> 0 | M12: =$D12*(SUM(F12:I12)) -> 0 | N12: =L12+M12 -> 0 | O12: =L12 -> 0 | P12: =(P$110*M12)/M$110 -> 0 | Q12: =O12+P12 -> 0 | R12: =L12 -> 0 | S12: =(S$110*P12)/P$110 -> 0 | T12: =R12+S12 -> 0 | U12: =E12 | V12: =Y12/D12 -> 0 | W12: =U12+V12 -> 0 | X12: =L12 -> 0 | Y12: =(Y$110*S12)/S$110 -> 0 | Z12: =X12+Y12 -> 0
A13: 45778 | B13: CERCO PERIMETRAL | C13: unid | D13: 1 | J13: =SUM(F13:I13) -> 0 | K13: =SUM(E13,J13) -> 0 | L13: =$D13*E13 -> 0 | M13: =$D13*(SUM(F13:I13)) -> 0 | N13: =L13+M13 -> 0 | O13: =L13 -> 0 | P13: =(P$110*M13)/M$110 -> 0 | Q13: =O13+P13 -> 0 | R13: =L13 -> 0 | S13: =(S$110*P13)/P$110 -> 0 | T13: =R13+S13 -> 0 | U13: =E13 | V13: =Y13/D13 -> 0 | W13: =U13+V13 -> 0 | X13: =L13 -> 0 | Y13: =(Y$110*S13)/S$110 -> 0 | Z13: =X13+Y13 -> 0
A14: 45809 | B14: REPLANTEO Y NIVELACION INICIAL DEL TERRENO | C14: unid | D14: 1 | I14: 700000 | J14: =SUM(F14:I14) -> 700000 | K14: =SUM(E14,J14) -> 700000 | L14: =$D14*E14 -> 0 | M14: =$D14*(SUM(F14:I14)) -> 700000 | N14: =L14+M14 -> 700000 | O14: =L14 -> 0 | P14: =(P$110*M14)/M$110 -> 1183000 | Q14: =O14+P14 -> 1183000 | R14: =L14 -> 0 | S14: =(S$110*P14)/P$110 -> 1597050 | T14: =R14+S14 -> 1597050 | U14: =E14 | V14: =Y14/D14 -> 1728008.1 | W14: =U14+V14 -> 1728008.1 | X14: =L14 -> 0 | Y14: =(Y$110*S14)/S$110 -> 1728008.1 | Z14: =X14+Y14 -> 1728008.1
A15: 45839 | B15: LIMPIEZA PERIODICA DE OBRA | C15: mes | D15: 12 | F15: 100000 | I15: 0 | J15: =SUM(F15:I15) -> 100000 | K15: =SUM(E15,J15) -> 100000 | L15: =$D15*E15 -> 0 | M15: =$D15*(SUM(F15:I15)) -> 1200000 | N15: =L15+M15 -> 1200000 | O15: =L15 -> 0 | P15: =(P$110*M15)/M$110 -> 2028000 | Q15: =O15+P15 -> 2028000 | R15: =L15 -> 0 | S15: =(S$110*P15)/P$110 -> 2737800 | T15: =R15+S15 -> 2737800 | U15: =E15 | V15: =Y15/D15 -> 246858.3 | W15: =U15+V15 -> 246858.3 | X15: =L15 -> 0 | Y15: =(Y$110*S15)/S$110 -> 2962299.6 | Z15: =X15+Y15 -> 2962299.6
A16: 45870 | B16: LIMPIEZA FINAL DE OBRA | C16: unid | D16: 1 | F16: 250000 | I16: 150000 | J16: =SUM(F16:I16) -> 400000 | K16: =SUM(E16,J16) -> 400000 | L16: =$D16*E16 -> 0 | M16: =$D16*(SUM(F16:I16)) -> 400000 | N16: =L16+M16 -> 400000 | O16: =L16 -> 0 | P16: =(P$110*M16)/M$110 -> 676000 | Q16: =O16+P16 -> 676000 | R16: =L16 -> 0 | S16: =(S$110*P16)/P$110 -> 912600 | T16: =R16+S16 -> 912600 | U16: =E16 | V16: =Y16/D16 -> 987433.2 | W16: =U16+V16 -> 987433.2 | X16: =L16 -> 0 | Y16: =(Y$110*S16)/S$110 -> 987433.2 | Z16: =X16+Y16 -> 987433.2
A17: 45901 | B17: AYUDA DE GREMIO | C17: mes | D17: 12 | F17: 150000 | J17: =SUM(F17:I17) -> 150000 | K17: =SUM(E17,J17) -> 150000 | L17: =$D17*E17 -> 0 | M17: =$D17*(SUM(F17:I17)) -> 1800000 | N17: =L17+M17 -> 1800000 | O17: =L17 -> 0 | P17: =(P$110*M17)/M$110 -> 3042000 | Q17: =O17+P17 -> 3042000 | R17: =L17 -> 0 | S17: =(S$110*P17)/P$110 -> 4106700 | T17: =R17+S17 -> 4106700 | U17: =E17 | V17: =Y17/D17 -> 370287.45 | W17: =U17+V17 -> 370287.45 | X17: =L17 -> 0 | Y17: =(Y$110*S17)/S$110 -> 4443449.4 | Z17: =X17+Y17 -> 4443449.4
A18: 45931 | B18: PROGRAMA DE SEGURIDAD E HIGENE DE ACUERDO A LA NORMATIVA VIGENTE (TODO EL PERSONAL ALCANZADO POR EL MISMO Y CON ART) | C18: mes | D18: 12 | I18: 200000 | J18: =SUM(F18:I18) -> 200000 | K18: =SUM(E18,J18) -> 200000 | L18: =$D18*E18 -> 0 | M18: =$D18*(SUM(F18:I18)) -> 2400000 | N18: =L18+M18 -> 2400000 | O18: =L18 -> 0 | P18: =(P$110*M18)/M$110 -> 4056000 | Q18: =O18+P18 -> 4056000 | R18: =L18 -> 0 | S18: =(S$110*P18)/P$110 -> 5475600 | T18: =R18+S18 -> 5475600 | U18: =E18 | V18: =Y18/D18 -> 493716.6 | W18: =U18+V18 -> 493716.6 | X18: =L18 -> 0 | Y18: =(Y$110*S18)/S$110 -> 5924599.2 | Z18: =X18+Y18 -> 5924599.2
A19: 2- DEMOLICION
A20: 45659 | B20: DEMOLICION LOSAS | C20: m² | D20: 30
A21: 45690 | B21: DEMOLICION COLUMNAS | C21: unid. | D21: 3
A22: 45718 | B22: DEMOLICION MUROS | C22: m² | D22: =48*3.4 -> 163.2
A23: 45749 | B23: DEMOLICION DE ESCALERA (1 x 0,84m) h- 4 escalones | C23: gl | D23: 1
A24: 45779 | B24: DEMOLICION EN SECTOR CANTERO | C24: m² | D24: 9
A25: 45810 | B25: DEMOLICION DE VOLUMEN PA | C25: gl | D25: 1
A26: 45840 | B26: DEMOLICION DE LOSA PARA INSTALACIONES | C26: gl | D26: 1
A27: 45871 | B27: DEMOLICION DE FUNDACIONES PARA REFORZAR ESTRUCTURA | C27: gl | D27: 1
A28: 45902 | B28: RETIRO DE PORTON | C28: unid. | D28: 1
A29: 45932 | B29: RETIRO DE CARPINTERIAS | C29: gl | D29: 1
A30: 45963 | B30: RETIRO DE PUERTA PRINCIPAL | C30: unid. | D30: 1
A31: 45993 | B31: RETIRO DE SOLADO EN PLANTA BAJA | C31: m² | D31: 118
A32: 2.13 | B32: RETIRO DE ALERO METALICO | C32: gl | D32: 1
A33: 2.14 | B33: DEMOLICION TOTAL DE ITEMS ANTERIORES | C33: gl | D33: 1 | E33: ='2.14'!I22 -> 0 | F33: ='2.14'!I36 -> 6180000 | G33: ='2.14'!I50 -> 7500000 | H33: ='2.14'!I64 -> 503700 | I33: ='2.14'!I78 -> 0 | J33: =SUM(F33:I33) -> 14183700 | K33: =SUM(E33,J33) -> 14183700 | L33: =$D33*E33 -> 0 | M33: =$D33*(SUM(F33:I33)) -> 14183700 | N33: =L33+M33 -> 14183700 | O33: =L33 -> 0 | P33: =(P$110*M33)/M$110 -> 23970453 | Q33: =O33+P33 -> 23970453 | R33: =L33 -> 0 | S33: =(S$110*P33)/P$110 -> 32360112 | T33: =R33+S33 -> 32360112 | U33: =E33 -> 0 | V33: =Y33/D33 -> 35013641 | W33: =U33+V33 -> 35013641 | X33: =L33 -> 0 | Y33: =(Y$110*S33)/S$110 -> 35013641 | Z33: =X33+Y33 -> 35013641
A34: 3-ESTRUCTURA
A35: FUNDACIONES
A36: 3.0-1 | B36: EXCAVACION DE BASES PARA REFORZAR ESTRUCTURA | C36: unid. | D36: 14 | E36: ='3.0-1'!I25 -> 0 | F36: ='3.0-1'!I39 -> 321428.57 | G36: ='3.0-1'!I53 -> 71428.571 | H36: ='3.0-1'!I67 -> 0 | I36: ='3.0-1'!I81 -> 0 | J36: =SUM(F36:I36) -> 392857.14 | K36: =SUM(E36,J36) -> 392857.14 | L36: =$D36*E36 -> 0 | M36: =$D36*(SUM(F36:I36)) -> 5500000 | N36: =L36+M36 -> 5500000 | O36: =L36 -> 0 | P36: =(P$110*M36)/M$110 -> 9295000 | Q36: =O36+P36 -> 9295000 | R36: =L36 -> 0 | S36: =(S$110*P36)/P$110 -> 12548250 | T36: =R36+S36 -> 12548250 | U36: =E36 -> 0 | V36: =Y36/D36 -> 969800.46 | W36: =U36+V36 -> 969800.46 | X36: =L36 -> 0 | Y36: =(Y$110*S36)/S$110 -> 13577206 | Z36: =X36+Y36 -> 13577206
A37: 3.0-2 | B37: EJECUCION DE BASES DE H 30 100x100 + TRONCO 25X25x100 + TENSORES 30x40cm | C37: unid. | D37: 14 | E37: ='3.0-2'!I26 -> 206681.2 | F37: ='3.0-2'!I40 -> 273214.29 | G37: ='3.0-2'!I54 -> 0 | H37: ='3.0-2'!I68 -> 24452.191 | I37: ='3.0-2'!I82 -> 0 | J37: =SUM(F37:I37) -> 297666.48 | K37: =SUM(E37,J37) -> 504347.68 | L37: =$D37*E37 -> 2893536.9 | M37: =$D37*(SUM(F37:I37)) -> 4167330.7 | N37: =L37+M37 -> 7060867.5 | O37: =L37 -> 2893536.9 | P37: =(P$110*M37)/M$110 -> 7042788.8 | Q37: =O37+P37 -> 9936325.7 | R37: =L37 -> 2893536.9 | S37: =(S$110*P37)/P$110 -> 9507764.9 | T37: =R37+S37 -> 12401302 | U37: =E37 -> 206681.2 | V37: =Y37/D37 -> 734814.41 | W37: =U37+V37 -> 941495.61 | X37: =L37 -> 2893536.9 | Y37: =(Y$110*S37)/S$110 -> 10287402 | Z37: =X37+Y37 -> 13180939
A38: 3.0-3 | B38: RELLENO DE FUNDACIONES (TOSCA + HORMIGON EN PLATEA DE FUNDACION) | C38: unid. | D38: 14 | E38: =' 3.0-3'!I25 -> 125774.59 | F38: =' 3.0-3'!I39 -> 107142.86 | G38: =' 3.0-3'!I53 -> 0 | H38: =' 3.0-3'!I67 -> 0 | I38: =' 3.0-3'!I81 -> 0 | J38: =SUM(F38:I38) -> 107142.86 | K38: =SUM(E38,J38) -> 232917.45 | L38: =$D38*E38 -> 1760844.3 | M38: =$D38*(SUM(F38:I38)) -> 1500000 | N38: =L38+M38 -> 3260844.3 | O38: =L38 -> 1760844.3 | P38: =(P$110*M38)/M$110 -> 2535000 | Q38: =O38+P38 -> 4295844.3 | R38: =L38 -> 1760844.3 | S38: =(S$110*P38)/P$110 -> 3422250 | T38: =R38+S38 -> 5183094.3 | U38: =E38 -> 125774.59 | V38: =Y38/D38 -> 264491.04 | W38: =U38+V38 -> 390265.63 | X38: =L38 -> 1760844.3 | Y38: =(Y$110*S38)/S$110 -> 3702874.5 | Z38: =X38+Y38 -> 5463718.8
A39: SOBRE PLANTA BAJA
A40: 3.1-1 | B40: VIGAS H30 SOBRE PLANTA BAJA 0,15x0,35 (Hierros 6 ∅8 con estribos ∅ 6 c/14) | C40: m | D40: 29 | E40: ='3.1-1'!I22 -> 17958.966 | F40: ='3.1-1'!I36 -> 49655.172 | G40: ='3.1-1'!I50 -> 0 | H40: ='3.1-1'!I64 -> 28161.198 | I40: ='3.1-1'!I78 -> 0 | J40: =SUM(F40:I40) -> 77816.37 | K40: =SUM(E40,J40) -> 95775.336 | L40: =$D40*E40 -> 520810 | M40: =$D40*(SUM(F40:I40)) -> 2256674.7 | N40: =L40+M40 -> 2777484.7 | O40: =L40 -> 520810 | P40: =(P$110*M40)/M$110 -> 3813780.3 | Q40: =O40+P40 -> 4334590.3 | R40: =L40 -> 520810 | S40: =(S$110*P40)/P$110 -> 5148603.4 | T40: =R40+S40 -> 5669413.4 | U40: =E40 -> 17958.966 | V40: =Y40/D40 -> 192096.17 | W40: =U40+V40 -> 210055.13 | X40: =L40 -> 520810 | Y40: =(Y$110*S40)/S$110 -> 5570788.9 | Z40: =X40+Y40 -> 6091598.9
A41: 3.1-2 | B41: VIGAS METALICAS + COLUMNA METALICA | C41: m | D41: =4+4.3 -> 8.3 | E41: ='3.1-2'!I22 -> 139757.45 | F41: ='3.1-2'!I36 -> 0 | G41: ='3.1-2'!I50 -> 0 | H41: ='3.1-2'!I64 -> 0 | I41: ='3.1-2'!I78 -> 120481.93 | J41: =SUM(F41:I41) -> 120481.93 | K41: =SUM(E41,J41) -> 260239.37 | L41: =$D41*E41 -> 1159986.8 | M41: =$D41*(SUM(F41:I41)) -> 1000000 | N41: =L41+M41 -> 2159986.8 | O41: =L41 -> 1159986.8 | P41: =(P$110*M41)/M$110 -> 1690000 | Q41: =O41+P41 -> 2849986.8 | R41: =L41 -> 1159986.8 | S41: =(S$110*P41)/P$110 -> 2281500 | T41: =R41+S41 -> 3441486.8 | U41: =E41 -> 139757.45 | V41: =Y41/D41 -> 297419.64 | W41: =U41+V41 -> 437177.09 | X41: =L41 -> 1159986.8 | Y41: =(Y$110*S41)/S$110 -> 2468583 | Z41: =X41+Y41 -> 3628569.8
A42: 3.1-3 | B42: LOSA DE VIGUETAS SECTOR COCINA e=0,08m | C42: m² | D42: 18 | E42: ='3.1-3'!I22 -> 49897.778 | F42: ='3.1-3'!I36 -> 29166.667 | G42: ='3.1-3'!I50 -> 0 | H42: ='3.1-3'!I64 -> 12111.111 | I42: ='3.1-3'!I78 -> 0 | J42: =SUM(F42:I42) -> 41277.778 | K42: =SUM(E42,J42) -> 91175.556 | L42: =$D42*E42 -> 898160 | M42: =$D42*(SUM(F42:I42)) -> 743000 | N42: =L42+M42 -> 1641160 | O42: =L42 -> 898160 | P42: =(P$110*M42)/M$110 -> 1255670 | Q42: =O42+P42 -> 2153830 | R42: =L42 -> 898160 | S42: =(S$110*P42)/P$110 -> 1695154.5 | T42: =R42+S42 -> 2593314.5 | U42: =E42 -> 49897.778 | V42: =Y42/D42 -> 101897.62 | W42: =U42+V42 -> 151795.4 | X42: =L42 -> 898160 | Y42: =(Y$110*S42)/S$110 -> 1834157.2 | Z42: =X42+Y42 -> 2732317.2
A43: 3.1-4 | B43: COLUMNAS DE HORMIGON ARMADO 20x20cm h 3,5m (Hierros 4 ∅12 con estribos ∅ 6 c/14) | C43: unid. | D43: 7 | E43: ='3.1-4'!I22 -> 114605 | F43: ='3.1-4'!I36 -> 171428.57 | G43: ='3.1-4'!I50 -> 0 | H43: ='3.1-4'!I66 -> 51573.91 | I43: ='3.1-4'!I80 -> 0 | J43: =SUM(F43:I43) -> 223002.48 | K43: =SUM(E43,J43) -> 337607.48 | L43: =$D43*E43 -> 802235 | M43: =$D43*(SUM(F43:I43)) -> 1561017.4 | N43: =L43+M43 -> 2363252.4 | O43: =L43 -> 802235 | P43: =(P$110*M43)/M$110 -> 2638119.4 | Q43: =O43+P43 -> 3440354.4 | R43: =L43 -> 802235 | S43: =(S$110*P43)/P$110 -> 3561461.1 | T43: =R43+S43 -> 4363696.1 | U43: =E43 -> 114605 | V43: =Y43/D43 -> 550500.13 | W43: =U43+V43 -> 665105.13 | X43: =L43 -> 802235 | Y43: =(Y$110*S43)/S$110 -> 3853500.9 | Z43: =X43+Y43 -> 4655735.9
A44: 3.1-5 | B44: COLUMNAS H30 EN MEDIANERA EN PLANTA BAJA 60x15 | C44: unid. | D44: 7 | E44: ='3.1-5'!I22 -> 173955.71 | F44: ='3.1-5'!I36 -> 117857.14 | G44: ='3.1-5'!I50 -> 0 | H44: ='3.1-5'!I66 -> 16488.196 | I44: ='3.1-5'!I80 -> 0 | J44: =SUM(F44:I44) -> 134345.34 | K44: =SUM(E44,J44) -> 308301.05 | L44: =$D44*E44 -> 1217690 | M44: =$D44*(SUM(F44:I44)) -> 940417.37 | N44: =L44+M44 -> 2158107.4 | O44: =L44 -> 1217690 | P44: =(P$110*M44)/M$110 -> 1589305.4 | Q44: =O44+P44 -> 2806995.4 | R44: =L44 -> 1217690 | S44: =(S$110*P44)/P$110 -> 2145562.2 | T44: =R44+S44 -> 3363252.2 | U44: =E44 -> 173955.71 | V44: =Y44/D44 -> 331642.62 | W44: =U44+V44 -> 505598.33 | X44: =L44 -> 1217690 | Y44: =(Y$110*S44)/S$110 -> 2321498.3 | Z44: =X44+Y44 -> 3539188.3
A45: SOBRE PLANTA ALTA
A46: 3.2-1 | B46: COLUMNAS H30 SOBRE PRIMER PISO 20x20. H=2,5 | C46: unid. | D46: 5 | E46: ='3.2-1'!I22 -> 60087 | F46: ='3.2-1'!I36 -> 165000 | G46: ='3.2-1'!I50 -> 0 | H46: ='3.2-1'!I66 -> 33611.474 | I46: ='3.2-1'!I80 -> 0 | J46: =SUM(F46:I46) -> 198611.47 | K46: =SUM(E46,J46) -> 258698.47 | L46: =$D46*E46 -> 300435 | M46: =$D46*(SUM(F46:I46)) -> 993057.37 | N46: =L46+M46 -> 1293492.4 | O46: =L46 -> 300435 | P46: =(P$110*M46)/M$110 -> 1678267 | Q46: =O46+P46 -> 1978702 | R46: =L46 -> 300435 | S46: =(S$110*P46)/P$110 -> 2265660.4 | T46: =R46+S46 -> 2566095.4 | U46: =E46 -> 60087 | V46: =Y46/D46 -> 490288.91 | W46: =U46+V46 -> 550375.91 | X46: =L46 -> 300435 | Y46: =(Y$110*S46)/S$110 -> 2451444.5 | Z46: =X46+Y46 -> 2751879.5
A47: 3.2-2 | B47: COLUMNAS H30 EN MEDIANERA SOBRE PRIMER PISO 60x15 | C47: unid. | D47: 6 | E47: ='3.2-2'!I22 -> 104427.08 | F47: ='3.2-2'!I36 -> 137500 | G47: ='3.2-2'!I50 -> 0 | H47: ='3.2-2'!I66 -> 19236.228 | I47: ='3.2-2'!I80 -> 0 | J47: =SUM(F47:I47) -> 156736.23 | K47: =SUM(E47,J47) -> 261163.31 | L47: =$D47*E47 -> 626562.5 | M47: =$D47*(SUM(F47:I47)) -> 940417.37 | N47: =L47+M47 -> 1566979.9 | O47: =L47 -> 626562.5 | P47: =(P$110*M47)/M$110 -> 1589305.4 | Q47: =O47+P47 -> 2215867.9 | R47: =L47 -> 626562.5 | S47: =(S$110*P47)/P$110 -> 2145562.2 | T47: =R47+S47 -> 2772124.7 | U47: =E47 -> 104427.08 | V47: =Y47/D47 -> 386916.39 | W47: =U47+V47 -> 491343.47 | X47: =L47 -> 626562.5 | Y47: =(Y$110*S47)/S$110 -> 2321498.3 | Z47: =X47+Y47 -> 2948060.8
A48: 3.2-3 | B48: VIGAS H30 SOBRE PRIMER PISO 15x45 (Hierros 2∅10 arriba, 3∅10 abajo con estribos ∅ 6 c/18) | C48: m | D48: 58 | E48: ='3.2-3'!I22 -> 20077.586 | F48: ='3.2-3'!I36 -> 34913.793 | G48: ='3.2-3'!I50 -> 0 | H48: ='3.2-3'!I66 -> 12970.254 | I48: ='3.2-3'!I80 -> 0 | J48: =SUM(F48:I48) -> 47884.047 | K48: =SUM(E48,J48) -> 67961.633 | L48: =$D48*E48 -> 1164500 | M48: =$D48*(SUM(F48:I48)) -> 2777274.7 | N48: =L48+M48 -> 3941774.7 | O48: =L48 -> 1164500 | P48: =(P$110*M48)/M$110 -> 4693594.3 | Q48: =O48+P48 -> 5858094.3 | R48: =L48 -> 1164500 | S48: =(S$110*P48)/P$110 -> 6336352.3 | T48: =R48+S48 -> 7500852.3 | U48: =E48 -> 20077.586 | V48: =Y48/D48 -> 118205.74 | W48: =U48+V48 -> 138283.33 | X48: =L48 -> 1164500 | Y48: =(Y$110*S48)/S$110 -> 6855933.2 | Z48: =X48+Y48 -> 8020433.2
A49: 3.2-4 | B49: LOSAS DE VIGUETAS SOBRE PRIMER PISO e=0,10cm | C49: m² | D49: 70 | E49: =' 3.2-4'!I22 -> 48924.514 | F49: =' 3.2-4'!I36 -> 21428.571 | G49: =' 3.2-4'!I50 -> 0 | H49: =' 3.2-4'!I64 -> 11590 | I49: =' 3.2-4'!I78 -> 0 | J49: =SUM(F49:I49) -> 33018.571 | K49: =SUM(E49,J49) -> 81943.086 | L49: =$D49*E49 -> 3424716 | M49: =$D49*(SUM(F49:I49)) -> 2311300 | N49: =L49+M49 -> 5736016 | O49: =L49 -> 3424716 | P49: =(P$110*M49)/M$110 -> 3906097 | Q49: =O49+P49 -> 7330813 | R49: =L49 -> 3424716 | S49: =(S$110*P49)/P$110 -> 5273231 | T49: =R49+S49 -> 8697946.9 | U49: =E49 -> 48924.514 | V49: =Y49/D49 -> 81509.084 | W49: =U49+V49 -> 130433.6 | X49: =L49 -> 3424716 | Y49: =(Y$110*S49)/S$110 -> 5705635.9 | Z49: =X49+Y49 -> 9130351.9
A50: CAJA DE ESCALERA
A51: 3.3-1 | B51: COLUMNAS H30 20x30 H=2,20m | C51: unid. | D51: 4 | E51: ='3.3-1'!I22 -> 76281.875 | F51: ='3.3-1'!I36 -> 112500 | G51: ='3.3-1'!I50 -> 0 | H51: ='3.3-1'!I66 -> 18854.342 | I51: ='3.3-1'!I80 -> 0 | J51: =SUM(F51:I51) -> 131354.34 | K51: =SUM(E51,J51) -> 207636.22 | L51: =$D51*E51 -> 305127.5 | M51: =$D51*(SUM(F51:I51)) -> 525417.37 | N51: =L51+M51 -> 830544.87 | O51: =L51 -> 305127.5 | P51: =(P$110*M51)/M$110 -> 887955.36 | Q51: =O51+P51 -> 1193082.9 | R51: =L51 -> 305127.5 | S51: =(S$110*P51)/P$110 -> 1198739.7 | T51: =R51+S51 -> 1503867.2 | U51: =E51 -> 76281.875 | V51: =Y51/D51 -> 324259.1 | W51: =U51+V51 -> 400540.97 | X51: =L51 -> 305127.5 | Y51: =(Y$110*S51)/S$110 -> 1297036.4 | Z51: =X51+Y51 -> 1602163.9
A52: 3.3-2 | B52: VIGAS H30 20x35 | C52: m | D52: 14 | E52: ='3.3-2'!I22 -> 25900.714 | F52: ='3.3-2'!I36 -> 37500 | G52: ='3.3-2'!I50 -> 0 | H52: ='3.3-2'!I66 -> 7400.8271 | I52: ='3.3-2'!I80 -> 0 | J52: =SUM(F52:I52) -> 44900.827 | K52: =SUM(E52,J52) -> 70801.541 | L52: =$D52*E52 -> 362610 | M52: =$D52*(SUM(F52:I52)) -> 628611.58 | N52: =L52+M52 -> 991221.58 | O52: =L52 -> 362610 | P52: =(P$110*M52)/M$110 -> 1062353.6 | Q52: =O52+P52 -> 1424963.6 | R52: =L52 -> 362610 | S52: =(S$110*P52)/P$110 -> 1434177.3 | T52: =R52+S52 -> 1796787.3 | U52: =E52 -> 25900.714 | V52: =Y52/D52 -> 110841.42 | W52: =U52+V52 -> 136742.13 | X52: =L52 -> 362610 | Y52: =(Y$110*S52)/S$110 -> 1551779.9 | Z52: =X52+Y52 -> 1914389.9
A53: 3.3-3 | B53: LOSAS DE VIGUETAS EN CAJA DE ESCALERAS e=0,08cm | C53: m² | D53: 7 | E53: ='3.3-3'!I22 -> 43382.857 | F53: ='3.3-3'!I36 -> 42857.143 | G53: ='3.3-3'!I50 -> 0 | H53: ='3.3-3'!I64 -> 0 | I53: ='3.3-3'!I78 -> 0 | J53: =SUM(F53:I53) -> 42857.143 | K53: =SUM(E53,J53) -> 86240 | L53: =$D53*E53 -> 303680 | M53: =$D53*(SUM(F53:I53)) -> 300000 | N53: =L53+M53 -> 603680 | O53: =L53 -> 303680 | P53: =(P$110*M53)/M$110 -> 507000 | Q53: =O53+P53 -> 810680 | R53: =L53 -> 303680 | S53: =(S$110*P53)/P$110 -> 684450 | T53: =R53+S53 -> 988130 | U53: =E53 -> 43382.857 | V53: =Y53/D53 -> 105796.41 | W53: =U53+V53 -> 149179.27 | X53: =L53 -> 303680 | Y53: =(Y$110*S53)/S$110 -> 740574.9 | Z53: =X53+Y53 -> 1044254.9
A54: 3.3-4 | B54: ESCALERA DE HORMIGON (con intrados recto) 90cm DE ANCHO | C54: gl | D54: 1 | E54: ='3.3-4'!I22 -> 572060 | F54: ='3.3-4'!I36 -> 2025000 | G54: ='3.3-4'!I50 -> 0 | H54: ='3.3-4'!I66 -> 296114.74 | I54: ='3.3-4'!I80 -> 0 | J54: =SUM(F54:I54) -> 2321114.7 | K54: =SUM(E54,J54) -> 2893174.7 | L54: =$D54*E54 -> 572060 | M54: =$D54*(SUM(F54:I54)) -> 2321114.7 | N54: =L54+M54 -> 2893174.7 | O54: =L54 -> 572060 | P54: =(P$110*M54)/M$110 -> 3922683.9 | Q54: =O54+P54 -> 4494743.9 | R54: =L54 -> 572060 | S54: =(S$110*P54)/P$110 -> 5295623.3 | T54: =R54+S54 -> 5867683.3 | U54: =E54 -> 572060 | V54: =Y54/D54 -> 5729864.4 | W54: =U54+V54 -> 6301924.4 | X54: =L54 -> 572060 | Y54: =(Y$110*S54)/S$110 -> 5729864.4 | Z54: =X54+Y54 -> 6301924.4
A55: 3.3-5 | B55: ESCALERA DE HORMIGON (con intrados recto) 90cm DE ANCHO | C55: gl | D55: 1 | E55: ='3.3-5'!I22 -> 563010 | F55: ='3.3-5'!I36 -> 2025000 | G55: ='3.3-5'!I50 -> 0 | H55: ='3.3-5'!I66 -> 260697.37 | I55: ='3.3-5'!I80 -> 0 | J55: =SUM(F55:I55) -> 2285697.4 | K55: =SUM(E55,J55) -> 2848707.4 | L55: =$D55*E55 -> 563010 | M55: =$D55*(SUM(F55:I55)) -> 2285697.4 | N55: =L55+M55 -> 2848707.4 | O55: =L55 -> 563010 | P55: =(P$110*M55)/M$110 -> 3862828.6 | Q55: =O55+P55 -> 4425838.6 | R55: =L55 -> 563010 | S55: =(S$110*P55)/P$110 -> 5214818.5 | T55: =R55+S55 -> 5777828.5 | U55: =E55 -> 563010 | V55: =Y55/D55 -> 5642433.7 | W55: =U55+V55 -> 6205443.7 | X55: =L55 -> 563010 | Y55: =(Y$110*S55)/S$110 -> 5642433.7 | Z55: =X55+Y55 -> 6205443.7
A56: 4-ALBAÑILERIA
A57: PLANTA BAJA
A58: 4.1-1 | B58: EJECUCION DE CAJON HIDROFUGO | C58: m | D58: 35 | E58: 10284 | F58: 13325 | G58: ='4.1-1'!I50 -> 0 | H58: ='4.1-1'!I64 -> 0 | I58: ='4.1-1'!I78 -> 0 | J58: =SUM(F58:I58) -> 13325 | K58: =SUM(E58,J58) -> 23609 | L58: =$D58*E58 -> 359940 | M58: =$D58*(SUM(F58:I58)) -> 466375 | N58: =L58+M58 -> 826315 | O58: =L58 -> 359940 | P58: =(P$110*M58)/M$110 -> 788173.75 | Q58: =O58+P58 -> 1148113.8 | R58: =L58 -> 359940 | S58: =(S$110*P58)/P$110 -> 1064034.6 | T58: =R58+S58 -> 1423974.6 | U58: =E58 -> 10284 | V58: =Y58/D58 -> 32893.868 | W58: =U58+V58 -> 43177.868 | X58: =L58 -> 359940 | Y58: =(Y$110*S58)/S$110 -> 1151285.4 | Z58: =X58+Y58 -> 1511225.4
A59: 4.1-2 | B59: EJECUCION DE MUROS DE LADRILLO VISTO EN FACHADA | C59: m² | D59: =(6.3*2.8)+27+(2.5*1.5) -> 48.39 | E59: ='4.1-2'!I22 -> 18863.002 | F59: ='4.1-2'!I36 -> 17048.977 | G59: ='4.1-2'!I50 -> 0 | H59: ='4.1-2'!I64 -> 3306.4683 | I59: ='4.1-2'!I78 -> 0 | J59: =SUM(F59:I59) -> 20355.445 | K59: =SUM(E59,J59) -> 39218.447 | L59: =$D59*E59 -> 912780.66 | M59: =$D59*(SUM(F59:I59)) -> 985000 | N59: =L59+M59 -> 1897780.7 | O59: =L59 -> 912780.66 | P59: =(P$110*M59)/M$110 -> 1664650 | Q59: =O59+P59 -> 2577430.7 | R59: =L59 -> 912780.66 | S59: =(S$110*P59)/P$110 -> 2247277.5 | T59: =R59+S59 -> 3160058.2 | U59: =E59 -> 18863.002 | V59: =Y59/D59 -> 50249.106 | W59: =U59+V59 -> 69112.108 | X59: =L59 -> 912780.66 | Y59: =(Y$110*S59)/S$110 -> 2431554.3 | Z59: =X59+Y59 -> 3344334.9
A60: 4.1-3 | B60: EJECUCION DE MURO DE LADRILLO VISTO EN COCINA (H- 1,20m) | C60: m² | D60: =5.7*1.2 -> 6.84 | E60: ='4.1-3'!I22 -> 15409.78 | F60: ='4.1-3'!I36 -> 24122.807 | G60: ='4.1-3'!I50 -> 0 | H60: ='4.1-3'!I64 -> 0 | I60: ='4.1-3'!I78 -> 0 | J60: =SUM(F60:I60) -> 24122.807 | K60: =SUM(E60,J60) -> 39532.587 | L60: =$D60*E60 -> 105402.89 | M60: =$D60*(SUM(F60:I60)) -> 165000 | N60: =L60+M60 -> 270402.89 | O60: =L60 -> 105402.89 | P60: =(P$110*M60)/M$110 -> 278850 | Q60: =O60+P60 -> 384252.89 | R60: =L60 -> 105402.89 | S60: =(S$110*P60)/P$110 -> 376447.5 | T60: =R60+S60 -> 481850.39 | U60: =E60 -> 15409.78 | V60: =Y60/D60 -> 59549.151 | W60: =U60+V60 -> 74958.931 | X60: =L60 -> 105402.89 | Y60: =(Y$110*S60)/S$110 -> 407316.2 | Z60: =X60+Y60 -> 512719.09
A61: 4.1-4 | B61: EJECUCION DE MURO DE LADRILLO VISTO EN PARED LIVING COMEDOR Y LAVADERO. H=3m | C61: m² | D61: =4*3 -> 12 | E61: ='4.1-4'!I22 -> 15278.409 | F61: ='4.1-4'!I36 -> 13750 | G61: ='4.1-4'!I50 -> 0 | H61: ='4.1-4'!I64 -> 0 | I61: ='4.1-4'!I78 -> 0 | J61: =SUM(F61:I61) -> 13750 | K61: =SUM(E61,J61) -> 29028.409 | L61: =$D61*E61 -> 183340.91 | M61: =$D61*(SUM(F61:I61)) -> 165000 | N61: =L61+M61 -> 348340.91 | O61: =L61 -> 183340.91 | P61: =(P$110*M61)/M$110 -> 278850 | Q61: =O61+P61 -> 462190.91 | R61: =L61 -> 183340.91 | S61: =(S$110*P61)/P$110 -> 376447.5 | T61: =R61+S61 -> 559788.41 | U61: =E61 -> 15278.409 | V61: =Y61/D61 -> 33943.016 | W61: =U61+V61 -> 49221.425 | X61: =L61 -> 183340.91 | Y61: =(Y$110*S61)/S$110 -> 407316.2 | Z61: =X61+Y61 -> 590657.1
A62: 4.1-5 | B62: EJECUCION DE MUROS DE LADRILLO HUECO DEL 8. H= 3,50m | C62: m² | D62: =4*3.5 -> 14 | E62: ='4.1-5'!I22 -> 14932.836 | F62: ='4.1-5'!I36 -> 21428.571 | G62: ='4.1-5'!I50 -> 0 | H62: ='4.1-5'!I64 -> 0 | I62: ='4.1-5'!I78 -> 0 | J62: =SUM(F62:I62) -> 21428.571 | K62: =SUM(E62,J62) -> 36361.407 | L62: =$D62*E62 -> 209059.7 | M62: =$D62*(SUM(F62:I62)) -> 300000 | N62: =L62+M62 -> 509059.7 | O62: =L62 -> 209059.7 | P62: =(P$110*M62)/M$110 -> 507000 | Q62: =O62+P62 -> 716059.7 | R62: =L62 -> 209059.7 | S62: =(S$110*P62)/P$110 -> 684450 | T62: =R62+S62 -> 893509.7 | U62: =E62 -> 14932.836 | V62: =Y62/D62 -> 52898.207 | W62: =U62+V62 -> 67831.043 | X62: =L62 -> 209059.7 | Y62: =(Y$110*S62)/S$110 -> 740574.9 | Z62: =X62+Y62 -> 949634.6
A63: 4.1-6 | B63: EJECUCION DE MUROS DE LADRILLO HUECO DEL 12. H= 3m | C63: m² | D63: =D61+(2.5*3)+(2.9*15) -> 63 | E63: ='4.1-6'!I22 -> 16917.46 | F63: ='4.1-6'!I36 -> 19047.619 | G63: ='4.1-6'!I50 -> 0 | H63: ='4.1-6'!I64 -> 1904.7619 | I63: ='4.1-6'!I78 -> 0 | J63: =SUM(F63:I63) -> 20952.381 | K63: =SUM(E63,J63) -> 37869.841 | L63: =$D63*E63 -> 1065800 | M63: =$D63*(SUM(F63:I63)) -> 1320000 | N63: =L63+M63 -> 2385800 | O63: =L63 -> 1065800 | P63: =(P$110*M63)/M$110 -> 2230800 | Q63: =O63+P63 -> 3296600 | R63: =L63 -> 1065800 | S63: =(S$110*P63)/P$110 -> 3011580 | T63: =R63+S63 -> 4077380 | U63: =E63 -> 16917.46 | V63: =Y63/D63 -> 51722.691 | W63: =U63+V63 -> 68640.152 | X63: =L63 -> 1065800 | Y63: =(Y$110*S63)/S$110 -> 3258529.6 | Z63: =X63+Y63 -> 4324329.6
A64: 4.1-7 | B64: EJECUCION DE REVOQUE GRUESO + FINO EN INTERIOR | C64: m² | D64: =D63+(D62*2)+D60+D61+D59 -> 158.23 | E64: =' 4.1-7'!I22 -> 5530.4586 | F64: =' 4.1-7'!I36 -> 12797.826 | G64: =' 4.1-7'!I50 -> 0 | H64: =' 4.1-7'!I64 -> 0 | I64: =' 4.1-7'!I78 -> 0 | J64: =SUM(F64:I64) -> 12797.826 | K64: =SUM(E64,J64) -> 18328.285 | L64: =$D64*E64 -> 875084.46 | M64: =$D64*(SUM(F64:I64)) -> 2025000 | N64: =L64+M64 -> 2900084.5 | O64: =L64 -> 875084.46 | P64: =(P$110*M64)/M$110 -> 3422250 | Q64: =O64+P64 -> 4297334.5 | R64: =L64 -> 875084.46 | S64: =(S$110*P64)/P$110 -> 4620037.5 | T64: =R64+S64 -> 5495122 | U64: =E64 -> 5530.4586 | V64: =Y64/D64 -> 31592.496 | W64: =U64+V64 -> 37122.954 | X64: =L64 -> 875084.46 | Y64: =(Y$110*S64)/S$110 -> 4998880.6 | Z64: =X64+Y64 -> 5873965
A65: 4.1-8 | B65: EJECUCION DE REVOQUE EXTERIOR EN MUROS | C65: m² | D65: =(2.9*1.5)+(0.8+0.8*2) -> 6.75 | E65: ='4.1-8'!I22 -> 14787.805 | F65: ='4.1-8'!I36 -> 24444.444 | G65: ='4.1-8'!I50 -> 0 | H65: ='4.1-8'!I64 -> 0 | I65: ='4.1-8'!I78 -> 0 | J65: =SUM(F65:I65) -> 24444.444 | K65: =SUM(E65,J65) -> 39232.25 | L65: =$D65*E65 -> 99817.686 | M65: =$D65*(SUM(F65:I65)) -> 165000 | N65: =L65+M65 -> 264817.69 | O65: =L65 -> 99817.686 | P65: =(P$110*M65)/M$110 -> 278850 | Q65: =O65+P65 -> 378667.69 | R65: =L65 -> 99817.686 | S65: =(S$110*P65)/P$110 -> 376447.5 | T65: =R65+S65 -> 476265.19 | U65: =E65 -> 14787.805 | V65: =Y65/D65 -> 60343.14 | W65: =U65+V65 -> 75130.945 | X65: =L65 -> 99817.686 | Y65: =(Y$110*S65)/S$110 -> 407316.2 | Z65: =X65+Y65 -> 507133.88
A66: 4.1-9 | B66: EJECUCION DE RECUADRO DE VANOS CARPINTERIAS | C66: unid. | D66: 10 | E66: ='4.1-9'!I22 -> 10753 | F66: ='4.1-9'!I36 -> 82500 | G66: ='4.1-9'!I50 -> 0 | H66: ='4.1-9'!I64 -> 0 | I66: ='4.1-9'!I78 -> 0 | J66: =SUM(F66:I66) -> 82500 | K66: =SUM(E66,J66) -> 93253 | L66: =$D66*E66 -> 107530 | M66: =$D66*(SUM(F66:I66)) -> 825000 | N66: =L66+M66 -> 932530 | O66: =L66 -> 107530 | P66: =(P$110*M66)/M$110 -> 1394250 | Q66: =O66+P66 -> 1501780 | R66: =L66 -> 107530 | S66: =(S$110*P66)/P$110 -> 1882237.5 | T66: =R66+S66 -> 1989767.5 | U66: =E66 -> 10753 | V66: =Y66/D66 -> 203658.1 | W66: =U66+V66 -> 214411.1 | X66: =L66 -> 107530 | Y66: =(Y$110*S66)/S$110 -> 2036581 | Z66: =X66+Y66 -> 2144111
A67: 4.1-10 | B67: EJECUCION DE CONTRAPISO 8cm DE HORMIGON H8 CON MALLA EN INTERIOR | C67: m² | D67: 77 | E67: ='4.1-10'!I22 -> 14592.895 | F67: 7135.14 | G67: ='4.1-10'!I50 -> 0 | H67: ='4.1-10'!I64 -> 0 | I67: ='4.1-10'!I78 -> 0 | J67: =SUM(F67:I67) -> 7135.14 | K67: =SUM(E67,J67) -> 21728.035 | L67: =$D67*E67 -> 1123652.9 | M67: =$D67*(SUM(F67:I67)) -> 549405.78 | N67: =L67+M67 -> 1673058.7 | O67: =L67 -> 1123652.9 | P67: =(P$110*M67)/M$110 -> 928495.77 | Q67: =O67+P67 -> 2052148.7 | R67: =L67 -> 1123652.9 | S67: =(S$110*P67)/P$110 -> 1253469.3 | T67: =R67+S67 -> 2377122.2 | U67: =E67 -> 14592.895 | V67: =Y67/D67 -> 17613.685 | W67: =U67+V67 -> 32206.58 | X67: =L67 -> 1123652.9 | Y67: =(Y$110*S67)/S$110 -> 1356253.8 | Z67: =X67+Y67 -> 2479906.7
A68: 4.1-11 | B68: EJECUCION DE CARPETA NIVELADORA INTERIOR + EXTERIOR | C68: m² | D68: =D31-D24 -> 109 | E68: ='4.1-11'!I22 -> 3309.8165 | F68: ='4.1-11'!I36 -> 11009.174 | G68: ='4.1-11'!I50 -> 0 | H68: ='4.1-11'!I64 -> 0 | I68: ='4.1-11'!I78 -> 0 | J68: =SUM(F68:I68) -> 11009.174 | K68: =SUM(E68,J68) -> 14318.991 | L68: =$D68*E68 -> 360770 | M68: =$D68*(SUM(F68:I68)) -> 1200000 | N68: =L68+M68 -> 1560770 | O68: =L68 -> 360770 | P68: =(P$110*M68)/M$110 -> 2028000 | Q68: =O68+P68 -> 2388770 | R68: =L68 -> 360770 | S68: =(S$110*P68)/P$110 -> 2737800 | T68: =R68+S68 -> 3098570 | U68: =E68 -> 3309.8165 | V68: =Y68/D68 -> 27177.061 | W68: =U68+V68 -> 30486.877 | X68: =L68 -> 360770 | Y68: =(Y$110*S68)/S$110 -> 2962299.6 | Z68: =X68+Y68 -> 3323069.6
A69: 4.1-12 | B69: RECUADRO DE ESCALERA | C69: m² | D69: 8.5 | E69: ='4.1-12'!I22 -> 5434.1176 | F69: ='4.1-12'!I36 -> 26470.588 | G69: ='4.1-12'!I50 -> 0 | H69: ='4.1-12'!I64 -> 0 | I69: ='4.1-12'!I78 -> 0 | J69: =SUM(F69:I69) -> 26470.588 | K69: =SUM(E69,J69) -> 31904.706 | L69: =$D69*E69 -> 46190 | M69: =$D69*(SUM(F69:I69)) -> 225000 | N69: =L69+M69 -> 271190 | O69: =L69 -> 46190 | P69: =(P$110*M69)/M$110 -> 380250 | Q69: =O69+P69 -> 426440 | R69: =L69 -> 46190 | S69: =(S$110*P69)/P$110 -> 513337.5 | T69: =R69+S69 -> 559527.5 | U69: =E69 -> 5434.1176 | V69: =Y69/D69 -> 65344.844 | W69: =U69+V69 -> 70778.962 | X69: =L69 -> 46190 | Y69: =(Y$110*S69)/S$110 -> 555431.18 | Z69: =X69+Y69 -> 601621.18
A70: PLANTA PRIMER PISO
A71: 4.2-1 | B71: EJECUCION DE MUROS DE LADRILLO PORTANTE DEL 12 EXTERIOR. H=2,5m | C71: m² | D71: =(27*2.5)+11.88 -> 79.38 | E71: ='4.2-1'!I22 -> 22169.211 | F71: ='4.2-1'!I36 -> 22675.737 | G71: ='4.2-1'!I50 -> 0 | H71: ='4.2-1'!I64 -> 2015.6211 | I71: ='4.2-1'!I78 -> 0 | J71: =SUM(F71:I71) -> 24691.358 | K71: =SUM(E71,J71) -> 46860.569 | L71: =$D71*E71 -> 1759792 | M71: =$D71*(SUM(F71:I71)) -> 1960000 | N71: =L71+M71 -> 3719792 | O71: =L71 -> 1759792 | P71: =(P$110*M71)/M$110 -> 3312400 | Q71: =O71+P71 -> 5072192 | R71: =L71 -> 1759792 | S71: =(S$110*P71)/P$110 -> 4471740 | T71: =R71+S71 -> 6231532 | U71: =E71 -> 22169.211 | V71: =Y71/D71 -> 60952.667 | W71: =U71+V71 -> 83121.878 | X71: =L71 -> 1759792 | Y71: =(Y$110*S71)/S$110 -> 4838422.7 | Z71: =X71+Y71 -> 6598214.7
A72: 4.2-2 | B72: EJECUCION DE MUROS DE LADRILLO PORTANTE DEL 12 INTERIOR. H=2,5m | C72: m² | D72: =(30*2.5)-7.2 -> 67.8 | E72: ='4.2-2'!I22 -> 22366.428 | F72: ='4.2-2'!I36 -> 22123.894 | G72: ='4.2-2'!I50 -> 0 | H72: ='4.2-2'!I64 -> 1769.9115 | I72: ='4.2-2'!I78 -> 0 | J72: =SUM(F72:I72) -> 23893.805 | K72: =SUM(E72,J72) -> 46260.233 | L72: =$D72*E72 -> 1516443.8 | M72: =$D72*(SUM(F72:I72)) -> 1620000 | N72: =L72+M72 -> 3136443.8 | O72: =L72 -> 1516443.8 | P72: =(P$110*M72)/M$110 -> 2737800 | Q72: =O72+P72 -> 4254243.8 | R72: =L72 -> 1516443.8 | S72: =(S$110*P72)/P$110 -> 3696030 | T72: =R72+S72 -> 5212473.8 | U72: =E72 -> 22366.428 | V72: =Y72/D72 -> 58983.842 | W72: =U72+V72 -> 81350.269 | X72: =L72 -> 1516443.8 | Y72: =(Y$110*S72)/S$110 -> 3999104.5 | Z72: =X72+Y72 -> 5515548.3
A73: 4.2-3 | B73: EJECUCION DE REVOQUE GRUESO + FINO EN INTERIOR | C73: m² | D73: =D71+(D72*2) -> 214.98 | E73: ='4.2-3'!I22 -> 5618.2528 | F73: ='4.2-3'!I36 -> 12559.308 | G73: ='4.2-3'!I50 -> 0 | H73: ='4.2-3'!I64 -> 0 | I73: ='4.2-3'!I78 -> 0 | J73: =SUM(F73:I73) -> 12559.308 | K73: =SUM(E73,J73) -> 18177.561 | L73: =$D73*E73 -> 1207812 | M73: =$D73*(SUM(F73:I73)) -> 2700000 | N73: =L73+M73 -> 3907812 | O73: =L73 -> 1207812 | P73: =(P$110*M73)/M$110 -> 4563000 | Q73: =O73+P73 -> 5770812 | R73: =L73 -> 1207812 | S73: =(S$110*P73)/P$110 -> 6160050 | T73: =R73+S73 -> 7367862 | U73: =E73 -> 5618.2528 | V73: =Y73/D73 -> 31003.694 | W73: =U73+V73 -> 36621.947 | X73: =L73 -> 1207812 | Y73: =(Y$110*S73)/S$110 -> 6665174.1 | Z73: =X73+Y73 -> 7872986.1
A74: 4.2-4 | B74: EJECUCION DE REVOQUE EXTERIOR EN MUROS. H=2,5m | C74: m² | D74: =D71 -> 79.38 | E74: ='4.2-4'!I22 -> 5155.714 | F74: ='4.2-4'!I36 -> 15117.158 | G74: ='4.2-4'!I50 -> 0 | H74: ='4.2-4'!I64 -> 0 | I74: ='4.2-4'!I78 -> 0 | J74: =SUM(F74:I74) -> 15117.158 | K74: =SUM(E74,J74) -> 20272.872 | L74: =$D74*E74 -> 409260.58 | M74: =$D74*(SUM(F74:I74)) -> 1200000 | N74: =L74+M74 -> 1609260.6 | O74: =L74 -> 409260.58 | P74: =(P$110*M74)/M$110 -> 2028000 | Q74: =O74+P74 -> 2437260.6 | R74: =L74 -> 409260.58 | S74: =(S$110*P74)/P$110 -> 2737800 | T74: =R74+S74 -> 3147060.6 | U74: =E74 -> 5155.714 | V74: =Y74/D74 -> 37317.959 | W74: =U74+V74 -> 42473.673 | X74: =L74 -> 409260.58 | Y74: =(Y$110*S74)/S$110 -> 2962299.6 | Z74: =X74+Y74 -> 3371560.2
A75: 4.2-5 | B75: EJECUCION DE RECUADRO DE VANOS CARPINTERIAS | C75: unid. | D75: 12 | E75: ='4.2-5'!I22 -> 10223.333 | F75: ='4.2-5'!I36 -> 68750 | G75: ='4.2-5'!I50 -> 0 | H75: ='4.2-5'!I64 -> 0 | I75: ='4.2-5'!I78 -> 0 | J75: =SUM(F75:I75) -> 68750 | K75: =SUM(E75,J75) -> 78973.333 | L75: =$D75*E75 -> 122680 | M75: =$D75*(SUM(F75:I75)) -> 825000 | N75: =L75+M75 -> 947680 | O75: =L75 -> 122680 | P75: =(P$110*M75)/M$110 -> 1394250 | Q75: =O75+P75 -> 1516930 | R75: =L75 -> 122680 | S75: =(S$110*P75)/P$110 -> 1882237.5 | T75: =R75+S75 -> 2004917.5 | U75: =E75 -> 10223.333 | V75: =Y75/D75 -> 169715.08 | W75: =U75+V75 -> 179938.41 | X75: =L75 -> 122680 | Y75: =(Y$110*S75)/S$110 -> 2036581 | Z75: =X75+Y75 -> 2159261
A76: 4.2-6 | B76: EJECUCION DE CONTRAPISOS DE HORMIGON H8 CON MALLA Y ASILACION HIDROFUGA (INTERIOR) | C76: m² | D76: =D49 -> 70 | E76: ='4.2-6'!I22 -> 18033.471 | F76: 7135.14 | G76: ='4.2-6'!I50 -> 0 | H76: ='4.2-6'!I64 -> 0 | I76: ='4.2-6'!I78 -> 0 | J76: =SUM(F76:I76) -> 7135.14 | K76: =SUM(E76,J76) -> 25168.611 | L76: =$D76*E76 -> 1262343 | M76: =$D76*(SUM(F76:I76)) -> 499459.8 | N76: =L76+M76 -> 1761802.8 | O76: =L76 -> 1262343 | P76: =(P$110*M76)/M$110 -> 844087.06 | Q76: =O76+P76 -> 2106430 | R76: =L76 -> 1262343 | S76: =(S$110*P76)/P$110 -> 1139517.5 | T76: =R76+S76 -> 2401860.5 | U76: =E76 -> 18033.471 | V76: =Y76/D76 -> 17613.685 | W76: =U76+V76 -> 35647.156 | X76: =L76 -> 1262343 | Y76: =(Y$110*S76)/S$110 -> 1232958 | Z76: =X76+Y76 -> 2495300.9
A77: 4.2-7 | B77: EJECUCION DE CARPETA NIVELADORA | C77: m² | D77: =D76 -> 70 | E77: =' 4.2-7'!I22 -> 3411.8571 | F77: =' 4.2-7'!I36 -> 11785.714 | G77: =' 4.2-7'!I50 -> 0 | H77: =' 4.2-7'!I64 -> 0 | I77: =' 4.2-7'!I78 -> 0 | J77: =SUM(F77:I77) -> 11785.714 | K77: =SUM(E77,J77) -> 15197.571 | L77: =$D77*E77 -> 238830 | M77: =$D77*(SUM(F77:I77)) -> 825000 | N77: =L77+M77 -> 1063830 | O77: =L77 -> 238830 | P77: =(P$110*M77)/M$110 -> 1394250 | Q77: =O77+P77 -> 1633080 | R77: =L77 -> 238830 | S77: =(S$110*P77)/P$110 -> 1882237.5 | T77: =R77+S77 -> 2121067.5 | U77: =E77 -> 3411.8571 | V77: =Y77/D77 -> 29094.014 | W77: =U77+V77 -> 32505.871 | X77: =L77 -> 238830 | Y77: =(Y$110*S77)/S$110 -> 2036581 | Z77: =X77+Y77 -> 2275411
A78: CAJA DE ESCALERA
A79: 4.3-1 | B79: EJECUCION DE MUROS DE LADRILLO PORTANTE DEL 15 EXTERIOR. H=2,2m | C79: m² | D79: =14*2.2 -> 30.8 | E79: ='4.3-1'!I22 -> 22049.734 | F79: ='4.3-1'!I36 -> 17045.455 | G79: ='4.3-1'!I50 -> 0 | H79: ='4.3-1'!I64 -> 0 | I79: ='4.3-1'!I78 -> 0 | J79: =SUM(F79:I79) -> 17045.455 | K79: =SUM(E79,J79) -> 39095.188 | L79: =$D79*E79 -> 679131.8 | M79: =$D79*(SUM(F79:I79)) -> 525000 | N79: =L79+M79 -> 1204131.8 | O79: =L79 -> 679131.8 | P79: =(P$110*M79)/M$110 -> 887250 | Q79: =O79+P79 -> 1566381.8 | R79: =L79 -> 679131.8 | S79: =(S$110*P79)/P$110 -> 1197787.5 | T79: =R79+S79 -> 1876919.3 | U79: =E79 -> 22049.734 | V79: =Y79/D79 -> 42078.119 | W79: =U79+V79 -> 64127.853 | X79: =L79 -> 679131.8 | Y79: =(Y$110*S79)/S$110 -> 1296006.1 | Z79: =X79+Y79 -> 1975137.9
A80: 4.3-2 | B80: EJECUCION DE REVOQUE GRUESO + FINO EN INTERIOR | C80: m² | D80: =D79 -> 30.8 | E80: ='4.3-2'!I22 -> 6596.179 | F80: ='4.3-2'!I36 -> 17045.455 | G80: ='4.3-2'!I50 -> 0 | H80: ='4.3-2'!I64 -> 0 | I80: ='4.3-2'!I78 -> 0 | J80: =SUM(F80:I80) -> 17045.455 | K80: =SUM(E80,J80) -> 23641.634 | L80: =$D80*E80 -> 203162.31 | M80: =$D80*(SUM(F80:I80)) -> 525000 | N80: =L80+M80 -> 728162.31 | O80: =L80 -> 203162.31 | P80: =(P$110*M80)/M$110 -> 887250 | Q80: =O80+P80 -> 1090412.3 | R80: =L80 -> 203162.31 | S80: =(S$110*P80)/P$110 -> 1197787.5 | T80: =R80+S80 -> 1400949.8 | U80: =E80 -> 6596.179 | V80: =Y80/D80 -> 42078.119 | W80: =U80+V80 -> 48674.298 | X80: =L80 -> 203162.31 | Y80: =(Y$110*S80)/S$110 -> 1296006.1 | Z80: =X80+Y80 -> 1499168.4
A81: 4.3-3 | B81: EJECUCION DE REVOQUE EXTERIOR EN MUROS. H=2,5m | C81: m² | D81: =D79 -> 30.8 | E81: ='4.3-3'!I22 -> 7290.8635 | F81: ='4.3-3'!I36 -> 7305.1948 | G81: ='4.3-3'!I50 -> 0 | H81: ='4.3-3'!I64 -> 0 | I81: ='4.3-3'!I78 -> 0 | J81: =SUM(F81:I81) -> 7305.1948 | K81: =SUM(E81,J81) -> 14596.058 | L81: =$D81*E81 -> 224558.6 | M81: =$D81*(SUM(F81:I81)) -> 225000 | N81: =L81+M81 -> 449558.59 | O81: =L81 -> 224558.6 | P81: =(P$110*M81)/M$110 -> 380250 | Q81: =O81+P81 -> 604808.59 | R81: =L81 -> 224558.6 | S81: =(S$110*P81)/P$110 -> 513337.5 | T81: =R81+S81 -> 737896.09 | U81: =E81 -> 7290.8635 | V81: =Y81/D81 -> 18033.48 | W81: =U81+V81 -> 25324.343 | X81: =L81 -> 224558.6 | Y81: =(Y$110*S81)/S$110 -> 555431.18 | Z81: =X81+Y81 -> 779989.77
A82: 4.3-4 | B82: EJECUCION DE RECUADRO DE VANOS CARPINTERIAS | C82: m | D82: 2 | E82: ='4.3-4'!I22 -> 20570 | F82: ='4.3-4'!I36 -> 45000 | G82: ='4.3-4'!I50 -> 0 | H82: ='4.3-4'!I64 -> 0 | I82: ='4.3-4'!I78 -> 0 | J82: =SUM(F82:I82) -> 45000 | K82: =SUM(E82,J82) -> 65570 | L82: =$D82*E82 -> 41140 | M82: =$D82*(SUM(F82:I82)) -> 90000 | N82: =L82+M82 -> 131140 | O82: =L82 -> 41140 | P82: =(P$110*M82)/M$110 -> 152100 | Q82: =O82+P82 -> 193240 | R82: =L82 -> 41140 | S82: =(S$110*P82)/P$110 -> 205335 | T82: =R82+S82 -> 246475 | U82: =E82 -> 20570 | V82: =Y82/D82 -> 111086.24 | W82: =U82+V82 -> 131656.23 | X82: =L82 -> 41140 | Y82: =(Y$110*S82)/S$110 -> 222172.47 | Z82: =X82+Y82 -> 263312.47
A83: 4.3-5 | B83: RECUADRO DE ESCALERAS | C83: m² | D83: 8 | E83: ='4.3-5'!I22 -> 11455 | F83: ='4.3-5'!I36 -> 65625 | G83: ='4.3-5'!I50 -> 0 | H83: ='4.3-5'!I64 -> 0 | I83: ='4.3-5'!I78 -> 0 | J83: =SUM(F83:I83) -> 65625 | K83: =SUM(E83,J83) -> 77080 | L83: =$D83*E83 -> 91640 | M83: =$D83*(SUM(F83:I83)) -> 525000 | N83: =L83+M83 -> 616640 | O83: =L83 -> 91640 | P83: =(P$110*M83)/M$110 -> 887250 | Q83: =O83+P83 -> 978890 | R83: =L83 -> 91640 | S83: =(S$110*P83)/P$110 -> 1197787.5 | T83: =R83+S83 -> 1289427.5 | U83: =E83 -> 11455 | V83: =Y83/D83 -> 162000.76 | W83: =U83+V83 -> 173455.76 | X83: =L83 -> 91640 | Y83: =(Y$110*S83)/S$110 -> 1296006.1 | Z83: =X83+Y83 -> 1387646.1
A84: 5-INSTALACIONES
A85: SANITARIA
A86: 5.1-1 | B86: EJECUCION DE INSTALACION CLOACAL SEGUN PLANO Incluye Tendido de Caños, Instalacion de Rejillas, LLP y Camara de Inspeccion) | C86: gl | D86: 1 | E86: =' 5.1-1'!I22 -> 402121.95 | F86: =' 5.1-1'!I36 -> 2700000 | G86: =' 5.1-1'!I50 -> 0 | H86: =' 5.1-1'!I64 -> 0 | I86: =' 5.1-1'!I78 -> 0 | J86: =SUM(F86:I86) -> 2700000 | K86: =SUM(E86,J86) -> 3102122 | L86: =$D86*E86 -> 402121.95 | M86: =$D86*(SUM(F86:I86)) -> 2700000 | N86: =L86+M86 -> 3102122 | O86: =L86 -> 402121.95 | P86: =(P$110*M86)/M$110 -> 4563000 | Q86: =O86+P86 -> 4965122 | R86: =L86 -> 402121.95 | S86: =(S$110*P86)/P$110 -> 6160050 | T86: =R86+S86 -> 6562172 | U86: =E86 -> 402121.95 | V86: =Y86/D86 -> 6665174.1 | W86: =U86+V86 -> 7067296.1 | X86: =L86 -> 402121.95 | Y86: =(Y$110*S86)/S$110 -> 6665174.1 | Z86: =X86+Y86 -> 7067296.1
A87: 5.1-2 | B87: EJECUCION DE INSTALACION DE AGUA FRIA (Incluye tendido de caños, llaves de paso, tanque) NO INCLUYE BOMBAS | C87: gl | D87: 1 | E87: ='5.1-2'!I22 -> 905400 | F87: ='5.1-2'!I36 -> 1740000 | G87: ='5.1-2'!I50 -> 0 | H87: ='5.1-2'!I64 -> 0 | I87: ='5.1-2'!I78 -> 0 | J87: =SUM(F87:I87) -> 1740000 | K87: =SUM(E87,J87) -> 2645400 | L87: =$D87*E87 -> 905400 | M87: =$D87*(SUM(F87:I87)) -> 1740000 | N87: =L87+M87 -> 2645400 | O87: =L87 -> 905400 | P87: =(P$110*M87)/M$110 -> 2940600 | Q87: =O87+P87 -> 3846000 | R87: =L87 -> 905400 | S87: =(S$110*P87)/P$110 -> 3969810 | T87: =R87+S87 -> 4875210 | U87: =E87 -> 905400 | V87: =Y87/D87 -> 4295334.4 | W87: =U87+V87 -> 5200734.4 | X87: =L87 -> 905400 | Y87: =(Y$110*S87)/S$110 -> 4295334.4 | Z87: =X87+Y87 -> 5200734.4
A88: 5.1-3 | B88: EJECUCION DE INSTALACION DE AGUA CALIENTE (Incluye tendido de caños, llaves de paso) NO INCLUYE TERMOTANQUE | C88: gl | D88: 1 | E88: ='5.1-3'!I22 -> 276000 | F88: ='5.1-3'!I36 -> 1500000 | G88: ='5.1-3'!I50 -> 0 | H88: ='5.1-3'!I64 -> 0 | I88: ='5.1-3'!I78 -> 0 | J88: =SUM(F88:I88) -> 1500000 | K88: =SUM(E88,J88) -> 1776000 | L88: =$D88*E88 -> 276000 | M88: =$D88*(SUM(F88:I88)) -> 1500000 | N88: =L88+M88 -> 1776000 | O88: =L88 -> 276000 | P88: =(P$110*M88)/M$110 -> 2535000 | Q88: =O88+P88 -> 2811000 | R88: =L88 -> 276000 | S88: =(S$110*P88)/P$110 -> 3422250 | T88: =R88+S88 -> 3698250 | U88: =E88 -> 276000 | V88: =Y88/D88 -> 3702874.5 | W88: =U88+V88 -> 3978874.5 | X88: =L88 -> 276000 | Y88: =(Y$110*S88)/S$110 -> 3702874.5 | Z88: =X88+Y88 -> 3978874.5
A89: 5.1-4 | B89: EJECUCION DE INSTALACION PLUVIAL (Incluye tendido de caños) | C89: gl | D89: 1 | E89: ='5.1-4'!I22 -> 278000 | F89: ='5.1-4'!I36 -> 1200000 | G89: ='5.1-4'!I50 -> 0 | H89: ='5.1-4'!I64 -> 0 | I89: ='5.1-4'!I78 -> 0 | J89: =SUM(F89:I89) -> 1200000 | K89: =SUM(E89,J89) -> 1478000 | L89: =$D89*E89 -> 278000 | M89: =$D89*(SUM(F89:I89)) -> 1200000 | N89: =L89+M89 -> 1478000 | O89: =L89 -> 278000 | P89: =(P$110*M89)/M$110 -> 2028000 | Q89: =O89+P89 -> 2306000 | R89: =L89 -> 278000 | S89: =(S$110*P89)/P$110 -> 2737800 | T89: =R89+S89 -> 3015800 | U89: =E89 -> 278000 | V89: =Y89/D89 -> 2962299.6 | W89: =U89+V89 -> 3240299.6 | X89: =L89 -> 278000 | Y89: =(Y$110*S89)/S$110 -> 2962299.6 | Z89: =X89+Y89 -> 3240299.6
A90: 5.1-5 | B90: COLOCACION DE ARTEFACTOS SANITARIOS (3 Bachas Bano, 1 Bacha Cocina, 3 Indoros, 2 Bidet, 2 Duchas) Incluye griferias. | C90: unid | D90: 11 | E90: ='5.1-5'!I22 -> 501818.18 | F90: 27777.78 | G90: ='5.1-5'!I50 -> 0 | H90: ='5.1-5'!I64 -> 0 | I90: ='5.1-5'!I78 -> 0 | J90: =SUM(F90:I90) -> 27777.78 | K90: =SUM(E90,J90) -> 529595.96 | L90: =$D90*E90 -> 5520000 | M90: =$D90*(SUM(F90:I90)) -> 305555.58 | N90: =L90+M90 -> 5825555.6 | O90: =L90 -> 5520000 | P90: =(P$110*M90)/M$110 -> 516388.93 | Q90: =O90+P90 -> 6036388.9 | R90: =L90 -> 5520000 | S90: =(S$110*P90)/P$110 -> 697125.06 | T90: =R90+S90 -> 6217125.1 | U90: =E90 -> 501818.18 | V90: =Y90/D90 -> 68571.755 | W90: =U90+V90 -> 570389.94 | X90: =L90 -> 5520000 | Y90: =(Y$110*S90)/S$110 -> 754289.31 | Z90: =X90+Y90 -> 6274289.3
A91: ELECTRICA
A92: 5.2-1 | B92: INSTALACION DE TABLERO + PUESTA A TIERRA | C92: gl | D92: 1 | E92: 2000000 | I92: 1000000 | J92: =SUM(F92:I92) -> 1000000 | K92: =SUM(E92,J92) -> 3000000 | L92: =$D92*E92 -> 2000000 | M92: =$D92*(SUM(F92:I92)) -> 1000000 | N92: =L92+M92 -> 3000000 | O92: =L92 -> 2000000 | P92: =(P$110*M92)/M$110 -> 1690000 | Q92: =O92+P92 -> 3690000 | R92: =L92 -> 2000000 | S92: =(S$110*P92)/P$110 -> 2281500 | T92: =R92+S92 -> 4281500 | U92: =E92 -> 2000000 | V92: =Y92/D92 -> 2468583 | W92: =U92+V92 -> 4468583 | X92: =L92 -> 2000000 | Y92: =(Y$110*S92)/S$110 -> 2468583 | Z92: =X92+Y92 -> 4468583
A93: 5.2-2 | B93: EJECUCION DE BOCAS (CAJA,CABLEADO Y CANOS) | C93: unid | D93: 38 | E93: 49717.74 | F93: $ - | G93: $ - | H93: $ - | I93: 30040.32 | J93: =SUM(F93:I93) -> 30040.32 | K93: =SUM(E93,J93) -> 79758.06 | L93: =$D93*E93 -> 1889274.1 | M93: =$D93*(SUM(F93:I93)) -> 1141532.2 | N93: =L93+M93 -> 3030806.3 | O93: =L93 -> 1889274.1 | P93: =(P$110*M93)/M$110 -> 1929189.4 | Q93: =O93+P93 -> 3818463.5 | R93: =L93 -> 1889274.1 | S93: =(S$110*P93)/P$110 -> 2604405.6 | T93: =R93+S93 -> 4493679.7 | U93: =E93 -> 49717.74 | V93: =Y93/D93 -> 74157.023 | W93: =U93+V93 -> 123874.76 | X93: =L93 -> 1889274.1 | Y93: =(Y$110*S93)/S$110 -> 2817966.9 | Z93: =X93+Y93 -> 4707241
A94: ACONDICIONAMIENTO TERMICO
A95: 5.3-1 | B95: RADIADORES | C95: gl | D95: 1 | E95: ='5.3-1'!I22 -> 3265600 | F95: ='5.3-1'!I36 -> 1820000 | J95: =SUM(F95:I95) -> 1820000 | K95: =SUM(E95,J95) -> 5085600 | L95: =$D95*E95 -> 3265600 | M95: =$D95*(SUM(F95:I95)) -> 1820000 | N95: =L95+M95 -> 5085600 | O95: =L95 -> 3265600 | P95: =(P$110*M95)/M$110 -> 3075800 | Q95: =O95+P95 -> 6341400 | R95: =L95 -> 3265600 | S95: =(S$110*P95)/P$110 -> 4152330 | T95: =R95+S95 -> 7417930 | U95: =E95 -> 3265600 | V95: =Y95/D95 -> 4492821.1 | W95: =U95+V95 -> 7758421.1 | X95: =L95 -> 3265600 | Y95: =(Y$110*S95)/S$110 -> 4492821.1 | Z95: =X95+Y95 -> 7758421.1
A96: 5.3-2 | B96: AYUDA DE GREMIO PARA INSTALACION DE AIRES ACONDICIONADOS SEGÚN PLANOS. INCLUYE CAJA DE PREINSTALACION, TOMA ELÉCTRICO, DESCARGA Y AYUDA DE GREMIO PARA MANOJO. | C96: unid | D96: 4 | E96: 49717.74 | F96: $ - | G96: $ - | H96: $ - | I96: 80000 | J96: =SUM(F96:I96) -> 80000 | K96: =SUM(E96,J96) -> 129717.74 | L96: =$D96*E96 -> 198870.96 | M96: =$D96*(SUM(F96:I96)) -> 320000 | N96: =L96+M96 -> 518870.96 | O96: =L96 -> 198870.96 | P96: =(P$110*M96)/M$110 -> 540800 | Q96: =O96+P96 -> 739670.96 | R96: =L96 -> 198870.96 | S96: =(S$110*P96)/P$110 -> 730080 | T96: =R96+S96 -> 928950.96 | U96: =E96 -> 49717.74 | V96: =Y96/D96 -> 197486.64 | W96: =U96+V96 -> 247204.38 | X96: =L96 -> 198870.96 | Y96: =(Y$110*S96)/S$110 -> 789946.56 | Z96: =X96+Y96 -> 988817.52
A97: 6- CIELORRASOS
A98: 45663 | B98: CIELORRASO DE PLACA DE ROCA DE YESO SUSPENDIDO EN COCINA | C98: m² | D98: =D67+D76 -> 147 | E98: ='6.1'!I22 -> 0 | F98: ='6.1'!I36 -> 0 | G98: ='6.1'!I50 -> 0 | H98: ='6.1'!I64 -> 0 | I98: ='6.1'!I78 -> 37000 | J98: =SUM(F98:I98) -> 37000 | K98: =SUM(E98,J98) -> 37000 | L98: =$D98*E98 -> 0 | M98: =$D98*(SUM(F98:I98)) -> 5439000 | N98: =L98+M98 -> 5439000 | O98: =L98 -> 0 | P98: =(P$110*M98)/M$110 -> 9191910 | Q98: =O98+P98 -> 9191910 | R98: =L98 -> 0 | S98: =(S$110*P98)/P$110 -> 12409078 | T98: =R98+S98 -> 12409078 | U98: =E98 -> 0 | V98: =Y98/D98 -> 91337.571 | W98: =U98+V98 -> 91337.571 | X98: =L98 -> 0 | Y98: =(Y$110*S98)/S$110 -> 13426623 | Z98: =X98+Y98 -> 13426623
A99: 7- TERMINACIONES
A100: 45664 | B100: COLOCACION DE PORCELANATO PULIDO BEIGE 60x60 EN PISOS. INCLUYE ZOCALOS | C100: m² | D100: =D77+D67 -> 147 | E100: ='7.1'!I22 -> 46612.245 | F100: ='7.1'!I36 -> 19897.959 | G100: ='7.1'!I50 -> 0 | H100: ='7.1'!I64 -> 816.32653 | I100: ='7.1'!I78 -> 0 | J100: =SUM(F100:I100) -> 20714.286 | K100: =SUM(E100,J100) -> 67326.531 | L100: =$D100*E100 -> 6852000 | M100: =$D100*(SUM(F100:I100)) -> 3045000 | N100: =L100+M100 -> 9897000 | O100: =L100 -> 6852000 | P100: =(P$110*M100)/M$110 -> 5146050 | Q100: =O100+P100 -> 11998050 | R100: =L100 -> 6852000 | S100: =(S$110*P100)/P$110 -> 6947167.5 | T100: =R100+S100 -> 13799168 | U100: =E100 -> 46612.245 | V100: =Y100/D100 -> 51134.934 | W100: =U100+V100 -> 97747.178 | X100: =L100 -> 6852000 | Y100: =(Y$110*S100)/S$110 -> 7516835.2 | Z100: =X100+Y100 -> 14368835
A101: 45695 | B101: COLOCACION DE PORCELANATO EN PAREDES DE BAÑOS PLANTA ALTA | C101: m² | D101: =16*1.8 -> 28.8 | E101: ='7.2'!I22 -> 33750 | F101: ='7.2'!I36 -> 28645.833 | G101: ='7.2'!I50 -> 0 | H101: ='7.2'!I64 -> 2777.7778 | I101: ='7.2'!I78 -> 0 | J101: =SUM(F101:I101) -> 31423.611 | K101: =SUM(E101,J101) -> 65173.611 | L101: =$D101*E101 -> 972000 | M101: =$D101*(SUM(F101:I101)) -> 905000 | N101: =L101+M101 -> 1877000 | O101: =L101 -> 972000 | P101: =(P$110*M101)/M$110 -> 1529450 | Q101: =O101+P101 -> 2501450 | R101: =L101 -> 972000 | S101: =(S$110*P101)/P$110 -> 2064757.5 | T101: =R101+S101 -> 3036757.5 | U101: =E101 -> 33750 | V101: =Y101/D101 -> 77571.792 | W101: =U101+V101 -> 111321.79 | X101: =L101 -> 972000 | Y101: =(Y$110*S101)/S$110 -> 2234067.6 | Z101: =X101+Y101 -> 3206067.6
A102: 7.3 | B102: PINTURA EN PAREDES EXTERIORES | C102: m² | D102: =(1.8*3)+(2.9*15)+11.88+22+(13.3*4) -> 135.98 | E102: 8137.41 | F102: $ - | G102: $ - | H102: $ - | I102: 11020.41 | J102: =SUM(F102:I102) -> 11020.41 | K102: =SUM(E102,J102) -> 19157.82 | L102: =$D102*E102 -> 1106525 | M102: =$D102*(SUM(F102:I102)) -> 1498555.4 | N102: =L102+M102 -> 2605080.4 | O102: =L102 -> 1106525 | P102: =(P$110*M102)/M$110 -> 2532558.5 | Q102: =O102+P102 -> 3639083.6 | R102: =L102 -> 1106525 | S102: =(S$110*P102)/P$110 -> 3418954 | T102: =R102+S102 -> 4525479 | U102: =E102 -> 8137.41 | V102: =Y102/D102 -> 27204.797 | W102: =U102+V102 -> 35342.207 | X102: =L102 -> 1106525 | Y102: =(Y$110*S102)/S$110 -> 3699308.3 | Z102: =X102+Y102 -> 4805833.3
...

Sheet 01_VENTA
A1: CASA LUGONES
A2: Arq. Andres Barone
A3: Pilar, 11 de Septiembre de 2025.
A5: PLANILLA COMPUTO Y PRESPUPUESTO
A7: ITEM | B7: DESCRIPCIÓN | C7: UNIDAD | D7: CANTIDAD | E7: TOTAL (NETO)
E8: V. UNITARIO | H8: V.GENERAL
E9: MAT. | F9: M.O | G9: GENERAL | H9: MAT. | I9: M.O | J9: GENERAL
A10: ='01_C&P'!A8 -> 1- TAREAS PRELIMINARES | C10: ='01_C&P'!C8 | D10: ='01_C&P'!D8
A11: ='01_C&P'!A9 -> 45658 | B11: ='01_C&P'!B9 -> OBRADOR | C11: ='01_C&P'!C9 -> mes | D11: ='01_C&P'!D9 -> 1 | E11: ='01_C&P'!U9 -> 800000 | F11: ='01_C&P'!V9 -> 1481149.8 | G11: ='01_C&P'!W9 -> 2281149.8 | H11: ='01_C&P'!X9 -> 800000 | I11: ='01_C&P'!Y9 -> 1481149.8 | J11: ='01_C&P'!Z9 -> 2281149.8
A12: ='01_C&P'!A10 -> 45689 | B12: ='01_C&P'!B10 -> CARTEL DE OBRA | C12: ='01_C&P'!C10 -> unid | D12: ='01_C&P'!D10 -> 1 | E12: ='01_C&P'!U10 | F12: ='01_C&P'!V10 -> 0 | G12: ='01_C&P'!W10 -> 0 | H12: ='01_C&P'!X10 -> 0 | I12: ='01_C&P'!Y10 -> 0 | J12: ='01_C&P'!Z10 -> 0
A13: ='01_C&P'!A11 -> 45717 | B13: ='01_C&P'!B11 -> BAÑO QUIMICO | C13: ='01_C&P'!C11 -> mes | D13: ='01_C&P'!D11 -> 12 | E13: ='01_C&P'!U11 | F13: ='01_C&P'!V11 -> 246858.3 | G13: ='01_C&P'!W11 -> 246858.3 | H13: ='01_C&P'!X11 -> 0 | I13: ='01_C&P'!Y11 -> 2962299.6 | J13: ='01_C&P'!Z11 -> 2962299.6
A14: ='01_C&P'!A12 -> 45748 | B14: ='01_C&P'!B12 -> INSTALACIONES PROVISORIAS | C14: ='01_C&P'!C12 -> unid | D14: ='01_C&P'!D12 -> 1 | E14: ='01_C&P'!U12 | F14: ='01_C&P'!V12 -> 0 | G14: ='01_C&P'!W12 -> 0 | H14: ='01_C&P'!X12 -> 0 | I14: ='01_C&P'!Y12 -> 0 | J14: ='01_C&P'!Z12 -> 0
A15: ='01_C&P'!A13 -> 45778 | B15: ='01_C&P'!B13 -> CERCO PERIMETRAL | C15: ='01_C&P'!C13 -> unid | D15: ='01_C&P'!D13 -> 1 | E15: ='01_C&P'!U13 | F15: ='01_C&P'!V13 -> 0 | G15: ='01_C&P'!W13 -> 0 | H15: ='01_C&P'!X13 -> 0 | I15: ='01_C&P'!Y13 -> 0 | J15: ='01_C&P'!Z13 -> 0
A16: ='01_C&P'!A14 -> 45809 | B16: ='01_C&P'!B14 -> REPLANTEO Y NIVELACION INICIAL DEL TERRENO | C16: ='01_C&P'!C14 -> unid | D16: ='01_C&P'!D14 -> 1 | E16: ='01_C&P'!U14 | F16: ='01_C&P'!V14 -> 1728008.1 | G16: ='01_C&P'!W14 -> 1728008.1 | H16: ='01_C&P'!X14 -> 0 | I16: ='01_C&P'!Y14 -> 1728008.1 | J16: ='01_C&P'!Z14 -> 1728008.1
A17: ='01_C&P'!A15 -> 45839 | B17: ='01_C&P'!B15 -> LIMPIEZA PERIODICA DE OBRA | C17: ='01_C&P'!C15 -> mes | D17: ='01_C&P'!D15 -> 12 | E17: ='01_C&P'!U15 | F17: ='01_C&P'!V15 -> 246858.3 | G17: ='01_C&P'!W15 -> 246858.3 | H17: ='01_C&P'!X15 -> 0 | I17: ='01_C&P'!Y15 -> 2962299.6 | J17: ='01_C&P'!Z15 -> 2962299.6
A18: ='01_C&P'!A16 -> 45870 | B18: ='01_C&P'!B16 -> LIMPIEZA FINAL DE OBRA | C18: ='01_C&P'!C16 -> unid | D18: ='01_C&P'!D16 -> 1 | E18: ='01_C&P'!U16 | F18: ='01_C&P'!V16 -> 987433.2 | G18: ='01_C&P'!W16 -> 987433.2 | H18: ='01_C&P'!X16 -> 0 | I18: ='01_C&P'!Y16 -> 987433.2 | J18: ='01_C&P'!Z16 -> 987433.2
A19: ='01_C&P'!A17 -> 45901 | B19: ='01_C&P'!B17 -> AYUDA DE GREMIO | C19: ='01_C&P'!C17 -> mes | D19: ='01_C&P'!D17 -> 12 | E19: ='01_C&P'!U17 | F19: ='01_C&P'!V17 -> 370287.45 | G19: ='01_C&P'!W17 -> 370287.45 | H19: ='01_C&P'!X17 -> 0 | I19: ='01_C&P'!Y17 -> 4443449.4 | J19: ='01_C&P'!Z17 -> 4443449.4
A20: ='01_C&P'!A18 -> 45931 | B20: ='01_C&P'!B18 -> PROGRAMA DE SEGURIDAD E HIGENE DE ACUERDO A LA NORMATIVA VIGENTE (TODO EL PERSONAL ALCANZADO POR EL MISMO Y CON ART) | C20: ='01_C&P'!C18 -> mes | D20: ='01_C&P'!D18 -> 12 | E20: ='01_C&P'!U18 | F20: ='01_C&P'!V18 -> 493716.6 | G20: ='01_C&P'!W18 -> 493716.6 | H20: ='01_C&P'!X18 -> 0 | I20: ='01_C&P'!Y18 -> 5924599.2 | J20: ='01_C&P'!Z18 -> 5924599.2
A21: ='01_C&P'!A19 -> 2- DEMOLICION | C21: ='01_C&P'!C19 | E21: ='01_C&P'!E19 | G21: ='01_C&P'!G19 | I21: ='01_C&P'!I19
A22: ='01_C&P'!A20 -> 45659 | B22: ='01_C&P'!B20 -> DEMOLICION LOSAS | C22: ='01_C&P'!C20 -> m² | D22: ='01_C&P'!D20 -> 30 | E22: ='01_C&P'!U20 | F22: ='01_C&P'!V20 | G22: ='01_C&P'!W20 | H22: ='01_C&P'!X20 | I22: ='01_C&P'!Y20 | J22: ='01_C&P'!Z20
A23: ='01_C&P'!A21 -> 45690 | B23: ='01_C&P'!B21 -> DEMOLICION COLUMNAS | C23: ='01_C&P'!C21 -> unid. | D23: ='01_C&P'!D21 -> 3 | E23: ='01_C&P'!U21 | F23: ='01_C&P'!V21 | G23: ='01_C&P'!W21 | H23: ='01_C&P'!X21 | I23: ='01_C&P'!Y21 | J23: ='01_C&P'!Z21
A24: ='01_C&P'!A22 -> 45718 | B24: ='01_C&P'!B22 -> DEMOLICION MUROS | C24: ='01_C&P'!C22 -> m² | D24: ='01_C&P'!D22 -> 163.2 | E24: ='01_C&P'!U22 | F24: ='01_C&P'!V22 | G24: ='01_C&P'!W22 | H24: ='01_C&P'!X22 | I24: ='01_C&P'!Y22 | J24: ='01_C&P'!Z22
A25: ='01_C&P'!A23 -> 45749 | B25: ='01_C&P'!B23 -> DEMOLICION DE ESCALERA (1 x 0,84m) h- 4 escalones | C25: ='01_C&P'!C23 -> gl | D25: ='01_C&P'!D23 -> 1 | E25: ='01_C&P'!U23 | F25: ='01_C&P'!V23 | G25: ='01_C&P'!W23 | H25: ='01_C&P'!X23 | I25: ='01_C&P'!Y23 | J25: ='01_C&P'!Z23
A26: ='01_C&P'!A24 -> 45779 | B26: ='01_C&P'!B24 -> DEMOLICION EN SECTOR CANTERO | C26: ='01_C&P'!C24 -> m² | D26: ='01_C&P'!D24 -> 9 | E26: ='01_C&P'!U24 | F26: ='01_C&P'!V24 | G26: ='01_C&P'!W24 | H26: ='01_C&P'!X24 | I26: ='01_C&P'!Y24 | J26: ='01_C&P'!Z24
A27: ='01_C&P'!A25 -> 45810 | B27: ='01_C&P'!B25 -> DEMOLICION DE VOLUMEN PA | C27: ='01_C&P'!C25 -> gl | D27: ='01_C&P'!D25 -> 1 | E27: ='01_C&P'!U25 | F27: ='01_C&P'!V25 | G27: ='01_C&P'!W25 | H27: ='01_C&P'!X25 | I27: ='01_C&P'!Y25 | J27: ='01_C&P'!Z25
A28: ='01_C&P'!A26 -> 45840 | B28: ='01_C&P'!B26 -> DEMOLICION DE LOSA PARA INSTALACIONES | C28: ='01_C&P'!C26 -> gl | D28: ='01_C&P'!D26 -> 1 | E28: ='01_C&P'!U26 | F28: ='01_C&P'!V26 | G28: ='01_C&P'!W26 | H28: ='01_C&P'!X26 | I28: ='01_C&P'!Y26 | J28: ='01_C&P'!Z26
A29: ='01_C&P'!A27 -> 45871 | B29: ='01_C&P'!B27 -> DEMOLICION DE FUNDACIONES PARA REFORZAR ESTRUCTURA | C29: ='01_C&P'!C27 -> gl | D29: ='01_C&P'!D27 -> 1 | E29: ='01_C&P'!U27 | F29: ='01_C&P'!V27 | G29: ='01_C&P'!W27 | H29: ='01_C&P'!X27 | I29: ='01_C&P'!Y27 | J29: ='01_C&P'!Z27
A30: ='01_C&P'!A28 -> 45902 | B30: ='01_C&P'!B28 -> RETIRO DE PORTON | C30: ='01_C&P'!C28 -> unid. | D30: ='01_C&P'!D28 -> 1 | E30: ='01_C&P'!U28 | F30: ='01_C&P'!V28 | G30: ='01_C&P'!W28 | H30: ='01_C&P'!X28 | I30: ='01_C&P'!Y28 | J30: ='01_C&P'!Z28
A31: ='01_C&P'!A29 -> 45932 | B31: ='01_C&P'!B29 -> RETIRO DE CARPINTERIAS | C31: ='01_C&P'!C29 -> gl | D31: ='01_C&P'!D29 -> 1 | E31: ='01_C&P'!U29 | F31: ='01_C&P'!V29 | G31: ='01_C&P'!W29 | H31: ='01_C&P'!X29 | I31: ='01_C&P'!Y29 | J31: ='01_C&P'!Z29
A32: ='01_C&P'!A30 -> 45963 | B32: ='01_C&P'!B30 -> RETIRO DE PUERTA PRINCIPAL | C32: ='01_C&P'!C30 -> unid. | D32: ='01_C&P'!D30 -> 1 | E32: ='01_C&P'!U30 | F32: ='01_C&P'!V30 | G32: ='01_C&P'!W30 | H32: ='01_C&P'!X30 | I32: ='01_C&P'!Y30 | J32: ='01_C&P'!Z30
A33: ='01_C&P'!A31 -> 45993 | B33: ='01_C&P'!B31 -> RETIRO DE SOLADO EN PLANTA BAJA | C33: ='01_C&P'!C31 -> m² | D33: ='01_C&P'!D31 -> 118 | E33: ='01_C&P'!U31 | F33: ='01_C&P'!V31 | G33: ='01_C&P'!W31 | H33: ='01_C&P'!X31 | I33: ='01_C&P'!Y31 | J33: ='01_C&P'!Z31
... A35: ='01_C&P'!A33 -> 2.14 | B35: ='01_C&P'!B33 -> DEMOLICION TOTAL DE ITEMS ANTERIORES | C35: ='01_C&P'!C33 -> gl | D35: ='01_C&P'!D33 -> 1 | E35: ='01_C&P'!U33 -> 0 | F35: ='01_C&P'!V33 -> 35013641 | G35: ='01_C&P'!W33 -> 35013641 | H35: ='01_C&P'!X33 -> 0 | I35: ='01_C&P'!Y33 -> 35013641 | J35: ='01_C&P'!Z33 -> 35013641
A36: ='01_C&P'!A34 -> 3-ESTRUCTURA | C36: ='01_C&P'!C34 | E36: ='01_C&P'!E34 | G36: ='01_C&P'!G34 | I36: ='01_C&P'!I34
A37: ='01_C&P'!A35 -> FUNDACIONES
A38: ='01_C&P'!A36 -> 3.0-1 | B38: ='01_C&P'!B36 -> EXCAVACION DE BASES PARA REFORZAR ESTRUCTURA | C38: ='01_C&P'!C36 -> unid. | D38: ='01_C&P'!D36 -> 14 | E38: ='01_C&P'!U36 -> 0 | F38: ='01_C&P'!V36 -> 969800.46 | G38: ='01_C&P'!W36 -> 969800.46 | H38: ='01_C&P'!X36 -> 0 | I38: ='01_C&P'!Y36 -> 13577206 | J38: ='01_C&P'!Z36 -> 13577206
A39: ='01_C&P'!A37 -> 3.0-2 | B39: ='01_C&P'!B37 -> EJECUCION DE BASES DE H 30 100x100 + TRONCO 25X25x100 + TENSORES 30x40cm | C39: ='01_C&P'!C37 -> unid. | D39: ='01_C&P'!D37 -> 14 | E39: ='01_C&P'!U37 -> 206681.2 | F39: ='01_C&P'!V37 -> 734814.41 | G39: ='01_C&P'!W37 -> 941495.61 | H39: ='01_C&P'!X37 -> 2893536.9 | I39: ='01_C&P'!Y37 -> 10287402 | J39: ='01_C&P'!Z37 -> 13180939
A40: ='01_C&P'!A38 -> 3.0-3 | B40: ='01_C&P'!B38 -> RELLENO DE FUNDACIONES (TOSCA + HORMIGON EN PLATEA DE FUNDACION) | C40: ='01_C&P'!C38 -> unid. | D40: ='01_C&P'!D38 -> 14 | E40: ='01_C&P'!U38 -> 125774.59 | F40: ='01_C&P'!V38 -> 264491.04 | G40: ='01_C&P'!W38 -> 390265.63 | H40: ='01_C&P'!X38 -> 1760844.3 | I40: ='01_C&P'!Y38 -> 3702874.5 | J40: ='01_C&P'!Z38 -> 5463718.8
A41: ='01_C&P'!A39 -> SOBRE PLANTA BAJA | C41: ='01_C&P'!C39 | E41: ='01_C&P'!E39 | G41: ='01_C&P'!G39 | I41: ='01_C&P'!I39
A42: ='01_C&P'!A40 -> 3.1-1 | B42: ='01_C&P'!B40 -> VIGAS H30 SOBRE PLANTA BAJA 0,15x0,35 (Hierros 6 ∅8 con estribos ∅ 6 c/14) | C42: ='01_C&P'!C40 -> m | D42: ='01_C&P'!D40 -> 29 | E42: ='01_C&P'!U40 -> 17958.966 | F42: ='01_C&P'!V40 -> 192096.17 | G42: ='01_C&P'!W40 -> 210055.13 | H42: ='01_C&P'!X40 -> 520810 | I42: ='01_C&P'!Y40 -> 5570788.9 | J42: ='01_C&P'!Z40 -> 6091598.9
A43: ='01_C&P'!A41 -> 3.1-2 | B43: ='01_C&P'!B41 -> VIGAS METALICAS + COLUMNA METALICA | C43: ='01_C&P'!C41 -> m | D43: ='01_C&P'!D41 -> 8.3 | E43: ='01_C&P'!U41 -> 139757.45 | F43: ='01_C&P'!V41 -> 297419.64 | G43: ='01_C&P'!W41 -> 437177.09 | H43: ='01_C&P'!X41 -> 1159986.8 | I43: ='01_C&P'!Y41 -> 2468583 | J43: ='01_C&P'!Z41 -> 3628569.8
A44: ='01_C&P'!A42 -> 3.1-3 | B44: ='01_C&P'!B42 -> LOSA DE VIGUETAS SECTOR COCINA e=0,08m | C44: ='01_C&P'!C42 -> m² | D44: ='01_C&P'!D42 -> 18 | E44: ='01_C&P'!U42 -> 49897.778 | F44: ='01_C&P'!V42 -> 101897.62 | G44: ='01_C&P'!W42 -> 151795.4 | H44: ='01_C&P'!X42 -> 898160 | I44: ='01_C&P'!Y42 -> 1834157.2 | J44: ='01_C&P'!Z42 -> 2732317.2
A45: ='01_C&P'!A43 -> 3.1-4 | B45: ='01_C&P'!B43 -> COLUMNAS DE HORMIGON ARMADO 20x20cm h 3,5m (Hierros 4 ∅12 con estribos ∅ 6 c/14) | C45: ='01_C&P'!C43 -> unid. | D45: ='01_C&P'!D43 -> 7 | E45: ='01_C&P'!U43 -> 114605 | F45: ='01_C&P'!V43 -> 550500.13 | G45: ='01_C&P'!W43 -> 665105.13 | H45: ='01_C&P'!X43 -> 802235 | I45: ='01_C&P'!Y43 -> 3853500.9 | J45: ='01_C&P'!Z43 -> 4655735.9
A46: ='01_C&P'!A44 -> 3.1-5 | B46: ='01_C&P'!B44 -> COLUMNAS H30 EN MEDIANERA EN PLANTA BAJA 60x15 | C46: ='01_C&P'!C44 -> unid. | D46: ='01_C&P'!D44 -> 7 | E46: ='01_C&P'!U44 -> 173955.71 | F46: ='01_C&P'!V44 -> 331642.62 | G46: ='01_C&P'!W44 -> 505598.33 | H46: ='01_C&P'!X44 -> 1217690 | I46: ='01_C&P'!Y44 -> 2321498.3 | J46: ='01_C&P'!Z44 -> 3539188.3
A47: ='01_C&P'!A45 -> SOBRE PLANTA ALTA | C47: ='01_C&P'!C45 | E47: ='01_C&P'!E45 | G47: ='01_C&P'!G45 | I47: ='01_C&P'!I45
A48: ='01_C&P'!A46 -> 3.2-1 | B48: ='01_C&P'!B46 -> COLUMNAS H30 SOBRE PRIMER PISO 20x20. H=2,5 | C48: ='01_C&P'!C46 -> unid. | D48: ='01_C&P'!D46 -> 5 | E48: ='01_C&P'!U46 -> 60087 | F48: ='01_C&P'!V46 -> 490288.91 | G48: ='01_C&P'!W46 -> 550375.91 | H48: ='01_C&P'!X46 -> 300435 | I48: ='01_C&P'!Y46 -> 2451444.5 | J48: ='01_C&P'!Z46 -> 2751879.5
A49: ='01_C&P'!A47 -> 3.2-2 | B49: ='01_C&P'!B47 -> COLUMNAS H30 EN MEDIANERA SOBRE PRIMER PISO 60x15 | C49: ='01_C&P'!C47 -> unid. | D49: ='01_C&P'!D47 -> 6 | E49: ='01_C&P'!U47 -> 104427.08 | F49: ='01_C&P'!V47 -> 386916.39 | G49: ='01_C&P'!W47 -> 491343.47 | H49: ='01_C&P'!X47 -> 626562.5 | I49: ='01_C&P'!Y47 -> 2321498.3 | J49: ='01_C&P'!Z47 -> 2948060.8
A50: ='01_C&P'!A48 -> 3.2-3 | B50: ='01_C&P'!B48 -> VIGAS H30 SOBRE PRIMER PISO 15x45 (Hierros 2∅10 arriba, 3∅10 abajo con estribos ∅ 6 c/18) | C50: ='01_C&P'!C48 -> m | D50: ='01_C&P'!D48 -> 58 | E50: ='01_C&P'!U48 -> 20077.586 | F50: ='01_C&P'!V48 -> 118205.74 | G50: ='01_C&P'!W48 -> 138283.33 | H50: ='01_C&P'!X48 -> 1164500 | I50: ='01_C&P'!Y48 -> 6855933.2 | J50: ='01_C&P'!Z48 -> 8020433.2
A51: ='01_C&P'!A49 -> 3.2-4 | B51: ='01_C&P'!B49 -> LOSAS DE VIGUETAS SOBRE PRIMER PISO e=0,10cm | C51: ='01_C&P'!C49 -> m² | D51: ='01_C&P'!D49 -> 70 | E51: ='01_C&P'!U49 -> 48924.514 | F51: ='01_C&P'!V49 -> 81509.084 | G51: ='01_C&P'!W49 -> 130433.6 | H51: ='01_C&P'!X49 -> 3424716 | I51: ='01_C&P'!Y49 -> 5705635.9 | J51: ='01_C&P'!Z49 -> 9130351.9
A52: ='01_C&P'!A50 -> CAJA DE ESCALERA | C52: ='01_C&P'!C50 | E52: ='01_C&P'!E50 | G52: ='01_C&P'!G50 | I52: ='01_C&P'!I50
A53: ='01_C&P'!A51 -> 3.3-1 | B53: ='01_C&P'!B51 -> COLUMNAS H30 20x30 H=2,20m | C53: ='01_C&P'!C51 -> unid. | D53: ='01_C&P'!D51 -> 4 | E53: ='01_C&P'!U51 -> 76281.875 | F53: ='01_C&P'!V51 -> 324259.1 | G53: ='01_C&P'!W51 -> 400540.97 | H53: ='01_C&P'!X51 -> 305127.5 | I53: ='01_C&P'!Y51 -> 1297036.4 | J53: ='01_C&P'!Z51 -> 1602163.9
A54: ='01_C&P'!A52 -> 3.3-2 | B54: ='01_C&P'!B52 -> VIGAS H30 20x35 | C54: ='01_C&P'!C52 -> m | D54: ='01_C&P'!D52 -> 14 | E54: ='01_C&P'!U52 -> 25900.714 | F54: ='01_C&P'!V52 -> 110841.42 | G54: ='01_C&P'!W52 -> 136742.13 | H54: ='01_C&P'!X52 -> 362610 | I54: ='01_C&P'!Y52 -> 1551779.9 | J54: ='01_C&P'!Z52 -> 1914389.9
A55: ='01_C&P'!A53 -> 3.3-3 | B55: ='01_C&P'!B53 -> LOSAS DE VIGUETAS EN CAJA DE ESCALERAS e=0,08cm | C55: ='01_C&P'!C53 -> m² | D55: ='01_C&P'!D53 -> 7 | E55: ='01_C&P'!U53 -> 43382.857 | F55: ='01_C&P'!V53 -> 105796.41 | G55: ='01_C&P'!W53 -> 149179.27 | H55: ='01_C&P'!X53 -> 303680 | I55: ='01_C&P'!Y53 -> 740574.9 | J55: ='01_C&P'!Z53 -> 1044254.9
A56: ='01_C&P'!A54 -> 3.3-4 | B56: ='01_C&P'!B54 -> ESCALERA DE HORMIGON (con intrados recto) 90cm DE ANCHO | C56: ='01_C&P'!C54 -> gl | D56: ='01_C&P'!D54 -> 1 | E56: ='01_C&P'!U54 -> 572060 | F56: ='01_C&P'!V54 -> 5729864.4 | G56: ='01_C&P'!W54 -> 6301924.4 | H56: ='01_C&P'!X54 -> 572060 | I56: ='01_C&P'!Y54 -> 5729864.4 | J56: ='01_C&P'!Z54 -> 6301924.4
A57: ='01_C&P'!A55 -> 3.3-5 | B57: ='01_C&P'!B55 -> ESCALERA DE HORMIGON (con intrados recto) 90cm DE ANCHO | C57: ='01_C&P'!C55 -> gl | D57: ='01_C&P'!D55 -> 1 | E57: ='01_C&P'!U55 -> 563010 | F57: ='01_C&P'!V55 -> 5642433.7 | G57: ='01_C&P'!W55 -> 6205443.7 | H57: ='01_C&P'!X55 -> 563010 | I57: ='01_C&P'!Y55 -> 5642433.7 | J57: ='01_C&P'!Z55 -> 6205443.7
A58: ='01_C&P'!A56 -> 4-ALBAÑILERIA | C58: ='01_C&P'!C56 | E58: ='01_C&P'!E56 | G58: ='01_C&P'!G56 | I58: ='01_C&P'!I56
A59: ='01_C&P'!A57 -> PLANTA BAJA | C59: ='01_C&P'!C57 | E59: ='01_C&P'!E57 | G59: ='01_C&P'!G57 | I59: ='01_C&P'!I57
A60: ='01_C&P'!A58 -> 4.1-1 | B60: ='01_C&P'!B58 -> EJECUCION DE CAJON HIDROFUGO | C60: ='01_C&P'!C58 -> m | D60: ='01_C&P'!D58 -> 35 | E60: ='01_C&P'!U58 -> 10284 | F60: ='01_C&P'!V58 -> 32893.868 | G60: ='01_C&P'!W58 -> 43177.868 | H60: ='01_C&P'!X58 -> 359940 | I60: ='01_C&P'!Y58 -> 1151285.4 | J60: ='01_C&P'!Z58 -> 1511225.4
A61: ='01_C&P'!A59 -> 4.1-2 | B61: ='01_C&P'!B59 -> EJECUCION DE MUROS DE LADRILLO VISTO EN FACHADA | C61: ='01_C&P'!C59 -> m² | D61: ='01_C&P'!D59 -> 48.39 | E61: ='01_C&P'!U59 -> 18863.002 | F61: ='01_C&P'!V59 -> 50249.106 | G61: ='01_C&P'!W59 -> 69112.108 | H61: ='01_C&P'!X59 -> 912780.66 | I61: ='01_C&P'!Y59 -> 2431554.3 | J61: ='01_C&P'!Z59 -> 3344334.9
A62: ='01_C&P'!A60 -> 4.1-3 | B62: ='01_C&P'!B60 -> EJECUCION DE MURO DE LADRILLO VISTO EN COCINA (H- 1,20m) | C62: ='01_C&P'!C60 -> m² | D62: ='01_C&P'!D60 -> 6.84 | E62: ='01_C&P'!U60 -> 15409.78 | F62: ='01_C&P'!V60 -> 59549.151 | G62: ='01_C&P'!W60 -> 74958.931 | H62: ='01_C&P'!X60 -> 105402.89 | I62: ='01_C&P'!Y60 -> 407316.2 | J62: ='01_C&P'!Z60 -> 512719.09
A63: ='01_C&P'!A61 -> 4.1-4 | B63: ='01_C&P'!B61 -> EJECUCION DE MURO DE LADRILLO VISTO EN PARED LIVING COMEDOR Y LAVADERO. H=3m | C63: ='01_C&P'!C61 -> m² | D63: ='01_C&P'!D61 -> 12 | E63: ='01_C&P'!U61 -> 15278.409 | F63: ='01_C&P'!V61 -> 33943.016 | G63: ='01_C&P'!W61 -> 49221.425 | H63: ='01_C&P'!X61 -> 183340.91 | I63: ='01_C&P'!Y61 -> 407316.2 | J63: ='01_C&P'!Z61 -> 590657.1
A64: ='01_C&P'!A62 -> 4.1-5 | B64: ='01_C&P'!B62 -> EJECUCION DE MUROS DE LADRILLO HUECO DEL 8. H= 3,50m | C64: ='01_C&P'!C62 -> m² | D64: ='01_C&P'!D62 -> 14 | E64: ='01_C&P'!U62 -> 14932.836 | F64: ='01_C&P'!V62 -> 52898.207 | G64: ='01_C&P'!W62 -> 67831.043 | H64: ='01_C&P'!X62 -> 209059.7 | I64: ='01_C&P'!Y62 -> 740574.9 | J64: ='01_C&P'!Z62 -> 949634.6
A65: ='01_C&P'!A63 -> 4.1-6 | B65: ='01_C&P'!B63 -> EJECUCION DE MUROS DE LADRILLO HUECO DEL 12. H= 3m | C65: ='01_C&P'!C63 -> m² | D65: ='01_C&P'!D63 -> 63 | E65: ='01_C&P'!U63 -> 16917.46 | F65: ='01_C&P'!V63 -> 51722.691 | G65: ='01_C&P'!W63 -> 68640.152 | H65: ='01_C&P'!X63 -> 1065800 | I65: ='01_C&P'!Y63 -> 3258529.6 | J65: ='01_C&P'!Z63 -> 4324329.6
A66: ='01_C&P'!A64 -> 4.1-7 | B66: ='01_C&P'!B64 -> EJECUCION DE REVOQUE GRUESO + FINO EN INTERIOR | C66: ='01_C&P'!C64 -> m² | D66: ='01_C&P'!D64 -> 158.23 | E66: ='01_C&P'!U64 -> 5530.4586 | F66: ='01_C&P'!V64 -> 31592.496 | G66: ='01_C&P'!W64 -> 37122.954 | H66: ='01_C&P'!X64 -> 875084.46 | I66: ='01_C&P'!Y64 -> 4998880.6 | J66: ='01_C&P'!Z64 -> 5873965
A67: ='01_C&P'!A65 -> 4.1-8 | B67: ='01_C&P'!B65 -> EJECUCION DE REVOQUE EXTERIOR EN MUROS | C67: ='01_C&P'!C65 -> m² | D67: ='01_C&P'!D65 -> 6.75 | E67: ='01_C&P'!U65 -> 14787.805 | F67: ='01_C&P'!V65 -> 60343.14 | G67: ='01_C&P'!W65 -> 75130.945 | H67: ='01_C&P'!X65 -> 99817.686 | I67: ='01_C&P'!Y65 -> 407316.2 | J67: ='01_C&P'!Z65 -> 507133.88
A68: ='01_C&P'!A66 -> 4.1-9 | B68: ='01_C&P'!B66 -> EJECUCION DE RECUADRO DE VANOS CARPINTERIAS | C68: ='01_C&P'!C66 -> unid. | D68: ='01_C&P'!D66 -> 10 | E68: ='01_C&P'!U66 -> 10753 | F68: ='01_C&P'!V66 -> 203658.1 | G68: ='01_C&P'!W66 -> 214411.1 | H68: ='01_C&P'!X66 -> 107530 | I68: ='01_C&P'!Y66 -> 2036581 | J68: ='01_C&P'!Z66 -> 2144111
A69: ='01_C&P'!A67 -> 4.1-10 | B69: ='01_C&P'!B67 -> EJECUCION DE CONTRAPISO 8cm DE HORMIGON H8 CON MALLA EN INTERIOR | C69: ='01_C&P'!C67 -> m² | D69: ='01_C&P'!D67 -> 77 | E69: ='01_C&P'!U67 -> 14592.895 | F69: ='01_C&P'!V67 -> 17613.685 | G69: ='01_C&P'!W67 -> 32206.58 | H69: ='01_C&P'!X67 -> 1123652.9 | I69: ='01_C&P'!Y67 -> 1356253.8 | J69: ='01_C&P'!Z67 -> 2479906.7
A70: ='01_C&P'!A68 -> 4.1-11 | B70: ='01_C&P'!B68 -> EJECUCION DE CARPETA NIVELADORA INTERIOR + EXTERIOR | C70: ='01_C&P'!C68 -> m² | D70: ='01_C&P'!D68 -> 109 | E70: ='01_C&P'!U68 -> 3309.8165 | F70: ='01_C&P'!V68 -> 27177.061 | G70: ='01_C&P'!W68 -> 30486.877 | H70: ='01_C&P'!X68 -> 360770 | I70: ='01_C&P'!Y68 -> 2962299.6 | J70: ='01_C&P'!Z68 -> 3323069.6
A71: ='01_C&P'!A69 -> 4.1-12 | B71: ='01_C&P'!B69 -> RECUADRO DE ESCALERA | C71: ='01_C&P'!C69 -> m² | D71: ='01_C&P'!D69 -> 8.5 | E71: ='01_C&P'!U69 -> 5434.1176 | F71: ='01_C&P'!V69 -> 65344.844 | G71: ='01_C&P'!W69 -> 70778.962 | H71: ='01_C&P'!X69 -> 46190 | I71: ='01_C&P'!Y69 -> 555431.18 | J71: ='01_C&P'!Z69 -> 601621.18
A72: ='01_C&P'!A70 -> PLANTA PRIMER PISO | C72: ='01_C&P'!C70 | E72: ='01_C&P'!E70 | G72: ='01_C&P'!G70 | I72: ='01_C&P'!I70
A73: ='01_C&P'!A71 -> 4.2-1 | B73: ='01_C&P'!B71 -> EJECUCION DE MUROS DE LADRILLO PORTANTE DEL 12 EXTERIOR. H=2,5m | C73: ='01_C&P'!C71 -> m² | D73: ='01_C&P'!D71 -> 79.38 | E73: ='01_C&P'!U71 -> 22169.211 | F73: ='01_C&P'!V71 -> 60952.667 | G73: ='01_C&P'!W71 -> 83121.878 | H73: ='01_C&P'!X71 -> 1759792 | I73: ='01_C&P'!Y71 -> 4838422.7 | J73: ='01_C&P'!Z71 -> 6598214.7
A74: ='01_C&P'!A72 -> 4.2-2 | B74: ='01_C&P'!B72 -> EJECUCION DE MUROS DE LADRILLO PORTANTE DEL 12 INTERIOR. H=2,5m | C74: ='01_C&P'!C72 -> m² | D74: ='01_C&P'!D72 -> 67.8 | E74: ='01_C&P'!U72 -> 22366.428 | F74: ='01_C&P'!V72 -> 58983.842 | G74: ='01_C&P'!W72 -> 81350.269 | H74: ='01_C&P'!X72 -> 1516443.8 | I74: ='01_C&P'!Y72 -> 3999104.5 | J74: ='01_C&P'!Z72 -> 5515548.3
A75: ='01_C&P'!A73 -> 4.2-3 | B75: ='01_C&P'!B73 -> EJECUCION DE REVOQUE GRUESO + FINO EN INTERIOR | C75: ='01_C&P'!C73 -> m² | D75: ='01_C&P'!D73 -> 214.98 | E75: ='01_C&P'!U73 -> 5618.2528 | F75: ='01_C&P'!V73 -> 31003.694 | G75: ='01_C&P'!W73 -> 36621.947 | H75: ='01_C&P'!X73 -> 1207812 | I75: ='01_C&P'!Y73 -> 6665174.1 | J75: ='01_C&P'!Z73 -> 7872986.1
A76: ='01_C&P'!A74 -> 4.2-4 | B76: ='01_C&P'!B74 -> EJECUCION DE REVOQUE EXTERIOR EN MUROS. H=2,5m | C76: ='01_C&P'!C74 -> m² | D76: ='01_C&P'!D74 -> 79.38 | E76: ='01_C&P'!U74 -> 5155.714 | F76: ='01_C&P'!V74 -> 37317.959 | G76: ='01_C&P'!W74 -> 42473.673 | H76: ='01_C&P'!X74 -> 409260.58 | I76: ='01_C&P'!Y74 -> 2962299.6 | J76: ='01_C&P'!Z74 -> 3371560.2
A77: ='01_C&P'!A75 -> 4.2-5 | B77: ='01_C&P'!B75 -> EJECUCION DE RECUADRO DE VANOS CARPINTERIAS | C77: ='01_C&P'!C75 -> unid. | D77: ='01_C&P'!D75 -> 12 | E77: ='01_C&P'!U75 -> 10223.333 | F77: ='01_C&P'!V75 -> 169715.08 | G77: ='01_C&P'!W75 -> 179938.41 | H77: ='01_C&P'!X75 -> 122680 | I77: ='01_C&P'!Y75 -> 2036581 | J77: ='01_C&P'!Z75 -> 2159261
A78: ='01_C&P'!A76 -> 4.2-6 | B78: ='01_C&P'!B76 -> EJECUCION DE CONTRAPISOS DE HORMIGON H8 CON MALLA Y ASILACION HIDROFUGA (INTERIOR) | C78: ='01_C&P'!C76 -> m² | D78: ='01_C&P'!D76 -> 70 | E78: ='01_C&P'!U76 -> 18033.471 | F78: ='01_C&P'!V76 -> 17613.685 | G78: ='01_C&P'!W76 -> 35647.156 | H78: ='01_C&P'!X76 -> 1262343 | I78: ='01_C&P'!Y76 -> 1232958 | J78: ='01_C&P'!Z76 -> 2495300.9
A79: ='01_C&P'!A77 -> 4.2-7 | B79: ='01_C&P'!B77 -> EJECUCION DE CARPETA NIVELADORA | C79: ='01_C&P'!C77 -> m² | D79: ='01_C&P'!D77 -> 70 | E79: ='01_C&P'!U77 -> 3411.8571 | F79: ='01_C&P'!V77 -> 29094.014 | G79: ='01_C&P'!W77 -> 32505.871 | H79: ='01_C&P'!X77 -> 238830 | I79: ='01_C&P'!Y77 -> 2036581 | J79: ='01_C&P'!Z77 -> 2275411
A80: ='01_C&P'!A78 -> CAJA DE ESCALERA | C80: ='01_C&P'!C78 | E80: ='01_C&P'!E78 | G80: ='01_C&P'!G78 | I80: ='01_C&P'!I78
A81: ='01_C&P'!A79 -> 4.3-1 | B81: ='01_C&P'!B79 -> EJECUCION DE MUROS DE LADRILLO PORTANTE DEL 15 EXTERIOR. H=2,2m | C81: ='01_C&P'!C79 -> m² | D81: ='01_C&P'!D79 -> 30.8 | E81: ='01_C&P'!U79 -> 22049.734 | F81: ='01_C&P'!V79 -> 42078.119 | G81: ='01_C&P'!W79 -> 64127.853 | H81: ='01_C&P'!X79 -> 679131.8 | I81: ='01_C&P'!Y79 -> 1296006.1 | J81: ='01_C&P'!Z79 -> 1975137.9
A82: ='01_C&P'!A80 -> 4.3-2 | B82: ='01_C&P'!B80 -> EJECUCION DE REVOQUE GRUESO + FINO EN INTERIOR | C82: ='01_C&P'!C80 -> m² | D82: ='01_C&P'!D80 -> 30.8 | E82: ='01_C&P'!U80 -> 6596.179 | F82: ='01_C&P'!V80 -> 42078.119 | G82: ='01_C&P'!W80 -> 48674.298 | H82: ='01_C&P'!X80 -> 203162.31 | I82: ='01_C&P'!Y80 -> 1296006.1 | J82: ='01_C&P'!Z80 -> 1499168.4
A83: ='01_C&P'!A81 -> 4.3-3 | B83: ='01_C&P'!B81 -> EJECUCION DE REVOQUE EXTERIOR EN MUROS. H=2,5m | C83: ='01_C&P'!C81 -> m² | D83: ='01_C&P'!D81 -> 30.8 | E83: ='01_C&P'!U81 -> 7290.8635 | F83: ='01_C&P'!V81 -> 18033.48 | G83: ='01_C&P'!W81 -> 25324.343 | H83: ='01_C&P'!X81 -> 224558.6 | I83: ='01_C&P'!Y81 -> 555431.18 | J83: ='01_C&P'!Z81 -> 779989.77
A84: ='01_C&P'!A82 -> 4.3-4 | B84: ='01_C&P'!B82 -> EJECUCION DE RECUADRO DE VANOS CARPINTERIAS | C84: ='01_C&P'!C82 -> m | D84: ='01_C&P'!D82 -> 2 | E84: ='01_C&P'!U82 -> 20570 | F84: ='01_C&P'!V82 -> 111086.24 | G84: ='01_C&P'!W82 -> 131656.23 | H84: ='01_C&P'!X82 -> 41140 | I84: ='01_C&P'!Y82 -> 222172.47 | J84: ='01_C&P'!Z82 -> 263312.47
A85: ='01_C&P'!A83 -> 4.3-5 | B85: ='01_C&P'!B83 -> RECUADRO DE ESCALERAS | C85: ='01_C&P'!C83 -> m² | D85: ='01_C&P'!D83 -> 8 | E85: ='01_C&P'!U83 -> 11455 | F85: ='01_C&P'!V83 -> 162000.76 | G85: ='01_C&P'!W83 -> 173455.76 | H85: ='01_C&P'!X83 -> 91640 | I85: ='01_C&P'!Y83 -> 1296006.1 | J85: ='01_C&P'!Z83 -> 1387646.1
A86: ='01_C&P'!A84 -> 5-INSTALACIONES | C86: ='01_C&P'!C84 | E86: ='01_C&P'!E84 | G86: ='01_C&P'!G84 | I86: ='01_C&P'!I84
A87: ='01_C&P'!A85 -> SANITARIA | C87: ='01_C&P'!C85 | E87: ='01_C&P'!E85 | G87: ='01_C&P'!G85 | I87: ='01_C&P'!I85
A88: ='01_C&P'!A86 -> 5.1-1 | B88: ='01_C&P'!B86 -> EJECUCION DE INSTALACION CLOACAL SEGUN PLANO Incluye Tendido de Caños, Instalacion de Rejillas, LLP y Camara de Inspeccion) | C88: ='01_C&P'!C86 -> gl | D88: ='01_C&P'!D86 -> 1 | E88: ='01_C&P'!U86 -> 402121.95 | F88: ='01_C&P'!V86 -> 6665174.1 | G88: ='01_C&P'!W86 -> 7067296.1 | H88: ='01_C&P'!X86 -> 402121.95 | I88: ='01_C&P'!Y86 -> 6665174.1 | J88: ='01_C&P'!Z86 -> 7067296.1
A89: ='01_C&P'!A87 -> 5.1-2 | B89: ='01_C&P'!B87 -> EJECUCION DE INSTALACION DE AGUA FRIA (Incluye tendido de caños, llaves de paso, tanque) NO INCLUYE BOMBAS | C89: ='01_C&P'!C87 -> gl | D89: ='01_C&P'!D87 -> 1 | E89: ='01_C&P'!U87 -> 905400 | F89: ='01_C&P'!V87 -> 4295334.4 | G89: ='01_C&P'!W87 -> 5200734.4 | H89: ='01_C&P'!X87 -> 905400 | I89: ='01_C&P'!Y87 -> 4295334.4 | J89: ='01_C&P'!Z87 -> 5200734.4
A90: ='01_C&P'!A88 -> 5.1-3 | B90: ='01_C&P'!B88 -> EJECUCION DE INSTALACION DE AGUA CALIENTE (Incluye tendido de caños, llaves de paso) NO INCLUYE TERMOTANQUE | C90: ='01_C&P'!C88 -> gl | D90: ='01_C&P'!D88 -> 1 | E90: ='01_C&P'!U88 -> 276000 | F90: ='01_C&P'!V88 -> 3702874.5 | G90: ='01_C&P'!W88 -> 3978874.5 | H90: ='01_C&P'!X88 -> 276000 | I90: ='01_C&P'!Y88 -> 3702874.5 | J90: ='01_C&P'!Z88 -> 3978874.5
A91: ='01_C&P'!A89 -> 5.1-4 | B91: ='01_C&P'!B89 -> EJECUCION DE INSTALACION PLUVIAL (Incluye tendido de caños) | C91: ='01_C&P'!C89 -> gl | D91: ='01_C&P'!D89 -> 1 | E91: ='01_C&P'!U89 -> 278000 | F91: ='01_C&P'!V89 -> 2962299.6 | G91: ='01_C&P'!W89 -> 3240299.6 | H91: ='01_C&P'!X89 -> 278000 | I91: ='01_C&P'!Y89 -> 2962299.6 | J91: ='01_C&P'!Z89 -> 3240299.6
A92: ='01_C&P'!A90 -> 5.1-5 | B92: ='01_C&P'!B90 -> COLOCACION DE ARTEFACTOS SANITARIOS (3 Bachas Bano, 1 Bacha Cocina, 3 Indoros, 2 Bidet, 2 Duchas) Incluye griferias. | C92: ='01_C&P'!C90 -> unid | D92: ='01_C&P'!D90 -> 11 | E92: ='01_C&P'!U90 -> 501818.18 | F92: ='01_C&P'!V90 -> 68571.755 | G92: ='01_C&P'!W90 -> 570389.94 | H92: ='01_C&P'!X90 -> 5520000 | I92: ='01_C&P'!Y90 -> 754289.31 | J92: ='01_C&P'!Z90 -> 6274289.3
A93: ='01_C&P'!A91 -> ELECTRICA | C93: ='01_C&P'!C91 | E93: ='01_C&P'!E91 | G93: ='01_C&P'!G91 | I93: ='01_C&P'!I91
A94: ='01_C&P'!A92 -> 5.2-1 | B94: ='01_C&P'!B92 -> INSTALACION DE TABLERO + PUESTA A TIERRA | C94: ='01_C&P'!C92 -> gl | D94: ='01_C&P'!D92 -> 1 | E94: ='01_C&P'!U92 -> 2000000 | F94: ='01_C&P'!V92 -> 2468583 | G94: ='01_C&P'!W92 -> 4468583 | H94: ='01_C&P'!X92 -> 2000000 | I94: ='01_C&P'!Y92 -> 2468583 | J94: ='01_C&P'!Z92 -> 4468583
A95: ='01_C&P'!A93 -> 5.2-2 | B95: ='01_C&P'!B93 -> EJECUCION DE BOCAS (CAJA,CABLEADO Y CANOS) | C95: ='01_C&P'!C93 -> unid | D95: ='01_C&P'!D93 -> 38 | E95: ='01_C&P'!U93 -> 49717.74 | F95: ='01_C&P'!V93 -> 74157.023 | G95: ='01_C&P'!W93 -> 123874.76 | H95: ='01_C&P'!X93 -> 1889274.1 | I95: ='01_C&P'!Y93 -> 2817966.9 | J95: ='01_C&P'!Z93 -> 4707241
A96: ='01_C&P'!A94 -> ACONDICIONAMIENTO TERMICO | C96: ='01_C&P'!C94 | E96: ='01_C&P'!E94 | G96: ='01_C&P'!G94 | I96: ='01_C&P'!I94
A97: ='01_C&P'!A95 -> 5.3-1 | B97: ='01_C&P'!B95 -> RADIADORES | C97: ='01_C&P'!C95 -> gl | D97: ='01_C&P'!D95 -> 1 | E97: ='01_C&P'!U95 -> 3265600 | F97: ='01_C&P'!V95 -> 4492821.1 | G97: ='01_C&P'!W95 -> 7758421.1 | H97: ='01_C&P'!X95 -> 3265600 | I97: ='01_C&P'!Y95 -> 4492821.1 | J97: ='01_C&P'!Z95 -> 7758421.1
A98: ='01_C&P'!A96 -> 5.3-2 | B98: ='01_C&P'!B96 -> AYUDA DE GREMIO PARA INSTALACION DE AIRES ACONDICIONADOS SEGÚN PLANOS. INCLUYE CAJA DE PREINSTALACION, TOMA ELÉCTRICO, DESCARGA Y AYUDA DE GREMIO PARA MANOJO. | C98: ='01_C&P'!C96 -> unid | D98: ='01_C&P'!D96 -> 4 | E98: ='01_C&P'!U96 -> 49717.74 | F98: ='01_C&P'!V96 -> 197486.64 | G98: ='01_C&P'!W96 -> 247204.38 | H98: ='01_C&P'!X96 -> 198870.96 | I98: ='01_C&P'!Y96 -> 789946.56 | J98: ='01_C&P'!Z96 -> 988817.52
A99: ='01_C&P'!A97 -> 6- CIELORRASOS | C99: ='01_C&P'!C97 | E99: ='01_C&P'!E97 | G99: ='01_C&P'!G97 | I99: ='01_C&P'!I97
A100: ='01_C&P'!A98 -> 45663 | B100: ='01_C&P'!B98 -> CIELORRASO DE PLACA DE ROCA DE YESO SUSPENDIDO EN COCINA | C100: ='01_C&P'!C98 -> m² | D100: ='01_C&P'!D98 -> 147 | E100: ='01_C&P'!U98 -> 0 | F100: ='01_C&P'!V98 -> 91337.571 | G100: ='01_C&P'!W98 -> 91337.571 | H100: ='01_C&P'!X98 -> 0 | I100: ='01_C&P'!Y98 -> 13426623 | J100: ='01_C&P'!Z98 -> 13426623
A101: ='01_C&P'!A99 -> 7- TERMINACIONES | C101: ='01_C&P'!C99 | E101: ='01_C&P'!E99 | G101: ='01_C&P'!G99 | I101: ='01_C&P'!I99
A102: ='01_C&P'!A100 -> 45664 | B102: ='01_C&P'!B100 -> COLOCACION DE PORCELANATO PULIDO BEIGE 60x60 EN PISOS. INCLUYE ZOCALOS | C102: ='01_C&P'!C100 -> m² | D102: ='01_C&P'!D100 -> 147 | E102: ='01_C&P'!U100 -> 46612.245 | F102: ='01_C&P'!V100 -> 51134.934 | G102: ='01_C&P'!W100 -> 97747.178 | H102: ='01_C&P'!X100 -> 6852000 | I102: ='01_C&P'!Y100 -> 7516835.2 | J102: ='01_C&P'!Z100 -> 14368835
A103: ='01_C&P'!A101 -> 45695 | B103: ='01_C&P'!B101 -> COLOCACION DE PORCELANATO EN PAREDES DE BAÑOS PLANTA ALTA | C103: ='01_C&P'!C101 -> m² | D103: ='01_C&P'!D101 -> 28.8 | E103: ='01_C&P'!U101 -> 33750 | F103: ='01_C&P'!V101 -> 77571.792 | G103: ='01_C&P'!W101 -> 111321.79 | H103: ='01_C&P'!X101 -> 972000 | I103: ='01_C&P'!Y101 -> 2234067.6 | J103: ='01_C&P'!Z101 -> 3206067.6
...

Sheet RESUMEN VENTA
A1: CASA LUGONES
A2: Arq. Andres Barone
A3: Pilar, 12 de septiembre de 2025,
A5: PLANILLA DE RESUMÉN DE PRESUPUESTO
H6: TC = | I6: 1450
D7: MAT. | E7: M. O. | F7: SUBTOTAL | G7: SUP | H7: VALOR / m ($) | I7: VALOR / m (u$u)
A8: 1- TAREAS PRELIMINARES | D8: =SUM('01_VENTA'!H11:H20) -> 800000 | E8: =SUM('01_VENTA'!I11:I20) -> 20489239 | F8: =SUM('01_VENTA'!J11:J20) -> 21289239 | G8: 1 | H8: =F8/G8 -> 21289239 | I8: =H8/$I$6 -> 14682.234
A9: 2- DEMOLICION | D9: ='01_VENTA'!H35 -> 0 | E9: ='01_VENTA'!I35 -> 35013641 | F9: ='01_VENTA'!J35 -> 35013641 | G9: 1 | H9: =F9/G9 -> 35013641 | I9: =H9/$I$6 -> 24147.338
A10: ='01_VENTA'!A36 -> 3-ESTRUCTURA
A11: ='01_VENTA'!A37 -> FUNDACIONES | D11: =SUM('01_VENTA'!H38:H40) -> 4654381.2 | E11: =SUM('01_VENTA'!I38:I40) -> 27567483 | F11: =SUM('01_VENTA'!J38:J40) -> 32221864 | G11: 125 | H11: =F11/G11 -> 257774.91 | I11: =H11/$I$6 -> 177.7758 | J11: =SUM(I11:I25) -> 2379.0751 | K11: SUP TOTAL
A12: ='01_VENTA'!A41 -> SOBRE PLANTA BAJA | D12: =SUM('01_VENTA'!H42:H46) -> 4598881.8 | E12: =SUM('01_VENTA'!I42:I46) -> 16048528 | F12: =SUM('01_VENTA'!J42:J46) -> 20647410 | G12: 77 | H12: =F12/G12 -> 268148.18 | I12: =H12/$I$6 -> 184.92978 | K12: INTERIOR
A13: ='01_VENTA'!A47 -> SOBRE PLANTA ALTA | D13: =SUM('01_VENTA'!H48:H51) -> 5516213.5 | E13: =SUM('01_VENTA'!I48:I51) -> 17334512 | F13: =SUM('01_VENTA'!J48:J51) -> 22850725 | G13: 71 | H13: =F13/G13 -> 321841.2 | I13: =H13/$I$6 -> 221.95945 | K13: INTERIOR
A14: ='01_VENTA'!A52 -> CAJA DE ESCALERA | D14: =SUM('01_VENTA'!H53:H57) -> 2106487.5 | E14: =SUM('01_VENTA'!I53:I57) -> 14961689 | F14: =SUM('01_VENTA'!J53:J57) -> 17068177 | G14: =7*3 -> 21 | H14: =F14/G14 -> 812770.32 | I14: =H14/$I$6 -> 560.53125 | K14: 7m3 x 3 | L14: PB+PA+TERRAZA
A15: ='01_VENTA'!A58 -> 4-ALBAÑILERIA
A16: ='01_VENTA'!A59 -> PLANTA BAJA | D16: =SUM('01_VENTA'!H60:H71) -> 5449369.2 | E16: =SUM('01_VENTA'!I60:I71) -> 20713339 | F16: =SUM('01_VENTA'!J60:J71) -> 26162708 | G16: 75 | H16: =F16/G16 -> 348836.11 | I16: =H16/$I$6 -> 240.57663
A17: ='01_VENTA'!A72 -> PLANTA PRIMER PISO | D17: =SUM('01_VENTA'!H73:H79) -> 6517161.3 | E17: =SUM('01_VENTA'!I73:I79) -> 23771121 | F17: =SUM('01_VENTA'!J73:J79) -> 30288282 | G17: 71 | H17: =F17/G17 -> 426595.52 | I17: =H17/$I$6 -> 294.20381
A18: ='01_VENTA'!A80 -> CAJA DE ESCALERA | D18: =SUM('01_VENTA'!H81:H85) -> 1239632.7 | E18: =SUM('01_VENTA'!I81:I85) -> 4665621.9 | F18: =SUM('01_VENTA'!J81:J85) -> 5905254.6 | G18: =7*3 -> 21 | H18: =F18/G18 -> 281202.6 | I18: =H18/$I$6 -> 193.93283
A19: ='01_VENTA'!A86 -> 5-INSTALACIONES
A20: ='01_VENTA'!A87 -> SANITARIA | D20: =SUM('01_VENTA'!H88:H92) -> 7381522 | E20: =SUM('01_VENTA'!I88:I92) -> 18379972 | F20: =SUM('01_VENTA'!J88:J92) -> 25761494 | G20: =109+70 -> 179 | H20: =F20/G20 -> 143918.96 | I20: =H20/$I$6 -> 99.254455 | K20: INTERIOR + EXTERIOR
A21: ='01_VENTA'!A93 -> ELECTRICA | D21: =SUM('01_VENTA'!H94:H95) -> 3889274.1 | E21: =SUM('01_VENTA'!I94:I95) -> 5286549.9 | F21: =SUM('01_VENTA'!J94:J95) -> 9175824 | G21: 147 | H21: =F21/G21 -> 62420.571 | I21: =H21/$I$6 -> 43.04867 | K21: INTERIOR
A22: ='01_VENTA'!A96 -> ACONDICIONAMIENTO TERMICO | D22: =SUM('01_VENTA'!H97:H98) -> 3464471 | E22: =SUM('01_VENTA'!I97:I98) -> 5282767.6 | F22: =SUM('01_VENTA'!J97:J98) -> 8747238.6 | G22: 147 | H22: =F22/G22 -> 59505.024 | I22: =H22/$I$6 -> 41.037948 | K22: INTERIOR
A23: ='01_VENTA'!A99 -> 6- CIELORRASOS | D23: =SUM('01_VENTA'!H100) -> 0 | E23: =SUM('01_VENTA'!I100) -> 13426623 | F23: =SUM('01_VENTA'!J100) -> 13426623 | G23: 147 | H23: =F23/G23 -> 91337.571 | I23: =H23/$I$6 -> 62.991428
A24: ='01_VENTA'!A101 -> 7- TERMINACIONES | D24: =SUM('01_VENTA'!H102:H108) -> 13217348 | E24: =SUM('01_VENTA'!I102:I108) -> 23912067 | F24: =SUM('01_VENTA'!J102:J108) -> 37129415 | G24: 147 | H24: =F24/G24 -> 252581.05 | I24: =H24/$I$6 -> 174.19383
A25: ='01_VENTA'!A109 -> 8-CUBIERTA | D25: =SUM('01_VENTA'!H110:H111) -> 2533024.2 | E25: =SUM('01_VENTA'!I110:I111) -> 7776036.5 | F25: =SUM('01_VENTA'!J110:J111) -> 10309061 | G25: 84 | H25: =F25/G25 -> 122726.91 | I25: =H25/$I$6 -> 84.63925
E26: TOTAL = | F26: =SUM(F8:F25) -> 3.1599696e+08
E27: TOTAL (u$u) = | F27: =F26/I6 -> 217928.93
F29: =G12+G13+G14 -> 169
F30: =F27/F29 -> 1289.5203 | G30: =(F27-I8-I9)/F29 -> 1059.7595

Sheet 2.14
A1: ='01_C&P'!A1 -> CASA LUGONES
A3: ='01_C&P'!A33 -> 2.14 | B3: =IF($A3=0,"",VLOOKUP($A3,'01_C&P'!$A$9:$D$172,2,FALSE)) -> DEMOLICION TOTAL DE ITEMS ANTERIORES | H3: =IF($A3=0,"",VLOOKUP($A3,'01_C&P'!$A$9:$D$172,4,FALSE)) -> 1 | I3: =IF($A3=0,"",VLOOKUP($A3,'01_C&P'!$A$9:$D$172,3,FALSE)) -> gl
A5: MATERIALES
A6: Código | B6: Descripción | C6: Unidad | D6: Cantidad | F6: Desperdicio | G6: Cantidad + Desperdicio | H6: Precio Unitario | I6: Subtotal
B7: =IF($A7=0,"",VLOOKUP($A7,'00_Mat'!$A$4:$J$1135,2,FALSE)) | C7: =IF($A7=0,"",VLOOKUP($A7,'00_Mat'!$A$4:$J$1135,3,FALSE)) | F7: 0.1 | G7: =ROUNDUP((D7+(D7*F7)),0) -> 0 | H7: =IF($A7=0,"",VLOOKUP($A7,'00_Mat'!$A$4:$J$1135,5,FALSE)) | I7: =H7*G7 -> 0
B8: =IF($A8=0,"",VLOOKUP($A8,'00_Mat'!$A$4:$J$1135,2,FALSE)) | C8: =IF($A8=0,"",VLOOKUP($A8,'00_Mat'!$A$4:$J$1135,3,FALSE)) | F8: 0.1 | G8: =ROUNDUP((D8+(D8*F8)),0) -> 0 | H8: =IF($A8=0,"",VLOOKUP($A8,'00_Mat'!$A$4:$J$1135,5,FALSE)) | I8: =H8*G8 -> 0
B9: =IF($A9=0,"",VLOOKUP($A9,'00_Mat'!$A$4:$J$1135,2,FALSE)) | C9: =IF($A9=0,"",VLOOKUP($A9,'00_Mat'!$A$4:$J$1135,3,FALSE)) | F9: 0.1 | G9: =ROUNDUP((D9+(D9*F9)),0) -> 0 | H9: =IF($A9=0,"",VLOOKUP($A9,'00_Mat'!$A$4:$J$1135,5,FALSE)) | I9: =H9*G9 -> 0
B10: =IF($A10=0,"",VLOOKUP($A10,'00_Mat'!$A$4:$J$1135,2,FALSE)) | C10: =IF($A10=0,"",VLOOKUP($A10,'00_Mat'!$A$4:$J$1135,3,FALSE)) | F10: 0.1 | G10: =ROUNDUP((D10+(D10*F10)),0) -> 0 | H10: =IF($A10=0,"",VLOOKUP($A10,'00_Mat'!$A$4:$J$1135,5,FALSE)) | I10: =H10*G10 -> 0
B11: =IF($A11=0,"",VLOOKUP($A11,'00_Mat'!$A$4:$J$1135,2,FALSE)) | C11: =IF($A11=0,"",VLOOKUP($A11,'00_Mat'!$A$4:$J$1135,3,FALSE)) | F11: 0.1 | G11: =ROUNDUP((D11+(D11*F11)),0) -> 0 | H11: =IF($A11=0,"",VLOOKUP($A11,'00_Mat'!$A$4:$J$1135,5,FALSE)) | I11: =H11*G11 -> 0
B12: =IF($A12=0,"",VLOOKUP($A12,'00_Mat'!$A$4:$J$1135,2,FALSE)) | C12: =IF($A12=0,"",VLOOKUP($A12,'00_Mat'!$A$4:$J$1135,3,FALSE)) | F12: 0.1 | G12: =ROUNDUP((D12+(D12*F12)),0) -> 0 | H12: =IF($A12=0,"",VLOOKUP($A12,'00_Mat'!$A$4:$J$1135,5,FALSE)) | I12: =H12*G12 -> 0
B13: =IF($A13=0,"",VLOOKUP($A13,'00_Mat'!$A$4:$J$1135,2,FALSE)) | C13: =IF($A13=0,"",VLOOKUP($A13,'00_Mat'!$A$4:$J$1135,3,FALSE)) | F13: 0.1 | G13: =ROUNDUP((D13+(D13*F13)),0) -> 0 | H13: =IF($A13=0,"",VLOOKUP($A13,'00_Mat'!$A$4:$J$1135,5,FALSE)) | I13: =H13*G13 -> 0
B14: =IF($A14=0,"",VLOOKUP($A14,'00_Mat'!$A$4:$J$1135,2,FALSE)) | C14: =IF($A14=0,"",VLOOKUP($A14,'00_Mat'!$A$4:$J$1135,3,FALSE)) | F14: 0.1 | G14: =ROUNDUP((D14+(D14*F14)),0) -> 0 | H14: =IF($A14=0,"",VLOOKUP($A14,'00_Mat'!$A$4:$J$1135,5,FALSE)) | I14: =H14*G14 -> 0
B15: =IF($A15=0,"",VLOOKUP($A15,'00_Mat'!$A$4:$J$1135,2,FALSE)) | C15: =IF($A15=0,"",VLOOKUP($A15,'00_Mat'!$A$4:$J$1135,3,FALSE)) | F15: 0.1 | G15: =ROUNDUP((D15+(D15*F15)),0) -> 0 | H15: =IF($A15=0,"",VLOOKUP($A15,'00_Mat'!$A$4:$J$1135,5,FALSE)) | I15: =H15*G15 -> 0
B16: =IF($A16=0,"",VLOOKUP($A16,'00_Mat'!$A$4:$J$1135,2,FALSE)) | C16: =IF($A16=0,"",VLOOKUP($A16,'00_Mat'!$A$4:$J$1135,3,FALSE)) | F16: 0.1 | G16: =ROUNDUP((D16+(D16*F16)),0) -> 0 | H16: =IF($A16=0,"",VLOOKUP($A16,'00_Mat'!$A$4:$J$1135,5,FALSE)) | I16: =H16*G16 -> 0
B17: =IF($A17=0,"",VLOOKUP($A17,'00_Mat'!$A$4:$J$1135,2,FALSE)) | C17: =IF($A17=0,"",VLOOKUP($A17,'00_Mat'!$A$4:$J$1135,3,FALSE)) | F17: 0.1 | G17: =ROUNDUP((D17+(D17*F17)),0) -> 0 | H17: =IF($A17=0,"",VLOOKUP($A17,'00_Mat'!$A$4:$J$1135,5,FALSE)) | I17: =H17*G17 -> 0
B18: =IF($A18=0,"",VLOOKUP($A18,'00_Mat'!$A$4:$J$1135,2,FALSE)) | C18: =IF($A18=0,"",VLOOKUP($A18,'00_Mat'!$A$4:$J$1135,3,FALSE)) | F18: 0.1 | G18: =ROUNDUP((D18+(D18*F18)),0) -> 0 | H18: =IF($A18=0,"",VLOOKUP($A18,'00_Mat'!$A$4:$J$1135,5,FALSE)) | I18: =H18*G18 -> 0
A20: TOTAL MATERIALES | I20: =SUM(I7:I18) -> 0
A21: =$I$3 -> gl | I21: =$H$3 -> 1
A22: TOTAL x | B22: =A21 -> gl | I22: =I20/I21 -> 0
A25: MANO DE OBRA - PERSONAS
A26: Código | B26: Descripción | C26: Unidad | D26: Cantidad | E26: Dias | F26: Desperdicio | G26: Cantidad + Desperdicio | H26: Precio Unitario | I26: Subtotal
A27: mo-ca | B27: =IF($A27=0,"",VLOOKUP($A27,'00_MO'!$A$4:$D$7,2,FALSE)) -> Capataz | C27: =IF($A27=0,"",VLOOKUP($A27,'00_MO'!$A$4:$D$7,3,FALSE)) -> u | D27: 1 | E27: 15 | F27: 0.25 | G27: =ROUNDUP(((D27*E27)*(1+F27)),0) -> 19 | H27: =IF($A27=0,"",VLOOKUP($A27,'00_MO'!$A$4:$D$7,4,FALSE)) -> 90000 | I27: =G27*H27 -> 1710000
A28: mo-of | B28: =IF($A28=0,"",VLOOKUP($A28,'00_MO'!$A$4:$D$7,2,FALSE)) -> Oficial | C28: =IF($A28=0,"",VLOOKUP($A28,'00_MO'!$A$4:$D$7,3,FALSE)) -> u | D28: 2 | E28: 15 | F28: 0.25 | G28: =ROUNDUP(((D28*E28)*(1+F28)),0) -> 38 | H28: =IF($A28=0,"",VLOOKUP($A28,'00_MO'!$A$4:$D$7,4,FALSE)) -> 75000 | I28: =G28*H28 -> 2850000
A29: mo-ay | B29: =IF($A29=0,"",VLOOKUP($A29,'00_MO'!$A$4:$D$7,2,FALSE)) -> Ayudante | C29: =IF($A29=0,"",VLOOKUP($A29,'00_MO'!$A$4:$D$7,3,FALSE)) -> u | D29: 1 | E29: 15 | F29: 0.25 | G29: =ROUNDUP(((D29*E29)*(1+F29)),0) -> 19 | H29: =IF($A29=0,"",VLOOKUP($A29,'00_MO'!$A$4:$D$7,4,FALSE)) -> 60000 | I29: =H29*G29 -> 1140000
A30: mo-ay | B30: =IF($A30=0,"",VLOOKUP($A30,'00_MO'!$A$4:$D$7,2,FALSE)) -> Ayudante | C30: =IF($A30=0,"",VLOOKUP($A30,'00_MO'!$A$4:$D$7,3,FALSE)) -> u | D30: 1 | E30: 7 | F30: 0.1 | G30: =ROUNDUP(((D30*E30)*(1+F30)),0) -> 8 | H30: =IF($A30=0,"",VLOOKUP($A30,'00_MO'!$A$4:$D$7,4,FALSE)) -> 60000 | I30: =H30*G30 -> 480000 | J30: PICADO DE INSTALACIONES SANITARIAS
B31: =IF($A31=0,"",VLOOKUP($A31,'00_MO'!$A$4:$D$7,2,FALSE)) | C31: =IF($A31=0,"",VLOOKUP($A31,'00_MO'!$A$4:$D$7,3,FALSE)) | G31: =ROUNDUP(((D31*E31)*(1+F31)),0) -> 0 | H31: =IF($A31=0,"",VLOOKUP($A31,'00_MO'!$A$4:$D$7,4,FALSE))
B32: =IF($A32=0,"",VLOOKUP($A32,'00_MO'!$A$4:$D$7,2,FALSE)) | C32: =IF($A32=0,"",VLOOKUP($A32,'00_MO'!$A$4:$D$7,3,FALSE)) | G32: =ROUNDUP(((D32*E32)*(1+F32)),0) -> 0 | H32: =IF($A32=0,"",VLOOKUP($A32,'00_MO'!$A$4:$D$7,4,FALSE))
A34: TOTAL | I34: =SUM(I27:I32) -> 6180000
A35: =$I$3 -> gl | I35: =$H$3 -> 1
A36: TOTAL x | B36: =A35 -> gl | I36: =I34/I35 -> 6180000
A39: MANO DE OBRA - EQUIPOS
A40: Código | B40: Descripción | C40: Unidad | D40: Cantidad | E40: Dias | F40: Desperdicio | G40: Cantidad + Desperdicio | H40: Precio Unitario | I40: Subtotal
A41: e-vol | B41: =IF($A41=0,"",VLOOKUP($A41,'00_Eq'!$A$4:$D$100,2,FALSE)) -> Volquete | C41: =IF($A41=0,"",VLOOKUP($A41,'00_Eq'!$A$4:$D$100,3,FALSE)) -> u | D41: 21 | E41: 1 | F41: 0.25 | G41: =ROUNDUP(((D41*E41)*(1+F41)),0) -> 27 | H41: =IF($A41=0,"",VLOOKUP($A41,'00_Eq'!$A$4:$D$100,4,FALSE)) -> 200000 | I41: =G41*H41 -> 5400000 | J41: PARA LOSA DE FUNDACION EXISTENTE
A42: E-MAR | B42: =IF($A42=0,"",VLOOKUP($A42,'00_Eq'!$A$4:$D$100,2,FALSE)) -> Martillete | C42: =IF($A42=0,"",VLOOKUP($A42,'00_Eq'!$A$4:$D$100,3,FALSE)) -> u | D42: 1 | E42: 21 | F42: 0.25 | G42: =ROUNDUP(((D42*E42)*(1+F42)),0) -> 27 | H42: =IF($A42=0,"",VLOOKUP($A42,'00_Eq'!$A$4:$D$100,4,FALSE)) -> 60000 | I42: =G42*H42 -> 1620000 | J42: PARA COLUMAS, VIGAS EN PB Y LOSA SOBRE PB
B43: =IF($A43=0,"",VLOOKUP($A43,'00_Eq'!$A$4:$D$100,2,FALSE)) | C43: =IF($A43=0,"",VLOOKUP($A43,'00_Eq'!$A$4:$D$100,3,FALSE)) | G43: =ROUNDUP(((D43*E43)*(1+F43)),0) -> 0 | H43: =IF($A43=0,"",VLOOKUP($A43,'00_Eq'!$A$4:$D$100,4,FALSE)) | I43: =G43*H43 -> 0
A44: E-MAR | B44: =IF($A44=0,"",VLOOKUP($A44,'00_Eq'!$A$4:$D$100,2,FALSE)) -> Martillete | C44: =IF($A44=0,"",VLOOKUP($A44,'00_Eq'!$A$4:$D$100,3,FALSE)) -> u | D44: 1 | E44: 7 | F44: 0.1 | G44: =ROUNDUP(((D44*E44)*(1+F44)),0) -> 8 | H44: =IF($A44=0,"",VLOOKUP($A44,'00_Eq'!$A$4:$D$100,4,FALSE)) -> 60000 | I44: =G44*H44 -> 480000 | J44: PARA INSTALACONES SANITARIAS
B45: =IF($A45=0,"",VLOOKUP($A45,'00_Eq'!$A$4:$D$100,2,FALSE)) | C45: =IF($A45=0,"",VLOOKUP($A45,'00_Eq'!$A$4:$D$100,3,FALSE)) | G45: =ROUNDUP(((D45*E45)*(1+F45)),0) -> 0 | H45: =IF($A45=0,"",VLOOKUP($A45,'00_Eq'!$A$4:$D$100,4,FALSE))
B46: =IF($A46=0,"",VLOOKUP($A46,'00_Eq'!$A$4:$D$100,2,FALSE)) | C46: =IF($A46=0,"",VLOOKUP($A46,'00_Eq'!$A$4:$D$100,3,FALSE)) | G46: =ROUNDUP(((D46*E46)*(1+F46)),0) -> 0 | H46: =IF($A46=0,"",VLOOKUP($A46,'00_Eq'!$A$4:$D$100,4,FALSE))
A48: TOTAL | I48: =SUM(I41:I46) -> 7500000
A49: =$I$3 -> gl | I49: =$H$3 -> 1
A50: TOTAL x | B50: =A49 -> gl | I50: =I48/I49 -> 7500000
A53: MANO DE OBRA - MATERIALES
A54: Código | B54: Descripción | C54: Unidad | D54: Cantidad | F54: Desperdicio | G54: Cantidad + Desperdicio | H54: Precio Unitario | I54: Subtotal
A55: PUN | B55: =IF($A55=0,"",VLOOKUP($A55,'00_Mat'!$A$4:$J$1135,2,FALSE)) -> Puntal | C55: =IF($A55=0,"",VLOOKUP($A55,'00_Mat'!$A$4:$J$1135,3,FALSE)) -> u | D55: 58 | F55: 0.25 | G55: =ROUNDUP((D55+(D55*F55)),0) -> 73 | H55: =IF($A55=0,"",VLOOKUP($A55,'00_Mat'!$A$4:$J$1135,5,FALSE)) -> 6900 | I55: =H55*G55 -> 503700 | J55: APUNTALAR TODA LA LOSA
B56: =IF($A56=0,"",VLOOKUP($A56,'00_Mat'!$A$4:$J$1135,2,FALSE)) | C56: =IF($A56=0,"",VLOOKUP($A56,'00_Mat'!$A$4:$J$1135,3,FALSE)) | F56: 0.25 | G56: =ROUNDUP((D56+(D56*F56)),0) -> 0 | H56: =IF($A56=0,"",VLOOKUP($A56,'00_Mat'!$A$4:$J$1135,5,FALSE))
B57: =IF($A57=0,"",VLOOKUP($A57,'00_Mat'!$A$4:$J$1135,2,FALSE)) | C57: =IF($A57=0,"",VLOOKUP($A57,'00_Mat'!$A$4:$J$1135,3,FALSE)) | F57: 0.25 | G57: =ROUNDUP((D57+(D57*F57)),0) -> 0 | H57: =IF($A57=0,"",VLOOKUP($A57,'00_Mat'!$A$4:$J$1135,5,FALSE))
B58: =IF($A58=0,"",VLOOKUP($A58,'00_Mat'!$A$4:$J$1135,2,FALSE)) | C58: =IF($A58=0,"",VLOOKUP($A58,'00_Mat'!$A$4:$J$1135,3,FALSE)) | F58: 0.25 | G58: =ROUNDUP((D58+(D58*F58)),0) -> 0 | H58: =IF($A58=0,"",VLOOKUP($A58,'00_Mat'!$A$4:$J$1135,5,FALSE))
B59: =IF($A59=0,"",VLOOKUP($A59,'00_Mat'!$A$4:$J$1135,2,FALSE)) | C59: =IF($A59=0,"",VLOOKUP($A59,'00_Mat'!$A$4:$J$1135,3,FALSE)) | F59: 0.25 | G59: =ROUNDUP((D59+(D59*F59)),0) -> 0 | H59: =IF($A59=0,"",VLOOKUP($A59,'00_Mat'!$A$4:$J$1135,5,FALSE))
B60: =IF($A60=0,"",VLOOKUP($A60,'00_Mat'!$A$4:$J$1135,2,FALSE)) | C60: =IF($A60=0,"",VLOOKUP($A60,'00_Mat'!$A$4:$J$1135,3,FALSE)) | F60: 0.25 | G60: =ROUNDUP((D60+(D60*F60)),0) -> 0 | H60: =IF($A60=0,"",VLOOKUP($A60,'00_Mat'!$A$4:$J$1135,5,FALSE))
A62: TOTAL | I62: =SUM(I55:I60) -> 503700
A63: =$I$3 -> gl | I63: =$H$3 -> 1
A64: TOTAL x | B64: =A63 -> gl | I64: =I62/I63 -> 503700
A67: MANO DE OBRA - SUBCONTRATOS
A68: Código | B68: Descripción | C68: Unidad | D68: Cantidad | E68: Dias | F68: Desperdicio | G68: Cantidad + Desperdicio | H68: Precio Unitario | I68: Subtotal
B69: =IF($A69=0,"",VLOOKUP($A69,'00_Sub'!$A$4:$D$1001,2,FALSE)) | C69: =IF($A69=0,"",VLOOKUP($A69,'00_Sub'!$A$4:$D$1001,3,FALSE)) | G69: =ROUNDUP((D69+(D69*F69)),0) -> 0 | H69: =IF($A69=0,"",VLOOKUP($A69,'00_Sub'!$A$4:$D$1001,4,FALSE))
B70: =IF($A70=0,"",VLOOKUP($A70,'00_Sub'!$A$4:$D$1001,2,FALSE)) | C70: =IF($A70=0,"",VLOOKUP($A70,'00_Sub'!$A$4:$D$1001,3,FALSE)) | G70: =ROUNDUP((D70+(D70*F70)),0) -> 0 | H70: =IF($A70=0,"",VLOOKUP($A70,'00_Sub'!$A$4:$D$1001,4,FALSE))
B71: =IF($A71=0,"",VLOOKUP($A71,'00_Sub'!$A$4:$D$1001,2,FALSE)) | C71: =IF($A71=0,"",VLOOKUP($A71,'00_Sub'!$A$4:$D$1001,3,FALSE)) | G71: =ROUNDUP((D71+(D71*F71)),0) -> 0 | H71: =IF($A71=0,"",VLOOKUP($A71,'00_Sub'!$A$4:$D$1001,4,FALSE))
B72: =IF($A72=0,"",VLOOKUP($A72,'00_Sub'!$A$4:$D$1001,2,FALSE)) | C72: =IF($A72=0,"",VLOOKUP($A72,'00_Sub'!$A$4:$D$1001,3,FALSE)) | G72: =ROUNDUP((D72+(D72*F72)),0) -> 0 | H72: =IF($A72=0,"",VLOOKUP($A72,'00_Sub'!$A$4:$D$1001,4,FALSE))
B73: =IF($A73=0,"",VLOOKUP($A73,'00_Sub'!$A$4:$D$1001,2,FALSE)) | C73: =IF($A73=0,"",VLOOKUP($A73,'00_Sub'!$A$4:$D$1001,3,FALSE)) | G73: =ROUNDUP((D73+(D73*F73)),0) -> 0 | H73: =IF($A73=0,"",VLOOKUP($A73,'00_Sub'!$A$4:$D$1001,4,FALSE))
B74: =IF($A74=0,"",VLOOKUP($A74,'00_Sub'!$A$4:$D$1001,2,FALSE)) | C74: =IF($A74=0,"",VLOOKUP($A74,'00_Sub'!$A$4:$D$1001,3,FALSE)) | G74: =ROUNDUP((D74+(D74*F74)),0) -> 0 | H74: =IF($A74=0,"",VLOOKUP($A74,'00_Sub'!$A$4:$D$1001,4,FALSE))
A76: TOTAL | I76: =SUM(I69:I74) -> 0
A77: =$I$3 -> gl | I77: =$H$3 -> 1
A78: TOTAL x | B78: =A77 -> gl | I78: =I76/I77 -> 0

Sheet 3.0-1
A1: ='01_C&P'!A1 -> CASA LUGONES
A3: ='01_C&P'!A36 -> 3.0-1 | B3: =IF($A3=0,"",VLOOKUP($A3,'01_C&P'!$A$9:$D$172,2,FALSE)) -> EXCAVACION DE BASES PARA REFORZAR ESTRUCTURA | H3: =IF($A3=0,"",VLOOKUP($A3,'01_C&P'!$A$9:$D$172,4,FALSE)) -> 14 | I3: =IF($A3=0,"",VLOOKUP($A3,'01_C&P'!$A$9:$D$172,3,FALSE)) -> unid.
A5: MATERIALES
A6: Código | B6: Descripción | C6: Unidad | D6: Cantidad | F6: Desperdicio | G6: Cantidad + Desperdicio | H6: Precio Unitario | I6: Subtotal
B7: =IF($A7=0,"",VLOOKUP($A7,'00_Mat'!$A$4:$J$1135,2,FALSE)) | C7: =IF($A7=0,"",VLOOKUP($A7,'00_Mat'!$A$4:$J$1135,3,FALSE)) | G7: =ROUNDUP((D7+(D7*F7)),0) -> 0 | H7: =IF($A7=0,"",VLOOKUP($A7,'00_Mat'!$A$4:$J$1135,5,FALSE)) | I7: =H7*G7 -> 0
B8: =IF($A8=0,"",VLOOKUP($A8,'00_Mat'!$A$4:$J$1135,2,FALSE)) | C8: =IF($A8=0,"",VLOOKUP($A8,'00_Mat'!$A$4:$J$1135,3,FALSE)) | G8: =ROUNDUP((D8+(D8*F8)),0) -> 0 | H8: =IF($A8=0,"",VLOOKUP($A8,'00_Mat'!$A$4:$J$1135,5,FALSE)) | I8: =H8*G8 -> 0
B9: =IF($A9=0,"",VLOOKUP($A9,'00_Mat'!$A$4:$J$1135,2,FALSE)) | C9: =IF($A9=0,"",VLOOKUP($A9,'00_Mat'!$A$4:$J$1135,3,FALSE)) | G9: =ROUNDUP((D9+(D9*F9)),0) -> 0 | H9: =IF($A9=0,"",VLOOKUP($A9,'00_Mat'!$A$4:$J$1135,5,FALSE)) | I9: =H9*G9 -> 0
B10: =IF($A10=0,"",VLOOKUP($A10,'00_Mat'!$A$4:$J$1135,2,FALSE)) | C10: =IF($A10=0,"",VLOOKUP($A10,'00_Mat'!$A$4:$J$1135,3,FALSE)) | G10: =ROUNDUP((D10+(D10*F10)),0) -> 0 | H10: =IF($A10=0,"",VLOOKUP($A10,'00_Mat'!$A$4:$J$1135,5,FALSE)) | I10: =H10*G10 -> 0
B11: =IF($A11=0,"",VLOOKUP($A11,'00_Mat'!$A$4:$J$1135,2,FALSE)) | C11: =IF($A11=0,"",VLOOKUP($A11,'00_Mat'!$A$4:$J$1135,3,FALSE)) | G11: =ROUNDUP((D11+(D11*F11)),0) -> 0 | H11: =IF($A11=0,"",VLOOKUP($A11,'00_Mat'!$A$4:$J$1135,5,FALSE)) | I11: =H11*G11 -> 0
B12: =IF($A12=0,"",VLOOKUP($A12,'00_Mat'!$A$4:$J$1135,2,FALSE)) | C12: =IF($A12=0,"",VLOOKUP($A12,'00_Mat'!$A$4:$J$1135,3,FALSE)) | G12: =ROUNDUP((D12+(D12*F12)),0) -> 0 | H12: =IF($A12=0,"",VLOOKUP($A12,'00_Mat'!$A$4:$J$1135,5,FALSE)) | I12: =H12*G12 -> 0
B13: =IF($A13=0,"",VLOOKUP($A13,'00_Mat'!$A$4:$J$1135,2,FALSE)) | C13: =IF($A13=0,"",VLOOKUP($A13,'00_Mat'!$A$4:$J$1135,3,FALSE)) | G13: =ROUNDUP((D13+(D13*F13)),0) -> 0 | H13: =IF($A13=0,"",VLOOKUP($A13,'00_Mat'!$A$4:$J$1135,5,FALSE)) | I13: =H13*G13 -> 0
B14: =IF($A14=0,"",VLOOKUP($A14,'00_Mat'!$A$4:$J$1135,2,FALSE)) | C14: =IF($A14=0,"",VLOOKUP($A14,'00_Mat'!$A$4:$J$1135,3,FALSE)) | G14: =ROUNDUP((D14+(D14*F14)),0) -> 0 | H14: =IF($A14=0,"",VLOOKUP($A14,'00_Mat'!$A$4:$J$1135,5,FALSE)) | I14: =H14*G14 -> 0
B15: =IF($A15=0,"",VLOOKUP($A15,'00_Mat'!$A$4:$J$1135,2,FALSE)) | C15: =IF($A15=0,"",VLOOKUP($A15,'00_Mat'!$A$4:$J$1135,3,FALSE)) | G15: =ROUNDUP((D15+(D15*F15)),0) -> 0 | H15: =IF($A15=0,"",VLOOKUP($A15,'00_Mat'!$A$4:$J$1135,5,FALSE)) | I15: =H15*G15 -> 0
B16: =IF($A16=0,"",VLOOKUP($A16,'00_Mat'!$A$4:$J$1135,2,FALSE)) | C16: =IF($A16=0,"",VLOOKUP($A16,'00_Mat'!$A$4:$J$1135,3,FALSE)) | G16: =ROUNDUP((D16+(D16*F16)),0) -> 0 | H16: =IF($A16=0,"",VLOOKUP($A16,'00_Mat'!$A$4:$J$1135,5,FALSE)) | I16: =H16*G16 -> 0
B17: =IF($A17=0,"",VLOOKUP($A17,'00_Mat'!$A$4:$J$1135,2,FALSE)) | C17: =IF($A17=0,"",VLOOKUP($A17,'00_Mat'!$A$4:$J$1135,3,FALSE)) | G17: =ROUNDUP((D17+(D17*F17)),0) -> 0 | H17: =IF($A17=0,"",VLOOKUP($A17,'00_Mat'!$A$4:$J$1135,5,FALSE)) | I17: =H17*G17 -> 0
B18: =IF($A18=0,"",VLOOKUP($A18,'00_Mat'!$A$4:$J$1135,2,FALSE)) | C18: =IF($A18=0,"",VLOOKUP($A18,'00_Mat'!$A$4:$J$1135,3,FALSE)) | G18: =ROUNDUP((D18+(D18*F18)),0) -> 0 | H18: =IF($A18=0,"",VLOOKUP($A18,'00_Mat'!$A$4:$J$1135,5,FALSE)) | I18: =H18*G18 -> 0
... B21: =IF($A21=0,"",VLOOKUP($A21,'00_Mat'!$A$4:$J$1135,2,FALSE)) | C21: =IF($A21=0,"",VLOOKUP($A21,'00_Mat'!$A$4:$J$1135,3,FALSE)) | G21: =ROUNDUP((D21+(D21*F21)),0) -> 0 | H21: =IF($A21=0,"",VLOOKUP($A21,'00_Mat'!$A$4:$J$1135,5,FALSE)) | I21: =H21*G21 -> 0
A23: TOTAL MATERIALES | I23: =SUM(I7:I18) -> 0
A24: =$I$3 -> unid. | I24: =$H$3 -> 14
A25: TOTAL x | B25: =A24 -> unid. | I25: =I23/I24 -> 0
A28: MANO DE OBRA - PERSONAS
A29: Código | B29: Descripción | C29: Unidad | D29: Cantidad | E29: Dias | F29: Desperdicio | G29: Cantidad + Desperdicio | H29: Precio Unitario | I29: Subtotal
A30: MO-CA | B30: =IF($A30=0,"",VLOOKUP($A30,'00_MO'!$A$4:$D$7,2,FALSE)) -> Capataz | C30: =IF($A30=0,"",VLOOKUP($A30,'00_MO'!$A$4:$D$7,3,FALSE)) -> u | D30: 1 | E30: 12 | F30: 0.25 | G30: =ROUNDUP(((D30*E30)*(1+F30)),0) -> 15 | H30: =IF($A30=0,"",VLOOKUP($A30,'00_MO'!$A$4:$D$7,4,FALSE)) -> 90000 | I30: =G30*H30 -> 1350000
A31: MO-OF | B31: =IF($A31=0,"",VLOOKUP($A31,'00_MO'!$A$4:$D$7,2,FALSE)) -> Oficial | C31: =IF($A31=0,"",VLOOKUP($A31,'00_MO'!$A$4:$D$7,3,FALSE)) -> u | D31: 2 | E31: 12 | F31: 0.25 | G31: =ROUNDUP(((D31*E31)*(1+F31)),0) -> 30 | H31: =IF($A31=0,"",VLOOKUP($A31,'00_MO'!$A$4:$D$7,4,FALSE)) -> 75000 | I31: =G31*H31 -> 2250000
A32: MO-AY | B32: =IF($A32=0,"",VLOOKUP($A32,'00_MO'!$A$4:$D$7,2,FALSE)) -> Ayudante | C32: =IF($A32=0,"",VLOOKUP($A32,'00_MO'!$A$4:$D$7,3,FALSE)) -> u | D32: 1 | E32: 12 | F32: 0.25 | G32: =ROUNDUP(((D32*E32)*(1+F32)),0) -> 15 | H32: =IF($A32=0,"",VLOOKUP($A32,'00_MO'!$A$4:$D$7,4,FALSE)) -> 60000 | I32: =G32*H32 -> 900000
B33: =IF($A33=0,"",VLOOKUP($A33,'00_MO'!$A$4:$D$7,2,FALSE)) | C33: =IF($A33=0,"",VLOOKUP($A33,'00_MO'!$A$4:$D$7,3,FALSE)) | G33: =ROUNDUP(((D33*E33)*(1+F33)),0) -> 0 | H33: =IF($A33=0,"",VLOOKUP($A33,'00_MO'!$A$4:$D$7,4,FALSE)) | I33: =G33*H33 -> 0
B34: =IF($A34=0,"",VLOOKUP($A34,'00_MO'!$A$4:$D$7,2,FALSE)) | C34: =IF($A34=0,"",VLOOKUP($A34,'00_MO'!$A$4:$D$7,3,FALSE)) | G34: =ROUNDUP(((D34*E34)*(1+F34)),0) -> 0 | H34: =IF($A34=0,"",VLOOKUP($A34,'00_MO'!$A$4:$D$7,4,FALSE)) | I34: =G34*H34 -> 0
B35: =IF($A35=0,"",VLOOKUP($A35,'00_MO'!$A$4:$D$7,2,FALSE)) | C35: =IF($A35=0,"",VLOOKUP($A35,'00_MO'!$A$4:$D$7,3,FALSE)) | G35: =ROUNDUP(((D35*E35)*(1+F35)),0) -> 0 | H35: =IF($A35=0,"",VLOOKUP($A35,'00_MO'!$A$4:$D$7,4,FALSE)) | I35: =G35*H35 -> 0
A37: TOTAL | I37: =SUM(I30:I35) -> 4500000
A38: =$I$3 -> unid. | I38: =$H$3 -> 14
A39: TOTAL x | B39: =A38 -> unid. | I39: =I37/I38 -> 321428.57
A42: MANO DE OBRA - EQUIPOS
A43: Código | B43: Descripción | C43: Unidad | D43: Cantidad | E43: Dias | F43: Desperdicio | G43: Cantidad + Desperdicio | H43: Precio Unitario | I43: Subtotal
A44: E-RET | B44: =IF($A44=0,"",VLOOKUP($A44,'00_Eq'!$A$4:$D$100,2,FALSE)) -> Retiro x camion | C44: =IF($A44=0,"",VLOOKUP($A44,'00_Eq'!$A$4:$D$100,3,FALSE)) -> u | D44: 1 | E44: 3 | F44: 0.25 | G44: =ROUNDUP(((D44*E44)*(1+F44)),0) -> 4 | H44: =IF($A44=0,"",VLOOKUP($A44,'00_Eq'!$A$4:$D$100,4,FALSE)) -> 250000 | I44: =G44*H44 -> 1000000
B45: =IF($A45=0,"",VLOOKUP($A45,'00_Eq'!$A$4:$D$100,2,FALSE)) | C45: =IF($A45=0,"",VLOOKUP($A45,'00_Eq'!$A$4:$D$100,3,FALSE)) | G45: =ROUNDUP(((D45*E45)*(1+F45)),0) -> 0 | H45: =IF($A45=0,"",VLOOKUP($A45,'00_Eq'!$A$4:$D$100,4,FALSE)) | I45: =G45*H45 -> 0
B46: =IF($A46=0,"",VLOOKUP($A46,'00_Eq'!$A$4:$D$100,2,FALSE)) | C46: =IF($A46=0,"",VLOOKUP($A46,'00_Eq'!$A$4:$D$100,3,FALSE)) | G46: =ROUNDUP(((D46*E46)*(1+F46)),0) -> 0 | H46: =IF($A46=0,"",VLOOKUP($A46,'00_Eq'!$A$4:$D$100,4,FALSE)) | I46: =G46*H46 -> 0
B47: =IF($A47=0,"",VLOOKUP($A47,'00_Eq'!$A$4:$D$100,2,FALSE)) | C47: =IF($A47=0,"",VLOOKUP($A47,'00_Eq'!$A$4:$D$100,3,FALSE)) | G47: =ROUNDUP(((D47*E47)*(1+F47)),0) -> 0 | H47: =IF($A47=0,"",VLOOKUP($A47,'00_Eq'!$A$4:$D$100,4,FALSE)) | I47: =G47*H47 -> 0
B48: =IF($A48=0,"",VLOOKUP($A48,'00_Eq'!$A$4:$D$100,2,FALSE)) | C48: =IF($A48=0,"",VLOOKUP($A48,'00_Eq'!$A$4:$D$100,3,FALSE)) | G48: =ROUNDUP(((D48*E48)*(1+F48)),0) -> 0 | H48: =IF($A48=0,"",VLOOKUP($A48,'00_Eq'!$A$4:$D$100,4,FALSE))
B49: =IF($A49=0,"",VLOOKUP($A49,'00_Eq'!$A$4:$D$100,2,FALSE)) | C49: =IF($A49=0,"",VLOOKUP($A49,'00_Eq'!$A$4:$D$100,3,FALSE)) | G49: =ROUNDUP(((D49*E49)*(1+F49)),0) -> 0 | H49: =IF($A49=0,"",VLOOKUP($A49,'00_Eq'!$A$4:$D$100,4,FALSE))
A51: TOTAL | I51: =SUM(I44:I49) -> 1000000
A52: =$I$3 -> unid. | I52: =$H$3 -> 14
A53: TOTAL x | B53: =A52 -> unid. | I53: =I51/I52 -> 71428.571
A56: MANO DE OBRA - MATERIALES
A57: Código | B57: Descripción | C57: Unidad | D57: Cantidad | F57: Desperdicio | G57: Cantidad + Desperdicio | H57: Precio Unitario | I57: Subtotal
B58: =IF($A58=0,"",VLOOKUP($A58,'00_Mat'!$A$4:$J$1135,2,FALSE)) | C58: =IF($A58=0,"",VLOOKUP($A58,'00_Mat'!$A$4:$J$1135,3,FALSE)) | G58: =ROUNDUP((D58+(D58*F58)),0) -> 0 | H58: =IF($A58=0,"",VLOOKUP($A58,'00_Mat'!$A$4:$J$1135,5,FALSE)) | I58: =H58*G58 -> 0
B59: =IF($A59=0,"",VLOOKUP($A59,'00_Mat'!$A$4:$J$1135,2,FALSE)) | C59: =IF($A59=0,"",VLOOKUP($A59,'00_Mat'!$A$4:$J$1135,3,FALSE)) | G59: =ROUNDUP((D59+(D59*F59)),0) -> 0 | H59: =IF($A59=0,"",VLOOKUP($A59,'00_Mat'!$A$4:$J$1135,5,FALSE)) | I59: =H59*G59 -> 0
B60: =IF($A60=0,"",VLOOKUP($A60,'00_Mat'!$A$4:$J$1135,2,FALSE)) | C60: =IF($A60=0,"",VLOOKUP($A60,'00_Mat'!$A$4:$J$1135,3,FALSE)) | G60: =ROUNDUP((D60+(D60*F60)),0) -> 0 | H60: =IF($A60=0,"",VLOOKUP($A60,'00_Mat'!$A$4:$J$1135,5,FALSE)) | I60: =H60*G60 -> 0
B61: =IF($A61=0,"",VLOOKUP($A61,'00_Mat'!$A$4:$J$1135,2,FALSE)) | C61: =IF($A61=0,"",VLOOKUP($A61,'00_Mat'!$A$4:$J$1135,3,FALSE)) | G61: =ROUNDUP((D61+(D61*F61)),0) -> 0 | H61: =IF($A61=0,"",VLOOKUP($A61,'00_Mat'!$A$4:$J$1135,5,FALSE)) | I61: =H61*G61 -> 0
B62: =IF($A62=0,"",VLOOKUP($A62,'00_Mat'!$A$4:$J$1135,2,FALSE)) | C62: =IF($A62=0,"",VLOOKUP($A62,'00_Mat'!$A$4:$J$1135,3,FALSE)) | G62: =ROUNDUP((D62+(D62*F62)),0) -> 0 | H62: =IF($A62=0,"",VLOOKUP($A62,'00_Mat'!$A$4:$J$1135,5,FALSE)) | I62: =H62*G62 -> 0
B63: =IF($A63=0,"",VLOOKUP($A63,'00_Mat'!$A$4:$J$1135,2,FALSE)) | C63: =IF($A63=0,"",VLOOKUP($A63,'00_Mat'!$A$4:$J$1135,3,FALSE)) | G63: =ROUNDUP((D63+(D63*F63)),0) -> 0 | H63: =IF($A63=0,"",VLOOKUP($A63,'00_Mat'!$A$4:$J$1135,5,FALSE)) | I63: =H63*G63 -> 0
B64: =IF($A64=0,"",VLOOKUP($A64,'00_Mat'!$A$4:$J$1135,2,FALSE)) | C64: =IF($A64=0,"",VLOOKUP($A64,'00_Mat'!$A$4:$J$1135,3,FALSE)) | G64: =ROUNDUP((D64+(D64*F64)),0) -> 0 | H64: =IF($A64=0,"",VLOOKUP($A64,'00_Mat'!$A$4:$J$1135,5,FALSE)) | I64: =H64*G64 -> 0
A65: TOTAL | I65: =SUM(I58:I64) -> 0
A66: =$I$3 -> unid. | I66: =$H$3 -> 14
A67: TOTAL x | B67: =A66 -> unid. | I67: =I65/I66 -> 0
A70: MANO DE OBRA - SUBCONTRATOS
A71: Código | B71: Descripción | C71: Unidad | D71: Cantidad | E71: Dias | F71: Desperdicio | G71: Cantidad + Desperdicio | H71: Precio Unitario | I71: Subtotal
B72: =IF($A72=0,"",VLOOKUP($A72,'00_Sub'!$A$4:$D$1001,2,FALSE)) | C72: =IF($A72=0,"",VLOOKUP($A72,'00_Sub'!$A$4:$D$1001,3,FALSE)) | G72: =ROUNDUP((D72+(D72*F72)),0) -> 0 | H72: =IF($A72=0,"",VLOOKUP($A72,'00_Sub'!$A$4:$D$1001,4,FALSE))
B73: =IF($A73=0,"",VLOOKUP($A73,'00_Sub'!$A$4:$D$1001,2,FALSE)) | C73: =IF($A73=0,"",VLOOKUP($A73,'00_Sub'!$A$4:$D$1001,3,FALSE)) | G73: =ROUNDUP((D73+(D73*F73)),0) -> 0 | H73: =IF($A73=0,"",VLOOKUP($A73,'00_Sub'!$A$4:$D$1001,4,FALSE))
B74: =IF($A74=0,"",VLOOKUP($A74,'00_Sub'!$A$4:$D$1001,2,FALSE)) | C74: =IF($A74=0,"",VLOOKUP($A74,'00_Sub'!$A$4:$D$1001,3,FALSE)) | G74: =ROUNDUP((D74+(D74*F74)),0) -> 0 | H74: =IF($A74=0,"",VLOOKUP($A74,'00_Sub'!$A$4:$D$1001,4,FALSE))
B75: =IF($A75=0,"",VLOOKUP($A75,'00_Sub'!$A$4:$D$1001,2,FALSE)) | C75: =IF($A75=0,"",VLOOKUP($A75,'00_Sub'!$A$4:$D$1001,3,FALSE)) | G75: =ROUNDUP((D75+(D75*F75)),0) -> 0 | H75: =IF($A75=0,"",VLOOKUP($A75,'00_Sub'!$A$4:$D$1001,4,FALSE))
B76: =IF($A76=0,"",VLOOKUP($A76,'00_Sub'!$A$4:$D$1001,2,FALSE)) | C76: =IF($A76=0,"",VLOOKUP($A76,'00_Sub'!$A$4:$D$1001,3,FALSE)) | G76: =ROUNDUP((D76+(D76*F76)),0) -> 0 | H76: =IF($A76=0,"",VLOOKUP($A76,'00_Sub'!$A$4:$D$1001,4,FALSE))
B77: =IF($A77=0,"",VLOOKUP($A77,'00_Sub'!$A$4:$D$1001,2,FALSE)) | C77: =IF($A77=0,"",VLOOKUP($A77,'00_Sub'!$A$4:$D$1001,3,FALSE)) | G77: =ROUNDUP((D77+(D77*F77)),0) -> 0 | H77: =IF($A77=0,"",VLOOKUP($A77,'00_Sub'!$A$4:$D$1001,4,FALSE))
A79: TOTAL | I79: =SUM(I72:I77) -> 0
A80: =$I$3 -> unid. | I80: =$H$3 -> 14
A81: TOTAL x | B81: =A80 -> unid. | I81: =I79/I80 -> 0

Sheet 3.0-2
A1: ='01_C&P'!A1 -> CASA LUGONES
A3: ='01_C&P'!A37 -> 3.0-2 | B3: =IF($A3=0,"",VLOOKUP($A3,'01_C&P'!$A$9:$D$172,2,FALSE)) -> EJECUCION DE BASES DE H 30 100x100 + TRONCO 25X25x100 + TENSORES 30x40cm | H3: =IF($A3=0,"",VLOOKUP($A3,'01_C&P'!$A$9:$D$172,4,FALSE)) -> 14 | I3: =IF($A3=0,"",VLOOKUP($A3,'01_C&P'!$A$9:$D$172,3,FALSE)) -> unid. | L3: REFERENCIA: VIVIENDAS
A5: MATERIALES
A6: Código | B6: Descripción | C6: Unidad | D6: Cantidad | F6: Desperdicio | G6: Cantidad + Desperdicio | H6: Precio Unitario | I6: Subtotal | O6: m3 | P6: CANTIDAD
A7: H30 | B7: =IF($A7=0,"",VLOOKUP($A7,'00_Mat'!$A$4:$J$1135,2,FALSE)) -> Hormigon H30 | C7: =IF($A7=0,"",VLOOKUP($A7,'00_Mat'!$A$4:$J$1135,3,FALSE)) -> m3 | D7: =O7+O8+O9+O10 -> 11.4065 | F7: 0.1 | G7: =ROUNDUP((D7+(D7*F7)),0) -> 13 | H7: =IF($A7=0,"",VLOOKUP($A7,'00_Mat'!$A$4:$J$1135,5,FALSE)) -> 125280 | I7: =H7*G7 -> 1628640 | J7: BASES + TRONCO | L7: 5 bases excentricas 1x1 | N7: 100x100X30 | O7: =(1*1*0.3)*5 -> 1.5 | P7: 5
A8: HADN12 | B8: =IF($A8=0,"",VLOOKUP($A8,'00_Mat'!$A$4:$J$1135,2,FALSE)) -> Hierros ADN 420 Φ 12 | C8: =IF($A8=0,"",VLOOKUP($A8,'00_Mat'!$A$4:$J$1135,3,FALSE)) -> u | D8: =P7*((16*0.8)/12) -> 5.3333333 | F8: 0.1 | G8: =ROUNDUP((D8+(D8*F8)),0) -> 6 | H8: =IF($A8=0,"",VLOOKUP($A8,'00_Mat'!$A$4:$J$1135,5,FALSE)) -> 20442.5 | I8: =H8*G8 -> 122655 | L8: 9 bases medianera | N8: 60x120*30 | O8: =(0.6*1.2*0.3)*9 -> 1.944 | P8: 9
A9: HADN12 | B9: =IF($A9=0,"",VLOOKUP($A9,'00_Mat'!$A$4:$J$1135,2,FALSE)) -> Hierros ADN 420 Φ 12 | C9: =IF($A9=0,"",VLOOKUP($A9,'00_Mat'!$A$4:$J$1135,3,FALSE)) -> u | D9: =((0.8*4)*H3)/12 -> 3.7333333 | E9: TRONCOS | F9: 0.1 | G9: =ROUNDUP((D9+(D9*F9)),0) -> 5 | H9: =IF($A9=0,"",VLOOKUP($A9,'00_Mat'!$A$4:$J$1135,5,FALSE)) -> 20442.5 | I9: =H9*G9 -> 102212.5 | L9: columnas medianera | N9: 20x65 | O9: =(0.2+0.65*1)*9 -> 7.65 | P9: 9
A10: HADN16 | B10: =IF($A10=0,"",VLOOKUP($A10,'00_Mat'!$A$4:$J$1135,2,FALSE)) -> Hierros ADN 420 Φ 16 | C10: =IF($A10=0,"",VLOOKUP($A10,'00_Mat'!$A$4:$J$1135,3,FALSE)) -> u | D10: =((0.8*4)*P8)/12 -> 2.4 | E10: TRONCO MED | F10: 0.1 | G10: =ROUNDUP((D10+(D10*F10)),0) -> 3 | H10: =IF($A10=0,"",VLOOKUP($A10,'00_Mat'!$A$4:$J$1135,5,FALSE)) -> 36603.12 | I10: =H10*G10 -> 109809.36 | L10: columnas excentricas | N10: 30x30 | O10: =(0.25*0.25*1)*5 -> 0.3125 | P10: 5
A11: HADN6 | B11: =IF($A11=0,"",VLOOKUP($A11,'00_Mat'!$A$4:$J$1135,2,FALSE)) -> Hierros ADN 420 Φ 6 | C11: =IF($A11=0,"",VLOOKUP($A11,'00_Mat'!$A$4:$J$1135,3,FALSE)) -> u | D11: =((1.8*10)/12)*P9 -> 13.5 | E11: TRONCO MED | F11: 0.1 | G11: =ROUNDUP((D11+(D11*F11)),0) -> 15 | H11: =IF($A11=0,"",VLOOKUP($A11,'00_Mat'!$A$4:$J$1135,5,FALSE)) -> 5250 | I11: =H11*G11 -> 78750
A12: HADN6 | B12: =IF($A12=0,"",VLOOKUP($A12,'00_Mat'!$A$4:$J$1135,2,FALSE)) -> Hierros ADN 420 Φ 6 | C12: =IF($A12=0,"",VLOOKUP($A12,'00_Mat'!$A$4:$J$1135,3,FALSE)) -> u | D12: =((1.3*10)/12)*P10 -> 5.4166667 | E12: TRONCO EX | F12: 0.1 | G12: =ROUNDUP((D12+(D12*F12)),0) -> 6 | H12: =IF($A12=0,"",VLOOKUP($A12,'00_Mat'!$A$4:$J$1135,5,FALSE)) -> 5250 | I12: =H12*G12 -> 31500
A13: H30 | B13: =IF($A13=0,"",VLOOKUP($A13,'00_Mat'!$A$4:$J$1135,2,FALSE)) -> Hormigon H30 | C13: =IF($A13=0,"",VLOOKUP($A13,'00_Mat'!$A$4:$J$1135,3,FALSE)) -> m3 | D13: =N19 -> 3.36 | F13: 0.1 | G13: =ROUNDUP((D13+(D13*F13)),0) -> 4 | H13: =IF($A13=0,"",VLOOKUP($A13,'00_Mat'!$A$4:$J$1135,5,FALSE)) -> 125280 | I13: =H13*G13 -> 501120 | J13: TENSORES
A14: HADN10 | B14: =IF($A14=0,"",VLOOKUP($A14,'00_Mat'!$A$4:$J$1135,2,FALSE)) -> Hierros ADN 420Φ 10 | C14: =IF($A14=0,"",VLOOKUP($A14,'00_Mat'!$A$4:$J$1135,3,FALSE)) -> u | D14: =(28*6)/12 -> 14 | F14: 0.1 | G14: =ROUNDUP((D14+(D14*F14)),0) -> 16 | H14: =IF($A14=0,"",VLOOKUP($A14,'00_Mat'!$A$4:$J$1135,5,FALSE)) -> 10000 | I14: =H14*G14 -> 160000
A15: HADN6 | B15: =IF($A15=0,"",VLOOKUP($A15,'00_Mat'!$A$4:$J$1135,2,FALSE)) -> Hierros ADN 420 Φ 6 | C15: =IF($A15=0,"",VLOOKUP($A15,'00_Mat'!$A$4:$J$1135,3,FALSE)) -> u | D15: =((28/0.15)*1.3)/12 -> 20.222222 | F15: 0.1 | G15: =ROUNDUP((D15+(D15*F15)),0) -> 23 | H15: =IF($A15=0,"",VLOOKUP($A15,'00_Mat'!$A$4:$J$1135,5,FALSE)) -> 5250 | I15: =H15*G15 -> 120750
A16: A-NY20050m2 | B16: =IF($A16=0,"",VLOOKUP($A16,'00_Mat'!$A$4:$J$1135,2,FALSE)) -> Nylon 200 Micrones (50 m2 x rollo) | C16: =IF($A16=0,"",VLOOKUP($A16,'00_Mat'!$A$4:$J$1135,3,FALSE)) | D16: 1 | F16: 0 | G16: =ROUNDUP((D16+(D16*F16)),0) -> 1 | H16: =IF($A16=0,"",VLOOKUP($A16,'00_Mat'!$A$4:$J$1135,5,FALSE)) -> 38100 | I16: =H16*G16 -> 38100
B17: =IF($A17=0,"",VLOOKUP($A17,'00_Mat'!$A$4:$J$1135,2,FALSE)) | C17: =IF($A17=0,"",VLOOKUP($A17,'00_Mat'!$A$4:$J$1135,3,FALSE)) | G17: =ROUNDUP((D17+(D17*F17)),0) -> 0 | H17: =IF($A17=0,"",VLOOKUP($A17,'00_Mat'!$A$4:$J$1135,5,FALSE)) | I17: =H17*G17 -> 0 | L17: TENSORES CALCULADOS COMO VIGAS DE ENCADENADO
B18: =IF($A18=0,"",VLOOKUP($A18,'00_Mat'!$A$4:$J$1135,2,FALSE)) | C18: =IF($A18=0,"",VLOOKUP($A18,'00_Mat'!$A$4:$J$1135,3,FALSE)) | G18: =ROUNDUP((D18+(D18*F18)),0) -> 0 | H18: =IF($A18=0,"",VLOOKUP($A18,'00_Mat'!$A$4:$J$1135,5,FALSE)) | I18: =H18*G18 -> 0
B19: =IF($A19=0,"",VLOOKUP($A19,'00_Mat'!$A$4:$J$1135,2,FALSE)) | C19: =IF($A19=0,"",VLOOKUP($A19,'00_Mat'!$A$4:$J$1135,3,FALSE)) | G19: =ROUNDUP((D19+(D19*F19)),0) -> 0 | H19: =IF($A19=0,"",VLOOKUP($A19,'00_Mat'!$A$4:$J$1135,5,FALSE)) | I19: =H19*G19 -> 0 | L19: 28M DE TENSORES | N19: =0.3*0.4*28 -> 3.36 | O19: m3
B20: =IF($A20=0,"",VLOOKUP($A20,'00_Mat'!$A$4:$J$1135,2,FALSE)) | C20: =IF($A20=0,"",VLOOKUP($A20,'00_Mat'!$A$4:$J$1135,3,FALSE)) | G20: =ROUNDUP((D20+(D20*F20)),0) -> 0 | H20: =IF($A20=0,"",VLOOKUP($A20,'00_Mat'!$A$4:$J$1135,5,FALSE)) | I20: =H20*G20 -> 0
B21: =IF($A21=0,"",VLOOKUP($A21,'00_Mat'!$A$4:$J$1135,2,FALSE)) | C21: =IF($A21=0,"",VLOOKUP($A21,'00_Mat'!$A$4:$J$1135,3,FALSE)) | G21: =ROUNDUP((D21+(D21*F21)),0) -> 0 | H21: =IF($A21=0,"",VLOOKUP($A21,'00_Mat'!$A$4:$J$1135,5,FALSE)) | I21: =H21*G21 -> 0
B22: =IF($A22=0,"",VLOOKUP($A22,'00_Mat'!$A$4:$J$1135,2,FALSE)) | C22: =IF($A22=0,"",VLOOKUP($A22,'00_Mat'!$A$4:$J$1135,3,FALSE)) | G22: =ROUNDUP((D22+(D22*F22)),0) -> 0 | H22: =IF($A22=0,"",VLOOKUP($A22,'00_Mat'!$A$4:$J$1135,5,FALSE)) | I22: =H22*G22 -> 0
A24: TOTAL MATERIALES | I24: =SUM(I7:I19) -> 2893536.9
A25: =$I$3 -> unid. | I25: =$H$3 -> 14
A26: TOTAL x | B26: =A25 -> unid. | I26: =I24/I25 -> 206681.2
A29: MANO DE OBRA - PERSONAS
A30: Código | B30: Descripción | C30: Unidad | D30: Cantidad | E30: Dias | F30: Desperdicio | G30: Cantidad + Desperdicio | H30: Precio Unitario | I30: Subtotal
A31: MO-CA | B31: =IF($A31=0,"",VLOOKUP($A31,'00_MO'!$A$4:$D$7,2,FALSE)) -> Capataz | C31: =IF($A31=0,"",VLOOKUP($A31,'00_MO'!$A$4:$D$7,3,FALSE)) -> u | D31: 1 | E31: =7+3 -> 10 | F31: 0.25 | G31: =ROUNDUP(((D31*E31)*(1+F31)),0) -> 13 | H31: =IF($A31=0,"",VLOOKUP($A31,'00_MO'!$A$4:$D$7,4,FALSE)) -> 90000 | I31: =G31*H31 -> 1170000 | L31: 1/2 dia x base y 3 dias totales de tensores
A32: MO-OF | B32: =IF($A32=0,"",VLOOKUP($A32,'00_MO'!$A$4:$D$7,2,FALSE)) -> Oficial | C32: =IF($A32=0,"",VLOOKUP($A32,'00_MO'!$A$4:$D$7,3,FALSE)) -> u | D32: 2 | E32: =7+3 -> 10 | F32: 0.25 | G32: =ROUNDUP(((D32*E32)*(1+F32)),0) -> 25 | H32: =IF($A32=0,"",VLOOKUP($A32,'00_MO'!$A$4:$D$7,4,FALSE)) -> 75000 | I32: =G32*H32 -> 1875000
A33: MO-AY | B33: =IF($A33=0,"",VLOOKUP($A33,'00_MO'!$A$4:$D$7,2,FALSE)) -> Ayudante | C33: =IF($A33=0,"",VLOOKUP($A33,'00_MO'!$A$4:$D$7,3,FALSE)) -> u | D33: 1 | E33: =7+3 -> 10 | F33: 0.25 | G33: =ROUNDUP(((D33*E33)*(1+F33)),0) -> 13 | H33: =IF($A33=0,"",VLOOKUP($A33,'00_MO'!$A$4:$D$7,4,FALSE)) -> 60000 | I33: =G33*H33 -> 780000
B34: =IF($A34=0,"",VLOOKUP($A34,'00_MO'!$A$4:$D$7,2,FALSE)) | C34: =IF($A34=0,"",VLOOKUP($A34,'00_MO'!$A$4:$D$7,3,FALSE)) | G34: =ROUNDUP(((D34*E34)*(1+F34)),0) -> 0 | H34: =IF($A34=0,"",VLOOKUP($A34,'00_MO'!$A$4:$D$7,4,FALSE)) | I34: =G34*H34 -> 0
B35: =IF($A35=0,"",VLOOKUP($A35,'00_MO'!$A$4:$D$7,2,FALSE)) | C35: =IF($A35=0,"",VLOOKUP($A35,'00_MO'!$A$4:$D$7,3,FALSE)) | G35: =ROUNDUP(((D35*E35)*(1+F35)),0) -> 0 | H35: =IF($A35=0,"",VLOOKUP($A35,'00_MO'!$A$4:$D$7,4,FALSE)) | I35: =G35*H35 -> 0
B36: =IF($A36=0,"",VLOOKUP($A36,'00_MO'!$A$4:$D$7,2,FALSE)) | C36: =IF($A36=0,"",VLOOKUP($A36,'00_MO'!$A$4:$D$7,3,FALSE)) | G36: =ROUNDUP(((D36*E36)*(1+F36)),0) -> 0 | H36: =IF($A36=0,"",VLOOKUP($A36,'00_MO'!$A$4:$D$7,4,FALSE)) | I36: =G36*H36 -> 0
A38: TOTAL | I38: =SUM(I31:I36) -> 3825000
A39: =$I$3 -> unid. | I39: =$H$3 -> 14
A40: TOTAL x | B40: =A39 -> unid. | I40: =I38/I39 -> 273214.29
A43: MANO DE OBRA - EQUIPOS
A44: Código | B44: Descripción | C44: Unidad | D44: Cantidad | E44: Dias | F44: Desperdicio | G44: Cantidad + Desperdicio | H44: Precio Unitario | I44: Subtotal
B45: =IF($A45=0,"",VLOOKUP($A45,'00_Eq'!$A$4:$D$100,2,FALSE)) | C45: =IF($A45=0,"",VLOOKUP($A45,'00_Eq'!$A$4:$D$100,3,FALSE)) | G45: =ROUNDUP(((D45*E45)*(1+F45)),0) -> 0 | H45: =IF($A45=0,"",VLOOKUP($A45,'00_Eq'!$A$4:$D$100,4,FALSE)) | I45: =G45*H45 -> 0
B46: =IF($A46=0,"",VLOOKUP($A46,'00_Eq'!$A$4:$D$100,2,FALSE)) | C46: =IF($A46=0,"",VLOOKUP($A46,'00_Eq'!$A$4:$D$100,3,FALSE)) | G46: =ROUNDUP(((D46*E46)*(1+F46)),0) -> 0 | H46: =IF($A46=0,"",VLOOKUP($A46,'00_Eq'!$A$4:$D$100,4,FALSE)) | I46: =G46*H46 -> 0
B47: =IF($A47=0,"",VLOOKUP($A47,'00_Eq'!$A$4:$D$100,2,FALSE)) | C47: =IF($A47=0,"",VLOOKUP($A47,'00_Eq'!$A$4:$D$100,3,FALSE)) | G47: =ROUNDUP(((D47*E47)*(1+F47)),0) -> 0 | H47: =IF($A47=0,"",VLOOKUP($A47,'00_Eq'!$A$4:$D$100,4,FALSE)) | I47: =G47*H47 -> 0
B48: =IF($A48=0,"",VLOOKUP($A48,'00_Eq'!$A$4:$D$100,2,FALSE)) | C48: =IF($A48=0,"",VLOOKUP($A48,'00_Eq'!$A$4:$D$100,3,FALSE)) | G48: =ROUNDUP(((D48*E48)*(1+F48)),0) -> 0 | H48: =IF($A48=0,"",VLOOKUP($A48,'00_Eq'!$A$4:$D$100,4,FALSE)) | I48: =G48*H48 -> 0
B49: =IF($A49=0,"",VLOOKUP($A49,'00_Eq'!$A$4:$D$100,2,FALSE)) | C49: =IF($A49=0,"",VLOOKUP($A49,'00_Eq'!$A$4:$D$100,3,FALSE)) | G49: =ROUNDUP(((D49*E49)*(1+F49)),0) -> 0 | H49: =IF($A49=0,"",VLOOKUP($A49,'00_Eq'!$A$4:$D$100,4,FALSE))
B50: =IF($A50=0,"",VLOOKUP($A50,'00_Eq'!$A$4:$D$100,2,FALSE)) | C50: =IF($A50=0,"",VLOOKUP($A50,'00_Eq'!$A$4:$D$100,3,FALSE)) | G50: =ROUNDUP(((D50*E50)*(1+F50)),0) -> 0 | H50: =IF($A50=0,"",VLOOKUP($A50,'00_Eq'!$A$4:$D$100,4,FALSE))
A52: TOTAL | I52: =SUM(I45:I50) -> 0
A53: =$I$3 -> unid. | I53: =$H$3 -> 14
A54: TOTAL x | B54: =A53 -> unid. | I54: =I52/I53 -> 0
A57: MANO DE OBRA - MATERIALES
A58: Código | B58: Descripción | C58: Unidad | D58: Cantidad | F58: Desperdicio | G58: Cantidad + Desperdicio | H58: Precio Unitario | I58: Subtotal
A59: dis | B59: =IF($A59=0,"",VLOOKUP($A59,'00_Mat'!$A$4:$J$1135,2,FALSE)) -> Disco corte | C59: =IF($A59=0,"",VLOOKUP($A59,'00_Mat'!$A$4:$J$1135,3,FALSE)) -> u | D59: 2 | F59: 0.1 | G59: =ROUNDUP((D59+(D59*F59)),0) -> 3 | H59: =IF($A59=0,"",VLOOKUP($A59,'00_Mat'!$A$4:$J$1135,5,FALSE)) -> 40000 | I59: =H59*G59 -> 120000
A60: AL | B60: =IF($A60=0,"",VLOOKUP($A60,'00_Mat'!$A$4:$J$1135,2,FALSE)) -> Alambre Fardo (k) | C60: =IF($A60=0,"",VLOOKUP($A60,'00_Mat'!$A$4:$J$1135,3,FALSE)) -> k | D60: 20 | F60: 0.1 | G60: =ROUNDUP((D60+(D60*F60)),0) -> 22 | H60: =IF($A60=0,"",VLOOKUP($A60,'00_Mat'!$A$4:$J$1135,5,FALSE)) -> 4326.45 | I60: =H60*G60 -> 95181.9
A61: CL2 | B61: =IF($A61=0,"",VLOOKUP($A61,'00_Mat'!$A$4:$J$1135,2,FALSE)) -> Clavos 2" punta paris (k) | C61: =IF($A61=0,"",VLOOKUP($A61,'00_Mat'!$A$4:$J$1135,3,FALSE)) -> k | D61: 15 | F61: 0.1 | G61: =ROUNDUP((D61+(D61*F61)),0) -> 17 | H61: =IF($A61=0,"",VLOOKUP($A61,'00_Mat'!$A$4:$J$1135,5,FALSE)) -> 3739.67 | I61: =H61*G61 -> 63574.39
A62: CL2.5 | B62: =IF($A62=0,"",VLOOKUP($A62,'00_Mat'!$A$4:$J$1135,2,FALSE)) -> Clavos 2,5" punta paris (k) | C62: =IF($A62=0,"",VLOOKUP($A62,'00_Mat'!$A$4:$J$1135,3,FALSE)) -> k | D62: 15 | F62: 0.1 | G62: =ROUNDUP((D62+(D62*F62)),0) -> 17 | H62: =IF($A62=0,"",VLOOKUP($A62,'00_Mat'!$A$4:$J$1135,5,FALSE)) -> 3739.67 | I62: =H62*G62 -> 63574.39
B63: =IF($A63=0,"",VLOOKUP($A63,'00_Mat'!$A$4:$J$1135,2,FALSE)) | C63: =IF($A63=0,"",VLOOKUP($A63,'00_Mat'!$A$4:$J$1135,3,FALSE)) | F63: 0.1 | G63: =ROUNDUP((D63+(D63*F63)),0) -> 0 | H63: =IF($A63=0,"",VLOOKUP($A63,'00_Mat'!$A$4:$J$1135,5,FALSE)) | I63: =H63*G63 -> 0
B64: =IF($A64=0,"",VLOOKUP($A64,'00_Mat'!$A$4:$J$1135,2,FALSE)) | C64: =IF($A64=0,"",VLOOKUP($A64,'00_Mat'!$A$4:$J$1135,3,FALSE)) | F64: 0.1 | G64: =ROUNDUP((D64+(D64*F64)),0) -> 0 | H64: =IF($A64=0,"",VLOOKUP($A64,'00_Mat'!$A$4:$J$1135,5,FALSE)) | I64: =H64*G64 -> 0
B65: =IF($A65=0,"",VLOOKUP($A65,'00_Mat'!$A$4:$J$1135,2,FALSE)) | C65: =IF($A65=0,"",VLOOKUP($A65,'00_Mat'!$A$4:$J$1135,3,FALSE)) | F65: 0.1 | G65: =ROUNDUP((D65+(D65*F65)),0) -> 0 | H65: =IF($A65=0,"",VLOOKUP($A65,'00_Mat'!$A$4:$J$1135,5,FALSE)) | I65: =H65*G65 -> 0
A66: TOTAL | I66: =SUM(I59:I65) -> 342330.68
A67: =$I$3 -> unid. | I67: =$H$3 -> 14
A68: TOTAL x | B68: =A67 -> unid. | I68: =I66/I67 -> 24452.191
A71: MANO DE OBRA - SUBCONTRATOS
A72: Código | B72: Descripción | C72: Unidad | D72: Cantidad | E72: Dias | F72: Desperdicio | G72: Cantidad + Desperdicio | H72: Precio Unitario | I72: Subtotal
B73: =IF($A73=0,"",VLOOKUP($A73,'00_Sub'!$A$4:$D$1001,2,FALSE)) | C73: =IF($A73=0,"",VLOOKUP($A73,'00_Sub'!$A$4:$D$1001,3,FALSE)) | G73: =ROUNDUP((D73+(D73*F73)),0) -> 0 | H73: =IF($A73=0,"",VLOOKUP($A73,'00_Sub'!$A$4:$D$1001,4,FALSE))
B74: =IF($A74=0,"",VLOOKUP($A74,'00_Sub'!$A$4:$D$1001,2,FALSE)) | C74: =IF($A74=0,"",VLOOKUP($A74,'00_Sub'!$A$4:$D$1001,3,FALSE)) | G74: =ROUNDUP((D74+(D74*F74)),0) -> 0 | H74: =IF($A74=0,"",VLOOKUP($A74,'00_Sub'!$A$4:$D$1001,4,FALSE))
B75: =IF($A75=0,"",VLOOKUP($A75,'00_Sub'!$A$4:$D$1001,2,FALSE)) | C75: =IF($A75=0,"",VLOOKUP($A75,'00_Sub'!$A$4:$D$1001,3,FALSE)) | G75: =ROUNDUP((D75+(D75*F75)),0) -> 0 | H75: =IF($A75=0,"",VLOOKUP($A75,'00_Sub'!$A$4:$D$1001,4,FALSE))
B76: =IF($A76=0,"",VLOOKUP($A76,'00_Sub'!$A$4:$D$1001,2,FALSE)) | C76: =IF($A76=0,"",VLOOKUP($A76,'00_Sub'!$A$4:$D$1001,3,FALSE)) | G76: =ROUNDUP((D76+(D76*F76)),0) -> 0 | H76: =IF($A76=0,"",VLOOKUP($A76,'00_Sub'!$A$4:$D$1001,4,FALSE))
B77: =IF($A77=0,"",VLOOKUP($A77,'00_Sub'!$A$4:$D$1001,2,FALSE)) | C77: =IF($A77=0,"",VLOOKUP($A77,'00_Sub'!$A$4:$D$1001,3,FALSE)) | G77: =ROUNDUP((D77+(D77*F77)),0) -> 0 | H77: =IF($A77=0,"",VLOOKUP($A77,'00_Sub'!$A$4:$D$1001,4,FALSE))
B78: =IF($A78=0,"",VLOOKUP($A78,'00_Sub'!$A$4:$D$1001,2,FALSE)) | C78: =IF($A78=0,"",VLOOKUP($A78,'00_Sub'!$A$4:$D$1001,3,FALSE)) | G78: =ROUNDUP((D78+(D78*F78)),0) -> 0 | H78: =IF($A78=0,"",VLOOKUP($A78,'00_Sub'!$A$4:$D$1001,4,FALSE))
A80: TOTAL | I80: =SUM(I73:I78) -> 0
A81: =$I$3 -> unid. | I81: =$H$3 -> 14
A82: TOTAL x | B82: =A81 -> unid. | I82: =I80/I81 -> 0

Sheet  3.0-3
A1: ='01_C&P'!A1 -> CASA LUGONES
A3: ='01_C&P'!A38 -> 3.0-3 | B3: =IF($A3=0,"",VLOOKUP($A3,'01_C&P'!$A$9:$D$172,2,FALSE)) -> RELLENO DE FUNDACIONES (TOSCA + HORMIGON EN PLATEA DE FUNDACION) | H3: =IF($A3=0,"",VLOOKUP($A3,'01_C&P'!$A$9:$D$172,4,FALSE)) -> 14 | I3: =IF($A3=0,"",VLOOKUP($A3,'01_C&P'!$A$9:$D$172,3,FALSE)) -> unid. | K3: M3 DE TOSCA X BASE + ESPONJAMIENTO | L3: =(1*1*1.2)*1.2 -> 1.44
K4: M3 DE H30 TENSORES + BASES EN PLATEA | L4: =((1*1*0.2)*14)+(28*0.2*0.3) -> 4.48
A5: MATERIALES | K5: M2 DE MALLA | L5: =(14+(28*0.3)) -> 22.4
A6: Código | B6: Descripción | C6: Unidad | D6: Cantidad | F6: Desperdicio | G6: Cantidad + Desperdicio | H6: Precio Unitario | I6: Subtotal
A7: H30 | B7: =IF($A7=0,"",VLOOKUP($A7,'00_Mat'!$A$4:$J$1135,2,FALSE)) -> Hormigon H30 | C7: =IF($A7=0,"",VLOOKUP($A7,'00_Mat'!$A$4:$J$1135,3,FALSE)) -> m3 | D7: =L4 -> 4.48 | F7: 0.5 | G7: =ROUNDUP((D7+(D7*F7)),0) -> 7 | H7: =IF($A7=0,"",VLOOKUP($A7,'00_Mat'!$A$4:$J$1135,5,FALSE)) -> 125280 | I7: =H7*G7 -> 876960
A8: TOS8 | B8: =IF($A8=0,"",VLOOKUP($A8,'00_Mat'!$A$4:$J$1135,2,FALSE)) -> Tosca | C8: =IF($A8=0,"",VLOOKUP($A8,'00_Mat'!$A$4:$J$1135,3,FALSE)) -> m3 | D8: =L3*14 -> 20.16 | F8: 0.25 | G8: =ROUNDUP((D8+(D8*F8)),0) -> 26 | H8: =IF($A8=0,"",VLOOKUP($A8,'00_Mat'!$A$4:$J$1135,5,FALSE)) -> 30000 | I8: =H8*G8 -> 780000
A9: m5,5 | B9: =IF($A9=0,"",VLOOKUP($A9,'00_Mat'!$A$4:$J$1135,2,FALSE)) -> Malla Φ 5,5 (2 m x 5 m) (hierros cada 0,18 x 0,18 m) - menos de 50 u (u) | C9: =IF($A9=0,"",VLOOKUP($A9,'00_Mat'!$A$4:$J$1135,3,FALSE)) -> u | D9: =(14+(28*0.3))/10 -> 2.24 | F9: 0.25 | G9: =ROUNDUP((D9+(D9*F9)),0) -> 3 | H9: =IF($A9=0,"",VLOOKUP($A9,'00_Mat'!$A$4:$J$1135,5,FALSE)) -> 34628.099 | I9: =H9*G9 -> 103884.3
B10: =IF($A10=0,"",VLOOKUP($A10,'00_Mat'!$A$4:$J$1135,2,FALSE)) | C10: =IF($A10=0,"",VLOOKUP($A10,'00_Mat'!$A$4:$J$1135,3,FALSE)) | G10: =ROUNDUP((D10+(D10*F10)),0) -> 0 | H10: =IF($A10=0,"",VLOOKUP($A10,'00_Mat'!$A$4:$J$1135,5,FALSE)) | I10: =H10*G10 -> 0
B11: =IF($A11=0,"",VLOOKUP($A11,'00_Mat'!$A$4:$J$1135,2,FALSE)) | C11: =IF($A11=0,"",VLOOKUP($A11,'00_Mat'!$A$4:$J$1135,3,FALSE)) | G11: =ROUNDUP((D11+(D11*F11)),0) -> 0 | H11: =IF($A11=0,"",VLOOKUP($A11,'00_Mat'!$A$4:$J$1135,5,FALSE)) | I11: =H11*G11 -> 0
B12: =IF($A12=0,"",VLOOKUP($A12,'00_Mat'!$A$4:$J$1135,2,FALSE)) | C12: =IF($A12=0,"",VLOOKUP($A12,'00_Mat'!$A$4:$J$1135,3,FALSE)) | G12: =ROUNDUP((D12+(D12*F12)),0) -> 0 | H12: =IF($A12=0,"",VLOOKUP($A12,'00_Mat'!$A$4:$J$1135,5,FALSE)) | I12: =H12*G12 -> 0
B13: =IF($A13=0,"",VLOOKUP($A13,'00_Mat'!$A$4:$J$1135,2,FALSE)) | C13: =IF($A13=0,"",VLOOKUP($A13,'00_Mat'!$A$4:$J$1135,3,FALSE)) | G13: =ROUNDUP((D13+(D13*F13)),0) -> 0 | H13: =IF($A13=0,"",VLOOKUP($A13,'00_Mat'!$A$4:$J$1135,5,FALSE)) | I13: =H13*G13 -> 0
B14: =IF($A14=0,"",VLOOKUP($A14,'00_Mat'!$A$4:$J$1135,2,FALSE)) | C14: =IF($A14=0,"",VLOOKUP($A14,'00_Mat'!$A$4:$J$1135,3,FALSE)) | G14: =ROUNDUP((D14+(D14*F14)),0) -> 0 | H14: =IF($A14=0,"",VLOOKUP($A14,'00_Mat'!$A$4:$J$1135,5,FALSE)) | I14: =H14*G14 -> 0
B15: =IF($A15=0,"",VLOOKUP($A15,'00_Mat'!$A$4:$J$1135,2,FALSE)) | C15: =IF($A15=0,"",VLOOKUP($A15,'00_Mat'!$A$4:$J$1135,3,FALSE)) | G15: =ROUNDUP((D15+(D15*F15)),0) -> 0 | H15: =IF($A15=0,"",VLOOKUP($A15,'00_Mat'!$A$4:$J$1135,5,FALSE)) | I15: =H15*G15 -> 0
B16: =IF($A16=0,"",VLOOKUP($A16,'00_Mat'!$A$4:$J$1135,2,FALSE)) | C16: =IF($A16=0,"",VLOOKUP($A16,'00_Mat'!$A$4:$J$1135,3,FALSE)) | G16: =ROUNDUP((D16+(D16*F16)),0) -> 0 | H16: =IF($A16=0,"",VLOOKUP($A16,'00_Mat'!$A$4:$J$1135,5,FALSE)) | I16: =H16*G16 -> 0
B17: =IF($A17=0,"",VLOOKUP($A17,'00_Mat'!$A$4:$J$1135,2,FALSE)) | C17: =IF($A17=0,"",VLOOKUP($A17,'00_Mat'!$A$4:$J$1135,3,FALSE)) | G17: =ROUNDUP((D17+(D17*F17)),0) -> 0 | H17: =IF($A17=0,"",VLOOKUP($A17,'00_Mat'!$A$4:$J$1135,5,FALSE)) | I17: =H17*G17 -> 0
B18: =IF($A18=0,"",VLOOKUP($A18,'00_Mat'!$A$4:$J$1135,2,FALSE)) | C18: =IF($A18=0,"",VLOOKUP($A18,'00_Mat'!$A$4:$J$1135,3,FALSE)) | G18: =ROUNDUP((D18+(D18*F18)),0) -> 0 | H18: =IF($A18=0,"",VLOOKUP($A18,'00_Mat'!$A$4:$J$1135,5,FALSE)) | I18: =H18*G18 -> 0
B19: =IF($A19=0,"",VLOOKUP($A19,'00_Mat'!$A$4:$J$1135,2,FALSE)) | C19: =IF($A19=0,"",VLOOKUP($A19,'00_Mat'!$A$4:$J$1135,3,FALSE)) | G19: =ROUNDUP((D19+(D19*F19)),0) -> 0 | H19: =IF($A19=0,"",VLOOKUP($A19,'00_Mat'!$A$4:$J$1135,5,FALSE)) | I19: =H19*G19 -> 0
B20: =IF($A20=0,"",VLOOKUP($A20,'00_Mat'!$A$4:$J$1135,2,FALSE)) | C20: =IF($A20=0,"",VLOOKUP($A20,'00_Mat'!$A$4:$J$1135,3,FALSE)) | G20: =ROUNDUP((D20+(D20*F20)),0) -> 0 | H20: =IF($A20=0,"",VLOOKUP($A20,'00_Mat'!$A$4:$J$1135,5,FALSE)) | I20: =H20*G20 -> 0
B21: =IF($A21=0,"",VLOOKUP($A21,'00_Mat'!$A$4:$J$1135,2,FALSE)) | C21: =IF($A21=0,"",VLOOKUP($A21,'00_Mat'!$A$4:$J$1135,3,FALSE)) | G21: =ROUNDUP((D21+(D21*F21)),0) -> 0 | H21: =IF($A21=0,"",VLOOKUP($A21,'00_Mat'!$A$4:$J$1135,5,FALSE)) | I21: =H21*G21 -> 0
A23: TOTAL MATERIALES | I23: =SUM(I7:I18) -> 1760844.3
A24: =$I$3 -> unid. | I24: =$H$3 -> 14
A25: TOTAL x | B25: =A24 -> unid. | I25: =I23/I24 -> 125774.59
A28: MANO DE OBRA - PERSONAS
A29: Código | B29: Descripción | C29: Unidad | D29: Cantidad | E29: Dias | F29: Desperdicio | G29: Cantidad + Desperdicio | H29: Precio Unitario | I29: Subtotal
A30: MO-CA | B30: =IF($A30=0,"",VLOOKUP($A30,'00_MO'!$A$4:$D$7,2,FALSE)) -> Capataz | C30: =IF($A30=0,"",VLOOKUP($A30,'00_MO'!$A$4:$D$7,3,FALSE)) -> u | D30: 1 | E30: 4 | F30: 0.25 | G30: =ROUNDUP(((D30*E30)*(1+F30)),0) -> 5 | H30: =IF($A30=0,"",VLOOKUP($A30,'00_MO'!$A$4:$D$7,4,FALSE)) -> 90000 | I30: =G30*H30 -> 450000
A31: MO-OF | B31: =IF($A31=0,"",VLOOKUP($A31,'00_MO'!$A$4:$D$7,2,FALSE)) -> Oficial | C31: =IF($A31=0,"",VLOOKUP($A31,'00_MO'!$A$4:$D$7,3,FALSE)) -> u | D31: 2 | E31: 4 | F31: 0.25 | G31: =ROUNDUP(((D31*E31)*(1+F31)),0) -> 10 | H31: =IF($A31=0,"",VLOOKUP($A31,'00_MO'!$A$4:$D$7,4,FALSE)) -> 75000 | I31: =G31*H31 -> 750000
A32: MO-AY | B32: =IF($A32=0,"",VLOOKUP($A32,'00_MO'!$A$4:$D$7,2,FALSE)) -> Ayudante | C32: =IF($A32=0,"",VLOOKUP($A32,'00_MO'!$A$4:$D$7,3,FALSE)) -> u | D32: 1 | E32: 4 | F32: 0.25 | G32: =ROUNDUP(((D32*E32)*(1+F32)),0) -> 5 | H32: =IF($A32=0,"",VLOOKUP($A32,'00_MO'!$A$4:$D$7,4,FALSE)) -> 60000 | I32: =G32*H32 -> 300000
B33: =IF($A33=0,"",VLOOKUP($A33,'00_MO'!$A$4:$D$7,2,FALSE)) | C33: =IF($A33=0,"",VLOOKUP($A33,'00_MO'!$A$4:$D$7,3,FALSE)) | G33: =ROUNDUP(((D33*E33)*(1+F33)),0) -> 0 | H33: =IF($A33=0,"",VLOOKUP($A33,'00_MO'!$A$4:$D$7,4,FALSE)) | I33: =G33*H33 -> 0
B34: =IF($A34=0,"",VLOOKUP($A34,'00_MO'!$A$4:$D$7,2,FALSE)) | C34: =IF($A34=0,"",VLOOKUP($A34,'00_MO'!$A$4:$D$7,3,FALSE)) | G34: =ROUNDUP(((D34*E34)*(1+F34)),0) -> 0 | H34: =IF($A34=0,"",VLOOKUP($A34,'00_MO'!$A$4:$D$7,4,FALSE)) | I34: =G34*H34 -> 0
B35: =IF($A35=0,"",VLOOKUP($A35,'00_MO'!$A$4:$D$7,2,FALSE)) | C35: =IF($A35=0,"",VLOOKUP($A35,'00_MO'!$A$4:$D$7,3,FALSE)) | G35: =ROUNDUP(((D35*E35)*(1+F35)),0) -> 0 | H35: =IF($A35=0,"",VLOOKUP($A35,'00_MO'!$A$4:$D$7,4,FALSE)) | I35: =G35*H35 -> 0
A37: TOTAL | I37: =SUM(I30:I35) -> 1500000
A38: =$I$3 -> unid. | I38: =$H$3 -> 14
A39: TOTAL x | B39: =A38 -> unid. | I39: =I37/I38 -> 107142.86
A42: MANO DE OBRA - EQUIPOS
A43: Código | B43: Descripción | C43: Unidad | D43: Cantidad | E43: Dias | F43: Desperdicio | G43: Cantidad + Desperdicio | H43: Precio Unitario | I43: Subtotal
A44: ='00_Eq'!A7 -> E-MP | B44: =IF($A44=0,"",VLOOKUP($A44,'00_Eq'!$A$4:$D$100,2,FALSE)) -> Motopison | C44: =IF($A44=0,"",VLOOKUP($A44,'00_Eq'!$A$4:$D$100,3,FALSE)) -> u | D44: 0 | E44: 0 | F44: 0.25 | G44: =ROUNDUP(((D44*E44)*(1+F44)),0) -> 0 | H44: =IF($A44=0,"",VLOOKUP($A44,'00_Eq'!$A$4:$D$100,4,FALSE)) -> 40000 | I44: =G44*H44 -> 0
B45: =IF($A45=0,"",VLOOKUP($A45,'00_Eq'!$A$4:$D$100,2,FALSE)) | C45: =IF($A45=0,"",VLOOKUP($A45,'00_Eq'!$A$4:$D$100,3,FALSE)) | G45: =ROUNDUP(((D45*E45)*(1+F45)),0) -> 0 | H45: =IF($A45=0,"",VLOOKUP($A45,'00_Eq'!$A$4:$D$100,4,FALSE)) | I45: =G45*H45 -> 0
B46: =IF($A46=0,"",VLOOKUP($A46,'00_Eq'!$A$4:$D$100,2,FALSE)) | C46: =IF($A46=0,"",VLOOKUP($A46,'00_Eq'!$A$4:$D$100,3,FALSE)) | G46: =ROUNDUP(((D46*E46)*(1+F46)),0) -> 0 | H46: =IF($A46=0,"",VLOOKUP($A46,'00_Eq'!$A$4:$D$100,4,FALSE)) | I46: =G46*H46 -> 0
B47: =IF($A47=0,"",VLOOKUP($A47,'00_Eq'!$A$4:$D$100,2,FALSE)) | C47: =IF($A47=0,"",VLOOKUP($A47,'00_Eq'!$A$4:$D$100,3,FALSE)) | G47: =ROUNDUP(((D47*E47)*(1+F47)),0) -> 0 | H47: =IF($A47=0,"",VLOOKUP($A47,'00_Eq'!$A$4:$D$100,4,FALSE)) | I47: =G47*H47 -> 0
B48: =IF($A48=0,"",VLOOKUP($A48,'00_Eq'!$A$4:$D$100,2,FALSE)) | C48: =IF($A48=0,"",VLOOKUP($A48,'00_Eq'!$A$4:$D$100,3,FALSE)) | G48: =ROUNDUP(((D48*E48)*(1+F48)),0) -> 0 | H48: =IF($A48=0,"",VLOOKUP($A48,'00_Eq'!$A$4:$D$100,4,FALSE))
B49: =IF($A49=0,"",VLOOKUP($A49,'00_Eq'!$A$4:$D$100,2,FALSE)) | C49: =IF($A49=0,"",VLOOKUP($A49,'00_Eq'!$A$4:$D$100,3,FALSE)) | G49: =ROUNDUP(((D49*E49)*(1+F49)),0) -> 0 | H49: =IF($A49=0,"",VLOOKUP($A49,'00_Eq'!$A$4:$D$100,4,FALSE))
A51: TOTAL | I51: =SUM(I44:I49) -> 0
A52: =$I$3 -> unid. | I52: =$H$3 -> 14
A53: TOTAL x | B53: =A52 -> unid. | I53: =I51/I52 -> 0
A56: MANO DE OBRA - MATERIALES
A57: Código | B57: Descripción | C57: Unidad | D57: Cantidad | F57: Desperdicio | G57: Cantidad + Desperdicio | H57: Precio Unitario | I57: Subtotal
B58: =IF($A58=0,"",VLOOKUP($A58,'00_Mat'!$A$4:$J$1135,2,FALSE)) | C58: =IF($A58=0,"",VLOOKUP($A58,'00_Mat'!$A$4:$J$1135,3,FALSE)) | D58: 2 | F58: 0.1 | G58: =ROUNDUP((D58+(D58*F58)),0) -> 3 | H58: =IF($A58=0,"",VLOOKUP($A58,'00_Mat'!$A$4:$J$1135,5,FALSE)) | I58: =H58*G58 -> 0
B59: =IF($A59=0,"",VLOOKUP($A59,'00_Mat'!$A$4:$J$1135,2,FALSE)) | C59: =IF($A59=0,"",VLOOKUP($A59,'00_Mat'!$A$4:$J$1135,3,FALSE)) | D59: 30 | F59: 0.1 | G59: =ROUNDUP((D59+(D59*F59)),0) -> 33 | H59: =IF($A59=0,"",VLOOKUP($A59,'00_Mat'!$A$4:$J$1135,5,FALSE)) | I59: =H59*G59 -> 0
B60: =IF($A60=0,"",VLOOKUP($A60,'00_Mat'!$A$4:$J$1135,2,FALSE)) | C60: =IF($A60=0,"",VLOOKUP($A60,'00_Mat'!$A$4:$J$1135,3,FALSE)) | D60: 20 | F60: 0.1 | G60: =ROUNDUP((D60+(D60*F60)),0) -> 22 | H60: =IF($A60=0,"",VLOOKUP($A60,'00_Mat'!$A$4:$J$1135,5,FALSE)) | I60: =H60*G60 -> 0
B61: =IF($A61=0,"",VLOOKUP($A61,'00_Mat'!$A$4:$J$1135,2,FALSE)) | C61: =IF($A61=0,"",VLOOKUP($A61,'00_Mat'!$A$4:$J$1135,3,FALSE)) | D61: 20 | F61: 0.1 | G61: =ROUNDUP((D61+(D61*F61)),0) -> 22 | H61: =IF($A61=0,"",VLOOKUP($A61,'00_Mat'!$A$4:$J$1135,5,FALSE)) | I61: =H61*G61 -> 0
B62: =IF($A62=0,"",VLOOKUP($A62,'00_Mat'!$A$4:$J$1135,2,FALSE)) | C62: =IF($A62=0,"",VLOOKUP($A62,'00_Mat'!$A$4:$J$1135,3,FALSE)) | D62: 10 | F62: 0.1 | G62: =ROUNDUP((D62+(D62*F62)),0) -> 11 | H62: =IF($A62=0,"",VLOOKUP($A62,'00_Mat'!$A$4:$J$1135,5,FALSE)) | I62: =H62*G62 -> 0
B63: =IF($A63=0,"",VLOOKUP($A63,'00_Mat'!$A$4:$J$1135,2,FALSE)) | C63: =IF($A63=0,"",VLOOKUP($A63,'00_Mat'!$A$4:$J$1135,3,FALSE)) | D63: 10 | F63: 0.1 | G63: =ROUNDUP((D63+(D63*F63)),0) -> 11 | H63: =IF($A63=0,"",VLOOKUP($A63,'00_Mat'!$A$4:$J$1135,5,FALSE)) | I63: =H63*G63 -> 0
B64: =IF($A64=0,"",VLOOKUP($A64,'00_Mat'!$A$4:$J$1135,2,FALSE)) | C64: =IF($A64=0,"",VLOOKUP($A64,'00_Mat'!$A$4:$J$1135,3,FALSE)) | D64: 10 | F64: 0.1 | G64: =ROUNDUP((D64+(D64*F64)),0) -> 11 | H64: =IF($A64=0,"",VLOOKUP($A64,'00_Mat'!$A$4:$J$1135,5,FALSE)) | I64: =H64*G64 -> 0
A65: TOTAL | I65: =SUM(I58:I64) -> 0
A66: =$I$3 -> unid. | I66: =$H$3 -> 14
A67: TOTAL x | B67: =A66 -> unid. | I67: =I65/I66 -> 0
A70: MANO DE OBRA - SUBCONTRATOS
A71: Código | B71: Descripción | C71: Unidad | D71: Cantidad | E71: Dias | F71: Desperdicio | G71: Cantidad + Desperdicio | H71: Precio Unitario | I71: Subtotal
B72: =IF($A72=0,"",VLOOKUP($A72,'00_Sub'!$A$4:$D$1001,2,FALSE)) | C72: =IF($A72=0,"",VLOOKUP($A72,'00_Sub'!$A$4:$D$1001,3,FALSE)) | G72: =ROUNDUP((D72+(D72*F72)),0) -> 0 | H72: =IF($A72=0,"",VLOOKUP($A72,'00_Sub'!$A$4:$D$1001,4,FALSE))
B73: =IF($A73=0,"",VLOOKUP($A73,'00_Sub'!$A$4:$D$1001,2,FALSE)) | C73: =IF($A73=0,"",VLOOKUP($A73,'00_Sub'!$A$4:$D$1001,3,FALSE)) | G73: =ROUNDUP((D73+(D73*F73)),0) -> 0 | H73: =IF($A73=0,"",VLOOKUP($A73,'00_Sub'!$A$4:$D$1001,4,FALSE))
B74: =IF($A74=0,"",VLOOKUP($A74,'00_Sub'!$A$4:$D$1001,2,FALSE)) | C74: =IF($A74=0,"",VLOOKUP($A74,'00_Sub'!$A$4:$D$1001,3,FALSE)) | G74: =ROUNDUP((D74+(D74*F74)),0) -> 0 | H74: =IF($A74=0,"",VLOOKUP($A74,'00_Sub'!$A$4:$D$1001,4,FALSE))
B75: =IF($A75=0,"",VLOOKUP($A75,'00_Sub'!$A$4:$D$1001,2,FALSE)) | C75: =IF($A75=0,"",VLOOKUP($A75,'00_Sub'!$A$4:$D$1001,3,FALSE)) | G75: =ROUNDUP((D75+(D75*F75)),0) -> 0 | H75: =IF($A75=0,"",VLOOKUP($A75,'00_Sub'!$A$4:$D$1001,4,FALSE))
B76: =IF($A76=0,"",VLOOKUP($A76,'00_Sub'!$A$4:$D$1001,2,FALSE)) | C76: =IF($A76=0,"",VLOOKUP($A76,'00_Sub'!$A$4:$D$1001,3,FALSE)) | G76: =ROUNDUP((D76+(D76*F76)),0) -> 0 | H76: =IF($A76=0,"",VLOOKUP($A76,'00_Sub'!$A$4:$D$1001,4,FALSE))
B77: =IF($A77=0,"",VLOOKUP($A77,'00_Sub'!$A$4:$D$1001,2,FALSE)) | C77: =IF($A77=0,"",VLOOKUP($A77,'00_Sub'!$A$4:$D$1001,3,FALSE)) | G77: =ROUNDUP((D77+(D77*F77)),0) -> 0 | H77: =IF($A77=0,"",VLOOKUP($A77,'00_Sub'!$A$4:$D$1001,4,FALSE))
A79: TOTAL | I79: =SUM(I72:I77) -> 0
A80: =$I$3 -> unid. | I80: =$H$3 -> 14
A81: TOTAL x | B81: =A80 -> unid. | I81: =I79/I80 -> 0

Sheet 3.1-1
A1: ='01_C&P'!A1 -> CASA LUGONES
L2: M3 HORMIGON
A3: ='01_C&P'!A40 -> 3.1-1 | B3: =IF($A3=0,"",VLOOKUP($A3,'01_C&P'!$A$9:$D$172,2,FALSE)) -> VIGAS H30 SOBRE PLANTA BAJA 0,15x0,35 (Hierros 6 ∅8 con estribos ∅ 6 c/14) | H3: =IF($A3=0,"",VLOOKUP($A3,'01_C&P'!$A$9:$D$172,4,FALSE)) -> 29 | I3: =IF($A3=0,"",VLOOKUP($A3,'01_C&P'!$A$9:$D$172,3,FALSE)) -> m | L3: =0.15*0.35*H3 -> 1.5225
A5: MATERIALES
A6: Código | B6: Descripción | C6: Unidad | D6: Cantidad | F6: Desperdicio | G6: Cantidad + Desperdicio | H6: Precio Unitario | I6: Subtotal
A7: H30 | B7: =IF($A7=0,"",VLOOKUP($A7,'00_Mat'!$A$4:$J$1135,2,FALSE)) -> Hormigon H30 | C7: =IF($A7=0,"",VLOOKUP($A7,'00_Mat'!$A$4:$J$1135,3,FALSE)) -> m3 | D7: =0.15*0.35*H3 -> 1.5225 | F7: 0.1 | G7: =ROUNDUP((D7+(D7*F7)),0) -> 2 | H7: =IF($A7=0,"",VLOOKUP($A7,'00_Mat'!$A$4:$J$1135,5,FALSE)) -> 125280 | I7: =H7*G7 -> 250560 | M7: YPF DA 49000 PERO TIENE CONSUMIBLES
A8: HADN10 | B8: =IF($A8=0,"",VLOOKUP($A8,'00_Mat'!$A$4:$J$1135,2,FALSE)) -> Hierros ADN 420Φ 10 | C8: =IF($A8=0,"",VLOOKUP($A8,'00_Mat'!$A$4:$J$1135,3,FALSE)) -> u | D8: =H3*6/12 -> 14.5 | F8: 0.1 | G8: =ROUNDUP((D8+(D8*F8)),0) -> 16 | H8: =IF($A8=0,"",VLOOKUP($A8,'00_Mat'!$A$4:$J$1135,5,FALSE)) -> 10000 | I8: =H8*G8 -> 160000
A9: HADN6 | B9: =IF($A9=0,"",VLOOKUP($A9,'00_Mat'!$A$4:$J$1135,2,FALSE)) -> Hierros ADN 420 Φ 6 | C9: =IF($A9=0,"",VLOOKUP($A9,'00_Mat'!$A$4:$J$1135,3,FALSE)) -> u | D9: =(29/0.14)*1.1/12 -> 18.988095 | F9: 0.1 | G9: =ROUNDUP((D9+(D9*F9)),0) -> 21 | H9: =IF($A9=0,"",VLOOKUP($A9,'00_Mat'!$A$4:$J$1135,5,FALSE)) -> 5250 | I9: =H9*G9 -> 110250
B10: =IF($A10=0,"",VLOOKUP($A10,'00_Mat'!$A$4:$J$1135,2,FALSE)) | C10: =IF($A10=0,"",VLOOKUP($A10,'00_Mat'!$A$4:$J$1135,3,FALSE)) | G10: =ROUNDUP((D10+(D10*F10)),0) -> 0 | H10: =IF($A10=0,"",VLOOKUP($A10,'00_Mat'!$A$4:$J$1135,5,FALSE)) | I10: =H10*G10 -> 0
B11: =IF($A11=0,"",VLOOKUP($A11,'00_Mat'!$A$4:$J$1135,2,FALSE)) | C11: =IF($A11=0,"",VLOOKUP($A11,'00_Mat'!$A$4:$J$1135,3,FALSE)) | G11: =ROUNDUP((D11+(D11*F11)),0) -> 0 | H11: =IF($A11=0,"",VLOOKUP($A11,'00_Mat'!$A$4:$J$1135,5,FALSE)) | I11: =H11*G11 -> 0
B12: =IF($A12=0,"",VLOOKUP($A12,'00_Mat'!$A$4:$J$1135,2,FALSE)) | C12: =IF($A12=0,"",VLOOKUP($A12,'00_Mat'!$A$4:$J$1135,3,FALSE)) | G12: =ROUNDUP((D12+(D12*F12)),0) -> 0 | H12: =IF($A12=0,"",VLOOKUP($A12,'00_Mat'!$A$4:$J$1135,5,FALSE)) | I12: =H12*G12 -> 0
B13: =IF($A13=0,"",VLOOKUP($A13,'00_Mat'!$A$4:$J$1135,2,FALSE)) | C13: =IF($A13=0,"",VLOOKUP($A13,'00_Mat'!$A$4:$J$1135,3,FALSE)) | G13: =ROUNDUP((D13+(D13*F13)),0) -> 0 | H13: =IF($A13=0,"",VLOOKUP($A13,'00_Mat'!$A$4:$J$1135,5,FALSE)) | I13: =H13*G13 -> 0
B14: =IF($A14=0,"",VLOOKUP($A14,'00_Mat'!$A$4:$J$1135,2,FALSE)) | C14: =IF($A14=0,"",VLOOKUP($A14,'00_Mat'!$A$4:$J$1135,3,FALSE)) | G14: =ROUNDUP((D14+(D14*F14)),0) -> 0 | H14: =IF($A14=0,"",VLOOKUP($A14,'00_Mat'!$A$4:$J$1135,5,FALSE)) | I14: =H14*G14 -> 0
B15: =IF($A15=0,"",VLOOKUP($A15,'00_Mat'!$A$4:$J$1135,2,FALSE)) | C15: =IF($A15=0,"",VLOOKUP($A15,'00_Mat'!$A$4:$J$1135,3,FALSE)) | G15: =ROUNDUP((D15+(D15*F15)),0) -> 0 | H15: =IF($A15=0,"",VLOOKUP($A15,'00_Mat'!$A$4:$J$1135,5,FALSE)) | I15: =H15*G15 -> 0
B16: =IF($A16=0,"",VLOOKUP($A16,'00_Mat'!$A$4:$J$1135,2,FALSE)) | C16: =IF($A16=0,"",VLOOKUP($A16,'00_Mat'!$A$4:$J$1135,3,FALSE)) | G16: =ROUNDUP((D16+(D16*F16)),0) -> 0 | H16: =IF($A16=0,"",VLOOKUP($A16,'00_Mat'!$A$4:$J$1135,5,FALSE)) | I16: =H16*G16 -> 0
B17: =IF($A17=0,"",VLOOKUP($A17,'00_Mat'!$A$4:$J$1135,2,FALSE)) | C17: =IF($A17=0,"",VLOOKUP($A17,'00_Mat'!$A$4:$J$1135,3,FALSE)) | G17: =ROUNDUP((D17+(D17*F17)),0) -> 0 | H17: =IF($A17=0,"",VLOOKUP($A17,'00_Mat'!$A$4:$J$1135,5,FALSE)) | I17: =H17*G17 -> 0
B18: =IF($A18=0,"",VLOOKUP($A18,'00_Mat'!$A$4:$J$1135,2,FALSE)) | C18: =IF($A18=0,"",VLOOKUP($A18,'00_Mat'!$A$4:$J$1135,3,FALSE)) | G18: =ROUNDUP((D18+(D18*F18)),0) -> 0 | H18: =IF($A18=0,"",VLOOKUP($A18,'00_Mat'!$A$4:$J$1135,5,FALSE)) | I18: =H18*G18 -> 0
A20: TOTAL MATERIALES | I20: =SUM(I7:I18) -> 520810
A21: =$I$3 -> m | I21: =$H$3 -> 29
A22: TOTAL x | B22: =A21 -> m | I22: =I20/I21 -> 17958.966
A25: MANO DE OBRA - PERSONAS
A26: Código | B26: Descripción | C26: Unidad | D26: Cantidad | E26: Dias | F26: Desperdicio | G26: Cantidad + Desperdicio | H26: Precio Unitario | I26: Subtotal
A27: MO-CA | B27: =IF($A27=0,"",VLOOKUP($A27,'00_MO'!$A$4:$D$7,2,FALSE)) -> Capataz | C27: =IF($A27=0,"",VLOOKUP($A27,'00_MO'!$A$4:$D$7,3,FALSE)) -> u | D27: 1 | E27: 2 | F27: 0.25 | G27: =ROUNDUP(((D27*E27)*(1+F27)),0) -> 3 | H27: =IF($A27=0,"",VLOOKUP($A27,'00_MO'!$A$4:$D$7,4,FALSE)) -> 90000 | I27: =G27*H27 -> 270000 | J27: Carpinteria | M27: IDEM YPF
A28: MO-OF | B28: =IF($A28=0,"",VLOOKUP($A28,'00_MO'!$A$4:$D$7,2,FALSE)) -> Oficial | C28: =IF($A28=0,"",VLOOKUP($A28,'00_MO'!$A$4:$D$7,3,FALSE)) -> u | D28: 2 | E28: 1 | F28: 0.25 | G28: =ROUNDUP(((D28*E28)*(1+F28)),0) -> 3 | H28: =IF($A28=0,"",VLOOKUP($A28,'00_MO'!$A$4:$D$7,4,FALSE)) -> 75000 | I28: =G28*H28 -> 225000 | J28: Carpinteria
A29: MO-AY | B29: =IF($A29=0,"",VLOOKUP($A29,'00_MO'!$A$4:$D$7,2,FALSE)) -> Ayudante | C29: =IF($A29=0,"",VLOOKUP($A29,'00_MO'!$A$4:$D$7,3,FALSE)) -> u | D29: 1 | E29: 1 | F29: 0.25 | G29: =ROUNDUP(((D29*E29)*(1+F29)),0) -> 2 | H29: =IF($A29=0,"",VLOOKUP($A29,'00_MO'!$A$4:$D$7,4,FALSE)) -> 60000 | I29: =G29*H29 -> 120000 | J29: Carpinteria
A30: MO-CA | B30: =IF($A30=0,"",VLOOKUP($A30,'00_MO'!$A$4:$D$7,2,FALSE)) -> Capataz | C30: =IF($A30=0,"",VLOOKUP($A30,'00_MO'!$A$4:$D$7,3,FALSE)) -> u | D30: 1 | E30: 2 | F30: 0.25 | G30: =ROUNDUP(((D30*E30)*(1+F30)),0) -> 3 | H30: =IF($A30=0,"",VLOOKUP($A30,'00_MO'!$A$4:$D$7,4,FALSE)) -> 90000 | I30: =G30*H30 -> 270000 | J30: Armadura + llenado
A31: MO-OF | B31: =IF($A31=0,"",VLOOKUP($A31,'00_MO'!$A$4:$D$7,2,FALSE)) -> Oficial | C31: =IF($A31=0,"",VLOOKUP($A31,'00_MO'!$A$4:$D$7,3,FALSE)) -> u | D31: 2 | E31: =E30 -> 2 | F31: 0.25 | G31: =ROUNDUP(((D31*E31)*(1+F31)),0) -> 5 | H31: =IF($A31=0,"",VLOOKUP($A31,'00_MO'!$A$4:$D$7,4,FALSE)) -> 75000 | I31: =G31*H31 -> 375000 | J31: Armadura + llenado
A32: MO-AY | B32: =IF($A32=0,"",VLOOKUP($A32,'00_MO'!$A$4:$D$7,2,FALSE)) -> Ayudante | C32: =IF($A32=0,"",VLOOKUP($A32,'00_MO'!$A$4:$D$7,3,FALSE)) -> u | D32: 1 | E32: =E31 -> 2 | F32: 0.25 | G32: =ROUNDUP(((D32*E32)*(1+F32)),0) -> 3 | H32: =IF($A32=0,"",VLOOKUP($A32,'00_MO'!$A$4:$D$7,4,FALSE)) -> 60000 | I32: =G32*H32 -> 180000 | J32: Armadura + llenado
A34: TOTAL | I34: =SUM(I27:I32) -> 1440000
A35: =$I$3 -> m | I35: =$H$3 -> 29
A36: TOTAL x | B36: =A35 -> m | I36: =I34/I35 -> 49655.172
A39: MANO DE OBRA - EQUIPOS
A40: Código | B40: Descripción | C40: Unidad | D40: Cantidad | E40: Dias | F40: Desperdicio | G40: Cantidad + Desperdicio | H40: Precio Unitario | I40: Subtotal
B41: =IF($A41=0,"",VLOOKUP($A41,'00_Eq'!$A$4:$D$100,2,FALSE)) | C41: =IF($A41=0,"",VLOOKUP($A41,'00_Eq'!$A$4:$D$100,3,FALSE)) | G41: =ROUNDUP(((D41*E41)*(1+F41)),0) -> 0 | H41: =IF($A41=0,"",VLOOKUP($A41,'00_Eq'!$A$4:$D$100,4,FALSE)) | I41: =G41*H41 -> 0
B42: =IF($A42=0,"",VLOOKUP($A42,'00_Eq'!$A$4:$D$100,2,FALSE)) | C42: =IF($A42=0,"",VLOOKUP($A42,'00_Eq'!$A$4:$D$100,3,FALSE)) | G42: =ROUNDUP(((D42*E42)*(1+F42)),0) -> 0 | H42: =IF($A42=0,"",VLOOKUP($A42,'00_Eq'!$A$4:$D$100,4,FALSE)) | I42: =G42*H42 -> 0
B43: =IF($A43=0,"",VLOOKUP($A43,'00_Eq'!$A$4:$D$100,2,FALSE)) | C43: =IF($A43=0,"",VLOOKUP($A43,'00_Eq'!$A$4:$D$100,3,FALSE)) | G43: =ROUNDUP(((D43*E43)*(1+F43)),0) -> 0 | H43: =IF($A43=0,"",VLOOKUP($A43,'00_Eq'!$A$4:$D$100,4,FALSE)) | I43: =G43*H43 -> 0
B44: =IF($A44=0,"",VLOOKUP($A44,'00_Eq'!$A$4:$D$100,2,FALSE)) | C44: =IF($A44=0,"",VLOOKUP($A44,'00_Eq'!$A$4:$D$100,3,FALSE)) | G44: =ROUNDUP(((D44*E44)*(1+F44)),0) -> 0 | H44: =IF($A44=0,"",VLOOKUP($A44,'00_Eq'!$A$4:$D$100,4,FALSE)) | I44: =G44*H44 -> 0
B45: =IF($A45=0,"",VLOOKUP($A45,'00_Eq'!$A$4:$D$100,2,FALSE)) | C45: =IF($A45=0,"",VLOOKUP($A45,'00_Eq'!$A$4:$D$100,3,FALSE)) | G45: =ROUNDUP(((D45*E45)*(1+F45)),0) -> 0 | H45: =IF($A45=0,"",VLOOKUP($A45,'00_Eq'!$A$4:$D$100,4,FALSE))
B46: =IF($A46=0,"",VLOOKUP($A46,'00_Eq'!$A$4:$D$100,2,FALSE)) | C46: =IF($A46=0,"",VLOOKUP($A46,'00_Eq'!$A$4:$D$100,3,FALSE)) | G46: =ROUNDUP(((D46*E46)*(1+F46)),0) -> 0 | H46: =IF($A46=0,"",VLOOKUP($A46,'00_Eq'!$A$4:$D$100,4,FALSE))
A48: TOTAL | I48: =SUM(I41:I46) -> 0
A49: =$I$3 -> m | I49: =$H$3 -> 29
A50: TOTAL x | B50: =A49 -> m | I50: =I48/I49 -> 0
A53: MANO DE OBRA - MATERIALES
A54: Código | B54: Descripción | C54: Unidad | D54: Cantidad | F54: Desperdicio | G54: Cantidad + Desperdicio | H54: Precio Unitario | I54: Subtotal
A55: dis | B55: =IF($A55=0,"",VLOOKUP($A55,'00_Mat'!$A$4:$J$1135,2,FALSE)) -> Disco corte | C55: =IF($A55=0,"",VLOOKUP($A55,'00_Mat'!$A$4:$J$1135,3,FALSE)) -> u | D55: 2 | F55: 0.1 | G55: =ROUNDUP((D55+(D55*F55)),0) -> 3 | H55: =IF($A55=0,"",VLOOKUP($A55,'00_Mat'!$A$4:$J$1135,5,FALSE)) -> 40000 | I55: =H55*G55 -> 120000
A56: pun | B56: =IF($A56=0,"",VLOOKUP($A56,'00_Mat'!$A$4:$J$1135,2,FALSE)) -> Puntal | C56: =IF($A56=0,"",VLOOKUP($A56,'00_Mat'!$A$4:$J$1135,3,FALSE)) -> u | D56: =H3*2 -> 58 | F56: 0.1 | G56: =ROUNDUP((D56+(D56*F56)),0) -> 64 | H56: =IF($A56=0,"",VLOOKUP($A56,'00_Mat'!$A$4:$J$1135,5,FALSE)) -> 6900 | I56: =H56*G56 -> 441600
A57: CL2.5 | B57: =IF($A57=0,"",VLOOKUP($A57,'00_Mat'!$A$4:$J$1135,2,FALSE)) -> Clavos 2,5" punta paris (k) | C57: =IF($A57=0,"",VLOOKUP($A57,'00_Mat'!$A$4:$J$1135,3,FALSE)) -> k | D57: 5 | F57: 0.1 | G57: =ROUNDUP((D57+(D57*F57)),0) -> 6 | H57: =IF($A57=0,"",VLOOKUP($A57,'00_Mat'!$A$4:$J$1135,5,FALSE)) -> 3739.67 | I57: =H57*G57 -> 22438.02
A58: AL | B58: =IF($A58=0,"",VLOOKUP($A58,'00_Mat'!$A$4:$J$1135,2,FALSE)) -> Alambre Fardo (k) | C58: =IF($A58=0,"",VLOOKUP($A58,'00_Mat'!$A$4:$J$1135,3,FALSE)) -> k | D58: 5 | F58: 0.1 | G58: =ROUNDUP((D58+(D58*F58)),0) -> 6 | H58: =IF($A58=0,"",VLOOKUP($A58,'00_Mat'!$A$4:$J$1135,5,FALSE)) -> 4326.45 | I58: =H58*G58 -> 25958.7
A59: CL2 | B59: =IF($A59=0,"",VLOOKUP($A59,'00_Mat'!$A$4:$J$1135,2,FALSE)) -> Clavos 2" punta paris (k) | C59: =IF($A59=0,"",VLOOKUP($A59,'00_Mat'!$A$4:$J$1135,3,FALSE)) -> k | D59: 5 | F59: 0.1 | G59: =ROUNDUP((D59+(D59*F59)),0) -> 6 | H59: =IF($A59=0,"",VLOOKUP($A59,'00_Mat'!$A$4:$J$1135,5,FALSE)) -> 3739.67 | I59: =H59*G59 -> 22438.02 | M59: YPF DA 6500 PERO TIENE LOS CONSUMIBLES ARRIBA
A60: F-PI | B60: =IF($A60=0,"",VLOOKUP($A60,'00_Mat'!$A$4:$J$1135,2,FALSE)) -> Fenolico scarp 18mm Pino cic | C60: =IF($A60=0,"",VLOOKUP($A60,'00_Mat'!$A$4:$J$1135,3,FALSE)) -> u | D60: 7 | F60: 0 | G60: =ROUNDUP((D60+(D60*F60)),0) -> 7 | H60: =IF($A60=0,"",VLOOKUP($A60,'00_Mat'!$A$4:$J$1135,5,FALSE)) -> 26320 | I60: =H60*G60 -> 184240
A62: TOTAL | I62: =SUM(I55:I60) -> 816674.74
A63: =$I$3 -> m | I63: =$H$3 -> 29
A64: TOTAL x | B64: =A63 -> m | I64: =I62/I63 -> 28161.198
A67: MANO DE OBRA - SUBCONTRATOS
A68: Código | B68: Descripción | C68: Unidad | D68: Cantidad | E68: Dias | F68: Desperdicio | G68: Cantidad + Desperdicio | H68: Precio Unitario | I68: Subtotal
B69: =IF($A69=0,"",VLOOKUP($A69,'00_Sub'!$A$4:$D$1001,2,FALSE)) | C69: =IF($A69=0,"",VLOOKUP($A69,'00_Sub'!$A$4:$D$1001,3,FALSE)) | G69: =ROUNDUP((D69+(D69*F69)),0) -> 0 | H69: =IF($A69=0,"",VLOOKUP($A69,'00_Sub'!$A$4:$D$1001,4,FALSE))
B70: =IF($A70=0,"",VLOOKUP($A70,'00_Sub'!$A$4:$D$1001,2,FALSE)) | C70: =IF($A70=0,"",VLOOKUP($A70,'00_Sub'!$A$4:$D$1001,3,FALSE)) | G70: =ROUNDUP((D70+(D70*F70)),0) -> 0 | H70: =IF($A70=0,"",VLOOKUP($A70,'00_Sub'!$A$4:$D$1001,4,FALSE))
B71: =IF($A71=0,"",VLOOKUP($A71,'00_Sub'!$A$4:$D$1001,2,FALSE)) | C71: =IF($A71=0,"",VLOOKUP($A71,'00_Sub'!$A$4:$D$1001,3,FALSE)) | G71: =ROUNDUP((D71+(D71*F71)),0) -> 0 | H71: =IF($A71=0,"",VLOOKUP($A71,'00_Sub'!$A$4:$D$1001,4,FALSE))
B72: =IF($A72=0,"",VLOOKUP($A72,'00_Sub'!$A$4:$D$1001,2,FALSE)) | C72: =IF($A72=0,"",VLOOKUP($A72,'00_Sub'!$A$4:$D$1001,3,FALSE)) | G72: =ROUNDUP((D72+(D72*F72)),0) -> 0 | H72: =IF($A72=0,"",VLOOKUP($A72,'00_Sub'!$A$4:$D$1001,4,FALSE))
B73: =IF($A73=0,"",VLOOKUP($A73,'00_Sub'!$A$4:$D$1001,2,FALSE)) | C73: =IF($A73=0,"",VLOOKUP($A73,'00_Sub'!$A$4:$D$1001,3,FALSE)) | G73: =ROUNDUP((D73+(D73*F73)),0) -> 0 | H73: =IF($A73=0,"",VLOOKUP($A73,'00_Sub'!$A$4:$D$1001,4,FALSE))
B74: =IF($A74=0,"",VLOOKUP($A74,'00_Sub'!$A$4:$D$1001,2,FALSE)) | C74: =IF($A74=0,"",VLOOKUP($A74,'00_Sub'!$A$4:$D$1001,3,FALSE)) | G74: =ROUNDUP((D74+(D74*F74)),0) -> 0 | H74: =IF($A74=0,"",VLOOKUP($A74,'00_Sub'!$A$4:$D$1001,4,FALSE))
A76: TOTAL | I76: =SUM(I69:I74) -> 0
A77: =$I$3 -> m | I77: =$H$3 -> 29
A78: TOTAL x | B78: =A77 -> m | I78: =I76/I77 -> 0

Sheet 3.1-2
A1: ='01_C&P'!A1 -> CASA LUGONES
A3: ='01_C&P'!A41 -> 3.1-2 | B3: =IF($A3=0,"",VLOOKUP($A3,'01_C&P'!$A$9:$D$172,2,FALSE)) -> VIGAS METALICAS + COLUMNA METALICA | H3: =IF($A3=0,"",VLOOKUP($A3,'01_C&P'!$A$9:$D$172,4,FALSE)) -> 8.3 | I3: =IF($A3=0,"",VLOOKUP($A3,'01_C&P'!$A$9:$D$172,3,FALSE)) -> m
A5: MATERIALES
A6: Código | B6: Descripción | C6: Unidad | D6: Cantidad | F6: Desperdicio | G6: Cantidad + Desperdicio | H6: Precio Unitario | I6: Subtotal
A7: IPE-220 | B7: =IF($A7=0,"",VLOOKUP($A7,'00_Mat'!$A$4:$J$1135,2,FALSE)) -> Perfil IPE 220 x12m | C7: =IF($A7=0,"",VLOOKUP($A7,'00_Mat'!$A$4:$J$1135,3,FALSE)) -> u | D7: 1 | F7: 0 | G7: =ROUNDUP((D7+(D7*F7)),0) -> 1 | H7: =IF($A7=0,"",VLOOKUP($A7,'00_Mat'!$A$4:$J$1135,5,FALSE)) -> 1105000 | I7: =H7*G7 -> 1105000 | M7: CHAMUYO
A8: ='00_Mat'!A251 -> TE-30x50x2 | B8: =IF($A8=0,"",VLOOKUP($A8,'00_Mat'!$A$4:$J$1135,2,FALSE)) -> Tubo Estructural 30 x 50 x 2,0 mm - 6 m largo | C8: =IF($A8=0,"",VLOOKUP($A8,'00_Mat'!$A$4:$J$1135,3,FALSE)) -> u | D8: 2 | F8: 0 | G8: =ROUNDUP((D8+(D8*F8)),0) -> 2 | H8: =IF($A8=0,"",VLOOKUP($A8,'00_Mat'!$A$4:$J$1135,5,FALSE)) -> 27493.405 | I8: =H8*G8 -> 54986.81
B9: =IF($A9=0,"",VLOOKUP($A9,'00_Mat'!$A$4:$J$1135,2,FALSE)) | C9: =IF($A9=0,"",VLOOKUP($A9,'00_Mat'!$A$4:$J$1135,3,FALSE)) | F9: 0.1 | G9: =ROUNDUP((D9+(D9*F9)),0) -> 0 | H9: =IF($A9=0,"",VLOOKUP($A9,'00_Mat'!$A$4:$J$1135,5,FALSE)) | I9: =H9*G9 -> 0
B10: =IF($A10=0,"",VLOOKUP($A10,'00_Mat'!$A$4:$J$1135,2,FALSE)) | C10: =IF($A10=0,"",VLOOKUP($A10,'00_Mat'!$A$4:$J$1135,3,FALSE)) | F10: 0.1 | G10: =ROUNDUP((D10+(D10*F10)),0) -> 0 | H10: =IF($A10=0,"",VLOOKUP($A10,'00_Mat'!$A$4:$J$1135,5,FALSE)) | I10: =H10*G10 -> 0
B11: =IF($A11=0,"",VLOOKUP($A11,'00_Mat'!$A$4:$J$1135,2,FALSE)) | C11: =IF($A11=0,"",VLOOKUP($A11,'00_Mat'!$A$4:$J$1135,3,FALSE)) | F11: 0.1 | G11: =ROUNDUP((D11+(D11*F11)),0) -> 0 | H11: =IF($A11=0,"",VLOOKUP($A11,'00_Mat'!$A$4:$J$1135,5,FALSE)) | I11: =H11*G11 -> 0
B12: =IF($A12=0,"",VLOOKUP($A12,'00_Mat'!$A$4:$J$1135,2,FALSE)) | C12: =IF($A12=0,"",VLOOKUP($A12,'00_Mat'!$A$4:$J$1135,3,FALSE)) | F12: 0.1 | G12: =ROUNDUP((D12+(D12*F12)),0) -> 0 | H12: =IF($A12=0,"",VLOOKUP($A12,'00_Mat'!$A$4:$J$1135,5,FALSE)) | I12: =H12*G12 -> 0
B13: =IF($A13=0,"",VLOOKUP($A13,'00_Mat'!$A$4:$J$1135,2,FALSE)) | C13: =IF($A13=0,"",VLOOKUP($A13,'00_Mat'!$A$4:$J$1135,3,FALSE)) | F13: 0.1 | G13: =ROUNDUP((D13+(D13*F13)),0) -> 0 | H13: =IF($A13=0,"",VLOOKUP($A13,'00_Mat'!$A$4:$J$1135,5,FALSE)) | I13: =H13*G13 -> 0
B14: =IF($A14=0,"",VLOOKUP($A14,'00_Mat'!$A$4:$J$1135,2,FALSE)) | C14: =IF($A14=0,"",VLOOKUP($A14,'00_Mat'!$A$4:$J$1135,3,FALSE)) | F14: 0.1 | G14: =ROUNDUP((D14+(D14*F14)),0) -> 0 | H14: =IF($A14=0,"",VLOOKUP($A14,'00_Mat'!$A$4:$J$1135,5,FALSE)) | I14: =H14*G14 -> 0
B15: =IF($A15=0,"",VLOOKUP($A15,'00_Mat'!$A$4:$J$1135,2,FALSE)) | C15: =IF($A15=0,"",VLOOKUP($A15,'00_Mat'!$A$4:$J$1135,3,FALSE)) | F15: 0.1 | G15: =ROUNDUP((D15+(D15*F15)),0) -> 0 | H15: =IF($A15=0,"",VLOOKUP($A15,'00_Mat'!$A$4:$J$1135,5,FALSE)) | I15: =H15*G15 -> 0
B16: =IF($A16=0,"",VLOOKUP($A16,'00_Mat'!$A$4:$J$1135,2,FALSE)) | C16: =IF($A16=0,"",VLOOKUP($A16,'00_Mat'!$A$4:$J$1135,3,FALSE)) | F16: 0.1 | G16: =ROUNDUP((D16+(D16*F16)),0) -> 0 | H16: =IF($A16=0,"",VLOOKUP($A16,'00_Mat'!$A$4:$J$1135,5,FALSE)) | I16: =H16*G16 -> 0
B17: =IF($A17=0,"",VLOOKUP($A17,'00_Mat'!$A$4:$J$1135,2,FALSE)) | C17: =IF($A17=0,"",VLOOKUP($A17,'00_Mat'!$A$4:$J$1135,3,FALSE)) | F17: 0.1 | G17: =ROUNDUP((D17+(D17*F17)),0) -> 0 | H17: =IF($A17=0,"",VLOOKUP($A17,'00_Mat'!$A$4:$J$1135,5,FALSE)) | I17: =H17*G17 -> 0
B18: =IF($A18=0,"",VLOOKUP($A18,'00_Mat'!$A$4:$J$1135,2,FALSE)) | C18: =IF($A18=0,"",VLOOKUP($A18,'00_Mat'!$A$4:$J$1135,3,FALSE)) | F18: 0.1 | G18: =ROUNDUP((D18+(D18*F18)),0) -> 0 | H18: =IF($A18=0,"",VLOOKUP($A18,'00_Mat'!$A$4:$J$1135,5,FALSE)) | I18: =H18*G18 -> 0
A20: TOTAL MATERIALES | I20: =SUM(I7:I18) -> 1159986.8
A21: =$I$3 -> m | I21: =$H$3 -> 8.3
A22: TOTAL x | B22: =A21 -> m | I22: =I20/I21 -> 139757.45
A25: MANO DE OBRA - PERSONAS
A26: Código | B26: Descripción | C26: Unidad | D26: Cantidad | E26: Dias | F26: Desperdicio | G26: Cantidad + Desperdicio | H26: Precio Unitario | I26: Subtotal
B27: =IF($A27=0,"",VLOOKUP($A27,'00_MO'!$A$4:$D$7,2,FALSE)) | C27: =IF($A27=0,"",VLOOKUP($A27,'00_MO'!$A$4:$D$7,3,FALSE)) | G27: =ROUNDUP(((D27*E27)*(1+F27)),0) -> 0 | H27: =IF($A27=0,"",VLOOKUP($A27,'00_MO'!$A$4:$D$7,4,FALSE)) | I27: =G27*H27 -> 0
B28: =IF($A28=0,"",VLOOKUP($A28,'00_MO'!$A$4:$D$7,2,FALSE)) | C28: =IF($A28=0,"",VLOOKUP($A28,'00_MO'!$A$4:$D$7,3,FALSE)) | G28: =ROUNDUP(((D28*E28)*(1+F28)),0) -> 0 | H28: =IF($A28=0,"",VLOOKUP($A28,'00_MO'!$A$4:$D$7,4,FALSE)) | I28: =G28*H28 -> 0
B29: =IF($A29=0,"",VLOOKUP($A29,'00_MO'!$A$4:$D$7,2,FALSE)) | C29: =IF($A29=0,"",VLOOKUP($A29,'00_MO'!$A$4:$D$7,3,FALSE)) | G29: =ROUNDUP(((D29*E29)*(1+F29)),0) -> 0 | H29: =IF($A29=0,"",VLOOKUP($A29,'00_MO'!$A$4:$D$7,4,FALSE)) | I29: =G29*H29 -> 0
B30: =IF($A30=0,"",VLOOKUP($A30,'00_MO'!$A$4:$D$7,2,FALSE)) | C30: =IF($A30=0,"",VLOOKUP($A30,'00_MO'!$A$4:$D$7,3,FALSE)) | G30: =ROUNDUP(((D30*E30)*(1+F30)),0) -> 0 | H30: =IF($A30=0,"",VLOOKUP($A30,'00_MO'!$A$4:$D$7,4,FALSE)) | I30: =G30*H30 -> 0
B31: =IF($A31=0,"",VLOOKUP($A31,'00_MO'!$A$4:$D$7,2,FALSE)) | C31: =IF($A31=0,"",VLOOKUP($A31,'00_MO'!$A$4:$D$7,3,FALSE)) | G31: =ROUNDUP(((D31*E31)*(1+F31)),0) -> 0 | H31: =IF($A31=0,"",VLOOKUP($A31,'00_MO'!$A$4:$D$7,4,FALSE)) | I31: =G31*H31 -> 0
B32: =IF($A32=0,"",VLOOKUP($A32,'00_MO'!$A$4:$D$7,2,FALSE)) | C32: =IF($A32=0,"",VLOOKUP($A32,'00_MO'!$A$4:$D$7,3,FALSE)) | G32: =ROUNDUP(((D32*E32)*(1+F32)),0) -> 0 | H32: =IF($A32=0,"",VLOOKUP($A32,'00_MO'!$A$4:$D$7,4,FALSE)) | I32: =G32*H32 -> 0
A34: TOTAL | I34: =SUM(I27:I32) -> 0
A35: =$I$3 -> m | I35: =$H$3 -> 8.3
A36: TOTAL x | B36: =A35 -> m | I36: =I34/I35 -> 0
A39: MANO DE OBRA - EQUIPOS
A40: Código | B40: Descripción | C40: Unidad | D40: Cantidad | E40: Dias | F40: Desperdicio | G40: Cantidad + Desperdicio | H40: Precio Unitario | I40: Subtotal
B41: =IF($A41=0,"",VLOOKUP($A41,'00_Eq'!$A$4:$D$100,2,FALSE)) | C41: =IF($A41=0,"",VLOOKUP($A41,'00_Eq'!$A$4:$D$100,3,FALSE)) | G41: =ROUNDUP(((D41*E41)*(1+F41)),0) -> 0 | H41: =IF($A41=0,"",VLOOKUP($A41,'00_Eq'!$A$4:$D$100,4,FALSE)) | I41: =G41*H41 -> 0
B42: =IF($A42=0,"",VLOOKUP($A42,'00_Eq'!$A$4:$D$100,2,FALSE)) | C42: =IF($A42=0,"",VLOOKUP($A42,'00_Eq'!$A$4:$D$100,3,FALSE)) | G42: =ROUNDUP(((D42*E42)*(1+F42)),0) -> 0 | H42: =IF($A42=0,"",VLOOKUP($A42,'00_Eq'!$A$4:$D$100,4,FALSE)) | I42: =G42*H42 -> 0
B43: =IF($A43=0,"",VLOOKUP($A43,'00_Eq'!$A$4:$D$100,2,FALSE)) | C43: =IF($A43=0,"",VLOOKUP($A43,'00_Eq'!$A$4:$D$100,3,FALSE)) | G43: =ROUNDUP(((D43*E43)*(1+F43)),0) -> 0 | H43: =IF($A43=0,"",VLOOKUP($A43,'00_Eq'!$A$4:$D$100,4,FALSE)) | I43: =G43*H43 -> 0
B44: =IF($A44=0,"",VLOOKUP($A44,'00_Eq'!$A$4:$D$100,2,FALSE)) | C44: =IF($A44=0,"",VLOOKUP($A44,'00_Eq'!$A$4:$D$100,3,FALSE)) | G44: =ROUNDUP(((D44*E44)*(1+F44)),0) -> 0 | H44: =IF($A44=0,"",VLOOKUP($A44,'00_Eq'!$A$4:$D$100,4,FALSE)) | I44: =G44*H44 -> 0
B45: =IF($A45=0,"",VLOOKUP($A45,'00_Eq'!$A$4:$D$100,2,FALSE)) | C45: =IF($A45=0,"",VLOOKUP($A45,'00_Eq'!$A$4:$D$100,3,FALSE)) | G45: =ROUNDUP(((D45*E45)*(1+F45)),0) -> 0 | H45: =IF($A45=0,"",VLOOKUP($A45,'00_Eq'!$A$4:$D$100,4,FALSE))
B46: =IF($A46=0,"",VLOOKUP($A46,'00_Eq'!$A$4:$D$100,2,FALSE)) | C46: =IF($A46=0,"",VLOOKUP($A46,'00_Eq'!$A$4:$D$100,3,FALSE)) | G46: =ROUNDUP(((D46*E46)*(1+F46)),0) -> 0 | H46: =IF($A46=0,"",VLOOKUP($A46,'00_Eq'!$A$4:$D$100,4,FALSE))
A48: TOTAL | I48: =SUM(I41:I46) -> 0
A49: =$I$3 -> m | I49: =$H$3 -> 8.3
A50: TOTAL x | B50: =A49 -> m | I50: =I48/I49 -> 0
A53: MANO DE OBRA - MATERIALES
A54: Código | B54: Descripción | C54: Unidad | D54: Cantidad | F54: Desperdicio | G54: Cantidad + Desperdicio | H54: Precio Unitario | I54: Subtotal
B55: =IF($A55=0,"",VLOOKUP($A55,'00_Mat'!$A$4:$J$1135,2,FALSE)) | C55: =IF($A55=0,"",VLOOKUP($A55,'00_Mat'!$A$4:$J$1135,3,FALSE)) | G55: =ROUNDUP((D55+(D55*F55)),0) -> 0 | H55: =IF($A55=0,"",VLOOKUP($A55,'00_Mat'!$A$4:$J$1135,5,FALSE))
B56: =IF($A56=0,"",VLOOKUP($A56,'00_Mat'!$A$4:$J$1135,2,FALSE)) | C56: =IF($A56=0,"",VLOOKUP($A56,'00_Mat'!$A$4:$J$1135,3,FALSE)) | G56: =ROUNDUP((D56+(D56*F56)),0) -> 0 | H56: =IF($A56=0,"",VLOOKUP($A56,'00_Mat'!$A$4:$J$1135,5,FALSE))
B57: =IF($A57=0,"",VLOOKUP($A57,'00_Mat'!$A$4:$J$1135,2,FALSE)) | C57: =IF($A57=0,"",VLOOKUP($A57,'00_Mat'!$A$4:$J$1135,3,FALSE)) | G57: =ROUNDUP((D57+(D57*F57)),0) -> 0 | H57: =IF($A57=0,"",VLOOKUP($A57,'00_Mat'!$A$4:$J$1135,5,FALSE))
B58: =IF($A58=0,"",VLOOKUP($A58,'00_Mat'!$A$4:$J$1135,2,FALSE)) | C58: =IF($A58=0,"",VLOOKUP($A58,'00_Mat'!$A$4:$J$1135,3,FALSE)) | G58: =ROUNDUP((D58+(D58*F58)),0) -> 0 | H58: =IF($A58=0,"",VLOOKUP($A58,'00_Mat'!$A$4:$J$1135,5,FALSE))
B59: =IF($A59=0,"",VLOOKUP($A59,'00_Mat'!$A$4:$J$1135,2,FALSE)) | C59: =IF($A59=0,"",VLOOKUP($A59,'00_Mat'!$A$4:$J$1135,3,FALSE)) | G59: =ROUNDUP((D59+(D59*F59)),0) -> 0 | H59: =IF($A59=0,"",VLOOKUP($A59,'00_Mat'!$A$4:$J$1135,5,FALSE))
B60: =IF($A60=0,"",VLOOKUP($A60,'00_Mat'!$A$4:$J$1135,2,FALSE)) | C60: =IF($A60=0,"",VLOOKUP($A60,'00_Mat'!$A$4:$J$1135,3,FALSE)) | G60: =ROUNDUP((D60+(D60*F60)),0) -> 0 | H60: =IF($A60=0,"",VLOOKUP($A60,'00_Mat'!$A$4:$J$1135,5,FALSE))
A62: TOTAL | I62: =SUM(I55:I60) -> 0
A63: =$I$3 -> m | I63: =$H$3 -> 8.3
A64: TOTAL x | B64: =A63 -> m | I64: =I62/I63 -> 0
A67: MANO DE OBRA - SUBCONTRATOS
A68: Código | B68: Descripción | C68: Unidad | D68: Cantidad | E68: Dias | F68: Desperdicio | G68: Cantidad + Desperdicio | H68: Precio Unitario | I68: Subtotal
B69: =IF($A69=0,"",VLOOKUP($A69,'00_Sub'!$A$4:$D$1001,2,FALSE)) | C69: =IF($A69=0,"",VLOOKUP($A69,'00_Sub'!$A$4:$D$1001,3,FALSE)) | D69: 1 | E69: 1 | G69: =ROUNDUP((D69+(D69*F69)),0) -> 1 | H69: 1000000 | I69: =H69*G69 -> 1000000 | M69: CHAMUYO
B70: =IF($A70=0,"",VLOOKUP($A70,'00_Sub'!$A$4:$D$1001,2,FALSE)) | C70: =IF($A70=0,"",VLOOKUP($A70,'00_Sub'!$A$4:$D$1001,3,FALSE)) | G70: =ROUNDUP((D70+(D70*F70)),0) -> 0 | H70: =IF($A70=0,"",VLOOKUP($A70,'00_Sub'!$A$4:$D$1001,4,FALSE))
B71: =IF($A71=0,"",VLOOKUP($A71,'00_Sub'!$A$4:$D$1001,2,FALSE)) | C71: =IF($A71=0,"",VLOOKUP($A71,'00_Sub'!$A$4:$D$1001,3,FALSE)) | G71: =ROUNDUP((D71+(D71*F71)),0) -> 0 | H71: =IF($A71=0,"",VLOOKUP($A71,'00_Sub'!$A$4:$D$1001,4,FALSE))
B72: =IF($A72=0,"",VLOOKUP($A72,'00_Sub'!$A$4:$D$1001,2,FALSE)) | C72: =IF($A72=0,"",VLOOKUP($A72,'00_Sub'!$A$4:$D$1001,3,FALSE)) | G72: =ROUNDUP((D72+(D72*F72)),0) -> 0 | H72: =IF($A72=0,"",VLOOKUP($A72,'00_Sub'!$A$4:$D$1001,4,FALSE))
B73: =IF($A73=0,"",VLOOKUP($A73,'00_Sub'!$A$4:$D$1001,2,FALSE)) | C73: =IF($A73=0,"",VLOOKUP($A73,'00_Sub'!$A$4:$D$1001,3,FALSE)) | G73: =ROUNDUP((D73+(D73*F73)),0) -> 0 | H73: =IF($A73=0,"",VLOOKUP($A73,'00_Sub'!$A$4:$D$1001,4,FALSE))
B74: =IF($A74=0,"",VLOOKUP($A74,'00_Sub'!$A$4:$D$1001,2,FALSE)) | C74: =IF($A74=0,"",VLOOKUP($A74,'00_Sub'!$A$4:$D$1001,3,FALSE)) | G74: =ROUNDUP((D74+(D74*F74)),0) -> 0 | H74: =IF($A74=0,"",VLOOKUP($A74,'00_Sub'!$A$4:$D$1001,4,FALSE))
A76: TOTAL | I76: =SUM(I69:I74) -> 1000000
A77: =$I$3 -> m | I77: =$H$3 -> 8.3
A78: TOTAL x | B78: =A77 -> m | I78: =I76/I77 -> 120481.93

Sheet 3.1-3
A1: ='01_C&P'!A1 -> CASA LUGONES
A3: ='01_C&P'!A42 -> 3.1-3 | B3: =IF($A3=0,"",VLOOKUP($A3,'01_C&P'!$A$9:$D$172,2,FALSE)) -> LOSA DE VIGUETAS SECTOR COCINA e=0,08m | H3: =IF($A3=0,"",VLOOKUP($A3,'01_C&P'!$A$9:$D$172,4,FALSE)) -> 18 | I3: =IF($A3=0,"",VLOOKUP($A3,'01_C&P'!$A$9:$D$172,3,FALSE)) -> m²
A5: MATERIALES
A6: Código | B6: Descripción | C6: Unidad | D6: Cantidad | F6: Desperdicio | G6: Cantidad + Desperdicio | H6: Precio Unitario | I6: Subtotal
A7: H30 | B7: =IF($A7=0,"",VLOOKUP($A7,'00_Mat'!$A$4:$J$1135,2,FALSE)) -> Hormigon H30 | C7: =IF($A7=0,"",VLOOKUP($A7,'00_Mat'!$A$4:$J$1135,3,FALSE)) -> m3 | D7: =H3*0.08 -> 1.44 | F7: 0.1 | G7: =ROUNDUP((D7+(D7*F7)),0) -> 2 | H7: =IF($A7=0,"",VLOOKUP($A7,'00_Mat'!$A$4:$J$1135,5,FALSE)) -> 125280 | I7: =H7*G7 -> 250560
A8: m8 | B8: =IF($A8=0,"",VLOOKUP($A8,'00_Mat'!$A$4:$J$1135,2,FALSE)) -> Malla Φ 8 (2 m x 5 m) (hierros cada 0,15 x 0,15 m) | C8: =IF($A8=0,"",VLOOKUP($A8,'00_Mat'!$A$4:$J$1135,3,FALSE)) -> u | D8: 2 | F8: 0 | G8: =ROUNDUP((D8+(D8*F8)),0) -> 2 | H8: =IF($A8=0,"",VLOOKUP($A8,'00_Mat'!$A$4:$J$1135,5,FALSE)) -> 50000 | I8: =H8*G8 -> 100000 | K8: CALCULADO A MANO. ME DA MUCHO MAS QUE YPF
A9: VI4 | B9: =IF($A9=0,"",VLOOKUP($A9,'00_Mat'!$A$4:$J$1135,2,FALSE)) -> Vigueta pretensada de hormigon 4m | C9: =IF($A9=0,"",VLOOKUP($A9,'00_Mat'!$A$4:$J$1135,3,FALSE)) -> u | D9: 12 | F9: 0.1 | G9: =ROUNDUP((D9+(D9*F9)),0) -> 14 | H9: =IF($A9=0,"",VLOOKUP($A9,'00_Mat'!$A$4:$J$1135,5,FALSE)) -> 26000 | I9: =H9*G9 -> 364000 | K9: YPF DA 18.000
A10: vi-eps | B10: =IF($A10=0,"",VLOOKUP($A10,'00_Mat'!$A$4:$J$1135,2,FALSE)) -> Ladrillos Telgopor 10cm | C10: =IF($A10=0,"",VLOOKUP($A10,'00_Mat'!$A$4:$J$1135,3,FALSE)) -> u | D10: 46 | F10: 0.1 | G10: =ROUNDUP((D10+(D10*F10)),0) -> 51 | H10: =IF($A10=0,"",VLOOKUP($A10,'00_Mat'!$A$4:$J$1135,5,FALSE)) -> 3600 | I10: =H10*G10 -> 183600 | K10: CASA 43,000 + 16.000 CONSUMIBLES
B11: =IF($A11=0,"",VLOOKUP($A11,'00_Mat'!$A$4:$J$1135,2,FALSE)) | C11: =IF($A11=0,"",VLOOKUP($A11,'00_Mat'!$A$4:$J$1135,3,FALSE)) | G11: =ROUNDUP((D11+(D11*F11)),0) -> 0 | H11: =IF($A11=0,"",VLOOKUP($A11,'00_Mat'!$A$4:$J$1135,5,FALSE)) | I11: =H11*G11 -> 0
B12: =IF($A12=0,"",VLOOKUP($A12,'00_Mat'!$A$4:$J$1135,2,FALSE)) | C12: =IF($A12=0,"",VLOOKUP($A12,'00_Mat'!$A$4:$J$1135,3,FALSE)) | G12: =ROUNDUP((D12+(D12*F12)),0) -> 0 | H12: =IF($A12=0,"",VLOOKUP($A12,'00_Mat'!$A$4:$J$1135,5,FALSE)) | I12: =H12*G12 -> 0
B13: =IF($A13=0,"",VLOOKUP($A13,'00_Mat'!$A$4:$J$1135,2,FALSE)) | C13: =IF($A13=0,"",VLOOKUP($A13,'00_Mat'!$A$4:$J$1135,3,FALSE)) | G13: =ROUNDUP((D13+(D13*F13)),0) -> 0 | H13: =IF($A13=0,"",VLOOKUP($A13,'00_Mat'!$A$4:$J$1135,5,FALSE)) | I13: =H13*G13 -> 0
B14: =IF($A14=0,"",VLOOKUP($A14,'00_Mat'!$A$4:$J$1135,2,FALSE)) | C14: =IF($A14=0,"",VLOOKUP($A14,'00_Mat'!$A$4:$J$1135,3,FALSE)) | G14: =ROUNDUP((D14+(D14*F14)),0) -> 0 | H14: =IF($A14=0,"",VLOOKUP($A14,'00_Mat'!$A$4:$J$1135,5,FALSE)) | I14: =H14*G14 -> 0
B15: =IF($A15=0,"",VLOOKUP($A15,'00_Mat'!$A$4:$J$1135,2,FALSE)) | C15: =IF($A15=0,"",VLOOKUP($A15,'00_Mat'!$A$4:$J$1135,3,FALSE)) | G15: =ROUNDUP((D15+(D15*F15)),0) -> 0 | H15: =IF($A15=0,"",VLOOKUP($A15,'00_Mat'!$A$4:$J$1135,5,FALSE)) | I15: =H15*G15 -> 0
B16: =IF($A16=0,"",VLOOKUP($A16,'00_Mat'!$A$4:$J$1135,2,FALSE)) | C16: =IF($A16=0,"",VLOOKUP($A16,'00_Mat'!$A$4:$J$1135,3,FALSE)) | G16: =ROUNDUP((D16+(D16*F16)),0) -> 0 | H16: =IF($A16=0,"",VLOOKUP($A16,'00_Mat'!$A$4:$J$1135,5,FALSE)) | I16: =H16*G16 -> 0
B17: =IF($A17=0,"",VLOOKUP($A17,'00_Mat'!$A$4:$J$1135,2,FALSE)) | C17: =IF($A17=0,"",VLOOKUP($A17,'00_Mat'!$A$4:$J$1135,3,FALSE)) | G17: =ROUNDUP((D17+(D17*F17)),0) -> 0 | H17: =IF($A17=0,"",VLOOKUP($A17,'00_Mat'!$A$4:$J$1135,5,FALSE)) | I17: =H17*G17 -> 0
B18: =IF($A18=0,"",VLOOKUP($A18,'00_Mat'!$A$4:$J$1135,2,FALSE)) | C18: =IF($A18=0,"",VLOOKUP($A18,'00_Mat'!$A$4:$J$1135,3,FALSE)) | G18: =ROUNDUP((D18+(D18*F18)),0) -> 0 | H18: =IF($A18=0,"",VLOOKUP($A18,'00_Mat'!$A$4:$J$1135,5,FALSE)) | I18: =H18*G18 -> 0
A20: TOTAL MATERIALES | I20: =SUM(I7:I18) -> 898160
A21: =$I$3 -> m² | I21: =$H$3 -> 18
A22: TOTAL x | B22: =A21 -> m² | I22: =I20/I21 -> 49897.778
A25: MANO DE OBRA - PERSONAS
A26: Código | B26: Descripción | C26: Unidad | D26: Cantidad | E26: Dias | F26: Desperdicio | G26: Cantidad + Desperdicio | H26: Precio Unitario | I26: Subtotal
A27: MO-CA | B27: =IF($A27=0,"",VLOOKUP($A27,'00_MO'!$A$4:$D$7,2,FALSE)) -> Capataz | C27: =IF($A27=0,"",VLOOKUP($A27,'00_MO'!$A$4:$D$7,3,FALSE)) -> u | D27: 1 | E27: 1 | F27: 0.25 | G27: =ROUNDUP(((D27*E27)*(1+F27)),0) -> 2 | H27: =IF($A27=0,"",VLOOKUP($A27,'00_MO'!$A$4:$D$7,4,FALSE)) -> 90000 | I27: =G27*H27 -> 180000
A28: MO-OF | B28: =IF($A28=0,"",VLOOKUP($A28,'00_MO'!$A$4:$D$7,2,FALSE)) -> Oficial | C28: =IF($A28=0,"",VLOOKUP($A28,'00_MO'!$A$4:$D$7,3,FALSE)) -> u | D28: 2 | E28: 1 | F28: 0.25 | G28: =ROUNDUP(((D28*E28)*(1+F28)),0) -> 3 | H28: =IF($A28=0,"",VLOOKUP($A28,'00_MO'!$A$4:$D$7,4,FALSE)) -> 75000 | I28: =G28*H28 -> 225000
A29: MO-AY | B29: =IF($A29=0,"",VLOOKUP($A29,'00_MO'!$A$4:$D$7,2,FALSE)) -> Ayudante | C29: =IF($A29=0,"",VLOOKUP($A29,'00_MO'!$A$4:$D$7,3,FALSE)) -> u | D29: 1 | E29: 1 | F29: 0.25 | G29: =ROUNDUP(((D29*E29)*(1+F29)),0) -> 2 | H29: =IF($A29=0,"",VLOOKUP($A29,'00_MO'!$A$4:$D$7,4,FALSE)) -> 60000 | I29: =G29*H29 -> 120000 | K29: 4,800 MAS QUE YPF
B30: =IF($A30=0,"",VLOOKUP($A30,'00_MO'!$A$4:$D$7,2,FALSE)) | C30: =IF($A30=0,"",VLOOKUP($A30,'00_MO'!$A$4:$D$7,3,FALSE)) | G30: =ROUNDUP(((D30*E30)*(1+F30)),0) -> 0 | H30: =IF($A30=0,"",VLOOKUP($A30,'00_MO'!$A$4:$D$7,4,FALSE)) | I30: =G30*H30 -> 0
B31: =IF($A31=0,"",VLOOKUP($A31,'00_MO'!$A$4:$D$7,2,FALSE)) | C31: =IF($A31=0,"",VLOOKUP($A31,'00_MO'!$A$4:$D$7,3,FALSE)) | G31: =ROUNDUP(((D31*E31)*(1+F31)),0) -> 0 | H31: =IF($A31=0,"",VLOOKUP($A31,'00_MO'!$A$4:$D$7,4,FALSE)) | I31: =G31*H31 -> 0
B32: =IF($A32=0,"",VLOOKUP($A32,'00_MO'!$A$4:$D$7,2,FALSE)) | C32: =IF($A32=0,"",VLOOKUP($A32,'00_MO'!$A$4:$D$7,3,FALSE)) | G32: =ROUNDUP(((D32*E32)*(1+F32)),0) -> 0 | H32: =IF($A32=0,"",VLOOKUP($A32,'00_MO'!$A$4:$D$7,4,FALSE)) | I32: =G32*H32 -> 0
A34: TOTAL | I34: =SUM(I27:I32) -> 525000
A35: =$I$3 -> m² | I35: =$H$3 -> 18
A36: TOTAL x | B36: =A35 -> m² | I36: =I34/I35 -> 29166.667
A39: MANO DE OBRA - EQUIPOS
A40: Código | B40: Descripción | C40: Unidad | D40: Cantidad | E40: Dias | F40: Desperdicio | G40: Cantidad + Desperdicio) | H40: Precio Unitario | I40: Subtotal
B41: =IF($A41=0,"",VLOOKUP($A41,'00_Eq'!$A$4:$D$100,2,FALSE)) | C41: =IF($A41=0,"",VLOOKUP($A41,'00_Eq'!$A$4:$D$100,3,FALSE)) | G41: =ROUNDUP(((D41*E41)*(1+F41)),0) -> 0 | H41: =IF($A41=0,"",VLOOKUP($A41,'00_Eq'!$A$4:$D$100,4,FALSE)) | I41: =G41*H41 -> 0
B42: =IF($A42=0,"",VLOOKUP($A42,'00_Eq'!$A$4:$D$100,2,FALSE)) | C42: =IF($A42=0,"",VLOOKUP($A42,'00_Eq'!$A$4:$D$100,3,FALSE)) | G42: =ROUNDUP(((D42*E42)*(1+F42)),0) -> 0 | H42: =IF($A42=0,"",VLOOKUP($A42,'00_Eq'!$A$4:$D$100,4,FALSE)) | I42: =G42*H42 -> 0
B43: =IF($A43=0,"",VLOOKUP($A43,'00_Eq'!$A$4:$D$100,2,FALSE)) | C43: =IF($A43=0,"",VLOOKUP($A43,'00_Eq'!$A$4:$D$100,3,FALSE)) | G43: =ROUNDUP(((D43*E43)*(1+F43)),0) -> 0 | H43: =IF($A43=0,"",VLOOKUP($A43,'00_Eq'!$A$4:$D$100,4,FALSE)) | I43: =G43*H43 -> 0
B44: =IF($A44=0,"",VLOOKUP($A44,'00_Eq'!$A$4:$D$100,2,FALSE)) | C44: =IF($A44=0,"",VLOOKUP($A44,'00_Eq'!$A$4:$D$100,3,FALSE)) | G44: =ROUNDUP(((D44*E44)*(1+F44)),0) -> 0 | H44: =IF($A44=0,"",VLOOKUP($A44,'00_Eq'!$A$4:$D$100,4,FALSE)) | I44: =G44*H44 -> 0
B45: =IF($A45=0,"",VLOOKUP($A45,'00_Eq'!$A$4:$D$100,2,FALSE)) | C45: =IF($A45=0,"",VLOOKUP($A45,'00_Eq'!$A$4:$D$100,3,FALSE)) | G45: =ROUNDUP(((D45*E45)*(1+F45)),0) -> 0 | H45: =IF($A45=0,"",VLOOKUP($A45,'00_Eq'!$A$4:$D$100,4,FALSE))
B46: =IF($A46=0,"",VLOOKUP($A46,'00_Eq'!$A$4:$D$100,2,FALSE)) | C46: =IF($A46=0,"",VLOOKUP($A46,'00_Eq'!$A$4:$D$100,3,FALSE)) | G46: =ROUNDUP(((D46*E46)*(1+F46)),0) -> 0 | H46: =IF($A46=0,"",VLOOKUP($A46,'00_Eq'!$A$4:$D$100,4,FALSE))
A48: TOTAL | I48: =SUM(I41:I46) -> 0
A49: =$I$3 -> m² | I49: =$H$3 -> 18
A50: TOTAL x | B50: =A49 -> m² | I50: =I48/I49 -> 0
A53: MANO DE OBRA - MATERIALES
A54: Código | B54: Descripción | C54: Unidad | D54: Cantidad | F54: Desperdicio | G54: Cantidad + Desperdicio | H54: Precio Unitario | I54: Subtotal
A55: dis | B55: =IF($A55=0,"",VLOOKUP($A55,'00_Mat'!$A$4:$J$1135,2,FALSE)) -> Disco corte | C55: =IF($A55=0,"",VLOOKUP($A55,'00_Mat'!$A$4:$J$1135,3,FALSE)) -> u | D55: 1 | F55: 0.1 | G55: =ROUNDUP((D55+(D55*F55)),0) -> 2 | H55: =IF($A55=0,"",VLOOKUP($A55,'00_Mat'!$A$4:$J$1135,5,FALSE)) -> 40000 | I55: =H55*G55 -> 80000
A56: PUN | B56: =IF($A56=0,"",VLOOKUP($A56,'00_Mat'!$A$4:$J$1135,2,FALSE)) -> Puntal | C56: =IF($A56=0,"",VLOOKUP($A56,'00_Mat'!$A$4:$J$1135,3,FALSE)) -> u | D56: =H3 -> 18 | F56: 0.1 | G56: =ROUNDUP((D56+(D56*F56)),0) -> 20 | H56: =IF($A56=0,"",VLOOKUP($A56,'00_Mat'!$A$4:$J$1135,5,FALSE)) -> 6900 | I56: =H56*G56 -> 138000
A57: CL2.5 | B57: =IF($A57=0,"",VLOOKUP($A57,'00_Mat'!$A$4:$J$1135,2,FALSE)) -> Clavos 2,5" punta paris (k) | C57: =IF($A57=0,"",VLOOKUP($A57,'00_Mat'!$A$4:$J$1135,3,FALSE)) -> k | D57: 0 | F57: 0.1 | G57: =ROUNDUP((D57+(D57*F57)),0) -> 0 | H57: =IF($A57=0,"",VLOOKUP($A57,'00_Mat'!$A$4:$J$1135,5,FALSE)) -> 3739.67 | I57: =H57*G57 -> 0
A58: AL | B58: =IF($A58=0,"",VLOOKUP($A58,'00_Mat'!$A$4:$J$1135,2,FALSE)) -> Alambre Fardo (k) | C58: =IF($A58=0,"",VLOOKUP($A58,'00_Mat'!$A$4:$J$1135,3,FALSE)) -> k | D58: 0 | F58: 0.1 | G58: =ROUNDUP((D58+(D58*F58)),0) -> 0 | H58: =IF($A58=0,"",VLOOKUP($A58,'00_Mat'!$A$4:$J$1135,5,FALSE)) -> 4326.45 | I58: =H58*G58 -> 0
A59: CL2 | B59: =IF($A59=0,"",VLOOKUP($A59,'00_Mat'!$A$4:$J$1135,2,FALSE)) -> Clavos 2" punta paris (k) | C59: =IF($A59=0,"",VLOOKUP($A59,'00_Mat'!$A$4:$J$1135,3,FALSE)) -> k | D59: 0 | F59: 0.1 | G59: =ROUNDUP((D59+(D59*F59)),0) -> 0 | H59: =IF($A59=0,"",VLOOKUP($A59,'00_Mat'!$A$4:$J$1135,5,FALSE)) -> 3739.67 | I59: =H59*G59 -> 0
A60: F-IND | B60: =IF($A60=0,"",VLOOKUP($A60,'00_Mat'!$A$4:$J$1135,2,FALSE)) -> Fenolico 18mm Industrial | C60: =IF($A60=0,"",VLOOKUP($A60,'00_Mat'!$A$4:$J$1135,3,FALSE)) -> u | D60: =H51/2.97 -> 0 | F60: 0 | G60: =ROUNDUP((D60+(D60*F60)),0) -> 0 | H60: =IF($A60=0,"",VLOOKUP($A60,'00_Mat'!$A$4:$J$1135,5,FALSE)) -> 32400 | I60: =H60*G60 -> 0
A62: TOTAL | I62: =SUM(I55:I60) -> 218000
A63: =$I$3 -> m² | I63: =$H$3 -> 18
A64: TOTAL x | B64: =A63 -> m² | I64: =I62/I63 -> 12111.111
A67: MANO DE OBRA - SUBCONTRATOS
A68: Código | B68: Descripción | C68: Unidad | D68: Cantidad | E68: Dias | F68: Desperdicio | G68: Cantidad + Desperdicio | H68: Precio Unitario | I68: Subtotal
B69: =IF($A69=0,"",VLOOKUP($A69,'00_Sub'!$A$4:$D$1001,2,FALSE)) | C69: =IF($A69=0,"",VLOOKUP($A69,'00_Sub'!$A$4:$D$1001,3,FALSE)) | G69: =ROUNDUP((D69+(D69*F69)),0) -> 0 | H69: =IF($A69=0,"",VLOOKUP($A69,'00_Sub'!$A$4:$D$1001,4,FALSE))
B70: =IF($A70=0,"",VLOOKUP($A70,'00_Sub'!$A$4:$D$1001,2,FALSE)) | C70: =IF($A70=0,"",VLOOKUP($A70,'00_Sub'!$A$4:$D$1001,3,FALSE)) | G70: =ROUNDUP((D70+(D70*F70)),0) -> 0 | H70: =IF($A70=0,"",VLOOKUP($A70,'00_Sub'!$A$4:$D$1001,4,FALSE))
B71: =IF($A71=0,"",VLOOKUP($A71,'00_Sub'!$A$4:$D$1001,2,FALSE)) | C71: =IF($A71=0,"",VLOOKUP($A71,'00_Sub'!$A$4:$D$1001,3,FALSE)) | G71: =ROUNDUP((D71+(D71*F71)),0) -> 0 | H71: =IF($A71=0,"",VLOOKUP($A71,'00_Sub'!$A$4:$D$1001,4,FALSE))
B72: =IF($A72=0,"",VLOOKUP($A72,'00_Sub'!$A$4:$D$1001,2,FALSE)) | C72: =IF($A72=0,"",VLOOKUP($A72,'00_Sub'!$A$4:$D$1001,3,FALSE)) | G72: =ROUNDUP((D72+(D72*F72)),0) -> 0 | H72: =IF($A72=0,"",VLOOKUP($A72,'00_Sub'!$A$4:$D$1001,4,FALSE))
B73: =IF($A73=0,"",VLOOKUP($A73,'00_Sub'!$A$4:$D$1001,2,FALSE)) | C73: =IF($A73=0,"",VLOOKUP($A73,'00_Sub'!$A$4:$D$1001,3,FALSE)) | G73: =ROUNDUP((D73+(D73*F73)),0) -> 0 | H73: =IF($A73=0,"",VLOOKUP($A73,'00_Sub'!$A$4:$D$1001,4,FALSE))
B74: =IF($A74=0,"",VLOOKUP($A74,'00_Sub'!$A$4:$D$1001,2,FALSE)) | C74: =IF($A74=0,"",VLOOKUP($A74,'00_Sub'!$A$4:$D$1001,3,FALSE)) | G74: =ROUNDUP((D74+(D74*F74)),0) -> 0 | H74: =IF($A74=0,"",VLOOKUP($A74,'00_Sub'!$A$4:$D$1001,4,FALSE))
A76: TOTAL | I76: =SUM(I69:I74) -> 0
A77: =$I$3 -> m² | I77: =$H$3 -> 18
A78: TOTAL x | B78: =A77 -> m² | I78: =I76/I77 -> 0

Sheet 3.1-4
A1: ='01_C&P'!A1 -> CASA LUGONES
A3: ='01_C&P'!A43 -> 3.1-4 | B3: =IF($A3=0,"",VLOOKUP($A3,'01_C&P'!$A$9:$D$172,2,FALSE)) -> COLUMNAS DE HORMIGON ARMADO 20x20cm h 3,5m (Hierros 4 ∅12 con estribos ∅ 6 c/14) | H3: =IF($A3=0,"",VLOOKUP($A3,'01_C&P'!$A$9:$D$172,4,FALSE)) -> 7 | I3: =IF($A3=0,"",VLOOKUP($A3,'01_C&P'!$A$9:$D$172,3,FALSE)) -> unid.
A5: MATERIALES
A6: Código | B6: Descripción | C6: Unidad | D6: Cantidad | F6: Desperdicio | G6: Cantidad + Desperdicio | H6: Precio Unitario | I6: Subtotal
A7: H30 | B7: =IF($A7=0,"",VLOOKUP($A7,'00_Mat'!$A$4:$J$1135,2,FALSE)) -> Hormigon H30 | C7: =IF($A7=0,"",VLOOKUP($A7,'00_Mat'!$A$4:$J$1135,3,FALSE)) -> m3 | D7: =(0.2*0.2*3.5)*H3 -> 0.98 | F7: 0.15 | G7: =ROUNDUP((D7+(D7*F7)),0) -> 2 | H7: =IF($A7=0,"",VLOOKUP($A7,'00_Mat'!$A$4:$J$1135,5,FALSE)) -> 125280 | I7: =H7*G7 -> 250560
A8: HADN6 | B8: =IF($A8=0,"",VLOOKUP($A8,'00_Mat'!$A$4:$J$1135,2,FALSE)) -> Hierros ADN 420 Φ 6 | C8: =IF($A8=0,"",VLOOKUP($A8,'00_Mat'!$A$4:$J$1135,3,FALSE)) -> u | D8: =(((3.5/0.14)*1)/12)*H3 -> 14.583333 | F8: 0.15 | G8: =ROUNDUP((D8+(D8*F8)),0) -> 17 | H8: =IF($A8=0,"",VLOOKUP($A8,'00_Mat'!$A$4:$J$1135,5,FALSE)) -> 5250 | I8: =H8*G8 -> 89250
A9: HADN12 | B9: =IF($A9=0,"",VLOOKUP($A9,'00_Mat'!$A$4:$J$1135,2,FALSE)) -> Hierros ADN 420 Φ 12 | C9: =IF($A9=0,"",VLOOKUP($A9,'00_Mat'!$A$4:$J$1135,3,FALSE)) -> u | D9: =((3.5*4)/12)*H3 -> 8.1666667 | F9: 0.15 | G9: =ROUNDUP((D9+(D9*F9)),0) -> 10 | H9: =IF($A9=0,"",VLOOKUP($A9,'00_Mat'!$A$4:$J$1135,5,FALSE)) -> 20442.5 | I9: =H9*G9 -> 204425
A10: GRO | B10: =IF($A10=0,"",VLOOKUP($A10,'00_Mat'!$A$4:$J$1135,2,FALSE)) -> Sika Grout 22kg | C10: =IF($A10=0,"",VLOOKUP($A10,'00_Mat'!$A$4:$J$1135,3,FALSE)) -> U | D10: 5 | F10: 0.1 | G10: =ROUNDUP((D10+(D10*F10)),0) -> 6 | H10: =IF($A10=0,"",VLOOKUP($A10,'00_Mat'!$A$4:$J$1135,5,FALSE)) -> 43000 | I10: =H10*G10 -> 258000 | J10: MATERIAL PARA TERMINAR DE LLENAR LA COLUMNA | O10: 1 COLUMNA X BOLSA
B11: =IF($A11=0,"",VLOOKUP($A11,'00_Mat'!$A$4:$J$1135,2,FALSE)) | C11: =IF($A11=0,"",VLOOKUP($A11,'00_Mat'!$A$4:$J$1135,3,FALSE)) | G11: =ROUNDUP((D11+(D11*F11)),0) -> 0 | H11: =IF($A11=0,"",VLOOKUP($A11,'00_Mat'!$A$4:$J$1135,5,FALSE)) | I11: =H11*G11 -> 0
B12: =IF($A12=0,"",VLOOKUP($A12,'00_Mat'!$A$4:$J$1135,2,FALSE)) | C12: =IF($A12=0,"",VLOOKUP($A12,'00_Mat'!$A$4:$J$1135,3,FALSE)) | G12: =ROUNDUP((D12+(D12*F12)),0) -> 0 | H12: =IF($A12=0,"",VLOOKUP($A12,'00_Mat'!$A$4:$J$1135,5,FALSE)) | I12: =H12*G12 -> 0
B13: =IF($A13=0,"",VLOOKUP($A13,'00_Mat'!$A$4:$J$1135,2,FALSE)) | C13: =IF($A13=0,"",VLOOKUP($A13,'00_Mat'!$A$4:$J$1135,3,FALSE)) | G13: =ROUNDUP((D13+(D13*F13)),0) -> 0 | H13: =IF($A13=0,"",VLOOKUP($A13,'00_Mat'!$A$4:$J$1135,5,FALSE)) | I13: =H13*G13 -> 0
B14: =IF($A14=0,"",VLOOKUP($A14,'00_Mat'!$A$4:$J$1135,2,FALSE)) | C14: =IF($A14=0,"",VLOOKUP($A14,'00_Mat'!$A$4:$J$1135,3,FALSE)) | G14: =ROUNDUP((D14+(D14*F14)),0) -> 0 | H14: =IF($A14=0,"",VLOOKUP($A14,'00_Mat'!$A$4:$J$1135,5,FALSE)) | I14: =H14*G14 -> 0
B15: =IF($A15=0,"",VLOOKUP($A15,'00_Mat'!$A$4:$J$1135,2,FALSE)) | C15: =IF($A15=0,"",VLOOKUP($A15,'00_Mat'!$A$4:$J$1135,3,FALSE)) | G15: =ROUNDUP((D15+(D15*F15)),0) -> 0 | H15: =IF($A15=0,"",VLOOKUP($A15,'00_Mat'!$A$4:$J$1135,5,FALSE)) | I15: =H15*G15 -> 0
B16: =IF($A16=0,"",VLOOKUP($A16,'00_Mat'!$A$4:$J$1135,2,FALSE)) | C16: =IF($A16=0,"",VLOOKUP($A16,'00_Mat'!$A$4:$J$1135,3,FALSE)) | G16: =ROUNDUP((D16+(D16*F16)),0) -> 0 | H16: =IF($A16=0,"",VLOOKUP($A16,'00_Mat'!$A$4:$J$1135,5,FALSE)) | I16: =H16*G16 -> 0
B17: =IF($A17=0,"",VLOOKUP($A17,'00_Mat'!$A$4:$J$1135,2,FALSE)) | C17: =IF($A17=0,"",VLOOKUP($A17,'00_Mat'!$A$4:$J$1135,3,FALSE)) | G17: =ROUNDUP((D17+(D17*F17)),0) -> 0 | H17: =IF($A17=0,"",VLOOKUP($A17,'00_Mat'!$A$4:$J$1135,5,FALSE)) | I17: =H17*G17 -> 0
B18: =IF($A18=0,"",VLOOKUP($A18,'00_Mat'!$A$4:$J$1135,2,FALSE)) | C18: =IF($A18=0,"",VLOOKUP($A18,'00_Mat'!$A$4:$J$1135,3,FALSE)) | G18: =ROUNDUP((D18+(D18*F18)),0) -> 0 | H18: =IF($A18=0,"",VLOOKUP($A18,'00_Mat'!$A$4:$J$1135,5,FALSE)) | I18: =H18*G18 -> 0
A20: TOTAL MATERIALES | I20: =SUM(I7:I18) -> 802235
A21: =$I$3 -> unid. | I21: =$H$3 -> 7
A22: TOTAL x | B22: =A21 -> unid. | I22: =I20/I21 -> 114605
A25: MANO DE OBRA - PERSONAS
A26: Código | B26: Descripción | C26: Unidad | D26: Cantidad | E26: Dias | F26: Desperdicio | G26: Cantidad + Desperdicio | H26: Precio Unitario | I26: Subtotal
A27: MO-CA | B27: =IF($A27=0,"",VLOOKUP($A27,'00_MO'!$A$4:$D$7,2,FALSE)) -> Capataz | C27: =IF($A27=0,"",VLOOKUP($A27,'00_MO'!$A$4:$D$7,3,FALSE)) -> u | D27: 1 | E27: 3 | F27: 0.25 | G27: =ROUNDUP(((D27*E27)*(1+F27)),0) -> 4 | H27: =IF($A27=0,"",VLOOKUP($A27,'00_MO'!$A$4:$D$7,4,FALSE)) -> 90000 | I27: =G27*H27 -> 360000
A28: MO-OF | B28: =IF($A28=0,"",VLOOKUP($A28,'00_MO'!$A$4:$D$7,2,FALSE)) -> Oficial | C28: =IF($A28=0,"",VLOOKUP($A28,'00_MO'!$A$4:$D$7,3,FALSE)) -> u | D28: 2 | E28: 3 | F28: 0.25 | G28: =ROUNDUP(((D28*E28)*(1+F28)),0) -> 8 | H28: =IF($A28=0,"",VLOOKUP($A28,'00_MO'!$A$4:$D$7,4,FALSE)) -> 75000 | I28: =G28*H28 -> 600000 | K28: MAS DIAS X SIKA GROUT
A29: MO-AY | B29: =IF($A29=0,"",VLOOKUP($A29,'00_MO'!$A$4:$D$7,2,FALSE)) -> Ayudante | C29: =IF($A29=0,"",VLOOKUP($A29,'00_MO'!$A$4:$D$7,3,FALSE)) -> u | D29: 1 | E29: 3 | F29: 0.25 | G29: =ROUNDUP(((D29*E29)*(1+F29)),0) -> 4 | H29: =IF($A29=0,"",VLOOKUP($A29,'00_MO'!$A$4:$D$7,4,FALSE)) -> 60000 | I29: =G29*H29 -> 240000
B30: =IF($A30=0,"",VLOOKUP($A30,'00_MO'!$A$4:$D$7,2,FALSE)) | C30: =IF($A30=0,"",VLOOKUP($A30,'00_MO'!$A$4:$D$7,3,FALSE)) | G30: =ROUNDUP(((D30*E30)*(1+F30)),0) -> 0 | H30: =IF($A30=0,"",VLOOKUP($A30,'00_MO'!$A$4:$D$7,4,FALSE)) | I30: =G30*H30 -> 0
B31: =IF($A31=0,"",VLOOKUP($A31,'00_MO'!$A$4:$D$7,2,FALSE)) | C31: =IF($A31=0,"",VLOOKUP($A31,'00_MO'!$A$4:$D$7,3,FALSE)) | G31: =ROUNDUP(((D31*E31)*(1+F31)),0) -> 0 | H31: =IF($A31=0,"",VLOOKUP($A31,'00_MO'!$A$4:$D$7,4,FALSE)) | I31: =G31*H31 -> 0
B32: =IF($A32=0,"",VLOOKUP($A32,'00_MO'!$A$4:$D$7,2,FALSE)) | C32: =IF($A32=0,"",VLOOKUP($A32,'00_MO'!$A$4:$D$7,3,FALSE)) | G32: =ROUNDUP(((D32*E32)*(1+F32)),0) -> 0 | H32: =IF($A32=0,"",VLOOKUP($A32,'00_MO'!$A$4:$D$7,4,FALSE)) | I32: =G32*H32 -> 0
A34: TOTAL | I34: =SUM(I27:I32) -> 1200000
A35: =$I$3 -> unid. | I35: =$H$3 -> 7
A36: TOTAL x | B36: =A35 -> unid. | I36: =I34/I35 -> 171428.57
A39: MANO DE OBRA - EQUIPOS
A40: Código | B40: Descripción | C40: Unidad | D40: Cantidad | E40: Dias | F40: Desperdicio | G40: Cantidad + Desperdicio | H40: Precio Unitario | I40: Subtotal
B41: =IF($A41=0,"",VLOOKUP($A41,'00_Eq'!$A$4:$D$100,2,FALSE)) | C41: =IF($A41=0,"",VLOOKUP($A41,'00_Eq'!$A$4:$D$100,3,FALSE)) | G41: =ROUNDUP(((D41*E41)*(1+F41)),0) -> 0 | H41: =IF($A41=0,"",VLOOKUP($A41,'00_Eq'!$A$4:$D$100,4,FALSE)) | I41: =G41*H41 -> 0
B42: =IF($A42=0,"",VLOOKUP($A42,'00_Eq'!$A$4:$D$100,2,FALSE)) | C42: =IF($A42=0,"",VLOOKUP($A42,'00_Eq'!$A$4:$D$100,3,FALSE)) | G42: =ROUNDUP(((D42*E42)*(1+F42)),0) -> 0 | H42: =IF($A42=0,"",VLOOKUP($A42,'00_Eq'!$A$4:$D$100,4,FALSE)) | I42: =G42*H42 -> 0
B43: =IF($A43=0,"",VLOOKUP($A43,'00_Eq'!$A$4:$D$100,2,FALSE)) | C43: =IF($A43=0,"",VLOOKUP($A43,'00_Eq'!$A$4:$D$100,3,FALSE)) | G43: =ROUNDUP(((D43*E43)*(1+F43)),0) -> 0 | H43: =IF($A43=0,"",VLOOKUP($A43,'00_Eq'!$A$4:$D$100,4,FALSE)) | I43: =G43*H43 -> 0
B44: =IF($A44=0,"",VLOOKUP($A44,'00_Eq'!$A$4:$D$100,2,FALSE)) | C44: =IF($A44=0,"",VLOOKUP($A44,'00_Eq'!$A$4:$D$100,3,FALSE)) | G44: =ROUNDUP(((D44*E44)*(1+F44)),0) -> 0 | H44: =IF($A44=0,"",VLOOKUP($A44,'00_Eq'!$A$4:$D$100,4,FALSE)) | I44: =G44*H44 -> 0
B45: =IF($A45=0,"",VLOOKUP($A45,'00_Eq'!$A$4:$D$100,2,FALSE)) | C45: =IF($A45=0,"",VLOOKUP($A45,'00_Eq'!$A$4:$D$100,3,FALSE)) | G45: =ROUNDUP(((D45*E45)*(1+F45)),0) -> 0 | H45: =IF($A45=0,"",VLOOKUP($A45,'00_Eq'!$A$4:$D$100,4,FALSE))
B46: =IF($A46=0,"",VLOOKUP($A46,'00_Eq'!$A$4:$D$100,2,FALSE)) | C46: =IF($A46=0,"",VLOOKUP($A46,'00_Eq'!$A$4:$D$100,3,FALSE)) | G46: =ROUNDUP(((D46*E46)*(1+F46)),0) -> 0 | H46: =IF($A46=0,"",VLOOKUP($A46,'00_Eq'!$A$4:$D$100,4,FALSE))
A48: TOTAL | I48: =SUM(I41:I46) -> 0
A49: =$I$3 -> unid. | I49: =$H$3 -> 7
A50: TOTAL x | B50: =A49 -> unid. | I50: =I48/I49 -> 0
A53: MANO DE OBRA - MATERIALES
A54: Código | B54: Descripción | C54: Unidad | D54: Cantidad | F54: Desperdicio | G54: Cantidad + Desperdicio | H54: Precio Unitario | I54: Subtotal
A55: dis | B55: =IF($A55=0,"",VLOOKUP($A55,'00_Mat'!$A$4:$J$1135,2,FALSE)) -> Disco corte | C55: =IF($A55=0,"",VLOOKUP($A55,'00_Mat'!$A$4:$J$1135,3,FALSE)) -> u | D55: 1 | F55: 0.15 | G55: =ROUNDUP((D55+(D55*F55)),0) -> 2 | H55: =IF($A55=0,"",VLOOKUP($A55,'00_Mat'!$A$4:$J$1135,5,FALSE)) -> 40000 | I55: =H55*G55 -> 80000
A56: F-P | B56: =IF($A56=0,"",VLOOKUP($A56,'00_Mat'!$A$4:$J$1135,2,FALSE)) -> Puntal 3 x 3 x 3,66 m | C56: =IF($A56=0,"",VLOOKUP($A56,'00_Mat'!$A$4:$J$1135,3,FALSE)) -> u | D56: 10 | F56: 0.15 | G56: =ROUNDUP((D56+(D56*F56)),0) -> 12 | H56: =IF($A56=0,"",VLOOKUP($A56,'00_Mat'!$A$4:$J$1135,5,FALSE)) -> 6500 | I56: =H56*G56 -> 78000
A57: F-T | B57: =IF($A57=0,"",VLOOKUP($A57,'00_Mat'!$A$4:$J$1135,2,FALSE)) -> Tabla 1 x 4 x 3,66 m | C57: =IF($A57=0,"",VLOOKUP($A57,'00_Mat'!$A$4:$J$1135,3,FALSE)) -> u | D57: 10 | F57: 0.15 | G57: =ROUNDUP((D57+(D57*F57)),0) -> 12 | H57: =IF($A57=0,"",VLOOKUP($A57,'00_Mat'!$A$4:$J$1135,5,FALSE)) -> 3000 | I57: =H57*G57 -> 36000
A58: CL2.5 | B58: =IF($A58=0,"",VLOOKUP($A58,'00_Mat'!$A$4:$J$1135,2,FALSE)) -> Clavos 2,5" punta paris (k) | C58: =IF($A58=0,"",VLOOKUP($A58,'00_Mat'!$A$4:$J$1135,3,FALSE)) -> k | D58: 2.5 | F58: 0.15 | G58: =ROUNDUP((D58+(D58*F58)),0) -> 3 | H58: =IF($A58=0,"",VLOOKUP($A58,'00_Mat'!$A$4:$J$1135,5,FALSE)) -> 3739.67 | I58: =H58*G58 -> 11219.01
A59: AL | B59: =IF($A59=0,"",VLOOKUP($A59,'00_Mat'!$A$4:$J$1135,2,FALSE)) -> Alambre Fardo (k) | C59: =IF($A59=0,"",VLOOKUP($A59,'00_Mat'!$A$4:$J$1135,3,FALSE)) -> k | D59: 2.5 | F59: 0.15 | G59: =ROUNDUP((D59+(D59*F59)),0) -> 3 | H59: =IF($A59=0,"",VLOOKUP($A59,'00_Mat'!$A$4:$J$1135,5,FALSE)) -> 4326.45 | I59: =H59*G59 -> 12979.35
A60: CL2 | B60: =IF($A60=0,"",VLOOKUP($A60,'00_Mat'!$A$4:$J$1135,2,FALSE)) -> Clavos 2" punta paris (k) | C60: =IF($A60=0,"",VLOOKUP($A60,'00_Mat'!$A$4:$J$1135,3,FALSE)) -> k | D60: 2.5 | F60: 0.15 | G60: =ROUNDUP((D60+(D60*F60)),0) -> 3 | H60: =IF($A60=0,"",VLOOKUP($A60,'00_Mat'!$A$4:$J$1135,5,FALSE)) -> 3739.67 | I60: =H60*G60 -> 11219.01
A61: F-PI | B61: =IF($A61=0,"",VLOOKUP($A61,'00_Mat'!$A$4:$J$1135,2,FALSE)) -> Fenolico scarp 18mm Pino cic | C61: =IF($A61=0,"",VLOOKUP($A61,'00_Mat'!$A$4:$J$1135,3,FALSE)) -> u | D61: 4 | F61: 0.15 | G61: =ROUNDUP((D61+(D61*F61)),0) -> 5 | H61: =IF($A61=0,"",VLOOKUP($A61,'00_Mat'!$A$4:$J$1135,5,FALSE)) -> 26320 | I61: =H61*G61 -> 131600
B62: =IF($A62=0,"",VLOOKUP($A62,'00_Mat'!$A$4:$J$1135,2,FALSE)) | C62: =IF($A62=0,"",VLOOKUP($A62,'00_Mat'!$A$4:$J$1135,3,FALSE)) | G62: =ROUNDUP((D62+(D62*F62)),0) -> 0 | H62: =IF($A62=0,"",VLOOKUP($A62,'00_Mat'!$A$4:$J$1135,5,FALSE)) | I62: =H62*G62 -> 0
A64: TOTAL | I64: =SUM(I55:I62) -> 361017.37
A65: =$I$3 -> unid. | I65: =$H$3 -> 7
A66: TOTAL x | B66: =A65 -> unid. | I66: =I64/I65 -> 51573.91
A69: MANO DE OBRA - SUBCONTRATOS
A70: Código | B70: Descripción | C70: Unidad | D70: Cantidad | E70: Dias | F70: Desperdicio | G70: Cantidad + Desperdicio | H70: Precio Unitario | I70: Subtotal
B71: =IF($A71=0,"",VLOOKUP($A71,'00_Sub'!$A$4:$D$1001,2,FALSE)) | C71: =IF($A71=0,"",VLOOKUP($A71,'00_Sub'!$A$4:$D$1001,3,FALSE)) | G71: =ROUNDUP((D71+(D71*F71)),0) -> 0 | H71: =IF($A71=0,"",VLOOKUP($A71,'00_Sub'!$A$4:$D$1001,4,FALSE))
B72: =IF($A72=0,"",VLOOKUP($A72,'00_Sub'!$A$4:$D$1001,2,FALSE)) | C72: =IF($A72=0,"",VLOOKUP($A72,'00_Sub'!$A$4:$D$1001,3,FALSE)) | G72: =ROUNDUP((D72+(D72*F72)),0) -> 0 | H72: =IF($A72=0,"",VLOOKUP($A72,'00_Sub'!$A$4:$D$1001,4,FALSE))
B73: =IF($A73=0,"",VLOOKUP($A73,'00_Sub'!$A$4:$D$1001,2,FALSE)) | C73: =IF($A73=0,"",VLOOKUP($A73,'00_Sub'!$A$4:$D$1001,3,FALSE)) | G73: =ROUNDUP((D73+(D73*F73)),0) -> 0 | H73: =IF($A73=0,"",VLOOKUP($A73,'00_Sub'!$A$4:$D$1001,4,FALSE))
B74: =IF($A74=0,"",VLOOKUP($A74,'00_Sub'!$A$4:$D$1001,2,FALSE)) | C74: =IF($A74=0,"",VLOOKUP($A74,'00_Sub'!$A$4:$D$1001,3,FALSE)) | G74: =ROUNDUP((D74+(D74*F74)),0) -> 0 | H74: =IF($A74=0,"",VLOOKUP($A74,'00_Sub'!$A$4:$D$1001,4,FALSE))
B75: =IF($A75=0,"",VLOOKUP($A75,'00_Sub'!$A$4:$D$1001,2,FALSE)) | C75: =IF($A75=0,"",VLOOKUP($A75,'00_Sub'!$A$4:$D$1001,3,FALSE)) | G75: =ROUNDUP((D75+(D75*F75)),0) -> 0 | H75: =IF($A75=0,"",VLOOKUP($A75,'00_Sub'!$A$4:$D$1001,4,FALSE))
B76: =IF($A76=0,"",VLOOKUP($A76,'00_Sub'!$A$4:$D$1001,2,FALSE)) | C76: =IF($A76=0,"",VLOOKUP($A76,'00_Sub'!$A$4:$D$1001,3,FALSE)) | G76: =ROUNDUP((D76+(D76*F76)),0) -> 0 | H76: =IF($A76=0,"",VLOOKUP($A76,'00_Sub'!$A$4:$D$1001,4,FALSE))
A78: TOTAL | I78: =SUM(I71:I76) -> 0
A79: =$I$3 -> unid. | I79: =$H$3 -> 7
A80: TOTAL x | B80: =A79 -> unid. | I80: =I78/I79 -> 0

Sheet 3.1-5
A1: ='01_C&P'!A1 -> CASA LUGONES
A3: ='01_C&P'!A44 -> 3.1-5 | B3: =IF($A3=0,"",VLOOKUP($A3,'01_C&P'!$A$9:$D$172,2,FALSE)) -> COLUMNAS H30 EN MEDIANERA EN PLANTA BAJA 60x15 | H3: =IF($A3=0,"",VLOOKUP($A3,'01_C&P'!$A$9:$D$172,4,FALSE)) -> 7 | I3: =IF($A3=0,"",VLOOKUP($A3,'01_C&P'!$A$9:$D$172,3,FALSE)) -> unid.
A5: MATERIALES
A6: Código | B6: Descripción | C6: Unidad | D6: Cantidad | F6: Desperdicio | G6: Cantidad + Desperdicio | H6: Precio Unitario | I6: Subtotal
A7: H30 | B7: =IF($A7=0,"",VLOOKUP($A7,'00_Mat'!$A$4:$J$1135,2,FALSE)) -> Hormigon H30 | C7: =IF($A7=0,"",VLOOKUP($A7,'00_Mat'!$A$4:$J$1135,3,FALSE)) -> m3 | D7: =(0.6*0.15*3.5)*H3 -> 2.205 | F7: 0.15 | G7: =ROUNDUP((D7+(D7*F7)),0) -> 3 | H7: =IF($A7=0,"",VLOOKUP($A7,'00_Mat'!$A$4:$J$1135,5,FALSE)) -> 125280 | I7: =H7*G7 -> 375840
A8: HADN6 | B8: =IF($A8=0,"",VLOOKUP($A8,'00_Mat'!$A$4:$J$1135,2,FALSE)) -> Hierros ADN 420 Φ 6 | C8: =IF($A8=0,"",VLOOKUP($A8,'00_Mat'!$A$4:$J$1135,3,FALSE)) -> u | D8: =(((3.6/0.14)*1.8)/12)*H3 -> 27 | F8: 0.15 | G8: =ROUNDUP((D8+(D8*F8)),0) -> 32 | H8: =IF($A8=0,"",VLOOKUP($A8,'00_Mat'!$A$4:$J$1135,5,FALSE)) -> 5250 | I8: =H8*G8 -> 168000
A9: HADN12 | B9: =IF($A9=0,"",VLOOKUP($A9,'00_Mat'!$A$4:$J$1135,2,FALSE)) -> Hierros ADN 420 Φ 12 | C9: =IF($A9=0,"",VLOOKUP($A9,'00_Mat'!$A$4:$J$1135,3,FALSE)) -> u | D9: =((3.6*8)/12)*H3 -> 16.8 | F9: 0.15 | G9: =ROUNDUP((D9+(D9*F9)),0) -> 20 | H9: =IF($A9=0,"",VLOOKUP($A9,'00_Mat'!$A$4:$J$1135,5,FALSE)) -> 20442.5 | I9: =H9*G9 -> 408850
A10: HADN10 | B10: =IF($A10=0,"",VLOOKUP($A10,'00_Mat'!$A$4:$J$1135,2,FALSE)) -> Hierros ADN 420Φ 10 | C10: =IF($A10=0,"",VLOOKUP($A10,'00_Mat'!$A$4:$J$1135,3,FALSE)) -> u | D10: =((3.6*2)/12)*H3 -> 4.2 | F10: 0.15 | G10: =ROUNDUP((D10+(D10*F10)),0) -> 5 | H10: =IF($A10=0,"",VLOOKUP($A10,'00_Mat'!$A$4:$J$1135,5,FALSE)) -> 10000 | I10: =H10*G10 -> 50000
A11: GRO | B11: =IF($A11=0,"",VLOOKUP($A11,'00_Mat'!$A$4:$J$1135,2,FALSE)) -> Sika Grout 22kg | C11: =IF($A11=0,"",VLOOKUP($A11,'00_Mat'!$A$4:$J$1135,3,FALSE)) -> U | D11: 5 | F11: 0 | G11: =ROUNDUP((D11+(D11*F11)),0) -> 5 | H11: =IF($A11=0,"",VLOOKUP($A11,'00_Mat'!$A$4:$J$1135,5,FALSE)) -> 43000 | I11: =H11*G11 -> 215000
B12: =IF($A12=0,"",VLOOKUP($A12,'00_Mat'!$A$4:$J$1135,2,FALSE)) | C12: =IF($A12=0,"",VLOOKUP($A12,'00_Mat'!$A$4:$J$1135,3,FALSE)) | G12: =ROUNDUP((D12+(D12*F12)),0) -> 0 | H12: =IF($A12=0,"",VLOOKUP($A12,'00_Mat'!$A$4:$J$1135,5,FALSE)) | I12: =H12*G12 -> 0 | M12: SACANDO EL SIKA:
B13: =IF($A13=0,"",VLOOKUP($A13,'00_Mat'!$A$4:$J$1135,2,FALSE)) | C13: =IF($A13=0,"",VLOOKUP($A13,'00_Mat'!$A$4:$J$1135,3,FALSE)) | G13: =ROUNDUP((D13+(D13*F13)),0) -> 0 | H13: =IF($A13=0,"",VLOOKUP($A13,'00_Mat'!$A$4:$J$1135,5,FALSE)) | I13: =H13*G13 -> 0 | M13: MAT + CONSUMIBLES YPF 175,000
B14: =IF($A14=0,"",VLOOKUP($A14,'00_Mat'!$A$4:$J$1135,2,FALSE)) | C14: =IF($A14=0,"",VLOOKUP($A14,'00_Mat'!$A$4:$J$1135,3,FALSE)) | G14: =ROUNDUP((D14+(D14*F14)),0) -> 0 | H14: =IF($A14=0,"",VLOOKUP($A14,'00_Mat'!$A$4:$J$1135,5,FALSE)) | I14: =H14*G14 -> 0 | M14: MAT + CONSUMIBLES CASA LUGONES 160,000
B15: =IF($A15=0,"",VLOOKUP($A15,'00_Mat'!$A$4:$J$1135,2,FALSE)) | C15: =IF($A15=0,"",VLOOKUP($A15,'00_Mat'!$A$4:$J$1135,3,FALSE)) | G15: =ROUNDUP((D15+(D15*F15)),0) -> 0 | H15: =IF($A15=0,"",VLOOKUP($A15,'00_Mat'!$A$4:$J$1135,5,FALSE)) | I15: =H15*G15 -> 0
B16: =IF($A16=0,"",VLOOKUP($A16,'00_Mat'!$A$4:$J$1135,2,FALSE)) | C16: =IF($A16=0,"",VLOOKUP($A16,'00_Mat'!$A$4:$J$1135,3,FALSE)) | G16: =ROUNDUP((D16+(D16*F16)),0) -> 0 | H16: =IF($A16=0,"",VLOOKUP($A16,'00_Mat'!$A$4:$J$1135,5,FALSE)) | I16: =H16*G16 -> 0
B17: =IF($A17=0,"",VLOOKUP($A17,'00_Mat'!$A$4:$J$1135,2,FALSE)) | C17: =IF($A17=0,"",VLOOKUP($A17,'00_Mat'!$A$4:$J$1135,3,FALSE)) | G17: =ROUNDUP((D17+(D17*F17)),0) -> 0 | H17: =IF($A17=0,"",VLOOKUP($A17,'00_Mat'!$A$4:$J$1135,5,FALSE)) | I17: =H17*G17 -> 0
B18: =IF($A18=0,"",VLOOKUP($A18,'00_Mat'!$A$4:$J$1135,2,FALSE)) | C18: =IF($A18=0,"",VLOOKUP($A18,'00_Mat'!$A$4:$J$1135,3,FALSE)) | G18: =ROUNDUP((D18+(D18*F18)),0) -> 0 | H18: =IF($A18=0,"",VLOOKUP($A18,'00_Mat'!$A$4:$J$1135,5,FALSE)) | I18: =H18*G18 -> 0
A20: TOTAL MATERIALES | I20: =SUM(I7:I18) -> 1217690
