Workbook

Sheet 00_Mat
A1: MATERIALES
A3: CODIGO | B3: MATERIALES CORRALON | C3: UNIDAD | D3: PRECIO CON IVA | E3: PRECIO SIN IVA | F3: DESCUENTO | G3: PRECIO CON DESCUENTO
A4: ARG | B4: Arena a granel (1m3) | C4: m3 | D4: 29403 | E4: =D4/1.21 -> 24300
A5: AR | B5: Bolson de Arena (1m3) | C5: m3 | E5: 33470
A6: PIEG | B6: Piedra a granel (1m3) | C6: m3 | D6: 58995 | E6: =D6/1.21 -> 48756.198
A7: PIEP | B7: Bolson de Piedra partida (1m3) | C7: m3 | E7: 74566
A8: PIE | B8: Bolson de Piedra (1m3) | C8: m3 | D8: 60000 | E8: 61700
A9: CEM | B9: Bolsa Cemento "Loma Negra" 25 k (u) | C9: u | E9: 7000 | I9: ML | J9: 46081
A10: CEM-GROUT | B10: Sika Grout 25k (u) | C10: u | E10: 31900
A11: CAL | B11: Bolsa Cal "Cacique" 25 k (u) | C11: u | D11: 6500 | E11: =D11/1.21 -> 5371.9008
A12: PLASTICOR | B12: Bolsa Plasticor 40k (u) | C12: u | D12: 8500 | E12: =D12/1.21 -> 7024.7934
A13: CER | B13: Ceresita 20 k (u) | C13: u | D13: 45000 | E13: =D13/1.21 -> 37190.083
A14: LP18 | B14: Ladrillo Portante 18 (u) | C14: u | E14: 1377
A15: LP12 | B15: Ladrillo Portante 12 (u) | C15: u | E15: 1110.2
A16: LH18 | B16: Ladrillo Hueco 18 (u) | C16: u | E16: 837
A17: LH12 | B17: Ladrillo Hueco 12 (u) | C17: u | E17: 726
A18: LH8 | B18: Ladrillo Hueco 8 (u) | C18: u | E18: 568.7 | I18: Su Corralon | J18: 45824
A19: LCOM | B19: Ladrillo Comun | C19: u | E19: 190.61 | I19: Su Corralon | J19: 45824
A20: LCOMVIST | B20: Ladrillo Comun Vista | C20: u | D20: 240 | E20: =D20/1.21 -> 198.34711 | I20: Su Corralon | J20: 45771
A21: LPINT | B21: Pavimento Intertrabado | C21: m2 | E21: 37600 | I21: Su Corralon | J21: 45824
A22: LGB | B22: Garden Block 38x38x8cm (1m2) | C22: m2 | E22: 22500 | I22: ml | J22: 45877
A23: LDC | B23: Deck Liston Hormigon Cemento Piso Durmiente 100 X 12 Cms (1m2) | E23: 41000 | I23: ml | J23: 45877
A24: YES | B24: Bolsa Yeso Tuyango 30 k (u) | C24: u | D24: 13879 | E24: 15000 | I24: ML | J24: 46081
A25: YES-P | B25: Bolsa Yeso Proyectado Tuyango 30 k (u) | C25: u | E25: 18000 | I25: ml | J25: 45902
A26: ES | B26: Cascote / Escombro (m3) | C26: m3 | E26: 35000 | I26: ML | J26: 45929
A27: TOS | B27: Tosca Compactada | C27: m3 | E27: 30000 | I27: Pablo | J27: 45778
A28: TN | B28: BOLSON Tierra negra | C28: m3 | E28: 33275 | I28: Su Corralon | J28: 45824
A29: TNF | B29: BOLSON Tierra negra fertil 10% compost | C29: m3 | E29: 86600 | I29: Su Corralon | J29: 45890
A30: TRA | B30: BOLSON Tierra negra abonada 40% compost | C30: m3 | E30: 94400 | I30: Su Corralon | J30: 45890
A31: TNFI | B31: TIERRA NEGRA FINA | C31: m3 | E31: 60000 | I31: Pablo | J31: 45896
A32: TNRL | B32: TIERRA NEGRA DE RELLENO LIMPIO | C32: m3 | E32: 25000 | I32: Pablo | J32: 45896
A33: TNR | B33: TIERRA NEGRA DE RELLENO | C33: m3 | E33: 20000 | I33: Pablo | J33: 45896
A34: CL2 | B34: Clavos 2" punta paris (k) | C34: k | E34: 4500 | I34: urquiza | J34: 46023
A35: CL2.5 | B35: Clavos 2,5" punta paris (k) | C35: k | E35: 4500 | I35: urquiza | J35: 46023
A36: AL-50k | B36: Alambre Fardo (50 k) | C36: k | E36: 220000 | I36: urquiza | J36: 46023
A37: ES24 | B37: Cascote / Escombro cada 24 m3 (m3) | C37: m3 | D37: 16500 | E37: =D37/1.21 -> 13636.364 | I37: Su Corralon | J37: 45412
A38: DISCO PORC | B38: Disco Amoladora para porcelanato. marca aliafor | E38: 22314 | I38: Su Corralon | J38: 45919
A39: DISCO | B39: Disco Ascerradora | C39: u | E39: 120000
A40: DIS | B40: Disco corte | C40: u | E40: 40000
A41: VI7 | B41: Vigueta pretensada de hormigon 7m | C41: u | E41: 34000
A42: VI6 | B42: Vigueta pretensada de hormigon 6m | C42: u | E42: 30111
A43: VI4 | B43: Vigueta pretensada de hormigon 4m | C43: u | E43: $ 26.000,00
A44: VI-EPS | B44: Ladrillos Telgopor 10cm | C44: u | E44: 3844
A45: P-pro | B45: Protex 215 x 1kg | C45: u | D45: =E45*1.21 -> 21780 | E45: 18000
A46: z-sell | B46: Adhesivo Zocalos Sellador Rellenador Atrim 420gr | C46: u | E46: 13000
A47: ME | B47: MECHA ROTOPERCUTORA | C47: u | E47: 5000
A48: EPS | B48: EPS aislante para techos 1x1 30mm 15 Kg Pack 5u | C48: u | E48: 60000
A49: GRO | B49: Sika Grout 22kg | C49: u | E49: $ 43.000,00
A52: CODIGO | B52: MATERIALES ACERO | D52: PRECIO CON IVA | E52: PRECIO SIN IVA
A53: M3,5 | B53: Malla Φ 3,5 (2 m x 5 m) (hierros cada 0,18 x 0,18 m) - menos de 50 u (u) | C53: u | D53: 23200 | E53: =D53/1.21 -> 19173.554
A54: M5 | B54: Malla Φ 5 (2 m x 5 m) (hierros cada 0,18 x 0,18 m) - menos de 50 u (u) | C54: u | D54: 36200 | E54: =D54/1.21 -> 29917.355
B55: Malla Φ 5,5 (2 m x 5 m) (hierros cada 0,18 x 0,18 m) - menos de 50 u (u) | C55: u | D55: 41900 | E55: =D55/1.21 -> 34628.099
A56: M3,5M | B56: Malla Φ 3,5 (2 m x 5 m) (hierros cada 0,18 x 0,18 m) - mas de 50 u (u) | C56: u | D56: 22600 | E56: =D56/1.21 -> 18677.686
A57: M5M | B57: Malla Φ 5 (2 m x 5 m) (hierros cada 0,18 x 0,18 m) - mas de 50 u (u) | C57: u | D57: 35800 | E57: =D57/1.21 -> 29586.777
A58: M5,5 | B58: Malla Φ 5,5 (2 m x 5 m) (hierros cada 0,18 x 0,18 m) | C58: u | D58: 36600 | E58: 37608
A59: M6 | B59: Malla Φ 6 (2 m x 5 m) (hierros cada 0,15 x 0,15 m) | C59: u
A60: M8 | B60: Malla Φ 8 (2 m x 5 m) (hierros cada 0,15 x 0,15 m) | C60: u | E60: 50000
A61: M8-Q335 | B61: Malla Φ 8 Q335 (2,4 m x 6 m) (hierros cada 0,15 x 0,15 m) | C61: u
A62: M-ELEC | B62: Malla electrosada (1x1) 250 | C62: m2 | E62: $ 30.000,00
A63: HADN6 | B63: Hierros ADN 420 Φ 6 | C63: u | E63: 5250
A64: HADN8 | B64: Hierros ADN 420 Φ 8 | C64: u | E64: 9050
A65: HADN10 | B65: Hierros ADN 420Φ 10 | C65: u | E65: 11237
A66: HADN12 | B66: Hierros ADN 420 Φ 12 | C66: u | E66: 20442.5
A67: HADN16 | B67: Hierros ADN 420 Φ 16 | C67: u | E67: 36603.12
A68: HADN20 | B68: Hierros ADN 420 Φ 20 | C68: U | E68: 55000
A69: - | B69: Hierros ADN 420 Φ 20 | C69: u | D69: 48744.82 | E69: =D69/1.21 -> 40284.975
A70: HADN25 | B70: Hierros ADN 420 Φ 25 | C70: u | D70: 83198.48 | E70: =D70/1.21 -> 68759.074
A71: HADN6K | B71: Hierros ADN 420 Φ 6 (k) | C71: k | E71: 1347.48
A72: HADN8K | B72: Hierros ADN 420 Φ 8 (k) | C72: k | E72: 1310.31
A73: HADN10K | B73: Hierros ADN 420Φ 10 (k) | C73: k | E73: 1310.31
A74: HADN12K | B74: Hierros ADN 420 Φ 12 (k) | C74: k | E74: 1301.01
A75: HADN16K | B75: Hierros ADN 420 Φ 16 (k) | C75: k | E75: 1263.84
A76: HADN20K | B76: Hierros ADN 420 Φ 20 (k) | C76: k | E76: 1263.84
A77: HADN25K | B77: Hierros ADN 420 Φ 25 (k) | C77: k | E77: 1263.84
A78: HADN6K | B78: Hierros ADN 420 Φ 6 (k) | C78: k | E78: 1455
A79: HADN8K | B79: Hierros ADN 420 Φ 8 (k) | C79: k | E79: 1374
A80: HADN10K | B80: Hierros ADN 420Φ 10 (k) | C80: k | E80: 1374
A81: HADN12K | B81: Hierros ADN 420 Φ 12 (k) | C81: k | E81: 1374
A82: HADN16K | B82: Hierros ADN 420 Φ 16 (k) | C82: k | E82: 1322
... A85: HL16 | B85: Hierros Liso Φ 16 - l=6 m | C85: m | E85: 20410
A86: C.E. 40X60 | B86: Cano estructural 40x60x1.6 (6mts) | C86: m | E86: $ 60.000,00
C87: u
A89: CODIGO | B89: MATERIALES PLOMERIA | D89: PRECIO CON IVA | E89: PRECIO SIN IVA
A90: LAVAT | B90: Lavatorio DECA (SOBRE MESADA) | C90: u | E90: 190000 | G90: 45937 | H90: https://www.mercadolibre.com.ar/bacha-deca-l1304017-rectangular-de-40-x-30-cm-color-blanco/p/MLA20245981?pdp_filters=item_id:MLA1883663480#is_advertising=true&searchVariation=MLA20245981&backend_model=search-backend&position=3&search_layout=grid&type=pad&tracking_id=802222b0-99c8-4b26-94f0-68151ba2ecc9&ad_domain=VQCATCORE_LST&ad_position=3&ad_click_id=ZWY3NTI1ZjUtZTQwMS00MTBiLWI0OWYtNmFkYzdmYTNjOTFi
A91: BACH | B91: Bacha cocina | C91: u | E91: 100000 | G91: 45937 | H91: https://www.mercadolibre.com.ar/bacha-de-cocina-doble-johnson-acero-cc-2818/p/MLA22290000?has_official_store=false&highlight=false&headerTopBrand=false#polycard_client=search-nordic&search_layout=grid&position=13&type=product&tracking_id=36b18fd0-fd18-4ef7-8e53-da437711f856&wid=MLA2194314818&sid=search
A92: INOD | B92: Inodoro FERRUM | C92: u | E92: 600000
A93: BID | B93: Bidet Ferrum Veneto BTA3J-B Blanco 3 Ag | C93: u | E93: 300000 | G93: 45937 | H93: https://www.mercadolibre.com.ar/ferrum-veneto-bidet-bta3j-b-blanco-3-ag/p/MLA28829954?has_official_store=false&highlight=true&headerTopBrand=false#polycard_client=search-nordic&search_layout=grid&position=2&type=product&tracking_id=fdc3d4b8-b24b-44f2-9682-547aac02c148&wid=MLA1932861148&sid=search
A94: INOD-BID | B94: Indoro y Bidet completos FERRUM | C94: u | E94: 1000000 | G94: 45937 | H94: https://articulo.mercadolibre.com.ar/MLA-660250308-inodoro-largo-tapa-amort-dep-y-bide-ferrum-veneto-_JM?has_official_store=false&highlight=false&searchVariation=25060632050&headerTopBrand=true#polycard_client=search-nordic&searchVariation=25060632050&search_layout=grid&position=38&type=item&tracking_id=b8012c01-662c-4429-bff6-2065056dc6d5
A95: GRIF-TOT | B95: Set de Griferias bano completo | C95: u | E95: 230000 | G95: 45937 | H95: https://www.mercadolibre.com.ar/griferia-set-lavatorio-bidet-ducha-bano-peirano-adra-90-166-pack-combo-color-cromo-acabado-cromado-juego-duchon-vanitory/p/MLA34176290?has_official_store=false&highlight=true&headerTopBrand=true#polycard_client=search-nordic&search_layout=grid&position=5&type=product&tracking_id=c3b8f1c0-4b46-4813-952d-325c5131e3bd&wid=MLA1484865149&sid=search
A96: PDP | B96: Pileta de patio AWADUCT | C96: u | E96: 12000
A97: GRIF-TOI | B97: Grfieria Lavatorio FV | C97: u | E97: 150000
A98: GRIF-COC | B98: Griferia mocomando cocina movible FV | C98: u | E98: 130000 | G98: 45937 | H98: https://www.mercadolibre.com.ar/canilla-cocina-monocomando-griferia-extensible-krumm-cromo-acabado-satinado-color-niquel/p/MLA26043589?pdp_filters=item_id:MLA1479119202#is_advertising=true&searchVariation=MLA26043589&backend_model=search-backend&position=2&search_layout=grid&type=pad&tracking_id=70e1d787-528b-4799-97f7-034afec552a7&ad_domain=VQCATCORE_LST&ad_position=2&ad_click_id=OGE0MThiODItODJiNi00NTU5LTkwNWQtNjdmZmU0ZjdiMWU2
A99: GRIF-CS | B99: Griferia CANILLA DE SERVICIO | C99: u | E99: 10000
A100: GRIF-DUCHA | B100: Grfieria Ducha FV | C100: u | E100: 360000
A101: GRIF-BID | B101: Grfieria Bide FV | C101: u | E101: 211000
A102: PDP-REJ | B102: Rejilla ATRIM Pileta Patio Reversible 12x12 Cuadrada Acero I | C102: u | E102: 26000
A103: INOD-DEP | B103: Deposito Capea Italiana Apoyo | C103: u | E103: 98608.68
A104: INOD | B104: Inodoro Capea Italiana Largo | C104: u | E104: 143129.81
A105: PL-E | B105: Embudo Pluvial 110 "Awaduct" | C105: u | E105: 20000
A106: PL-TRI | B106: Tritubo 40 mm (3 mm espesor) | C106: m | E106: 4487.71
...

Sheet 00_MO
A1: MANO DE OBRA
A3: CODIGO | B3: MATERIALES CORRALON | C3: UNIDAD | D3: PRECIO SIN IVA | E3: FECHA
A4: MO-CA | B4: Capataz | C4: u | D4: =80000*1.5 -> 120000 | E4: 46063
A5: MO-PU | B5: Puntero | C5: u | D5: =70000*1.5 -> 105000 | E5: 46063
A6: MO-OF | B6: Oficial | C6: u | D6: =60000*1.5 -> 90000 | E6: 46063
A7: MO-AY | B7: Ayudante | C7: u | D7: =40000*1.5 -> 60000 | E7: 46063

Sheet 00_Eq
A1: EQUIPOS
A3: CODIGO | B3: MATERIALES CORRALON | C3: UNIDAD | D3: PRECIO SIN IVA | E3: REFERENCIA | F3: FECHA
A4: E-MC | B4: Mini Cargadora | C4: u | D4: 420000 | E4: JP VIAL | F4: 45945 | G4: CON MAQUINISTA Y GASOIL
A5: E-MCM | B5: Mini Cargadora con martillo | C5: u | D5: 550000 | E5: Pablo | F5: 45804
A6: E-ME | B6: Mini Excavadora | C6: u | D6: 550000 | E6: Pablo | F6: 45804
A7: E-MP | B7: Motopison | C7: u | D7: 40000
A8: E-RP | B8: Retropala | C8: u | D8: 680000 | E8: JP VIAL | F8: 45945 | G8: CON MAQUINISTA Y GASOIL
A9: E-VC | B9: Vibrocompactador | C9: u | D9: 680000 | E9: JP VIAL | F9: 45945 | G9: CON MAQUINISTA Y GASOIL
A10: E-MN | B10: Motoniveladora | C10: u | D10: 900000 | E10: JP VIAL | F10: 45945 | G10: CON MAQUINISTA Y GASOIL
A11: E-CAMCH | B11: Camion Chasis | C11: u | D11: 350000 | E11: JP VIAL | F11: 45945 | G11: CON MAQUINISTA Y GASOIL
A12: E-REG | B12: Regador | C12: u | D12: 350000 | E12: JP VIAL | F12: 45945 | G12: CON MAQUINISTA Y GASOIL
A13: E-MAR | B13: Martillete | C13: u | D13: 45000 | E13: allquifer | F13: 45916
A14: E-ASC | B14: Ascerradora | C14: u | D14: 60000 | F14: 45890
A15: E-RET | B15: Retiro x camion | C15: u | D15: 160000 | E15: Nico | F15: 45890
A16: E-MR | B16: Mini Retro | C16: u | D16: 480000 | E16: Pablo | F16: 45804
A17: MS-TM3 | B17: TOSCA x M3 | C17: m3 | D17: 30000 | E17: Pablo | F17: 45804
A18: MS-TCA | B18: TOSCA X EQUIPO | C18: m3 | D18: 10500 | E18: JP VIAL | F18: 45945
A19: MS-ER | B19: EXCAVACION Y RETIRO | C19: m3 | D19: 30000 | G19: precio a chekear
A20: MS-TC | B20: TOSCA COMPACTADA | C20: m3 | D20: 25000 | E20: Pablo | F20: 45804
A21: MS-ARBOL | B21: RETIRO DE ARBOL | C21: u | D21: 570000 | E21: Pablo | F21: 45804
A22: E-CAM | B22: Camioneta | C22: u | D22: 200000
A23: E-TRAS | B23: TRASLADO DE MAQUINARIA | C23: u | D23: 300000 | E23: Pablo | F23: 45804
A24: E-VOL | B24: Volquete | C24: u | D24: 200000
A25: E-EXC | B25: Excavadora 22TN | C25: u | D25: 900000 | E25: JP VIAL | F25: 45945 | G25: CON MAQUINISTA Y GASOIL
A26: E-TOP | B26: Topadora | C26: u | D26: 1350000 | E26: JP VIAL | F26: 45945 | G26: CON MAQUINISTA Y GASOIL
A27: E-PALA | B27: Pala frontal | C27: u | D27: 800000 | E27: JP VIAL | F27: 45945 | G27: CON MAQUINISTA Y GASOIL

Sheet 00_Sub
A1: SUBCONTRATOS
A3: CODIGO | B3: PINTURA | C3: UNIDAD | D3: PRECIO SIN IVA | E3: REFERENCIA | F3: FECHA
A4: SUB-PI | B4: Pintura Interior: 1Mano Enduido + Yeso, 1 Mano Enduido, 2 a 3 Manos de Pintura | C4: m2 | D4: 15000 | E4: CHIZO | F4: 45904
A5: SUB-PIC | B5: Pintura Interior Cielorraso con una mano de enduido | C5: m2 | D5: 10000 | E5: CHIZO | F5: 45904
A6: SUB-PET | B6: Pintura Exterior Tarquini | C6: m2 | D6: 12000 | E6: CHIZO | F6: 45904
A7: SUB-PE | B7: Pintura Exterior | C7: m2 | D7: 10000
A8: SUB-PIY | B8: Pintura interior sobre yeso con una mano de enduido, lijado, fijado y pintado | C8: m2 | D8: 10000 | E8: CHIZO | F8: 45904
A9: SUB-PI | B9: Pintura Interior | C9: m2 | D9: 8000
A10: SUB-END | B10: Enduido | C10: m2 | D10: 8000
A11: SUB-PPS | B11: Pintura Puerta Simple Hoja | C11: u | D11: 25000
A12: SUB-PPD | B12: Pintura Puerta Doble Hoja | C12: u | D12: 50000
A13: CODIGO | B13: DURLOCK | C13: UNIDAD | D13: PRECIO SIN IVA | E13: REFERENCIA | F13: FECHA
A14: SUB-CIE | B14: Instalacion de Cielorraso Durlock. Incluye Materiales. | C14: m2 | D14: 37000 | E14: CLAUDIO | F14: 45791
A15: SUB-CIEDES | B15: Instalacion de Cielorraso Desmontable. Incluye Materiales. | C15: m2 | D15: 37000 | E15: CLAUDIO | F15: 45791
A16: SUB-CIECO | B16: Instalacion de Cielorraso Durlock Cortineros. Incluye Materiales. | C16: m | D16: 45000 | E16: CLAUDIO | F16: 45791
A17: SUB-CIECA | B17: Instalacion de Cajon Durlock. Incluye Materiales. | C17: m | D17: 20000 | E17: CLAUDIO | F17: 45791
A18: SUB-CIEGL | B18: Instalacion de Cielorraso Durlock Garganta Led. Incluye Materiales. | C18: m | D18: 45000 | E18: CLAUDIO | F18: 45791
A19: SUB-TAB | B19: Instalacion de Tabique Durlock. Incluye Materiales. | C19: m2 | D19: 48000 | E19: CLAUDIO | F19: 45791
A20: SUB-BZ | B20: Instlacion Buña Z. Incluye Materiales. | C20: m | D20: 16000 | E20: CLAUDIO | F20: 45791
A21: SUB-CAN | B21: Instalacion Cantonera. Incluye Materiales. | C21: m | D21: 16000 | E21: CLAUDIO | F21: 45791
A22: CODIGO | B22: ELECTRICIDAD | C22: UNIDAD | D22: PRECIO SIN IVA | E22: REFERENCIA | F22: FECHA
A23: SUB-E-BOC | B23: Boca. Mano de obra y Materiales. | C23: boca | D23: 100000 | E23: CABEZA | F23: 45800
A24: SUB-E-COL | B24: Colocacion de artefatcos | C24: u | D24: 7000 | E24: CABEZA | F24: 45800
A25: SUB-E-AAC | B25: Alimentacion aire acondicionado con split. (Mo y mat) | C25: u | D25: 100000 | E25: CABEZA | F25: 45800
A26: SUB-E-TAB | B26: Instalacion de Tablero para 100 bocas (casa chica). Incluye alimentacion desde el pilar. | C26: u | D26: 100000 | E26: CABEZA | F26: 45800
A27: SUB-ELE-B | B27: Boca mano de obra | C27: boca | D27: 60000 | E27: CABEZA | F27: 45800
A28: CODIGO | B28: PISERO | C28: UNIDAD | D28: PRECIO SIN IVA | E28: REFERENCIA | F28: FECHA
A29: SUB-PIS | B29: PISO | C29: m² | D29: 10000 | E29: CESAR | F29: 46079
A30: SUB-COR | B30: CORDON | C30: m | D30: 10000 | E30: CEFERINO | F30: 45800
A31: SUB-CONT | B31: BOMBEO HORMIGON CELULAR. Incluye mano de obra y bomba. | C31: m² | D31: 12000 | E31: ISMAEL | F31: 46079
A32: CODIGO | B32: REVESTIMIENTOS | C32: UNIDAD | D32: PRECIO SIN IVA | E32: REFERENCIA | F32: FECHA
A33: SUB-SIDING | B33: Colocion de siding en pared | C33: m2 | D33: 18000
A34: SUB-REV-CH | B34: Revestimiento de chapa | C34: m2 | D34: 18000 | E34: Hugo | F34: 45902
A35: SUB-YP | B35: Ejecucion de yeso proyectado en Pared | C35: m2 | D35: 10000 | E35: ISMAEL | F35: 45902
A36: SUB-YAC | B36: Ejecucion de yeso proyectado aristas y cantonera | C36: unidad | D36: 10000 | E36: ISMAEL | F36: 45902
A37: CODIGO | B37: MOVIMIENTO DE SUELOS | C37: UNIDAD | D37: PRECIO SIN IVA | E37: REFERENCIA | F37: FECHA
A38: MS-MC | B38: MINICARGADORA | C38: u | D38: 420000 | E38: PABLO | F38: 45743
A39: MS-MCM | B39: MINICARGADORA CON MARTILLO | C39: u | D39: 550000 | E39: PABLO | F39: 45743
A40: MS-MR | B40: MINIRETRO EXCAVADORA | C40: u | D40: 550000 | E40: PABLO | F40: 45743
A41: MS-T | B41: TRASLADO DE MAQUINARIA | C41: u | D41: 300000 | E41: PABLO | F41: 45743
A42: MS-RV | B42: RETIRO X VIAJE | C42: u | D42: 60000 | E42: PABLO | F42: 45743
A43: MS-RVL | B43: RETIRO X m la Lucila - sobre camion | C43: m3 | D43: 30000 | E43: NICO | F43: 45929
A44: MS-TM3 | B44: TOSCA x M3 | C44: m3 | D44: 30000 | E44: PABLO | F44: 45743
A45: MS-TM3L | B45: TOSCA x M3 la Lucila - Compactada | C45: m3 | D45: 55000 | E45: NICO | F45: 45929
A46: MS-TCA | B46: TOSCA X CAMION | C46: m3 | D46: =D44*8 -> 240000 | E46: PABLO | F46: 45743
A47: MS-ER | B47: EXCAVACION Y RETIRO | C47: m3 | D47: 21000 | E47: PABLO | F47: 45743
A48: MS-TC | B48: TOSCA COMPACTADA | C48: m3 | D48: 25000 | E48: PABLO | F48: 45743
A49: MS-ARBOL | B49: RETIRO DE ARBOL | C49: u | D49: 200000 | E49: PABLO | F49: 45743
A50: CODIGO | B50: INSTALACIONES | C50: UNIDAD | D50: PRECIO SIN IVA | E50: REFERENCIA | F50: FECHA
A51: Perfracion | B51: Perforacion para bobas de 7.5 HP de 17m3/h materiales y mo | D51: 2800000 | E51: NICO | F51: 45883
A52: CODIGO | B52: GAS | C52: UNIDAD | D52: PRECIO SIN IVA | E52: REFERENCIA | F52: FECHA
A53: GAS-B | B53: BOCA | C53: u | D53: 390000 | E53: AGUSTIN | F53: 45895
A54: GAS-20M | B54: INSTALACION 20 M CAÑERIA | C54: u | D54: 430000 | E54: AGUSTIN | F54: 45895
A55: GAS-CAL | B55: INSTALACION CALDERA SOLO GAS | C55: u | D55: 90000 | E55: AGUSTIN | F55: 45895
A56: GAS-ANA | B56: INSTALACION ANAFE | C56: u | D56: 70000 | E56: AGUSTIN | F56: 45895
A57: CODIGO | B57: ZINGUERO | C57: UNIDAD | D57: PRECIO SIN IVA | E57: REFERENCIA | F57: FECHA
A58: SUB-ZING | B58: Zinguero | C58: u | D58: 700000
A59: CODIGO | B59: SERVICIOS | C59: UNIDAD | D59: PRECIO SIN IVA | E59: REFERENCIA | F59: FECHA
A60: BQ | B60: BAÑO QUIMICO | C60: u | D60: 65000 | E60: RENTAPLAST | F60: 45916
A61: OBR | B61: OBRADOR | C61: u | D61: 148000 | E61: TCOM | F61: 45916
A62: CODIGO | B62: YESERO (EVER hermano de Jorge) | C62: UNIDAD | D62: PRECIO SIN IVA | E62: REFERENCIA | F62: FECHA
A63: SUB-YES-PARED | B63: YESO APLICADO EN PARED | C63: m2 | D63: 10000 | E63: EVER | F63: 46081 | G63: 3m2 de rendimiento x bolsa de yeso (30kg)
A64: SUB-YES-CIEL | B64: YESO APLICADO EN CIELORRASO | C64: m2 | D64: 20000 | E64: EVER | F64: 46081
A65: SUB-YES-CIEL-ARM | B65: YESO APLICADO EN CIELORRASO ARMADO | C65: m2 | D65: 30000 | E65: EVER | F65: 46081
A66: SUB-YES-BUNA | B66: YESO APLICADO - BUNA (x metro lineal) | C66: m | D66: 8000 | E66: EVER | F66: 46081
A67: SUB-YES-ARISTA | B67: YESO APLICADO - ARISTA Y CANTONERA (x metro lineal) | C67: m | D67: 8000 | E67: EVER | F67: 46081
A68: CODIGO | B68: SILLETERO | C68: UNIDAD | D68: PRECIO SIN IVA | E68: REFERENCIA | F68: FECHA
A69: SILL- PE | B69: PINTURA EXTERIOR CON SILLETA | C69: m2 | D69: 13000 | E69: oscar benitez | F69: 45936
A70: SILL-RE | B70: REVOQUE EXTERIOR CON SILLETA. (con ceresita) | C70: m2 | D70: 25000 | E70: oscar benitez | F70: 45936

Sheet 00_JEF + ESTR
A1: JEFATURA DE OBRA (mes)
A3: Jefatura de Obra | B3: =SUM(B4:B5) -> 2500000
A4: Jorge | B4: -
A5: Jefe de Obra | B5: 2500000
A6: Gastos Estructura | B6: =SUM(B7:B10) -> 3400000
A7: Nafta Jefe de Obra | B7: 500000
A8: Nafta Jorge | B8: 500000
A9: Guille | B9: 400000
A10: Herramientas | B10: 2000000
D11: MESES | E11: G.E. + J.d. O TOTAL
B12: =SUM(B6+B3) -> 5900000 | D12: ='01_C&P'!D9 -> 16 | E12: =(D12*B12) -> 94400000

Sheet 01_C&P
A1: EDIFICIO LAS HERAS
A3: PLANILLA COMPUTO Y PRESPUPUESTO
A5: ITEM | B5: DESCRIPCIÓN | C5: UNIDAD | D5: CANTIDAD | E5: SUBTOTAL 01: GASTOS DIRECTOS | O5: SUBTOTAL 02: GASTOS INDIRECTOS | R5: SUBTOTAL 03: BENEFICIOS | U5: TOTAL (NETO)
E6: V.UNITARIO | L6: V.GENERAL | O6: V. GENERAL | R6: V. GENERAL | U6: V. UNITARIO | X6: V.GENERAL
E7: MAT. | F7: M.O.: JORNALES | G7: M.O.: EQUIPOS | H7: M.O.: MATERIALES | I7: M.O.: SUBCONTRATOS | J7: M.O. | K7: GENERAL | L7: MAT. | M7: M.O | N7: GENERAL | O7: MAT. | P7: M.O. | Q7: GENERAL | R7: MAT. | S7: M.O. | T7: GENERAL | U7: MAT. | V7: M.O | W7: GENERAL | X7: MAT. | Y7: M.O | Z7: GENERAL
A8: 1- TAREAS PRELIMINARES
A9: 0.1 | B9: OBRADOR | C9: mes | D9: 16 | I9: 700000 | J9: =SUM(F9:I9) -> 700000 | K9: =SUM(E9,J9) -> 700000 | L9: =$D9*E9 -> 0 | M9: =$D9*(SUM(F9:I9)) -> 11200000 | N9: =L9+M9 -> 11200000 | O9: =L9 -> 0 | P9: =(P$130*M9)/M$130 -> 12790400 | Q9: =O9+P9 -> 12790400 | R9: =L9 -> 0 | S9: =(S$130*P9)/P$130 -> 15988000 | T9: =R9+S9 -> 15988000 | U9: =E9 | V9: =Y9/D9 -> 1081188.5 | W9: =U9+V9 -> 1081188.5 | X9: =L9 -> 0 | Y9: =(Y$130*S9)/S$130 -> 17299016 | Z9: =X9+Y9 -> 17299016
A10: 0.2 | B10: BANOS QUIMICOS (2) | C10: mes | D10: =D9 -> 16 | I10: 240000 | J10: =SUM(F10:I10) -> 240000 | K10: =SUM(E10,J10) -> 240000 | L10: =$D10*E10 -> 0 | M10: =$D10*(SUM(F10:I10)) -> 3840000 | N10: =L10+M10 -> 3840000 | O10: =L10 -> 0 | P10: =(P$130*M10)/M$130 -> 4385280 | Q10: =O10+P10 -> 4385280 | R10: =L10 -> 0 | S10: =(S$130*P10)/P$130 -> 5481600 | T10: =R10+S10 -> 5481600 | U10: =E10 | V10: =Y10/D10 -> 370693.2 | W10: =U10+V10 -> 370693.2 | X10: =L10 -> 0 | Y10: =(Y$130*S10)/S$130 -> 5931091.2 | Z10: =X10+Y10 -> 5931091.2
A11: 0.3 | B11: INSTALACIONES PROVISORIAS | C11: gl | D11: 1 | I11: 5000000 | J11: =SUM(F11:I11) -> 5000000 | K11: =SUM(E11,J11) -> 5000000 | L11: =$D11*E11 -> 0 | M11: =$D11*(SUM(F11:I11)) -> 5000000 | N11: =L11+M11 -> 5000000 | O11: =L11 -> 0 | P11: =(P$130*M11)/M$130 -> 5710000 | Q11: =O11+P11 -> 5710000 | R11: =L11 -> 0 | S11: =(S$130*P11)/P$130 -> 7137500 | T11: =R11+S11 -> 7137500 | U11: =E11 | V11: =Y11/D11 -> 7722775 | W11: =U11+V11 -> 7722775 | X11: =L11 -> 0 | Y11: =(Y$130*S11)/S$130 -> 7722775 | Z11: =X11+Y11 -> 7722775
A12: 0.4 | B12: LIMPIEZA PERIODICA DE OBRA | C12: mes | D12: =D9 -> 16 | I12: 1000000 | J12: =SUM(F12:I12) -> 1000000 | K12: =SUM(E12,J12) -> 1000000 | L12: =$D12*E12 -> 0 | M12: =$D12*(SUM(F12:I12)) -> 16000000 | N12: =L12+M12 -> 16000000 | O12: =L12 -> 0 | P12: =(P$130*M12)/M$130 -> 18272000 | Q12: =O12+P12 -> 18272000 | R12: =L12 -> 0 | S12: =(S$130*P12)/P$130 -> 22840000 | T12: =R12+S12 -> 22840000 | U12: =E12 | V12: =Y12/D12 -> 1544555 | W12: =U12+V12 -> 1544555 | X12: =L12 -> 0 | Y12: =(Y$130*S12)/S$130 -> 24712880 | Z12: =X12+Y12 -> 24712880
A13: 0.5 | B13: ACARREO DE MATERIALES | C13: mes | D13: =D9 -> 16 | I13: 1000000 | J13: =SUM(F13:I13) -> 1000000 | K13: =SUM(E13,J13) -> 1000000 | L13: =$D13*E13 -> 0 | M13: =$D13*(SUM(F13:I13)) -> 16000000 | N13: =L13+M13 -> 16000000 | O13: =L13 -> 0 | P13: =(P$130*M13)/M$130 -> 18272000 | Q13: =O13+P13 -> 18272000 | R13: =L13 -> 0 | S13: =(S$130*P13)/P$130 -> 22840000 | T13: =R13+S13 -> 22840000 | U13: =E13 | V13: =Y13/D13 -> 1544555 | W13: =U13+V13 -> 1544555 | X13: =L13 -> 0 | Y13: =(Y$130*S13)/S$130 -> 24712880 | Z13: =X13+Y13 -> 24712880
A14: 0.6 | B14: AYUDA DE GREMIOS | C14: mes | D14: =D9 -> 16 | I14: 3000000 | J14: =SUM(F14:I14) -> 3000000 | K14: =SUM(E14,J14) -> 3000000 | L14: =$D14*E14 -> 0 | M14: =$D14*(SUM(F14:I14)) -> 48000000 | N14: =L14+M14 -> 48000000 | O14: =L14 -> 0 | P14: =(P$130*M14)/M$130 -> 54816000 | Q14: =O14+P14 -> 54816000 | R14: =L14 -> 0 | S14: =(S$130*P14)/P$130 -> 68520000 | T14: =R14+S14 -> 68520000 | U14: =E14 | V14: =Y14/D14 -> 4633665 | W14: =U14+V14 -> 4633665 | X14: =L14 -> 0 | Y14: =(Y$130*S14)/S$130 -> 74138640 | Z14: =X14+Y14 -> 74138640
A15: 0.7 | B15: LIMPIEZA FINAL | C15: gl | D15: 1 | I15: 2000000 | J15: =SUM(F15:I15) -> 2000000 | K15: =SUM(E15,J15) -> 2000000 | L15: =$D15*E15 -> 0 | M15: =$D15*(SUM(F15:I15)) -> 2000000 | N15: =L15+M15 -> 2000000 | O15: =L15 -> 0 | P15: =(P$130*M15)/M$130 -> 2284000 | Q15: =O15+P15 -> 2284000 | R15: =L15 -> 0 | S15: =(S$130*P15)/P$130 -> 2855000 | T15: =R15+S15 -> 2855000 | U15: =E15 | V15: =Y15/D15 -> 3089110 | W15: =U15+V15 -> 3089110 | X15: =L15 -> 0 | Y15: =(Y$130*S15)/S$130 -> 3089110 | Z15: =X15+Y15 -> 3089110
A16: 0.8 | B16: ESTRUCTURA DE ENCOFRADO Y APUNTALAMIENTO PROVISORIO | C16: gl | D16: 1 | G16: =ESTRUCTURA!I50 -> 129142648 | J16: =SUM(F16:I16) -> 129142648 | K16: =SUM(E16,J16) -> 129142648 | L16: =$D16*E16 -> 0 | M16: =$D16*(SUM(F16:I16)) -> 129142648 | N16: =L16+M16 -> 129142648 | O16: =L16 -> 0 | P16: =(P$130*M16)/M$130 -> 147480904 | Q16: =O16+P16 -> 147480904 | R16: =L16 -> 0 | S16: =(S$130*P16)/P$130 -> 184351130 | T16: =R16+S16 -> 184351130 | U16: =E16 | V16: =Y16/D16 -> 1.9946792e+08 | W16: =U16+V16 -> 1.9946792e+08 | X16: =L16 -> 0 | Y16: =(Y$130*S16)/S$130 -> 1.9946792e+08 | Z16: =X16+Y16 -> 1.9946792e+08
A17: EXCAVACION
A18: 0.9 | B18: EXCAVACION BASES Y TRONCOS | C18: m³ | D18: =172*2.13 -> 366.36 | E18: ='0.9'!$I$22 -> 0 | F18: ='0.9'!$I$36 -> 0 | G18: ='0.9'!$I$50 -> 37504.094 | H18: ='0.9'!$I$64 -> 0 | I18: ='0.9'!$I$78 -> 0 | J18: =SUM(F18:I18) -> 37504.094 | K18: =SUM(E18,J18) -> 37504.094 | L18: =$D18*E18 -> 0 | M18: =$D18*(SUM(F18:I18)) -> 13740000 | N18: =L18+M18 -> 13740000 | O18: =L18 -> 0 | P18: =(P$130*M18)/M$130 -> 15691080 | Q18: =O18+P18 -> 15691080 | R18: =L18 -> 0 | S18: =(S$130*P18)/P$130 -> 19613850 | T18: =R18+S18 -> 19613850 | U18: =E18 -> 0 | V18: =Y18/D18 -> 57927.136 | W18: =U18+V18 -> 57927.136 | X18: =L18 -> 0 | Y18: =(Y$130*S18)/S$130 -> 21222186 | Z18: =X18+Y18 -> 21222186
A19: 0.10 | B19: EXCAVACION TENSORES | C19: m³ | D19: =(45*0.4)*0.3 -> 5.4 | E19: ='0.10'!$I$22 -> 0 | F19: ='0.10'!$I$36 -> 0 | G19: ='0.10'!$I$50 -> 50000 | H19: ='0.10'!$I$64 -> 0 | I19: ='0.10'!$I$78 -> 0 | J19: =SUM(F19:I19) -> 50000 | K19: =SUM(E19,J19) -> 50000 | L19: =$D19*E19 -> 0 | M19: =$D19*(SUM(F19:I19)) -> 270000 | N19: =L19+M19 -> 270000 | O19: =L19 -> 0 | P19: =(P$130*M19)/M$130 -> 308340 | Q19: =O19+P19 -> 308340 | R19: =L19 -> 0 | S19: =(S$130*P19)/P$130 -> 385425 | T19: =R19+S19 -> 385425 | U19: =E19 -> 0 | V19: =Y19/D19 -> 77227.75 | W19: =U19+V19 -> 77227.75 | X19: =L19 -> 0 | Y19: =(Y$130*S19)/S$130 -> 417029.85 | Z19: =X19+Y19 -> 417029.85
A20: 0.11 | B20: EXCAVACION TRONERAS | C20: m³ | D20: =6*46 -> 276 | E20: ='0.11'!$I$22 -> 0 | F20: ='0.11'!$I$36 -> 0 | G20: ='0.11'!$I$50 -> 37500 | H20: ='0.11'!$I$64 -> 0 | I20: ='0.11'!$I$78 -> 0 | J20: =SUM(F20:I20) -> 37500 | K20: =SUM(E20,J20) -> 37500 | L20: =$D20*E20 -> 0 | M20: =$D20*(SUM(F20:I20)) -> 10350000 | N20: =L20+M20 -> 10350000 | O20: =L20 -> 0 | P20: =(P$130*M20)/M$130 -> 11819700 | Q20: =O20+P20 -> 11819700 | R20: =L20 -> 0 | S20: =(S$130*P20)/P$130 -> 14774625 | T20: =R20+S20 -> 14774625 | U20: =E20 -> 0 | V20: =Y20/D20 -> 57920.812 | W20: =U20+V20 -> 57920.812 | X20: =L20 -> 0 | Y20: =(Y$130*S20)/S$130 -> 15986144 | Z20: =X20+Y20 -> 15986144
A21: OBRA GRIS - FUNDACIONES
A22: 0.12 | B22: BASES | C22: m³ | D22: 108 | E22: ='0.12'!$I$22 -> 264204.49 | F22: ='0.12'!$I$36 -> 65000 | G22: ='0.12'!$I$50 -> 0 | H22: ='0.12'!$I$64 -> 6111.1111 | I22: ='0.12'!$I$78 -> 0 | J22: =SUM(F22:I22) -> 71111.111 | K22: =SUM(E22,J22) -> 335315.6 | L22: =$D22*E22 -> 28534084 | M22: =$D22*(SUM(F22:I22)) -> 7680000 | N22: =L22+M22 -> 36214084 | O22: =L22 -> 28534084 | P22: =(P$130*M22)/M$130 -> 8770560 | Q22: =O22+P22 -> 37304644 | R22: =L22 -> 28534084 | S22: =(S$130*P22)/P$130 -> 10963200 | T22: =R22+S22 -> 39497284 | U22: =E22 -> 264204.49 | V22: =Y22/D22 -> 109835.02 | W22: =U22+V22 -> 374039.51 | X22: =L22 -> 28534084 | Y22: =(Y$130*S22)/S$130 -> 11862182 | Z22: =X22+Y22 -> 40396267
A23: 0.13 | B23: TRONCOS | C23: m³ | D23: 20 | E23: ='0.13'!$I$22 -> 290615.56 | F23: ='0.13'!$I$36 -> 351000 | G23: ='0.13'!$I$50 -> 0 | H23: ='0.13'!$I$64 -> 13475 | I23: ='0.13'!$I$78 -> 0 | J23: =SUM(F23:I23) -> 364475 | K23: =SUM(E23,J23) -> 655090.56 | L23: =$D23*E23 -> 5812311.3 | M23: =$D23*(SUM(F23:I23)) -> 7289500 | N23: =L23+M23 -> 13101811 | O23: =L23 -> 5812311.3 | P23: =(P$130*M23)/M$130 -> 8324609 | Q23: =O23+P23 -> 14136920 | R23: =L23 -> 5812311.3 | S23: =(S$130*P23)/P$130 -> 10405761 | T23: =R23+S23 -> 16218073 | U23: =E23 -> 290615.56 | V23: =Y23/D23 -> 562951.68 | W23: =U23+V23 -> 853567.25 | X23: =L23 -> 5812311.3 | Y23: =(Y$130*S23)/S$130 -> 11259034 | Z23: =X23+Y23 -> 17071345
A24: 0.14 | B24: TENSORES | C24: m³ | D24: =D19 -> 5.4 | E24: ='0.14'!$I$22 -> 389379.44 | F24: ='0.14'!$I$36 -> 386111.11 | G24: ='0.14'!$I$50 -> 0 | H24: ='0.14'!$I$64 -> 0 | I24: ='0.14'!$I$78 -> 0 | J24: =SUM(F24:I24) -> 386111.11 | K24: =SUM(E24,J24) -> 775490.56 | L24: =$D24*E24 -> 2102649 | M24: =$D24*(SUM(F24:I24)) -> 2085000 | N24: =L24+M24 -> 4187649 | O24: =L24 -> 2102649 | P24: =(P$130*M24)/M$130 -> 2381070 | Q24: =O24+P24 -> 4483719 | R24: =L24 -> 2102649 | S24: =(S$130*P24)/P$130 -> 2976337.5 | T24: =R24+S24 -> 5078986.5 | U24: =E24 -> 389379.44 | V24: =Y24/D24 -> 596369.85 | W24: =U24+V24 -> 985749.29 | X24: =L24 -> 2102649 | Y24: =(Y$130*S24)/S$130 -> 3220397.2 | Z24: =X24+Y24 -> 5323046.2
A25: 0.15 | B25: TABIQUES DE SUBMURACION | C25: m³ | D25: =95*3*0.15 -> 42.75 | E25: ='0.15'!$I$22 -> 442353.68 | F25: ='0.15'!$I$36 -> 369239.77 | G25: ='0.15'!$I$50 -> 0 | H25: ='0.15'!$I$64 -> 5146.1988 | I25: ='0.15'!$I$78 -> 0 | J25: =SUM(F25:I25) -> 374385.96 | K25: =SUM(E25,J25) -> 816739.65 | L25: =$D25*E25 -> 18910620 | M25: =$D25*(SUM(F25:I25)) -> 16005000 | N25: =L25+M25 -> 34915620 | O25: =L25 -> 18910620 | P25: =(P$130*M25)/M$130 -> 18277710 | Q25: =O25+P25 -> 37188330 | R25: =L25 -> 18910620 | S25: =(S$130*P25)/P$130 -> 22847138 | T25: =R25+S25 -> 41757758 | U25: =E25 -> 442353.68 | V25: =Y25/D25 -> 578259.71 | W25: =U25+V25 -> 1020613.4 | X25: =L25 -> 18910620 | Y25: =(Y$130*S25)/S$130 -> 24720603 | Z25: =X25+Y25 -> 43631223
A26: OBRA GRIS - SOBRE SUBSUELO
A27: 36892 | B27: COLUMNAS Y TABIQUES | C27: m³ | D27: 23 | E27: ='1.1'!$I$22 -> 548114.34 | F27: ='1.1'!$I$36 -> 599347.83 | G27: ='1.1'!$I$50 -> 0 | H27: ='1.1'!$I$64 -> 13869.565 | I27: ='1.1'!$I$78 -> 0 | J27: =SUM(F27:I27) -> 613217.39 | K27: =SUM(E27,J27) -> 1161331.7 | L27: =$D27*E27 -> 12606630 | M27: =$D27*(SUM(F27:I27)) -> 14104000 | N27: =L27+M27 -> 26710630 | O27: =L27 -> 12606630 | P27: =(P$130*M27)/M$130 -> 16106768 | Q27: =O27+P27 -> 28713398 | R27: =L27 -> 12606630 | S27: =(S$130*P27)/P$130 -> 20133460 | T27: =R27+S27 -> 32740090 | U27: =E27 -> 548114.34 | V27: =Y27/D27 -> 947147.99 | W27: =U27+V27 -> 1495262.3 | X27: =L27 -> 12606630 | Y27: =(Y$130*S27)/S$130 -> 21784404 | Z27: =X27+Y27 -> 34391034
A28: 46054 | B28: VIGAS | C28: m³ | D28: 16 | E28: ='1.2'!$I$22 -> 539468.37 | F28: ='1.2'!$I$36 -> 861562.5 | G28: ='1.2'!$I$50 -> 0 | H28: ='1.2'!$I$64 -> 19937.5 | I28: ='1.2'!$I$78 -> 0 | J28: =SUM(F28:I28) -> 881500 | K28: =SUM(E28,J28) -> 1420968.4 | L28: =$D28*E28 -> 8631493.9 | M28: =$D28*(SUM(F28:I28)) -> 14104000 | N28: =L28+M28 -> 22735494 | O28: =L28 -> 8631493.9 | P28: =(P$130*M28)/M$130 -> 16106768 | Q28: =O28+P28 -> 24738262 | R28: =L28 -> 8631493.9 | S28: =(S$130*P28)/P$130 -> 20133460 | T28: =R28+S28 -> 28764954 | U28: =E28 -> 539468.37 | V28: =Y28/D28 -> 1361525.2 | W28: =U28+V28 -> 1900993.6 | X28: =L28 -> 8631493.9 | Y28: =(Y$130*S28)/S$130 -> 21784404 | Z28: =X28+Y28 -> 30415898
A29: 46082 | B29: LOSA | C29: m³ | D29: =54+3 -> 57 | E29: ='1.3'!$I$22 -> 362272.74 | F29: ='1.3'!$I$36 -> 342105.26 | G29: ='1.3'!$I$50 -> 0 | H29: ='1.3'!$I$64 -> 8587.7193 | I29: ='1.3'!$I$78 -> 0 | J29: =SUM(F29:I29) -> 350692.98 | K29: =SUM(E29,J29) -> 712965.72 | L29: =$D29*E29 -> 20649546 | M29: =$D29*(SUM(F29:I29)) -> 19989500 | N29: =L29+M29 -> 40639046 | O29: =L29 -> 20649546 | P29: =(P$130*M29)/M$130 -> 22828009 | Q29: =O29+P29 -> 43477555 | R29: =L29 -> 20649546 | S29: =(S$130*P29)/P$130 -> 28535011 | T29: =R29+S29 -> 49184557 | U29: =E29 -> 362272.74 | V29: =Y29/D29 -> 541664.6 | W29: =U29+V29 -> 903937.34 | X29: =L29 -> 20649546 | Y29: =(Y$130*S29)/S$130 -> 30874882 | Z29: =X29+Y29 -> 51524428
A30: 1.31 | B30: LOSA DE SUPRESION SOBRE SUELO COMPACTADO. e=10cm. | C30: m³ | D30: =390*0.1 -> 39 | E30: ='1.31'!$I$22 -> 218369.72 | F30: ='1.31'!$I$36 -> 129615.38 | G30: ='1.31'!$I$50 -> 0 | H30: ='1.31'!$I$64 -> 0 | I30: ='1.31'!$I$78 -> 0 | J30: =SUM(F30:I30) -> 129615.38 | K30: =SUM(E30,J30) -> 347985.1 | L30: =$D30*E30 -> 8516419 | M30: =$D30*(SUM(F30:I30)) -> 5055000 | N30: =L30+M30 -> 13571419 | O30: =L30 -> 8516419 | P30: =(P$130*M30)/M$130 -> 5772810 | Q30: =O30+P30 -> 14289229 | R30: =L30 -> 8516419 | S30: =(S$130*P30)/P$130 -> 7216012.5 | T30: =R30+S30 -> 15732432 | U30: =E30 -> 218369.72 | V30: =Y30/D30 -> 200198.09 | W30: =U30+V30 -> 418567.81 | X30: =L30 -> 8516419 | Y30: =(Y$130*S30)/S$130 -> 7807725.5 | Z30: =X30+Y30 -> 16324145
A31: 1.32 | B31: PAVIMENTO ALISADO EN ESTACIONAMIENTO. e=10cm | C31: m² | D31: 310 | E31: ='1.32'!$I$22 -> 25336.66 | F31: ='1.32'!$I$36 -> 3725.8065 | G31: ='1.32'!$I$50 -> 0 | H31: ='1.32'!$I$64 -> 0 | I31: ='1.32'!$I$78 -> 12516.129 | J31: =SUM(F31:I31) -> 16241.935 | K31: =SUM(E31,J31) -> 41578.595 | L31: =$D31*E31 -> 7854364.5 | M31: =$D31*(SUM(F31:I31)) -> 5035000 | N31: =L31+M31 -> 12889364 | O31: =L31 -> 7854364.5 | P31: =(P$130*M31)/M$130 -> 5749970 | Q31: =O31+P31 -> 13604334 | R31: =L31 -> 7854364.5 | S31: =(S$130*P31)/P$130 -> 7187462.5 | T31: =R31+S31 -> 15041827 | U31: =E31 -> 25336.66 | V31: =Y31/D31 -> 25086.563 | W31: =U31+V31 -> 50423.222 | X31: =L31 -> 7854364.5 | Y31: =(Y$130*S31)/S$130 -> 7776834.4 | Z31: =X31+Y31 -> 15631199
A32: 46113 | B32: MAMPOSTERIA. | C32: m² | D32: =120*3 -> 360 | E32: ='1.4'!$I$22 -> 28937.371 | F32: ='1.4'!$I$36 -> 16625 | G32: ='1.4'!$I$50 -> 0 | H32: ='1.4'!$I$64 -> 222.22222 | I32: ='1.4'!$I$78 -> 0 | J32: =SUM(F32:I32) -> 16847.222 | K32: =SUM(E32,J32) -> 45784.593 | L32: =$D32*E32 -> 10417454 | M32: =$D32*(SUM(F32:I32)) -> 6065000 | N32: =L32+M32 -> 16482454 | O32: =L32 -> 10417454 | P32: =(P$130*M32)/M$130 -> 6926230 | Q32: =O32+P32 -> 17343684 | R32: =L32 -> 10417454 | S32: =(S$130*P32)/P$130 -> 8657787.5 | T32: =R32+S32 -> 19075241 | U32: =E32 -> 28937.371 | V32: =Y32/D32 -> 26021.461 | W32: =U32+V32 -> 54958.832 | X32: =L32 -> 10417454 | Y32: =(Y$130*S32)/S$130 -> 9367726.1 | Z32: =X32+Y32 -> 19785180
A33: 46143 | B33: CONTRAPISO . e=12cm | C33: m² | D33: 80 | E33: ='1.5'!$I$22 -> 18664.73 | F33: ='1.5'!$I$36 -> 14437.5 | G33: ='1.5'!$I$50 -> 0 | H33: ='1.5'!$I$64 -> 0 | I33: ='1.5'!$I$78 -> 15000 | J33: =SUM(F33:I33) -> 29437.5 | K33: =SUM(E33,J33) -> 48102.23 | L33: =$D33*E33 -> 1493178.4 | M33: =$D33*(SUM(F33:I33)) -> 2355000 | N33: =L33+M33 -> 3848178.4 | O33: =L33 -> 1493178.4 | P33: =(P$130*M33)/M$130 -> 2689410 | Q33: =O33+P33 -> 4182588.4 | R33: =L33 -> 1493178.4 | S33: =(S$130*P33)/P$130 -> 3361762.5 | T33: =R33+S33 -> 4854940.9 | U33: =E33 -> 18664.73 | V33: =Y33/D33 -> 45467.838 | W33: =U33+V33 -> 64132.568 | X33: =L33 -> 1493178.4 | Y33: =(Y$130*S33)/S$130 -> 3637427 | Z33: =X33+Y33 -> 5130605.5
A34: 46174 | B34: CARPETA . e=3cm | C34: m² | D34: =D33 -> 80 | E34: ='1.6'!$I$22 -> 5017.625 | F34: ='1.6'!$I$36 -> 17625 | G34: ='1.6'!$I$50 -> 0 | H34: ='1.6'!$I$64 -> 0 | I34: ='1.6'!$I$78 -> 0 | J34: =SUM(F34:I34) -> 17625 | K34: =SUM(E34,J34) -> 22642.625 | L34: =$D34*E34 -> 401410 | M34: =$D34*(SUM(F34:I34)) -> 1410000 | N34: =L34+M34 -> 1811410 | O34: =L34 -> 401410 | P34: =(P$130*M34)/M$130 -> 1610220 | Q34: =O34+P34 -> 2011630 | R34: =L34 -> 401410 | S34: =(S$130*P34)/P$130 -> 2012775 | T34: =R34+S34 -> 2414185 | U34: =E34 -> 5017.625 | V34: =Y34/D34 -> 27222.782 | W34: =U34+V34 -> 32240.407 | X34: =L34 -> 401410 | Y34: =(Y$130*S34)/S$130 -> 2177822.5 | Z34: =X34+Y34 -> 2579232.5
A35: 46204 | B35: REVOQUE INTERIOR. (GRUESO FRATAZADO) | C35: m² | D35: =30*3*2 -> 180 | E35: ='1.7'!$I$22 -> 2871.4118 | F35: ='1.7'!$I$36 -> 26000 | G35: ='1.7'!$I$50 -> 0 | H35: ='1.7'!$I$64 -> 0 | I35: ='1.7'!$I$78 -> 0 | J35: =SUM(F35:I35) -> 26000 | K35: =SUM(E35,J35) -> 28871.412 | L35: =$D35*E35 -> 516854.13 | M35: =$D35*(SUM(F35:I35)) -> 4680000 | N35: =L35+M35 -> 5196854.1 | O35: =L35 -> 516854.13 | P35: =(P$130*M35)/M$130 -> 5344560 | Q35: =O35+P35 -> 5861414.1 | R35: =L35 -> 516854.13 | S35: =(S$130*P35)/P$130 -> 6680700 | T35: =R35+S35 -> 7197554.1 | U35: =E35 -> 2871.4118 | V35: =Y35/D35 -> 40158.43 | W35: =U35+V35 -> 43029.842 | X35: =L35 -> 516854.13 | Y35: =(Y$130*S35)/S$130 -> 7228517.4 | Z35: =X35+Y35 -> 7745371.5
A36: 46235 | B36: REVOQUE INTERTIOR HIDROFUGO. | C36: m² | D36: =94*3*1 -> 282 | E36: ='1.8'!$I$22 -> 3811.6746 | F36: ='1.8'!$I$36 -> 35053.191 | G36: ='1.8'!$I$50 -> 0 | H36: ='1.8'!$I$64 -> 0 | I36: ='1.8'!$I$78 -> 0 | J36: =SUM(F36:I36) -> 35053.191 | K36: =SUM(E36,J36) -> 38864.866 | L36: =$D36*E36 -> 1074892.2 | M36: =$D36*(SUM(F36:I36)) -> 9885000 | N36: =L36+M36 -> 10959892 | O36: =L36 -> 1074892.2 | P36: =(P$130*M36)/M$130 -> 11288670 | Q36: =O36+P36 -> 12363562 | R36: =L36 -> 1074892.2 | S36: =(S$130*P36)/P$130 -> 14110838 | T36: =R36+S36 -> 15185730 | U36: =E36 -> 3811.6746 | V36: =Y36/D36 -> 54141.582 | W36: =U36+V36 -> 57953.257 | X36: =L36 -> 1074892.2 | Y36: =(Y$130*S36)/S$130 -> 15267926 | Z36: =X36+Y36 -> 16342818
A37: OBRA GRIS - SOBRE PLANTA BAJA
A38: 45293 | B38: COLUMNAS Y TABIQUES | C38: m³ | D38: 31 | E38: ='2.1.'!I22 -> 537748.84 | F38: ='2.1.'!I36 -> 377419.35 | G38: ='2.1.'!I50 -> 0 | H38: ='2.1.'!I64 -> 15790.323 | I38: ='2.1.'!I78 -> 0 | J38: =SUM(F38:I38) -> 393209.68 | K38: =SUM(E38,J38) -> 930958.52 | L38: =$D38*E38 -> 16670214 | M38: =$D38*(SUM(F38:I38)) -> 12189500 | N38: =L38+M38 -> 28859714 | O38: =L38 -> 16670214 | P38: =(P$130*M38)/M$130 -> 13920409 | Q38: =O38+P38 -> 30590623 | R38: =L38 -> 16670214 | S38: =(S$130*P38)/P$130 -> 17400511 | T38: =R38+S38 -> 34070725 | U38: =E38 -> 537748.84 | V38: =Y38/D38 -> 607333.97 | W38: =U38+V38 -> 1145082.8 | X38: =L38 -> 16670214 | Y38: =(Y$130*S38)/S$130 -> 18827353 | Z38: =X38+Y38 -> 35497567
A39: n | B39: VIGAS | C39: m³ | D39: 14 | E39: ='2.2.'!I22 -> 559896.94 | F39: ='2.2.'!I36 -> 835714.29 | G39: ='2.2.'!I50 -> 0 | H39: ='2.2.'!I64 -> 19250 | I39: ='2.2.'!I78 -> 0 | J39: =SUM(F39:I39) -> 854964.29 | K39: =SUM(E39,J39) -> 1414861.2 | L39: =$D39*E39 -> 7838557.2 | M39: =$D39*(SUM(F39:I39)) -> 11969500 | N39: =L39+M39 -> 19808057 | O39: =L39 -> 7838557.2 | P39: =(P$130*M39)/M$130 -> 13669169 | Q39: =O39+P39 -> 21507726 | R39: =L39 -> 7838557.2 | S39: =(S$130*P39)/P$130 -> 17086461 | T39: =R39+S39 -> 24925018 | U39: =E39 -> 559896.94 | V39: =Y39/D39 -> 1320539.4 | W39: =U39+V39 -> 1880436.3 | X39: =L39 -> 7838557.2 | Y39: =(Y$130*S39)/S$130 -> 18487551 | Z39: =X39+Y39 -> 26326108
A40: 45353 | B40: LOSA | C40: m³ | D40: =23+3 -> 26 | E40: ='2.3'!I22 -> 417771.5 | F40: ='2.3'!I36 -> 570000 | G40: ='2.3'!I50 -> 0 | H40: ='2.3'!I64 -> 10365.385 | I40: ='2.3'!I78 -> 0 | J40: =SUM(F40:I40) -> 580365.38 | K40: =SUM(E40,J40) -> 998136.88 | L40: =$D40*E40 -> 10862059 | M40: =$D40*(SUM(F40:I40)) -> 15089500 | N40: =L40+M40 -> 25951559 | O40: =L40 -> 10862059 | P40: =(P$130*M40)/M$130 -> 17232209 | Q40: =O40+P40 -> 28094268 | R40: =L40 -> 10862059 | S40: =(S$130*P40)/P$130 -> 21540261 | T40: =R40+S40 -> 32402320 | U40: =E40 -> 417771.5 | V40: =Y40/D40 -> 896406.26 | W40: =U40+V40 -> 1314177.8 | X40: =L40 -> 10862059 | Y40: =(Y$130*S40)/S$130 -> 23306563 | Z40: =X40+Y40 -> 34168622
A41: 46114 | B41: MAMPOSTERIA. | C41: m² | D41: =85*4 -> 340 | E41: ='2.4'!I22 -> 28748.294 | F41: ='2.4'!I36 -> 17161.765 | G41: ='2.4'!I50 -> 0 | H41: ='2.4'!I64 -> 235.29412 | I41: ='2.4'!I78 -> 0 | J41: =SUM(F41:I41) -> 17397.059 | K41: =SUM(E41,J41) -> 46145.353 | L41: =$D41*E41 -> 9774420.1 | M41: =$D41*(SUM(F41:I41)) -> 5915000 | N41: =L41+M41 -> 15689420 | O41: =L41 -> 9774420.1 | P41: =(P$130*M41)/M$130 -> 6754930 | Q41: =O41+P41 -> 16529350 | R41: =L41 -> 9774420.1 | S41: =(S$130*P41)/P$130 -> 8443662.5 | T41: =R41+S41 -> 18218083 | U41: =E41 -> 28748.294 | V41: =Y41/D41 -> 26870.714 | W41: =U41+V41 -> 55619.009 | X41: =L41 -> 9774420.1 | Y41: =(Y$130*S41)/S$130 -> 9136042.8 | Z41: =X41+Y41 -> 18910463
A42: 46144 | B42: CONTRAPISO INTERIOR . e=12cm | C42: m² | D42: =144 -> 144 | E42: ='2.5'!I22 -> 20997.164 | F42: ='2.5'!I36 -> 8020.8333 | G42: ='2.5'!I50 -> 0 | H42: ='2.5'!I64 -> 0 | I42: ='2.5'!I78 -> 15000 | J42: =SUM(F42:I42) -> 23020.833 | K42: =SUM(E42,J42) -> 44017.997 | L42: =$D42*E42 -> 3023591.6 | M42: =$D42*(SUM(F42:I42)) -> 3315000 | N42: =L42+M42 -> 6338591.6 | O42: =L42 -> 3023591.6 | P42: =(P$130*M42)/M$130 -> 3785730 | Q42: =O42+P42 -> 6809321.6 | R42: =L42 -> 3023591.6 | S42: =(S$130*P42)/P$130 -> 4732162.5 | T42: =R42+S42 -> 7755754.1 | U42: =E42 -> 20997.164 | V42: =Y42/D42 -> 35556.943 | W42: =U42+V42 -> 56554.107 | X42: =L42 -> 3023591.6 | Y42: =(Y$130*S42)/S$130 -> 5120199.8 | Z42: =X42+Y42 -> 8143791.4
A43: 2.51 | B43: PAVIMENTO ALISADO EN ESTACIONAMIENTO. e=10cm | C43: m² | D43: 267 | E43: ='2.51'!I22 -> 26130.315 | F43: ='2.51'!I36 -> 4325.8427 | G43: ='2.51'!I50 -> 0 | H43: ='2.51'!I64 -> 0 | I43: ='2.51'!I78 -> 12509.363 | J43: =SUM(F43:I43) -> 16835.206 | K43: =SUM(E43,J43) -> 42965.521 | L43: =$D43*E43 -> 6976794 | M43: =$D43*(SUM(F43:I43)) -> 4495000 | N43: =L43+M43 -> 11471794 | O43: =L43 -> 6976794 | P43: =(P$130*M43)/M$130 -> 5133290 | Q43: =O43+P43 -> 12110084 | R43: =L43 -> 6976794 | S43: =(S$130*P43)/P$130 -> 6416612.5 | T43: =R43+S43 -> 13393406 | U43: =E43 -> 26130.315 | V43: =Y43/D43 -> 26002.902 | W43: =U43+V43 -> 52133.216 | X43: =L43 -> 6976794 | Y43: =(Y$130*S43)/S$130 -> 6942774.7 | Z43: =X43+Y43 -> 13919569
A44: 46175 | B44: CARPETA INTERIOR. e=3cm | C44: m² | D44: =144 -> 144 | E44: ='2.6'!I22 -> 9043.2639 | F44: ='2.6'!I36 -> 16250 | G44: ='2.6'!I50 -> 0 | H44: ='2.6'!I64 -> 0 | I44: ='2.6'!I78 -> 0 | J44: =SUM(F44:I44) -> 16250 | K44: =SUM(E44,J44) -> 25293.264 | L44: =$D44*E44 -> 1302230 | M44: =$D44*(SUM(F44:I44)) -> 2340000 | N44: =L44+M44 -> 3642230 | O44: =L44 -> 1302230 | P44: =(P$130*M44)/M$130 -> 2672280 | Q44: =O44+P44 -> 3974510 | R44: =L44 -> 1302230 | S44: =(S$130*P44)/P$130 -> 3340350 | T44: =R44+S44 -> 4642580 | U44: =E44 -> 9043.2639 | V44: =Y44/D44 -> 25099.019 | W44: =U44+V44 -> 34142.283 | X44: =L44 -> 1302230 | Y44: =(Y$130*S44)/S$130 -> 3614258.7 | Z44: =X44+Y44 -> 4916488.7
A45: 46205 | B45: REVOQUE INTERIOR. (GRUESO FRATAZADO) | C45: m² | D45: =28*4*2 -> 224 | E45: ='2.7'!I22 -> 2828.8895 | F45: ='2.7'!I36 -> 24375 | G45: ='2.7'!I50 -> 0 | H45: ='2.7'!I64 -> 0 | I45: ='2.7'!I78 -> 0 | J45: =SUM(F45:I45) -> 24375 | K45: =SUM(E45,J45) -> 27203.889 | L45: =$D45*E45 -> 633671.24 | M45: =$D45*(SUM(F45:I45)) -> 5460000 | N45: =L45+M45 -> 6093671.2 | O45: =L45 -> 633671.24 | P45: =(P$130*M45)/M$130 -> 6235320 | Q45: =O45+P45 -> 6868991.2 | R45: =L45 -> 633671.24 | S45: =(S$130*P45)/P$130 -> 7794150 | T45: =R45+S45 -> 8427821.2 | U45: =E45 -> 2828.8895 | V45: =Y45/D45 -> 37648.528 | W45: =U45+V45 -> 40477.418 | X45: =L45 -> 633671.24 | Y45: =(Y$130*S45)/S$130 -> 8433270.3 | Z45: =X45+Y45 -> 9066941.5
A46: 46236 | B46: REVOQUE EXTERIOR (GRUESO FRATAZADO) CON HIDROFUGO. | C46: m² | D46: =57*4*2 -> 456 | E46: ='2.8'!I22 -> 3712.7998 | F46: ='2.8'!I36 -> 0 | G46: ='2.8'!I50 -> 0 | H46: ='2.8'!I64 -> 0 | I46: ='2.8'!I78 -> 37500 | J46: =SUM(F46:I46) -> 37500 | K46: =SUM(E46,J46) -> 41212.8 | L46: =$D46*E46 -> 1693036.7 | M46: =$D46*(SUM(F46:I46)) -> 17100000 | N46: =L46+M46 -> 18793037 | O46: =L46 -> 1693036.7 | P46: =(P$130*M46)/M$130 -> 19528200 | Q46: =O46+P46 -> 21221237 | R46: =L46 -> 1693036.7 | S46: =(S$130*P46)/P$130 -> 24410250 | T46: =R46+S46 -> 26103287 | U46: =E46 -> 3712.7998 | V46: =Y46/D46 -> 57920.812 | W46: =U46+V46 -> 61633.612 | X46: =L46 -> 1693036.7 | Y46: =(Y$130*S46)/S$130 -> 26411890 | Z46: =X46+Y46 -> 28104927
A47: OBRA GRIS - SOBRE PRIMER PISO
A48: 46025 | B48: COLUMNAS Y TABIQUES | C48: m³ | D48: 18 | E48: ='3.1'!$I$22 -> 517211.35 | F48: ='3.1'!$I$36 -> 549166.67 | G48: ='3.1'!$I$50 -> 0 | H48: ='3.1'!$I$64 -> 14972.222 | I48: ='3.1'!$I$78 -> 0 | J48: =SUM(F48:I48) -> 564138.89 | K48: =SUM(E48,J48) -> 1081350.2 | L48: =$D48*E48 -> 9309804.2 | M48: =$D48*(SUM(F48:I48)) -> 10154500 | N48: =L48+M48 -> 19464304 | O48: =L48 -> 9309804.2 | P48: =(P$130*M48)/M$130 -> 11596439 | Q48: =O48+P48 -> 20906243 | R48: =L48 -> 9309804.2 | S48: =(S$130*P48)/P$130 -> 14495549 | T48: =R48+S48 -> 23805353 | U48: =E48 -> 517211.35 | V48: =Y48/D48 -> 871343.54 | W48: =U48+V48 -> 1388554.9 | X48: =L48 -> 9309804.2 | Y48: =(Y$130*S48)/S$130 -> 15684184 | Z48: =X48+Y48 -> 24993988
A49: 46056 | B49: VIGAS | C49: m³ | D49: 13 | E49: ='3.2'!$I$22 -> 631622.87 | F49: ='3.2'!$I$36 -> 760384.62 | G49: ='3.2'!$I$50 -> 0 | H49: ='3.2'!$I$64 -> 20730.769 | I49: ='3.2'!$I$78 -> 0 | J49: =SUM(F49:I49) -> 781115.38 | K49: =SUM(E49,J49) -> 1412738.3 | L49: =$D49*E49 -> 8211097.4 | M49: =$D49*(SUM(F49:I49)) -> 10154500 | N49: =L49+M49 -> 18365597 | O49: =L49 -> 8211097.4 | P49: =(P$130*M49)/M$130 -> 11596439 | Q49: =O49+P49 -> 19807536 | R49: =L49 -> 8211097.4 | S49: =(S$130*P49)/P$130 -> 14495549 | T49: =R49+S49 -> 22706646 | U49: =E49 -> 631622.87 | V49: =Y49/D49 -> 1206475.7 | W49: =U49+V49 -> 1838098.5 | X49: =L49 -> 8211097.4 | Y49: =(Y$130*S49)/S$130 -> 15684184 | Z49: =X49+Y49 -> 23895281
A50: 46084 | B50: LOSA | C50: m³ | D50: =21+3 -> 24 | E50: ='3.3'!$I$22 -> 381107.08 | F50: ='3.3'!$I$36 -> 411875 | G50: ='3.3'!$I$50 -> 0 | H50: ='3.3'!$I$64 -> 20395.833 | I50: ='3.3'!$I$78 -> 0 | J50: =SUM(F50:I50) -> 432270.83 | K50: =SUM(E50,J50) -> 813377.92 | L50: =$D50*E50 -> 9146570 | M50: =$D50*(SUM(F50:I50)) -> 10374500 | N50: =L50+M50 -> 19521070 | O50: =L50 -> 9146570 | P50: =(P$130*M50)/M$130 -> 11847679 | Q50: =O50+P50 -> 20994249 | R50: =L50 -> 9146570 | S50: =(S$130*P50)/P$130 -> 14809599 | T50: =R50+S50 -> 23956169 | U50: =E50 -> 381107.08 | V50: =Y50/D50 -> 667666.08 | W50: =U50+V50 -> 1048773.2 | X50: =L50 -> 9146570 | Y50: =(Y$130*S50)/S$130 -> 16023986 | Z50: =X50+Y50 -> 25170556
A51: 46115 | B51: MAMPOSTERIA. | C51: m² | D51: =37+183+100 -> 320 | E51: ='3.4'!$I$22 -> 29083.526 | F51: ='3.4'!$I$36 -> 18703.125 | G51: ='3.4'!$I$50 -> 0 | H51: ='3.4'!$I$64 -> 250 | I51: ='3.4'!$I$78 -> 0 | J51: =SUM(F51:I51) -> 18953.125 | K51: =SUM(E51,J51) -> 48036.651 | L51: =$D51*E51 -> 9306728.5 | M51: =$D51*(SUM(F51:I51)) -> 6065000 | N51: =L51+M51 -> 15371728 | O51: =L51 -> 9306728.5 | P51: =(P$130*M51)/M$130 -> 6926230 | Q51: =O51+P51 -> 16232958 | R51: =L51 -> 9306728.5 | S51: =(S$130*P51)/P$130 -> 8657787.5 | T51: =R51+S51 -> 17964516 | U51: =E51 -> 29083.526 | V51: =Y51/D51 -> 29274.144 | W51: =U51+V51 -> 58357.67 | X51: =L51 -> 9306728.5 | Y51: =(Y$130*S51)/S$130 -> 9367726.1 | Z51: =X51+Y51 -> 18674455
A52: 46145 | B52: CONTRAPISO . e=12cm | C52: m² | D52: 270 | E52: ='3.5'!$I$22 -> 18509.528 | F52: ='3.5'!$I$36 -> 4277.7778 | G52: ='3.5'!$I$50 -> 0 | H52: ='3.5'!$I$64 -> 0 | I52: ='3.5'!$I$78 -> 14400 | J52: =SUM(F52:I52) -> 18677.778 | K52: =SUM(E52,J52) -> 37187.306 | L52: =$D52*E52 -> 4997572.5 | M52: =$D52*(SUM(F52:I52)) -> 5043000 | N52: =L52+M52 -> 10040572 | O52: =L52 -> 4997572.5 | P52: =(P$130*M52)/M$130 -> 5759106 | Q52: =O52+P52 -> 10756678 | R52: =L52 -> 4997572.5 | S52: =(S$130*P52)/P$130 -> 7198882.5 | T52: =R52+S52 -> 12196455 | U52: =E52 -> 18509.528 | V52: =Y52/D52 -> 28848.855 | W52: =U52+V52 -> 47358.383 | X52: =L52 -> 4997572.5 | Y52: =(Y$130*S52)/S$130 -> 7789190.9 | Z52: =X52+Y52 -> 12786763
A53: 46176 | B53: CARPETA . e=3cm | C53: m² | D53: 270 | E53: ='3.6'!$I$22 -> 4823.0741 | F53: ='3.6'!$I$36 -> 16777.778 | G53: ='3.6'!$I$50 -> 0 | H53: ='3.6'!$I$64 -> 0 | I53: ='3.6'!$I$78 -> 0 | J53: =SUM(F53:I53) -> 16777.778 | K53: =SUM(E53,J53) -> 21600.852 | L53: =$D53*E53 -> 1302230 | M53: =$D53*(SUM(F53:I53)) -> 4530000 | N53: =L53+M53 -> 5832230 | O53: =L53 -> 1302230 | P53: =(P$130*M53)/M$130 -> 5173260 | Q53: =O53+P53 -> 6475490 | R53: =L53 -> 1302230 | S53: =(S$130*P53)/P$130 -> 6466575 | T53: =R53+S53 -> 7768805 | U53: =E53 -> 4823.0741 | V53: =Y53/D53 -> 25914.201 | W53: =U53+V53 -> 30737.275 | X53: =L53 -> 1302230 | Y53: =(Y$130*S53)/S$130 -> 6996834.2 | Z53: =X53+Y53 -> 8299064.2
A54: 46206 | B54: REVOQUE INTERIOR. (GRUESO FRATAZADO) | C54: m² | D54: 244 | E54: ='3.7'!$I$22 -> 2908.3149 | F54: ='3.7'!$I$36 -> 25573.77 | G54: ='3.7'!$I$50 -> 0 | H54: ='3.7'!$I$64 -> 0 | I54: ='3.7'!$I$78 -> 0 | J54: =SUM(F54:I54) -> 25573.77 | K54: =SUM(E54,J54) -> 28482.085 | L54: =$D54*E54 -> 709628.84 | M54: =$D54*(SUM(F54:I54)) -> 6240000 | N54: =L54+M54 -> 6949628.8 | O54: =L54 -> 709628.84 | P54: =(P$130*M54)/M$130 -> 7126080 | Q54: =O54+P54 -> 7835708.8 | R54: =L54 -> 709628.84 | S54: =(S$130*P54)/P$130 -> 8907600 | T54: =R54+S54 -> 9617228.8 | U54: =E54 -> 2908.3149 | V54: =Y54/D54 -> 39500.095 | W54: =U54+V54 -> 42408.41 | X54: =L54 -> 709628.84 | Y54: =(Y$130*S54)/S$130 -> 9638023.2 | Z54: =X54+Y54 -> 10347652
A55: 46237 | B55: REVOQUE EXTERIOR (GRUESO FRATAZADO) CON HIDROFUGO. | C55: m² | D55: =284 -> 284 | E55: ='3.8'!$I$22 -> 3803.7469 | F55: ='3.8'!$I$36 -> 0 | G55: ='3.8'!$I$50 -> 0 | H55: ='3.8'!$I$64 -> 0 | I55: ='3.8'!$I$78 -> 37500 | J55: =SUM(F55:I55) -> 37500 | K55: =SUM(E55,J55) -> 41303.747 | L55: =$D55*E55 -> 1080264.1 | M55: =$D55*(SUM(F55:I55)) -> 10650000 | N55: =L55+M55 -> 11730264 | O55: =L55 -> 1080264.1 | P55: =(P$130*M55)/M$130 -> 12162300 | Q55: =O55+P55 -> 13242564 | R55: =L55 -> 1080264.1 | S55: =(S$130*P55)/P$130 -> 15202875 | T55: =R55+S55 -> 16283139 | U55: =E55 -> 3803.7469 | V55: =Y55/D55 -> 57920.812 | W55: =U55+V55 -> 61724.559 | X55: =L55 -> 1080264.1 | Y55: =(Y$130*S55)/S$130 -> 16449511 | Z55: =X55+Y55 -> 17529775
A56: OBRA GRIS - SOBRE SEGUNDO PISO
A57: 46025 | B57: COLUMNAS Y TABIQUES | C57: m³ | D57: 18 | E57: ='3.1'!$I$22 -> 517211.35 | F57: ='3.1'!$I$36 -> 549166.67 | G57: ='3.1'!$I$50 -> 0 | H57: ='3.1'!$I$64 -> 14972.222 | I57: ='3.1'!$I$78 -> 0 | J57: =SUM(F57:I57) -> 564138.89 | K57: =SUM(E57,J57) -> 1081350.2 | L57: =$D57*E57 -> 9309804.2 | M57: =$D57*(SUM(F57:I57)) -> 10154500 | N57: =L57+M57 -> 19464304 | O57: =L57 -> 9309804.2 | P57: =(P$130*M57)/M$130 -> 11596439 | Q57: =O57+P57 -> 20906243 | R57: =L57 -> 9309804.2 | S57: =(S$130*P57)/P$130 -> 14495549 | T57: =R57+S57 -> 23805353 | U57: =E57 -> 517211.35 | V57: =Y57/D57 -> 871343.54 | W57: =U57+V57 -> 1388554.9 | X57: =L57 -> 9309804.2 | Y57: =(Y$130*S57)/S$130 -> 15684184 | Z57: =X57+Y57 -> 24993988
A58: 46056 | B58: VIGAS | C58: m³ | D58: 13 | E58: ='3.2'!$I$22 -> 631622.87 | F58: ='3.2'!$I$36 -> 760384.62 | G58: ='3.2'!$I$50 -> 0 | H58: ='3.2'!$I$64 -> 20730.769 | I58: ='3.2'!$I$78 -> 0 | J58: =SUM(F58:I58) -> 781115.38 | K58: =SUM(E58,J58) -> 1412738.3 | L58: =$D58*E58 -> 8211097.4 | M58: =$D58*(SUM(F58:I58)) -> 10154500 | N58: =L58+M58 -> 18365597 | O58: =L58 -> 8211097.4 | P58: =(P$130*M58)/M$130 -> 11596439 | Q58: =O58+P58 -> 19807536 | R58: =L58 -> 8211097.4 | S58: =(S$130*P58)/P$130 -> 14495549 | T58: =R58+S58 -> 22706646 | U58: =E58 -> 631622.87 | V58: =Y58/D58 -> 1206475.7 | W58: =U58+V58 -> 1838098.5 | X58: =L58 -> 8211097.4 | Y58: =(Y$130*S58)/S$130 -> 15684184 | Z58: =X58+Y58 -> 23895281
A59: 46084 | B59: LOSA | C59: m³ | D59: =21+3 -> 24 | E59: ='3.3'!$I$22 -> 381107.08 | F59: ='3.3'!$I$36 -> 411875 | G59: ='3.3'!$I$50 -> 0 | H59: ='3.3'!$I$64 -> 20395.833 | I59: ='3.3'!$I$78 -> 0 | J59: =SUM(F59:I59) -> 432270.83 | K59: =SUM(E59,J59) -> 813377.92 | L59: =$D59*E59 -> 9146570 | M59: =$D59*(SUM(F59:I59)) -> 10374500 | N59: =L59+M59 -> 19521070 | O59: =L59 -> 9146570 | P59: =(P$130*M59)/M$130 -> 11847679 | Q59: =O59+P59 -> 20994249 | R59: =L59 -> 9146570 | S59: =(S$130*P59)/P$130 -> 14809599 | T59: =R59+S59 -> 23956169 | U59: =E59 -> 381107.08 | V59: =Y59/D59 -> 667666.08 | W59: =U59+V59 -> 1048773.2 | X59: =L59 -> 9146570 | Y59: =(Y$130*S59)/S$130 -> 16023986 | Z59: =X59+Y59 -> 25170556
A60: 46115 | B60: MAMPOSTERIA. | C60: m² | D60: =37+183+100 -> 320 | E60: ='3.4'!$I$22 -> 29083.526 | F60: ='3.4'!$I$36 -> 18703.125 | G60: ='3.4'!$I$50 -> 0 | H60: ='3.4'!$I$64 -> 250 | I60: ='3.4'!$I$78 -> 0 | J60: =SUM(F60:I60) -> 18953.125 | K60: =SUM(E60,J60) -> 48036.651 | L60: =$D60*E60 -> 9306728.5 | M60: =$D60*(SUM(F60:I60)) -> 6065000 | N60: =L60+M60 -> 15371728 | O60: =L60 -> 9306728.5 | P60: =(P$130*M60)/M$130 -> 6926230 | Q60: =O60+P60 -> 16232958 | R60: =L60 -> 9306728.5 | S60: =(S$130*P60)/P$130 -> 8657787.5 | T60: =R60+S60 -> 17964516 | U60: =E60 -> 29083.526 | V60: =Y60/D60 -> 29274.144 | W60: =U60+V60 -> 58357.67 | X60: =L60 -> 9306728.5 | Y60: =(Y$130*S60)/S$130 -> 9367726.1 | Z60: =X60+Y60 -> 18674455
A61: 46145 | B61: CONTRAPISO . e=12cm | C61: m² | D61: 270 | E61: ='3.5'!$I$22 -> 18509.528 | F61: ='3.5'!$I$36 -> 4277.7778 | G61: ='3.5'!$I$50 -> 0 | H61: ='3.5'!$I$64 -> 0 | I61: ='3.5'!$I$78 -> 14400 | J61: =SUM(F61:I61) -> 18677.778 | K61: =SUM(E61,J61) -> 37187.306 | L61: =$D61*E61 -> 4997572.5 | M61: =$D61*(SUM(F61:I61)) -> 5043000 | N61: =L61+M61 -> 10040572 | O61: =L61 -> 4997572.5 | P61: =(P$130*M61)/M$130 -> 5759106 | Q61: =O61+P61 -> 10756678 | R61: =L61 -> 4997572.5 | S61: =(S$130*P61)/P$130 -> 7198882.5 | T61: =R61+S61 -> 12196455 | U61: =E61 -> 18509.528 | V61: =Y61/D61 -> 28848.855 | W61: =U61+V61 -> 47358.383 | X61: =L61 -> 4997572.5 | Y61: =(Y$130*S61)/S$130 -> 7789190.9 | Z61: =X61+Y61 -> 12786763
A62: 46176 | B62: CARPETA . e=3cm | C62: m² | D62: 270 | E62: ='3.6'!$I$22 -> 4823.0741 | F62: ='3.6'!$I$36 -> 16777.778 | G62: ='3.6'!$I$50 -> 0 | H62: ='3.6'!$I$64 -> 0 | I62: ='3.6'!$I$78 -> 0 | J62: =SUM(F62:I62) -> 16777.778 | K62: =SUM(E62,J62) -> 21600.852 | L62: =$D62*E62 -> 1302230 | M62: =$D62*(SUM(F62:I62)) -> 4530000 | N62: =L62+M62 -> 5832230 | O62: =L62 -> 1302230 | P62: =(P$130*M62)/M$130 -> 5173260 | Q62: =O62+P62 -> 6475490 | R62: =L62 -> 1302230 | S62: =(S$130*P62)/P$130 -> 6466575 | T62: =R62+S62 -> 7768805 | U62: =E62 -> 4823.0741 | V62: =Y62/D62 -> 25914.201 | W62: =U62+V62 -> 30737.275 | X62: =L62 -> 1302230 | Y62: =(Y$130*S62)/S$130 -> 6996834.2 | Z62: =X62+Y62 -> 8299064.2
A63: 46206 | B63: REVOQUE INTERIOR. (GRUESO FRATAZADO) | C63: m² | D63: 244 | E63: ='3.7'!$I$22 -> 2908.3149 | F63: ='3.7'!$I$36 -> 25573.77 | G63: ='3.7'!$I$50 -> 0 | H63: ='3.7'!$I$64 -> 0 | I63: ='3.7'!$I$78 -> 0 | J63: =SUM(F63:I63) -> 25573.77 | K63: =SUM(E63,J63) -> 28482.085 | L63: =$D63*E63 -> 709628.84 | M63: =$D63*(SUM(F63:I63)) -> 6240000 | N63: =L63+M63 -> 6949628.8 | O63: =L63 -> 709628.84 | P63: =(P$130*M63)/M$130 -> 7126080 | Q63: =O63+P63 -> 7835708.8 | R63: =L63 -> 709628.84 | S63: =(S$130*P63)/P$130 -> 8907600 | T63: =R63+S63 -> 9617228.8 | U63: =E63 -> 2908.3149 | V63: =Y63/D63 -> 39500.095 | W63: =U63+V63 -> 42408.41 | X63: =L63 -> 709628.84 | Y63: =(Y$130*S63)/S$130 -> 9638023.2 | Z63: =X63+Y63 -> 10347652
A64: 46237 | B64: REVOQUE EXTERIOR (GRUESO FRATAZADO) CON HIDROFUGO. | C64: m² | D64: =284 -> 284 | E64: ='3.8'!$I$22 -> 3803.7469 | F64: ='3.8'!$I$36 -> 0 | G64: ='3.8'!$I$50 -> 0 | H64: ='3.8'!$I$64 -> 0 | I64: ='3.8'!$I$78 -> 37500 | J64: =SUM(F64:I64) -> 37500 | K64: =SUM(E64,J64) -> 41303.747 | L64: =$D64*E64 -> 1080264.1 | M64: =$D64*(SUM(F64:I64)) -> 10650000 | N64: =L64+M64 -> 11730264 | O64: =L64 -> 1080264.1 | P64: =(P$130*M64)/M$130 -> 12162300 | Q64: =O64+P64 -> 13242564 | R64: =L64 -> 1080264.1 | S64: =(S$130*P64)/P$130 -> 15202875 | T64: =R64+S64 -> 16283139 | U64: =E64 -> 3803.7469 | V64: =Y64/D64 -> 57920.812 | W64: =U64+V64 -> 61724.559 | X64: =L64 -> 1080264.1 | Y64: =(Y$130*S64)/S$130 -> 16449511 | Z64: =X64+Y64 -> 17529775
A65: OBRA GRIS - SOBRE TERCER PISO
A66: 46025 | B66: COLUMNAS Y TABIQUES | C66: m³ | D66: 18 | E66: ='3.1'!$I$22 -> 517211.35 | F66: ='3.1'!$I$36 -> 549166.67 | G66: ='3.1'!$I$50 -> 0 | H66: ='3.1'!$I$64 -> 14972.222 | I66: ='3.1'!$I$78 -> 0 | J66: =SUM(F66:I66) -> 564138.89 | K66: =SUM(E66,J66) -> 1081350.2 | L66: =$D66*E66 -> 9309804.2 | M66: =$D66*(SUM(F66:I66)) -> 10154500 | N66: =L66+M66 -> 19464304 | O66: =L66 -> 9309804.2 | P66: =(P$130*M66)/M$130 -> 11596439 | Q66: =O66+P66 -> 20906243 | R66: =L66 -> 9309804.2 | S66: =(S$130*P66)/P$130 -> 14495549 | T66: =R66+S66 -> 23805353 | U66: =E66 -> 517211.35 | V66: =Y66/D66 -> 871343.54 | W66: =U66+V66 -> 1388554.9 | X66: =L66 -> 9309804.2 | Y66: =(Y$130*S66)/S$130 -> 15684184 | Z66: =X66+Y66 -> 24993988
A67: 46056 | B67: VIGAS | C67: m³ | D67: 13 | E67: ='3.2'!$I$22 -> 631622.87 | F67: ='3.2'!$I$36 -> 760384.62 | G67: ='3.2'!$I$50 -> 0 | H67: ='3.2'!$I$64 -> 20730.769 | I67: ='3.2'!$I$78 -> 0 | J67: =SUM(F67:I67) -> 781115.38 | K67: =SUM(E67,J67) -> 1412738.3 | L67: =$D67*E67 -> 8211097.4 | M67: =$D67*(SUM(F67:I67)) -> 10154500 | N67: =L67+M67 -> 18365597 | O67: =L67 -> 8211097.4 | P67: =(P$130*M67)/M$130 -> 11596439 | Q67: =O67+P67 -> 19807536 | R67: =L67 -> 8211097.4 | S67: =(S$130*P67)/P$130 -> 14495549 | T67: =R67+S67 -> 22706646 | U67: =E67 -> 631622.87 | V67: =Y67/D67 -> 1206475.7 | W67: =U67+V67 -> 1838098.5 | X67: =L67 -> 8211097.4 | Y67: =(Y$130*S67)/S$130 -> 15684184 | Z67: =X67+Y67 -> 23895281
A68: 46084 | B68: LOSA | C68: m³ | D68: =21+3 -> 24 | E68: ='3.3'!$I$22 -> 381107.08 | F68: ='3.3'!$I$36 -> 411875 | G68: ='3.3'!$I$50 -> 0 | H68: ='3.3'!$I$64 -> 20395.833 | I68: ='3.3'!$I$78 -> 0 | J68: =SUM(F68:I68) -> 432270.83 | K68: =SUM(E68,J68) -> 813377.92 | L68: =$D68*E68 -> 9146570 | M68: =$D68*(SUM(F68:I68)) -> 10374500 | N68: =L68+M68 -> 19521070 | O68: =L68 -> 9146570 | P68: =(P$130*M68)/M$130 -> 11847679 | Q68: =O68+P68 -> 20994249 | R68: =L68 -> 9146570 | S68: =(S$130*P68)/P$130 -> 14809599 | T68: =R68+S68 -> 23956169 | U68: =E68 -> 381107.08 | V68: =Y68/D68 -> 667666.08 | W68: =U68+V68 -> 1048773.2 | X68: =L68 -> 9146570 | Y68: =(Y$130*S68)/S$130 -> 16023986 | Z68: =X68+Y68 -> 25170556
A69: 46115 | B69: MAMPOSTERIA. | C69: m² | D69: =37+183+100 -> 320 | E69: ='3.4'!$I$22 -> 29083.526 | F69: ='3.4'!$I$36 -> 18703.125 | G69: ='3.4'!$I$50 -> 0 | H69: ='3.4'!$I$64 -> 250 | I69: ='3.4'!$I$78 -> 0 | J69: =SUM(F69:I69) -> 18953.125 | K69: =SUM(E69,J69) -> 48036.651 | L69: =$D69*E69 -> 9306728.5 | M69: =$D69*(SUM(F69:I69)) -> 6065000 | N69: =L69+M69 -> 15371728 | O69: =L69 -> 9306728.5 | P69: =(P$130*M69)/M$130 -> 6926230 | Q69: =O69+P69 -> 16232958 | R69: =L69 -> 9306728.5 | S69: =(S$130*P69)/P$130 -> 8657787.5 | T69: =R69+S69 -> 17964516 | U69: =E69 -> 29083.526 | V69: =Y69/D69 -> 29274.144 | W69: =U69+V69 -> 58357.67 | X69: =L69 -> 9306728.5 | Y69: =(Y$130*S69)/S$130 -> 9367726.1 | Z69: =X69+Y69 -> 18674455
A70: 46145 | B70: CONTRAPISO . e=12cm | C70: m² | D70: 270 | E70: ='3.5'!$I$22 -> 18509.528 | F70: ='3.5'!$I$36 -> 4277.7778 | G70: ='3.5'!$I$50 -> 0 | H70: ='3.5'!$I$64 -> 0 | I70: ='3.5'!$I$78 -> 14400 | J70: =SUM(F70:I70) -> 18677.778 | K70: =SUM(E70,J70) -> 37187.306 | L70: =$D70*E70 -> 4997572.5 | M70: =$D70*(SUM(F70:I70)) -> 5043000 | N70: =L70+M70 -> 10040572 | O70: =L70 -> 4997572.5 | P70: =(P$130*M70)/M$130 -> 5759106 | Q70: =O70+P70 -> 10756678 | R70: =L70 -> 4997572.5 | S70: =(S$130*P70)/P$130 -> 7198882.5 | T70: =R70+S70 -> 12196455 | U70: =E70 -> 18509.528 | V70: =Y70/D70 -> 28848.855 | W70: =U70+V70 -> 47358.383 | X70: =L70 -> 4997572.5 | Y70: =(Y$130*S70)/S$130 -> 7789190.9 | Z70: =X70+Y70 -> 12786763
A71: 46176 | B71: CARPETA . e=3cm | C71: m² | D71: 270 | E71: ='3.6'!$I$22 -> 4823.0741 | F71: ='3.6'!$I$36 -> 16777.778 | G71: ='3.6'!$I$50 -> 0 | H71: ='3.6'!$I$64 -> 0 | I71: ='3.6'!$I$78 -> 0 | J71: =SUM(F71:I71) -> 16777.778 | K71: =SUM(E71,J71) -> 21600.852 | L71: =$D71*E71 -> 1302230 | M71: =$D71*(SUM(F71:I71)) -> 4530000 | N71: =L71+M71 -> 5832230 | O71: =L71 -> 1302230 | P71: =(P$130*M71)/M$130 -> 5173260 | Q71: =O71+P71 -> 6475490 | R71: =L71 -> 1302230 | S71: =(S$130*P71)/P$130 -> 6466575 | T71: =R71+S71 -> 7768805 | U71: =E71 -> 4823.0741 | V71: =Y71/D71 -> 25914.201 | W71: =U71+V71 -> 30737.275 | X71: =L71 -> 1302230 | Y71: =(Y$130*S71)/S$130 -> 6996834.2 | Z71: =X71+Y71 -> 8299064.2
A72: 46206 | B72: REVOQUE INTERIOR. (GRUESO FRATAZADO) | C72: m² | D72: 244 | E72: ='3.7'!$I$22 -> 2908.3149 | F72: ='3.7'!$I$36 -> 25573.77 | G72: ='3.7'!$I$50 -> 0 | H72: ='3.7'!$I$64 -> 0 | I72: ='3.7'!$I$78 -> 0 | J72: =SUM(F72:I72) -> 25573.77 | K72: =SUM(E72,J72) -> 28482.085 | L72: =$D72*E72 -> 709628.84 | M72: =$D72*(SUM(F72:I72)) -> 6240000 | N72: =L72+M72 -> 6949628.8 | O72: =L72 -> 709628.84 | P72: =(P$130*M72)/M$130 -> 7126080 | Q72: =O72+P72 -> 7835708.8 | R72: =L72 -> 709628.84 | S72: =(S$130*P72)/P$130 -> 8907600 | T72: =R72+S72 -> 9617228.8 | U72: =E72 -> 2908.3149 | V72: =Y72/D72 -> 39500.095 | W72: =U72+V72 -> 42408.41 | X72: =L72 -> 709628.84 | Y72: =(Y$130*S72)/S$130 -> 9638023.2 | Z72: =X72+Y72 -> 10347652
A73: 46237 | B73: REVOQUE EXTERIOR (GRUESO FRATAZADO) CON HIDROFUGO. | C73: m² | D73: =284 -> 284 | E73: ='3.8'!$I$22 -> 3803.7469 | F73: ='3.8'!$I$36 -> 0 | G73: ='3.8'!$I$50 -> 0 | H73: ='3.8'!$I$64 -> 0 | I73: ='3.8'!$I$78 -> 37500 | J73: =SUM(F73:I73) -> 37500 | K73: =SUM(E73,J73) -> 41303.747 | L73: =$D73*E73 -> 1080264.1 | M73: =$D73*(SUM(F73:I73)) -> 10650000 | N73: =L73+M73 -> 11730264 | O73: =L73 -> 1080264.1 | P73: =(P$130*M73)/M$130 -> 12162300 | Q73: =O73+P73 -> 13242564 | R73: =L73 -> 1080264.1 | S73: =(S$130*P73)/P$130 -> 15202875 | T73: =R73+S73 -> 16283139 | U73: =E73 -> 3803.7469 | V73: =Y73/D73 -> 57920.812 | W73: =U73+V73 -> 61724.559 | X73: =L73 -> 1080264.1 | Y73: =(Y$130*S73)/S$130 -> 16449511 | Z73: =X73+Y73 -> 17529775
A74: OBRA GRIS - SOBRE CUARTO PISO
A75: 46025 | B75: COLUMNAS Y TABIQUES | C75: m³ | D75: 18 | E75: ='3.1'!$I$22 -> 517211.35 | F75: ='3.1'!$I$36 -> 549166.67 | G75: ='3.1'!$I$50 -> 0 | H75: ='3.1'!$I$64 -> 14972.222 | I75: ='3.1'!$I$78 -> 0 | J75: =SUM(F75:I75) -> 564138.89 | K75: =SUM(E75,J75) -> 1081350.2 | L75: =$D75*E75 -> 9309804.2 | M75: =$D75*(SUM(F75:I75)) -> 10154500 | N75: =L75+M75 -> 19464304 | O75: =L75 -> 9309804.2 | P75: =(P$130*M75)/M$130 -> 11596439 | Q75: =O75+P75 -> 20906243 | R75: =L75 -> 9309804.2 | S75: =(S$130*P75)/P$130 -> 14495549 | T75: =R75+S75 -> 23805353 | U75: =E75 -> 517211.35 | V75: =Y75/D75 -> 871343.54 | W75: =U75+V75 -> 1388554.9 | X75: =L75 -> 9309804.2 | Y75: =(Y$130*S75)/S$130 -> 15684184 | Z75: =X75+Y75 -> 24993988
A76: 46056 | B76: VIGAS | C76: m³ | D76: 13 | E76: ='3.2'!$I$22 -> 631622.87 | F76: ='3.2'!$I$36 -> 760384.62 | G76: ='3.2'!$I$50 -> 0 | H76: ='3.2'!$I$64 -> 20730.769 | I76: ='3.2'!$I$78 -> 0 | J76: =SUM(F76:I76) -> 781115.38 | K76: =SUM(E76,J76) -> 1412738.3 | L76: =$D76*E76 -> 8211097.4 | M76: =$D76*(SUM(F76:I76)) -> 10154500 | N76: =L76+M76 -> 18365597 | O76: =L76 -> 8211097.4 | P76: =(P$130*M76)/M$130 -> 11596439 | Q76: =O76+P76 -> 19807536 | R76: =L76 -> 8211097.4 | S76: =(S$130*P76)/P$130 -> 14495549 | T76: =R76+S76 -> 22706646 | U76: =E76 -> 631622.87 | V76: =Y76/D76 -> 1206475.7 | W76: =U76+V76 -> 1838098.5 | X76: =L76 -> 8211097.4 | Y76: =(Y$130*S76)/S$130 -> 15684184 | Z76: =X76+Y76 -> 23895281
A77: 46084 | B77: LOSA | C77: m³ | D77: =21+3 -> 24 | E77: ='3.3'!$I$22 -> 381107.08 | F77: ='3.3'!$I$36 -> 411875 | G77: ='3.3'!$I$50 -> 0 | H77: ='3.3'!$I$64 -> 20395.833 | I77: ='3.3'!$I$78 -> 0 | J77: =SUM(F77:I77) -> 432270.83 | K77: =SUM(E77,J77) -> 813377.92 | L77: =$D77*E77 -> 9146570 | M77: =$D77*(SUM(F77:I77)) -> 10374500 | N77: =L77+M77 -> 19521070 | O77: =L77 -> 9146570 | P77: =(P$130*M77)/M$130 -> 11847679 | Q77: =O77+P77 -> 20994249 | R77: =L77 -> 9146570 | S77: =(S$130*P77)/P$130 -> 14809599 | T77: =R77+S77 -> 23956169 | U77: =E77 -> 381107.08 | V77: =Y77/D77 -> 667666.08 | W77: =U77+V77 -> 1048773.2 | X77: =L77 -> 9146570 | Y77: =(Y$130*S77)/S$130 -> 16023986 | Z77: =X77+Y77 -> 25170556
A78: 46115 | B78: MAMPOSTERIA. | C78: m² | D78: =37+183+100 -> 320 | E78: ='3.4'!$I$22 -> 29083.526 | F78: ='3.4'!$I$36 -> 18703.125 | G78: ='3.4'!$I$50 -> 0 | H78: ='3.4'!$I$64 -> 250 | I78: ='3.4'!$I$78 -> 0 | J78: =SUM(F78:I78) -> 18953.125 | K78: =SUM(E78,J78) -> 48036.651 | L78: =$D78*E78 -> 9306728.5 | M78: =$D78*(SUM(F78:I78)) -> 6065000 | N78: =L78+M78 -> 15371728 | O78: =L78 -> 9306728.5 | P78: =(P$130*M78)/M$130 -> 6926230 | Q78: =O78+P78 -> 16232958 | R78: =L78 -> 9306728.5 | S78: =(S$130*P78)/P$130 -> 8657787.5 | T78: =R78+S78 -> 17964516 | U78: =E78 -> 29083.526 | V78: =Y78/D78 -> 29274.144 | W78: =U78+V78 -> 58357.67 | X78: =L78 -> 9306728.5 | Y78: =(Y$130*S78)/S$130 -> 9367726.1 | Z78: =X78+Y78 -> 18674455
A79: 46145 | B79: CONTRAPISO . e=12cm | C79: m² | D79: 270 | E79: ='3.5'!$I$22 -> 18509.528 | F79: ='3.5'!$I$36 -> 4277.7778 | G79: ='3.5'!$I$50 -> 0 | H79: ='3.5'!$I$64 -> 0 | I79: ='3.5'!$I$78 -> 14400 | J79: =SUM(F79:I79) -> 18677.778 | K79: =SUM(E79,J79) -> 37187.306 | L79: =$D79*E79 -> 4997572.5 | M79: =$D79*(SUM(F79:I79)) -> 5043000 | N79: =L79+M79 -> 10040572 | O79: =L79 -> 4997572.5 | P79: =(P$130*M79)/M$130 -> 5759106 | Q79: =O79+P79 -> 10756678 | R79: =L79 -> 4997572.5 | S79: =(S$130*P79)/P$130 -> 7198882.5 | T79: =R79+S79 -> 12196455 | U79: =E79 -> 18509.528 | V79: =Y79/D79 -> 28848.855 | W79: =U79+V79 -> 47358.383 | X79: =L79 -> 4997572.5 | Y79: =(Y$130*S79)/S$130 -> 7789190.9 | Z79: =X79+Y79 -> 12786763
A80: 46176 | B80: CARPETA . e=3cm | C80: m² | D80: 270 | E80: ='3.6'!$I$22 -> 4823.0741 | F80: ='3.6'!$I$36 -> 16777.778 | G80: ='3.6'!$I$50 -> 0 | H80: ='3.6'!$I$64 -> 0 | I80: ='3.6'!$I$78 -> 0 | J80: =SUM(F80:I80) -> 16777.778 | K80: =SUM(E80,J80) -> 21600.852 | L80: =$D80*E80 -> 1302230 | M80: =$D80*(SUM(F80:I80)) -> 4530000 | N80: =L80+M80 -> 5832230 | O80: =L80 -> 1302230 | P80: =(P$130*M80)/M$130 -> 5173260 | Q80: =O80+P80 -> 6475490 | R80: =L80 -> 1302230 | S80: =(S$130*P80)/P$130 -> 6466575 | T80: =R80+S80 -> 7768805 | U80: =E80 -> 4823.0741 | V80: =Y80/D80 -> 25914.201 | W80: =U80+V80 -> 30737.275 | X80: =L80 -> 1302230 | Y80: =(Y$130*S80)/S$130 -> 6996834.2 | Z80: =X80+Y80 -> 8299064.2
A81: 46206 | B81: REVOQUE INTERIOR. (GRUESO FRATAZADO) | C81: m² | D81: 244 | E81: ='3.7'!$I$22 -> 2908.3149 | F81: ='3.7'!$I$36 -> 25573.77 | G81: ='3.7'!$I$50 -> 0 | H81: ='3.7'!$I$64 -> 0 | I81: ='3.7'!$I$78 -> 0 | J81: =SUM(F81:I81) -> 25573.77 | K81: =SUM(E81,J81) -> 28482.085 | L81: =$D81*E81 -> 709628.84 | M81: =$D81*(SUM(F81:I81)) -> 6240000 | N81: =L81+M81 -> 6949628.8 | O81: =L81 -> 709628.84 | P81: =(P$130*M81)/M$130 -> 7126080 | Q81: =O81+P81 -> 7835708.8 | R81: =L81 -> 709628.84 | S81: =(S$130*P81)/P$130 -> 8907600 | T81: =R81+S81 -> 9617228.8 | U81: =E81 -> 2908.3149 | V81: =Y81/D81 -> 39500.095 | W81: =U81+V81 -> 42408.41 | X81: =L81 -> 709628.84 | Y81: =(Y$130*S81)/S$130 -> 9638023.2 | Z81: =X81+Y81 -> 10347652
A82: 46237 | B82: REVOQUE EXTERIOR (GRUESO FRATAZADO) CON HIDROFUGO. | C82: m² | D82: =284 -> 284 | E82: ='3.8'!$I$22 -> 3803.7469 | F82: ='3.8'!$I$36 -> 0 | G82: ='3.8'!$I$50 -> 0 | H82: ='3.8'!$I$64 -> 0 | I82: ='3.8'!$I$78 -> 37500 | J82: =SUM(F82:I82) -> 37500 | K82: =SUM(E82,J82) -> 41303.747 | L82: =$D82*E82 -> 1080264.1 | M82: =$D82*(SUM(F82:I82)) -> 10650000 | N82: =L82+M82 -> 11730264 | O82: =L82 -> 1080264.1 | P82: =(P$130*M82)/M$130 -> 12162300 | Q82: =O82+P82 -> 13242564 | R82: =L82 -> 1080264.1 | S82: =(S$130*P82)/P$130 -> 15202875 | T82: =R82+S82 -> 16283139 | U82: =E82 -> 3803.7469 | V82: =Y82/D82 -> 57920.812 | W82: =U82+V82 -> 61724.559 | X82: =L82 -> 1080264.1 | Y82: =(Y$130*S82)/S$130 -> 16449511 | Z82: =X82+Y82 -> 17529775
A83: OBRA GRIS - SOBRE QUINTO PISO
A84: 46025 | B84: COLUMNAS Y TABIQUES | C84: m³ | D84: 18 | E84: ='3.1'!$I$22 -> 517211.35 | F84: ='3.1'!$I$36 -> 549166.67 | G84: ='3.1'!$I$50 -> 0 | H84: ='3.1'!$I$64 -> 14972.222 | I84: ='3.1'!$I$78 -> 0 | J84: =SUM(F84:I84) -> 564138.89 | K84: =SUM(E84,J84) -> 1081350.2 | L84: =$D84*E84 -> 9309804.2 | M84: =$D84*(SUM(F84:I84)) -> 10154500 | N84: =L84+M84 -> 19464304 | O84: =L84 -> 9309804.2 | P84: =(P$130*M84)/M$130 -> 11596439 | Q84: =O84+P84 -> 20906243 | R84: =L84 -> 9309804.2 | S84: =(S$130*P84)/P$130 -> 14495549 | T84: =R84+S84 -> 23805353 | U84: =E84 -> 517211.35 | V84: =Y84/D84 -> 871343.54 | W84: =U84+V84 -> 1388554.9 | X84: =L84 -> 9309804.2 | Y84: =(Y$130*S84)/S$130 -> 15684184 | Z84: =X84+Y84 -> 24993988
A85: 46056 | B85: VIGAS | C85: m³ | D85: 13 | E85: ='3.2'!$I$22 -> 631622.87 | F85: ='3.2'!$I$36 -> 760384.62 | G85: ='3.2'!$I$50 -> 0 | H85: ='3.2'!$I$64 -> 20730.769 | I85: ='3.2'!$I$78 -> 0 | J85: =SUM(F85:I85) -> 781115.38 | K85: =SUM(E85,J85) -> 1412738.3 | L85: =$D85*E85 -> 8211097.4 | M85: =$D85*(SUM(F85:I85)) -> 10154500 | N85: =L85+M85 -> 18365597 | O85: =L85 -> 8211097.4 | P85: =(P$130*M85)/M$130 -> 11596439 | Q85: =O85+P85 -> 19807536 | R85: =L85 -> 8211097.4 | S85: =(S$130*P85)/P$130 -> 14495549 | T85: =R85+S85 -> 22706646 | U85: =E85 -> 631622.87 | V85: =Y85/D85 -> 1206475.7 | W85: =U85+V85 -> 1838098.5 | X85: =L85 -> 8211097.4 | Y85: =(Y$130*S85)/S$130 -> 15684184 | Z85: =X85+Y85 -> 23895281
A86: 46084 | B86: LOSA | C86: m³ | D86: =21+3 -> 24 | E86: ='3.3'!$I$22 -> 381107.08 | F86: ='3.3'!$I$36 -> 411875 | G86: ='3.3'!$I$50 -> 0 | H86: ='3.3'!$I$64 -> 20395.833 | I86: ='3.3'!$I$78 -> 0 | J86: =SUM(F86:I86) -> 432270.83 | K86: =SUM(E86,J86) -> 813377.92 | L86: =$D86*E86 -> 9146570 | M86: =$D86*(SUM(F86:I86)) -> 10374500 | N86: =L86+M86 -> 19521070 | O86: =L86 -> 9146570 | P86: =(P$130*M86)/M$130 -> 11847679 | Q86: =O86+P86 -> 20994249 | R86: =L86 -> 9146570 | S86: =(S$130*P86)/P$130 -> 14809599 | T86: =R86+S86 -> 23956169 | U86: =E86 -> 381107.08 | V86: =Y86/D86 -> 667666.08 | W86: =U86+V86 -> 1048773.2 | X86: =L86 -> 9146570 | Y86: =(Y$130*S86)/S$130 -> 16023986 | Z86: =X86+Y86 -> 25170556
A87: 46115 | B87: MAMPOSTERIA. | C87: m² | D87: =37+183+100 -> 320 | E87: ='3.4'!$I$22 -> 29083.526 | F87: ='3.4'!$I$36 -> 18703.125 | G87: ='3.4'!$I$50 -> 0 | H87: ='3.4'!$I$64 -> 250 | I87: ='3.4'!$I$78 -> 0 | J87: =SUM(F87:I87) -> 18953.125 | K87: =SUM(E87,J87) -> 48036.651 | L87: =$D87*E87 -> 9306728.5 | M87: =$D87*(SUM(F87:I87)) -> 6065000 | N87: =L87+M87 -> 15371728 | O87: =L87 -> 9306728.5 | P87: =(P$130*M87)/M$130 -> 6926230 | Q87: =O87+P87 -> 16232958 | R87: =L87 -> 9306728.5 | S87: =(S$130*P87)/P$130 -> 8657787.5 | T87: =R87+S87 -> 17964516 | U87: =E87 -> 29083.526 | V87: =Y87/D87 -> 29274.144 | W87: =U87+V87 -> 58357.67 | X87: =L87 -> 9306728.5 | Y87: =(Y$130*S87)/S$130 -> 9367726.1 | Z87: =X87+Y87 -> 18674455
A88: 46145 | B88: CONTRAPISO . e=12cm | C88: m² | D88: 270 | E88: ='3.5'!$I$22 -> 18509.528 | F88: ='3.5'!$I$36 -> 4277.7778 | G88: ='3.5'!$I$50 -> 0 | H88: ='3.5'!$I$64 -> 0 | I88: ='3.5'!$I$78 -> 14400 | J88: =SUM(F88:I88) -> 18677.778 | K88: =SUM(E88,J88) -> 37187.306 | L88: =$D88*E88 -> 4997572.5 | M88: =$D88*(SUM(F88:I88)) -> 5043000 | N88: =L88+M88 -> 10040572 | O88: =L88 -> 4997572.5 | P88: =(P$130*M88)/M$130 -> 5759106 | Q88: =O88+P88 -> 10756678 | R88: =L88 -> 4997572.5 | S88: =(S$130*P88)/P$130 -> 7198882.5 | T88: =R88+S88 -> 12196455 | U88: =E88 -> 18509.528 | V88: =Y88/D88 -> 28848.855 | W88: =U88+V88 -> 47358.383 | X88: =L88 -> 4997572.5 | Y88: =(Y$130*S88)/S$130 -> 7789190.9 | Z88: =X88+Y88 -> 12786763
A89: 46176 | B89: CARPETA . e=3cm | C89: m² | D89: 270 | E89: ='3.6'!$I$22 -> 4823.0741 | F89: ='3.6'!$I$36 -> 16777.778 | G89: ='3.6'!$I$50 -> 0 | H89: ='3.6'!$I$64 -> 0 | I89: ='3.6'!$I$78 -> 0 | J89: =SUM(F89:I89) -> 16777.778 | K89: =SUM(E89,J89) -> 21600.852 | L89: =$D89*E89 -> 1302230 | M89: =$D89*(SUM(F89:I89)) -> 4530000 | N89: =L89+M89 -> 5832230 | O89: =L89 -> 1302230 | P89: =(P$130*M89)/M$130 -> 5173260 | Q89: =O89+P89 -> 6475490 | R89: =L89 -> 1302230 | S89: =(S$130*P89)/P$130 -> 6466575 | T89: =R89+S89 -> 7768805 | U89: =E89 -> 4823.0741 | V89: =Y89/D89 -> 25914.201 | W89: =U89+V89 -> 30737.275 | X89: =L89 -> 1302230 | Y89: =(Y$130*S89)/S$130 -> 6996834.2 | Z89: =X89+Y89 -> 8299064.2
A90: 46206 | B90: REVOQUE INTERIOR. (GRUESO FRATAZADO) | C90: m² | D90: 244 | E90: ='3.7'!$I$22 -> 2908.3149 | F90: ='3.7'!$I$36 -> 25573.77 | G90: ='3.7'!$I$50 -> 0 | H90: ='3.7'!$I$64 -> 0 | I90: ='3.7'!$I$78 -> 0 | J90: =SUM(F90:I90) -> 25573.77 | K90: =SUM(E90,J90) -> 28482.085 | L90: =$D90*E90 -> 709628.84 | M90: =$D90*(SUM(F90:I90)) -> 6240000 | N90: =L90+M90 -> 6949628.8 | O90: =L90 -> 709628.84 | P90: =(P$130*M90)/M$130 -> 7126080 | Q90: =O90+P90 -> 7835708.8 | R90: =L90 -> 709628.84 | S90: =(S$130*P90)/P$130 -> 8907600 | T90: =R90+S90 -> 9617228.8 | U90: =E90 -> 2908.3149 | V90: =Y90/D90 -> 39500.095 | W90: =U90+V90 -> 42408.41 | X90: =L90 -> 709628.84 | Y90: =(Y$130*S90)/S$130 -> 9638023.2 | Z90: =X90+Y90 -> 10347652
A91: 46237 | B91: REVOQUE EXTERIOR (GRUESO FRATAZADO) CON HIDROFUGO. | C91: m² | D91: =284 -> 284 | E91: ='3.8'!$I$22 -> 3803.7469 | F91: ='3.8'!$I$36 -> 0 | G91: ='3.8'!$I$50 -> 0 | H91: ='3.8'!$I$64 -> 0 | I91: ='3.8'!$I$78 -> 37500 | J91: =SUM(F91:I91) -> 37500 | K91: =SUM(E91,J91) -> 41303.747 | L91: =$D91*E91 -> 1080264.1 | M91: =$D91*(SUM(F91:I91)) -> 10650000 | N91: =L91+M91 -> 11730264 | O91: =L91 -> 1080264.1 | P91: =(P$130*M91)/M$130 -> 12162300 | Q91: =O91+P91 -> 13242564 | R91: =L91 -> 1080264.1 | S91: =(S$130*P91)/P$130 -> 15202875 | T91: =R91+S91 -> 16283139 | U91: =E91 -> 3803.7469 | V91: =Y91/D91 -> 57920.812 | W91: =U91+V91 -> 61724.559 | X91: =L91 -> 1080264.1 | Y91: =(Y$130*S91)/S$130 -> 16449511 | Z91: =X91+Y91 -> 17529775
A92: OBRA GRIS - SOBRE SEXTO PISO
A93: 46025 | B93: COLUMNAS Y TABIQUES | C93: m³ | D93: 18 | E93: ='3.1'!$I$22 -> 517211.35 | F93: ='3.1'!$I$36 -> 549166.67 | G93: ='3.1'!$I$50 -> 0 | H93: ='3.1'!$I$64 -> 14972.222 | I93: ='3.1'!$I$78 -> 0 | J93: =SUM(F93:I93) -> 564138.89 | K93: =SUM(E93,J93) -> 1081350.2 | L93: =$D93*E93 -> 9309804.2 | M93: =$D93*(SUM(F93:I93)) -> 10154500 | N93: =L93+M93 -> 19464304 | O93: =L93 -> 9309804.2 | P93: =(P$130*M93)/M$130 -> 11596439 | Q93: =O93+P93 -> 20906243 | R93: =L93 -> 9309804.2 | S93: =(S$130*P93)/P$130 -> 14495549 | T93: =R93+S93 -> 23805353 | U93: =E93 -> 517211.35 | V93: =Y93/D93 -> 871343.54 | W93: =U93+V93 -> 1388554.9 | X93: =L93 -> 9309804.2 | Y93: =(Y$130*S93)/S$130 -> 15684184 | Z93: =X93+Y93 -> 24993988
A94: 46056 | B94: VIGAS | C94: m³ | D94: 13 | E94: ='3.2'!$I$22 -> 631622.87 | F94: ='3.2'!$I$36 -> 760384.62 | G94: ='3.2'!$I$50 -> 0 | H94: ='3.2'!$I$64 -> 20730.769 | I94: ='3.2'!$I$78 -> 0 | J94: =SUM(F94:I94) -> 781115.38 | K94: =SUM(E94,J94) -> 1412738.3 | L94: =$D94*E94 -> 8211097.4 | M94: =$D94*(SUM(F94:I94)) -> 10154500 | N94: =L94+M94 -> 18365597 | O94: =L94 -> 8211097.4 | P94: =(P$130*M94)/M$130 -> 11596439 | Q94: =O94+P94 -> 19807536 | R94: =L94 -> 8211097.4 | S94: =(S$130*P94)/P$130 -> 14495549 | T94: =R94+S94 -> 22706646 | U94: =E94 -> 631622.87 | V94: =Y94/D94 -> 1206475.7 | W94: =U94+V94 -> 1838098.5 | X94: =L94 -> 8211097.4 | Y94: =(Y$130*S94)/S$130 -> 15684184 | Z94: =X94+Y94 -> 23895281
A95: 46084 | B95: LOSA | C95: m³ | D95: =21+3 -> 24 | E95: ='3.3'!$I$22 -> 381107.08 | F95: ='3.3'!$I$36 -> 411875 | G95: ='3.3'!$I$50 -> 0 | H95: ='3.3'!$I$64 -> 20395.833 | I95: ='3.3'!$I$78 -> 0 | J95: =SUM(F95:I95) -> 432270.83 | K95: =SUM(E95,J95) -> 813377.92 | L95: =$D95*E95 -> 9146570 | M95: =$D95*(SUM(F95:I95)) -> 10374500 | N95: =L95+M95 -> 19521070 | O95: =L95 -> 9146570 | P95: =(P$130*M95)/M$130 -> 11847679 | Q95: =O95+P95 -> 20994249 | R95: =L95 -> 9146570 | S95: =(S$130*P95)/P$130 -> 14809599 | T95: =R95+S95 -> 23956169 | U95: =E95 -> 381107.08 | V95: =Y95/D95 -> 667666.08 | W95: =U95+V95 -> 1048773.2 | X95: =L95 -> 9146570 | Y95: =(Y$130*S95)/S$130 -> 16023986 | Z95: =X95+Y95 -> 25170556
A96: 46115 | B96: MAMPOSTERIA. | C96: m² | D96: =37+183+100 -> 320 | E96: ='3.4'!$I$22 -> 29083.526 | F96: ='3.4'!$I$36 -> 18703.125 | G96: ='3.4'!$I$50 -> 0 | H96: ='3.4'!$I$64 -> 250 | I96: ='3.4'!$I$78 -> 0 | J96: =SUM(F96:I96) -> 18953.125 | K96: =SUM(E96,J96) -> 48036.651 | L96: =$D96*E96 -> 9306728.5 | M96: =$D96*(SUM(F96:I96)) -> 6065000 | N96: =L96+M96 -> 15371728 | O96: =L96 -> 9306728.5 | P96: =(P$130*M96)/M$130 -> 6926230 | Q96: =O96+P96 -> 16232958 | R96: =L96 -> 9306728.5 | S96: =(S$130*P96)/P$130 -> 8657787.5 | T96: =R96+S96 -> 17964516 | U96: =E96 -> 29083.526 | V96: =Y96/D96 -> 29274.144 | W96: =U96+V96 -> 58357.67 | X96: =L96 -> 9306728.5 | Y96: =(Y$130*S96)/S$130 -> 9367726.1 | Z96: =X96+Y96 -> 18674455
A97: 46145 | B97: CONTRAPISO . e=12cm | C97: m² | D97: 270 | E97: ='3.5'!$I$22 -> 18509.528 | F97: ='3.5'!$I$36 -> 4277.7778 | G97: ='3.5'!$I$50 -> 0 | H97: ='3.5'!$I$64 -> 0 | I97: ='3.5'!$I$78 -> 14400 | J97: =SUM(F97:I97) -> 18677.778 | K97: =SUM(E97,J97) -> 37187.306 | L97: =$D97*E97 -> 4997572.5 | M97: =$D97*(SUM(F97:I97)) -> 5043000 | N97: =L97+M97 -> 10040572 | O97: =L97 -> 4997572.5 | P97: =(P$130*M97)/M$130 -> 5759106 | Q97: =O97+P97 -> 10756678 | R97: =L97 -> 4997572.5 | S97: =(S$130*P97)/P$130 -> 7198882.5 | T97: =R97+S97 -> 12196455 | U97: =E97 -> 18509.528 | V97: =Y97/D97 -> 28848.855 | W97: =U97+V97 -> 47358.383 | X97: =L97 -> 4997572.5 | Y97: =(Y$130*S97)/S$130 -> 7789190.9 | Z97: =X97+Y97 -> 12786763
A98: 46176 | B98: CARPETA . e=3cm | C98: m² | D98: 270 | E98: ='3.6'!$I$22 -> 4823.0741 | F98: ='3.6'!$I$36 -> 16777.778 | G98: ='3.6'!$I$50 -> 0 | H98: ='3.6'!$I$64 -> 0 | I98: ='3.6'!$I$78 -> 0 | J98: =SUM(F98:I98) -> 16777.778 | K98: =SUM(E98,J98) -> 21600.852 | L98: =$D98*E98 -> 1302230 | M98: =$D98*(SUM(F98:I98)) -> 4530000 | N98: =L98+M98 -> 5832230 | O98: =L98 -> 1302230 | P98: =(P$130*M98)/M$130 -> 5173260 | Q98: =O98+P98 -> 6475490 | R98: =L98 -> 1302230 | S98: =(S$130*P98)/P$130 -> 6466575 | T98: =R98+S98 -> 7768805 | U98: =E98 -> 4823.0741 | V98: =Y98/D98 -> 25914.201 | W98: =U98+V98 -> 30737.275 | X98: =L98 -> 1302230 | Y98: =(Y$130*S98)/S$130 -> 6996834.2 | Z98: =X98+Y98 -> 8299064.2
A99: 46206 | B99: REVOQUE INTERIOR. (GRUESO FRATAZADO) | C99: m² | D99: 244 | E99: ='3.7'!$I$22 -> 2908.3149 | F99: ='3.7'!$I$36 -> 25573.77 | G99: ='3.7'!$I$50 -> 0 | H99: ='3.7'!$I$64 -> 0 | I99: ='3.7'!$I$78 -> 0 | J99: =SUM(F99:I99) -> 25573.77 | K99: =SUM(E99,J99) -> 28482.085 | L99: =$D99*E99 -> 709628.84 | M99: =$D99*(SUM(F99:I99)) -> 6240000 | N99: =L99+M99 -> 6949628.8 | O99: =L99 -> 709628.84 | P99: =(P$130*M99)/M$130 -> 7126080 | Q99: =O99+P99 -> 7835708.8 | R99: =L99 -> 709628.84 | S99: =(S$130*P99)/P$130 -> 8907600 | T99: =R99+S99 -> 9617228.8 | U99: =E99 -> 2908.3149 | V99: =Y99/D99 -> 39500.095 | W99: =U99+V99 -> 42408.41 | X99: =L99 -> 709628.84 | Y99: =(Y$130*S99)/S$130 -> 9638023.2 | Z99: =X99+Y99 -> 10347652
A100: 46237 | B100: REVOQUE EXTERIOR (GRUESO FRATAZADO) CON HIDROFUGO. | C100: m² | D100: =284 -> 284 | E100: ='3.8'!$I$22 -> 3803.7469 | F100: ='3.8'!$I$36 -> 0 | G100: ='3.8'!$I$50 -> 0 | H100: ='3.8'!$I$64 -> 0 | I100: ='3.8'!$I$78 -> 37500 | J100: =SUM(F100:I100) -> 37500 | K100: =SUM(E100,J100) -> 41303.747 | L100: =$D100*E100 -> 1080264.1 | M100: =$D100*(SUM(F100:I100)) -> 10650000 | N100: =L100+M100 -> 11730264 | O100: =L100 -> 1080264.1 | P100: =(P$130*M100)/M$130 -> 12162300 | Q100: =O100+P100 -> 13242564 | R100: =L100 -> 1080264.1 | S100: =(S$130*P100)/P$130 -> 15202875 | T100: =R100+S100 -> 16283139 | U100: =E100 -> 3803.7469 | V100: =Y100/D100 -> 57920.812 | W100: =U100+V100 -> 61724.559 | X100: =L100 -> 1080264.1 | Y100: =(Y$130*S100)/S$130 -> 16449511 | Z100: =X100+Y100 -> 17529775
A101: OBRA GRIS - SOBRE SEPTIMO PISO
A102: 46025 | B102: COLUMNAS Y TABIQUES | C102: m³ | D102: 18 | E102: ='3.1'!$I$22 -> 517211.35 | F102: ='3.1'!$I$36 -> 549166.67 | G102: ='3.1'!$I$50 -> 0 | H102: ='3.1'!$I$64 -> 14972.222 | I102: ='3.1'!$I$78 -> 0 | J102: =SUM(F102:I102) -> 564138.89 | K102: =SUM(E102,J102) -> 1081350.2 | L102: =$D102*E102 -> 9309804.2 | M102: =$D102*(SUM(F102:I102)) -> 10154500 | N102: =L102+M102 -> 19464304 | O102: =L102 -> 9309804.2 | P102: =(P$130*M102)/M$130 -> 11596439 | Q102: =O102+P102 -> 20906243 | R102: =L102 -> 9309804.2 | S102: =(S$130*P102)/P$130 -> 14495549 | T102: =R102+S102 -> 23805353 | U102: =E102 -> 517211.35 | V102: =Y102/D102 -> 871343.54 | W102: =U102+V102 -> 1388554.9 | X102: =L102 -> 9309804.2 | Y102: =(Y$130*S102)/S$130 -> 15684184 | Z102: =X102+Y102 -> 24993988
...

Sheet 01_VENTA
A1: EDIFICIO LAS HERAS
A3: Pilar, 04 de Marzo de 2026.
A5: PLANILLA COMPUTO Y PRESPUPUESTO
A7: ITEM | B7: DESCRIPCIÓN | C7: UNIDAD | D7: CANTIDAD | E7: TOTAL (NETO)
E8: V. UNITARIO | H8: V.GENERAL
E9: MAT. | F9: M.O | G9: GENERAL | H9: MAT. | I9: M.O | J9: GENERAL
A10: 1- TAREAS PRELIMINARES
A11: ='01_C&P'!A9 -> 0.1 | B11: ='01_C&P'!B9 -> OBRADOR | C11: ='01_C&P'!C9 -> mes | D11: ='01_C&P'!D9 -> 16 | E11: ='01_C&P'!U9 | F11: ='01_C&P'!V9 -> 1081188.5 | G11: ='01_C&P'!W9 -> 1081188.5 | H11: ='01_C&P'!X9 -> 0 | I11: ='01_C&P'!Y9 -> 17299016 | J11: =H11+I11 -> 17299016
A12: ='01_C&P'!A10 -> 0.2 | B12: ='01_C&P'!B10 -> BANOS QUIMICOS (2) | C12: ='01_C&P'!C10 -> mes | D12: ='01_C&P'!D10 -> 16 | E12: ='01_C&P'!U10 | F12: ='01_C&P'!V10 -> 370693.2 | G12: ='01_C&P'!W10 -> 370693.2 | H12: ='01_C&P'!X10 -> 0 | I12: ='01_C&P'!Y10 -> 5931091.2 | J12: =H12+I12 -> 5931091.2
A13: ='01_C&P'!A11 -> 0.3 | B13: ='01_C&P'!B11 -> INSTALACIONES PROVISORIAS | C13: ='01_C&P'!C11 -> gl | D13: ='01_C&P'!D11 -> 1 | E13: ='01_C&P'!U11 | F13: ='01_C&P'!V11 -> 7722775 | G13: ='01_C&P'!W11 -> 7722775 | H13: ='01_C&P'!X11 -> 0 | I13: ='01_C&P'!Y11 -> 7722775 | J13: =H13+I13 -> 7722775
A14: ='01_C&P'!A12 -> 0.4 | B14: ='01_C&P'!B12 -> LIMPIEZA PERIODICA DE OBRA | C14: ='01_C&P'!C12 -> mes | D14: ='01_C&P'!D12 -> 16 | E14: ='01_C&P'!U12 | F14: ='01_C&P'!V12 -> 1544555 | G14: ='01_C&P'!W12 -> 1544555 | H14: ='01_C&P'!X12 -> 0 | I14: ='01_C&P'!Y12 -> 24712880 | J14: =H14+I14 -> 24712880
A15: ='01_C&P'!A13 -> 0.5 | B15: ='01_C&P'!B13 -> ACARREO DE MATERIALES | C15: ='01_C&P'!C13 -> mes | D15: ='01_C&P'!D13 -> 16 | E15: ='01_C&P'!U13 | F15: ='01_C&P'!V13 -> 1544555 | G15: ='01_C&P'!W13 -> 1544555 | H15: ='01_C&P'!X13 -> 0 | I15: ='01_C&P'!Y13 -> 24712880 | J15: =H15+I15 -> 24712880
A16: ='01_C&P'!A14 -> 0.6 | B16: ='01_C&P'!B14 -> AYUDA DE GREMIOS | C16: ='01_C&P'!C14 -> mes | D16: ='01_C&P'!D14 -> 16 | E16: ='01_C&P'!U14 | F16: ='01_C&P'!V14 -> 4633665 | G16: ='01_C&P'!W14 -> 4633665 | H16: ='01_C&P'!X14 -> 0 | I16: ='01_C&P'!Y14 -> 74138640 | J16: =H16+I16 -> 74138640
A17: ='01_C&P'!A15 -> 0.7 | B17: ='01_C&P'!B15 -> LIMPIEZA FINAL | C17: ='01_C&P'!C15 -> gl | D17: ='01_C&P'!D15 -> 1 | E17: ='01_C&P'!U15 | F17: ='01_C&P'!V15 -> 3089110 | G17: ='01_C&P'!W15 -> 3089110 | H17: ='01_C&P'!X15 -> 0 | I17: ='01_C&P'!Y15 -> 3089110 | J17: =H17+I17 -> 3089110
A18: ='01_C&P'!A16 -> 0.8 | B18: ='01_C&P'!B16 -> ESTRUCTURA DE ENCOFRADO Y APUNTALAMIENTO PROVISORIO | C18: ='01_C&P'!C16 -> gl | D18: ='01_C&P'!D16 -> 1 | E18: ='01_C&P'!U16 | F18: ='01_C&P'!V16 -> 1.9946792e+08 | G18: ='01_C&P'!W16 -> 1.9946792e+08 | H18: ='01_C&P'!X16 -> 0 | I18: ='01_C&P'!Y16 -> 1.9946792e+08 | J18: =H18+I18 -> 1.9946792e+08
A19: ='01_C&P'!A17 -> EXCAVACION
A20: ='01_C&P'!A18 -> 0.9 | B20: ='01_C&P'!B18 -> EXCAVACION BASES Y TRONCOS | C20: ='01_C&P'!C18 -> m³ | D20: ='01_C&P'!D18 -> 366.36 | E20: ='01_C&P'!U18 -> 0 | F20: ='01_C&P'!V18 -> 57927.136 | G20: ='01_C&P'!W18 -> 57927.136 | H20: ='01_C&P'!X18 -> 0 | I20: ='01_C&P'!Y18 -> 21222186 | J20: =H20+I20 -> 21222186
A21: ='01_C&P'!A19 -> 0.10 | B21: ='01_C&P'!B19 -> EXCAVACION TENSORES | C21: ='01_C&P'!C19 -> m³ | D21: ='01_C&P'!D19 -> 5.4 | E21: ='01_C&P'!U19 -> 0 | F21: ='01_C&P'!V19 -> 77227.75 | G21: ='01_C&P'!W19 -> 77227.75 | H21: ='01_C&P'!X19 -> 0 | I21: ='01_C&P'!Y19 -> 417029.85 | J21: =H21+I21 -> 417029.85
A22: ='01_C&P'!A20 -> 0.11 | B22: ='01_C&P'!B20 -> EXCAVACION TRONERAS | C22: ='01_C&P'!C20 -> m³ | D22: ='01_C&P'!D20 -> 276 | E22: ='01_C&P'!U20 -> 0 | F22: ='01_C&P'!V20 -> 57920.812 | G22: ='01_C&P'!W20 -> 57920.812 | H22: ='01_C&P'!X20 -> 0 | I22: ='01_C&P'!Y20 -> 15986144 | J22: =H22+I22 -> 15986144
A23: ='01_C&P'!A21 -> OBRA GRIS - FUNDACIONES
A24: ='01_C&P'!A22 -> 0.12 | B24: ='01_C&P'!B22 -> BASES | C24: ='01_C&P'!C22 -> m³ | D24: ='01_C&P'!D22 -> 108 | E24: ='01_C&P'!U22 -> 264204.49 | F24: ='01_C&P'!V22 -> 109835.02 | G24: ='01_C&P'!W22 -> 374039.51 | H24: ='01_C&P'!X22 -> 28534084 | I24: ='01_C&P'!Y22 -> 11862182 | J24: =H24+I24 -> 40396267
A25: ='01_C&P'!A23 -> 0.13 | B25: ='01_C&P'!B23 -> TRONCOS | C25: ='01_C&P'!C23 -> m³ | D25: ='01_C&P'!D23 -> 20 | E25: ='01_C&P'!U23 -> 290615.56 | F25: ='01_C&P'!V23 -> 562951.68 | G25: ='01_C&P'!W23 -> 853567.25 | H25: ='01_C&P'!X23 -> 5812311.3 | I25: ='01_C&P'!Y23 -> 11259034 | J25: =H25+I25 -> 17071345
A26: ='01_C&P'!A24 -> 0.14 | B26: ='01_C&P'!B24 -> TENSORES | C26: ='01_C&P'!C24 -> m³ | D26: ='01_C&P'!D24 -> 5.4 | E26: ='01_C&P'!U24 -> 389379.44 | F26: ='01_C&P'!V24 -> 596369.85 | G26: ='01_C&P'!W24 -> 985749.29 | H26: ='01_C&P'!X24 -> 2102649 | I26: ='01_C&P'!Y24 -> 3220397.2 | J26: =H26+I26 -> 5323046.2
A27: ='01_C&P'!A25 -> 0.15 | B27: ='01_C&P'!B25 -> TABIQUES DE SUBMURACION | C27: ='01_C&P'!C25 -> m³ | D27: ='01_C&P'!D25 -> 42.75 | E27: ='01_C&P'!U25 -> 442353.68 | F27: ='01_C&P'!V25 -> 578259.71 | G27: ='01_C&P'!W25 -> 1020613.4 | H27: ='01_C&P'!X25 -> 18910620 | I27: ='01_C&P'!Y25 -> 24720603 | J27: =H27+I27 -> 43631223
A28: ='01_C&P'!A26 -> OBRA GRIS - SOBRE SUBSUELO
A29: ='01_C&P'!A27 -> 36892 | B29: ='01_C&P'!B27 -> COLUMNAS Y TABIQUES | C29: ='01_C&P'!C27 -> m³ | D29: ='01_C&P'!D27 -> 23 | E29: ='01_C&P'!U27 -> 548114.34 | F29: ='01_C&P'!V27 -> 947147.99 | G29: ='01_C&P'!W27 -> 1495262.3 | H29: ='01_C&P'!X27 -> 12606630 | I29: ='01_C&P'!Y27 -> 21784404 | J29: =H29+I29 -> 34391034
A30: ='01_C&P'!A28 -> 46054 | B30: ='01_C&P'!B28 -> VIGAS | C30: ='01_C&P'!C28 -> m³ | D30: ='01_C&P'!D28 -> 16 | E30: ='01_C&P'!U28 -> 539468.37 | F30: ='01_C&P'!V28 -> 1361525.2 | G30: ='01_C&P'!W28 -> 1900993.6 | H30: ='01_C&P'!X28 -> 8631493.9 | I30: ='01_C&P'!Y28 -> 21784404 | J30: =H30+I30 -> 30415898
A31: ='01_C&P'!A29 -> 46082 | B31: ='01_C&P'!B29 -> LOSA | C31: ='01_C&P'!C29 -> m³ | D31: ='01_C&P'!D29 -> 57 | E31: ='01_C&P'!U29 -> 362272.74 | F31: ='01_C&P'!V29 -> 541664.6 | G31: ='01_C&P'!W29 -> 903937.34 | H31: ='01_C&P'!X29 -> 20649546 | I31: ='01_C&P'!Y29 -> 30874882 | J31: =H31+I31 -> 51524428
A32: ='01_C&P'!A30 -> 1.31 | B32: ='01_C&P'!B30 -> LOSA DE SUPRESION SOBRE SUELO COMPACTADO. e=10cm. | C32: ='01_C&P'!C30 -> m³ | D32: ='01_C&P'!D30 -> 39 | E32: ='01_C&P'!U30 -> 218369.72 | F32: ='01_C&P'!V30 -> 200198.09 | G32: ='01_C&P'!W30 -> 418567.81 | H32: ='01_C&P'!X30 -> 8516419 | I32: ='01_C&P'!Y30 -> 7807725.5 | J32: =H32+I32 -> 16324145
A33: ='01_C&P'!A31 -> 1.32 | B33: ='01_C&P'!B31 -> PAVIMENTO ALISADO EN ESTACIONAMIENTO. e=10cm | C33: ='01_C&P'!C31 -> m² | D33: ='01_C&P'!D31 -> 310 | E33: ='01_C&P'!U31 -> 25336.66 | F33: ='01_C&P'!V31 -> 25086.563 | G33: ='01_C&P'!W31 -> 50423.222 | H33: ='01_C&P'!X31 -> 7854364.5 | I33: ='01_C&P'!Y31 -> 7776834.4 | J33: =H33+I33 -> 15631199
A34: ='01_C&P'!A32 -> 46113 | B34: ='01_C&P'!B32 -> MAMPOSTERIA. | C34: ='01_C&P'!C32 -> m² | D34: ='01_C&P'!D32 -> 360 | E34: ='01_C&P'!U32 -> 28937.371 | F34: ='01_C&P'!V32 -> 26021.461 | G34: ='01_C&P'!W32 -> 54958.832 | H34: ='01_C&P'!X32 -> 10417454 | I34: ='01_C&P'!Y32 -> 9367726.1 | J34: =H34+I34 -> 19785180
A35: ='01_C&P'!A33 -> 46143 | B35: ='01_C&P'!B33 -> CONTRAPISO . e=12cm | C35: ='01_C&P'!C33 -> m² | D35: ='01_C&P'!D33 -> 80 | E35: ='01_C&P'!U33 -> 18664.73 | F35: ='01_C&P'!V33 -> 45467.838 | G35: ='01_C&P'!W33 -> 64132.568 | H35: ='01_C&P'!X33 -> 1493178.4 | I35: ='01_C&P'!Y33 -> 3637427 | J35: =H35+I35 -> 5130605.5
A36: ='01_C&P'!A34 -> 46174 | B36: ='01_C&P'!B34 -> CARPETA . e=3cm | C36: ='01_C&P'!C34 -> m² | D36: ='01_C&P'!D34 -> 80 | E36: ='01_C&P'!U34 -> 5017.625 | F36: ='01_C&P'!V34 -> 27222.782 | G36: ='01_C&P'!W34 -> 32240.407 | H36: ='01_C&P'!X34 -> 401410 | I36: ='01_C&P'!Y34 -> 2177822.5 | J36: =H36+I36 -> 2579232.5
A37: ='01_C&P'!A35 -> 46204 | B37: ='01_C&P'!B35 -> REVOQUE INTERIOR. (GRUESO FRATAZADO) | C37: ='01_C&P'!C35 -> m² | D37: ='01_C&P'!D35 -> 180 | E37: ='01_C&P'!U35 -> 2871.4118 | F37: ='01_C&P'!V35 -> 40158.43 | G37: ='01_C&P'!W35 -> 43029.842 | H37: ='01_C&P'!X35 -> 516854.13 | I37: ='01_C&P'!Y35 -> 7228517.4 | J37: =H37+I37 -> 7745371.5
A38: ='01_C&P'!A36 -> 46235 | B38: ='01_C&P'!B36 -> REVOQUE INTERTIOR HIDROFUGO. | C38: ='01_C&P'!C36 -> m² | D38: ='01_C&P'!D36 -> 282 | E38: ='01_C&P'!U36 -> 3811.6746 | F38: ='01_C&P'!V36 -> 54141.582 | G38: ='01_C&P'!W36 -> 57953.257 | H38: ='01_C&P'!X36 -> 1074892.2 | I38: ='01_C&P'!Y36 -> 15267926 | J38: =H38+I38 -> 16342818
A39: ='01_C&P'!A37 -> OBRA GRIS - SOBRE PLANTA BAJA
A40: ='01_C&P'!A38 -> 45293 | B40: ='01_C&P'!B38 -> COLUMNAS Y TABIQUES | C40: ='01_C&P'!C38 -> m³ | D40: ='01_C&P'!D38 -> 31 | E40: ='01_C&P'!U38 -> 537748.84 | F40: ='01_C&P'!V38 -> 607333.97 | G40: ='01_C&P'!W38 -> 1145082.8 | H40: ='01_C&P'!X38 -> 16670214 | I40: ='01_C&P'!Y38 -> 18827353 | J40: =H40+I40 -> 35497567
A41: ='01_C&P'!A39 -> n | B41: ='01_C&P'!B39 -> VIGAS | C41: ='01_C&P'!C39 -> m³ | D41: ='01_C&P'!D39 -> 14 | E41: ='01_C&P'!U39 -> 559896.94 | F41: ='01_C&P'!V39 -> 1320539.4 | G41: ='01_C&P'!W39 -> 1880436.3 | H41: ='01_C&P'!X39 -> 7838557.2 | I41: ='01_C&P'!Y39 -> 18487551 | J41: =H41+I41 -> 26326108
A42: ='01_C&P'!A40 -> 45353 | B42: ='01_C&P'!B40 -> LOSA | C42: ='01_C&P'!C40 -> m³ | D42: ='01_C&P'!D40 -> 26 | E42: ='01_C&P'!U40 -> 417771.5 | F42: ='01_C&P'!V40 -> 896406.26 | G42: ='01_C&P'!W40 -> 1314177.8 | H42: ='01_C&P'!X40 -> 10862059 | I42: ='01_C&P'!Y40 -> 23306563 | J42: =H42+I42 -> 34168622
A43: ='01_C&P'!A41 -> 46114 | B43: ='01_C&P'!B41 -> MAMPOSTERIA. | C43: ='01_C&P'!C41 -> m² | D43: ='01_C&P'!D41 -> 340 | E43: ='01_C&P'!U41 -> 28748.294 | F43: ='01_C&P'!V41 -> 26870.714 | G43: ='01_C&P'!W41 -> 55619.009 | H43: ='01_C&P'!X41 -> 9774420.1 | I43: ='01_C&P'!Y41 -> 9136042.8 | J43: =H43+I43 -> 18910463
A44: ='01_C&P'!A42 -> 46144 | B44: ='01_C&P'!B42 -> CONTRAPISO INTERIOR . e=12cm | C44: ='01_C&P'!C42 -> m² | D44: ='01_C&P'!D42 -> 144 | E44: ='01_C&P'!U42 -> 20997.164 | F44: ='01_C&P'!V42 -> 35556.943 | G44: ='01_C&P'!W42 -> 56554.107 | H44: ='01_C&P'!X42 -> 3023591.6 | I44: ='01_C&P'!Y42 -> 5120199.8 | J44: =H44+I44 -> 8143791.4
A45: ='01_C&P'!A43 -> 2.51 | B45: ='01_C&P'!B43 -> PAVIMENTO ALISADO EN ESTACIONAMIENTO. e=10cm | C45: ='01_C&P'!C43 -> m² | D45: ='01_C&P'!D43 -> 267 | E45: ='01_C&P'!U43 -> 26130.315 | F45: ='01_C&P'!V43 -> 26002.902 | G45: ='01_C&P'!W43 -> 52133.216 | H45: ='01_C&P'!X43 -> 6976794 | I45: ='01_C&P'!Y43 -> 6942774.7 | J45: =H45+I45 -> 13919569
A46: ='01_C&P'!A44 -> 46175 | B46: ='01_C&P'!B44 -> CARPETA INTERIOR. e=3cm | C46: ='01_C&P'!C44 -> m² | D46: ='01_C&P'!D44 -> 144 | E46: ='01_C&P'!U44 -> 9043.2639 | F46: ='01_C&P'!V44 -> 25099.019 | G46: ='01_C&P'!W44 -> 34142.283 | H46: ='01_C&P'!X44 -> 1302230 | I46: ='01_C&P'!Y44 -> 3614258.7 | J46: =H46+I46 -> 4916488.7
A47: ='01_C&P'!A45 -> 46205 | B47: ='01_C&P'!B45 -> REVOQUE INTERIOR. (GRUESO FRATAZADO) | C47: ='01_C&P'!C45 -> m² | D47: ='01_C&P'!D45 -> 224 | E47: ='01_C&P'!U45 -> 2828.8895 | F47: ='01_C&P'!V45 -> 37648.528 | G47: ='01_C&P'!W45 -> 40477.418 | H47: ='01_C&P'!X45 -> 633671.24 | I47: ='01_C&P'!Y45 -> 8433270.3 | J47: =H47+I47 -> 9066941.5
A48: ='01_C&P'!A46 -> 46236 | B48: ='01_C&P'!B46 -> REVOQUE EXTERIOR (GRUESO FRATAZADO) CON HIDROFUGO. | C48: ='01_C&P'!C46 -> m² | D48: ='01_C&P'!D46 -> 456 | E48: ='01_C&P'!U46 -> 3712.7998 | F48: ='01_C&P'!V46 -> 57920.812 | G48: ='01_C&P'!W46 -> 61633.612 | H48: ='01_C&P'!X46 -> 1693036.7 | I48: ='01_C&P'!Y46 -> 26411890 | J48: =H48+I48 -> 28104927
A49: ='01_C&P'!A47 -> OBRA GRIS - SOBRE PRIMER PISO
A50: ='01_C&P'!A48 -> 46025 | B50: ='01_C&P'!B48 -> COLUMNAS Y TABIQUES | C50: ='01_C&P'!C48 -> m³ | D50: ='01_C&P'!D48 -> 18 | E50: ='01_C&P'!U48 -> 517211.35 | F50: ='01_C&P'!V48 -> 871343.54 | G50: ='01_C&P'!W48 -> 1388554.9 | H50: ='01_C&P'!X48 -> 9309804.2 | I50: ='01_C&P'!Y48 -> 15684184 | J50: =H50+I50 -> 24993988
A51: ='01_C&P'!A49 -> 46056 | B51: ='01_C&P'!B49 -> VIGAS | C51: ='01_C&P'!C49 -> m³ | D51: ='01_C&P'!D49 -> 13 | E51: ='01_C&P'!U49 -> 631622.87 | F51: ='01_C&P'!V49 -> 1206475.7 | G51: ='01_C&P'!W49 -> 1838098.5 | H51: ='01_C&P'!X49 -> 8211097.4 | I51: ='01_C&P'!Y49 -> 15684184 | J51: =H51+I51 -> 23895281
A52: ='01_C&P'!A50 -> 46084 | B52: ='01_C&P'!B50 -> LOSA | C52: ='01_C&P'!C50 -> m³ | D52: ='01_C&P'!D50 -> 24 | E52: ='01_C&P'!U50 -> 381107.08 | F52: ='01_C&P'!V50 -> 667666.08 | G52: ='01_C&P'!W50 -> 1048773.2 | H52: ='01_C&P'!X50 -> 9146570 | I52: ='01_C&P'!Y50 -> 16023986 | J52: =H52+I52 -> 25170556
A53: ='01_C&P'!A51 -> 46115 | B53: ='01_C&P'!B51 -> MAMPOSTERIA. | C53: ='01_C&P'!C51 -> m² | D53: ='01_C&P'!D51 -> 320 | E53: ='01_C&P'!U51 -> 29083.526 | F53: ='01_C&P'!V51 -> 29274.144 | G53: ='01_C&P'!W51 -> 58357.67 | H53: ='01_C&P'!X51 -> 9306728.5 | I53: ='01_C&P'!Y51 -> 9367726.1 | J53: =H53+I53 -> 18674455
A54: ='01_C&P'!A52 -> 46145 | B54: ='01_C&P'!B52 -> CONTRAPISO . e=12cm | C54: ='01_C&P'!C52 -> m² | D54: ='01_C&P'!D52 -> 270 | E54: ='01_C&P'!U52 -> 18509.528 | F54: ='01_C&P'!V52 -> 28848.855 | G54: ='01_C&P'!W52 -> 47358.383 | H54: ='01_C&P'!X52 -> 4997572.5 | I54: ='01_C&P'!Y52 -> 7789190.9 | J54: =H54+I54 -> 12786763
A55: ='01_C&P'!A53 -> 46176 | B55: ='01_C&P'!B53 -> CARPETA . e=3cm | C55: ='01_C&P'!C53 -> m² | D55: ='01_C&P'!D53 -> 270 | E55: ='01_C&P'!U53 -> 4823.0741 | F55: ='01_C&P'!V53 -> 25914.201 | G55: ='01_C&P'!W53 -> 30737.275 | H55: ='01_C&P'!X53 -> 1302230 | I55: ='01_C&P'!Y53 -> 6996834.2 | J55: =H55+I55 -> 8299064.2
A56: ='01_C&P'!A54 -> 46206 | B56: ='01_C&P'!B54 -> REVOQUE INTERIOR. (GRUESO FRATAZADO) | C56: ='01_C&P'!C54 -> m² | D56: ='01_C&P'!D54 -> 244 | E56: ='01_C&P'!U54 -> 2908.3149 | F56: ='01_C&P'!V54 -> 39500.095 | G56: ='01_C&P'!W54 -> 42408.41 | H56: ='01_C&P'!X54 -> 709628.84 | I56: ='01_C&P'!Y54 -> 9638023.2 | J56: =H56+I56 -> 10347652
A57: ='01_C&P'!A55 -> 46237 | B57: ='01_C&P'!B55 -> REVOQUE EXTERIOR (GRUESO FRATAZADO) CON HIDROFUGO. | C57: ='01_C&P'!C55 -> m² | D57: ='01_C&P'!D55 -> 284 | E57: ='01_C&P'!U55 -> 3803.7469 | F57: ='01_C&P'!V55 -> 57920.812 | G57: ='01_C&P'!W55 -> 61724.559 | H57: ='01_C&P'!X55 -> 1080264.1 | I57: ='01_C&P'!Y55 -> 16449511 | J57: =H57+I57 -> 17529775
A58: ='01_C&P'!A56 -> OBRA GRIS - SOBRE SEGUNDO PISO
A59: ='01_C&P'!A57 -> 46025 | B59: ='01_C&P'!B57 -> COLUMNAS Y TABIQUES | C59: ='01_C&P'!C57 -> m³ | D59: ='01_C&P'!D57 -> 18 | E59: ='01_C&P'!U57 -> 517211.35 | F59: ='01_C&P'!V57 -> 871343.54 | G59: ='01_C&P'!W57 -> 1388554.9 | H59: ='01_C&P'!X57 -> 9309804.2 | I59: ='01_C&P'!Y57 -> 15684184 | J59: =H59+I59 -> 24993988
A60: ='01_C&P'!A58 -> 46056 | B60: ='01_C&P'!B58 -> VIGAS | C60: ='01_C&P'!C58 -> m³ | D60: ='01_C&P'!D58 -> 13 | E60: ='01_C&P'!U58 -> 631622.87 | F60: ='01_C&P'!V58 -> 1206475.7 | G60: ='01_C&P'!W58 -> 1838098.5 | H60: ='01_C&P'!X58 -> 8211097.4 | I60: ='01_C&P'!Y58 -> 15684184 | J60: =H60+I60 -> 23895281
A61: ='01_C&P'!A59 -> 46084 | B61: ='01_C&P'!B59 -> LOSA | C61: ='01_C&P'!C59 -> m³ | D61: ='01_C&P'!D59 -> 24 | E61: ='01_C&P'!U59 -> 381107.08 | F61: ='01_C&P'!V59 -> 667666.08 | G61: ='01_C&P'!W59 -> 1048773.2 | H61: ='01_C&P'!X59 -> 9146570 | I61: ='01_C&P'!Y59 -> 16023986 | J61: =H61+I61 -> 25170556
A62: ='01_C&P'!A60 -> 46115 | B62: ='01_C&P'!B60 -> MAMPOSTERIA. | C62: ='01_C&P'!C60 -> m² | D62: ='01_C&P'!D60 -> 320 | E62: ='01_C&P'!U60 -> 29083.526 | F62: ='01_C&P'!V60 -> 29274.144 | G62: ='01_C&P'!W60 -> 58357.67 | H62: ='01_C&P'!X60 -> 9306728.5 | I62: ='01_C&P'!Y60 -> 9367726.1 | J62: =H62+I62 -> 18674455
A63: ='01_C&P'!A61 -> 46145 | B63: ='01_C&P'!B61 -> CONTRAPISO . e=12cm | C63: ='01_C&P'!C61 -> m² | D63: ='01_C&P'!D61 -> 270 | E63: ='01_C&P'!U61 -> 18509.528 | F63: ='01_C&P'!V61 -> 28848.855 | G63: ='01_C&P'!W61 -> 47358.383 | H63: ='01_C&P'!X61 -> 4997572.5 | I63: ='01_C&P'!Y61 -> 7789190.9 | J63: =H63+I63 -> 12786763
A64: ='01_C&P'!A62 -> 46176 | B64: ='01_C&P'!B62 -> CARPETA . e=3cm | C64: ='01_C&P'!C62 -> m² | D64: ='01_C&P'!D62 -> 270 | E64: ='01_C&P'!U62 -> 4823.0741 | F64: ='01_C&P'!V62 -> 25914.201 | G64: ='01_C&P'!W62 -> 30737.275 | H64: ='01_C&P'!X62 -> 1302230 | I64: ='01_C&P'!Y62 -> 6996834.2 | J64: =H64+I64 -> 8299064.2
A65: ='01_C&P'!A63 -> 46206 | B65: ='01_C&P'!B63 -> REVOQUE INTERIOR. (GRUESO FRATAZADO) | C65: ='01_C&P'!C63 -> m² | D65: ='01_C&P'!D63 -> 244 | E65: ='01_C&P'!U63 -> 2908.3149 | F65: ='01_C&P'!V63 -> 39500.095 | G65: ='01_C&P'!W63 -> 42408.41 | H65: ='01_C&P'!X63 -> 709628.84 | I65: ='01_C&P'!Y63 -> 9638023.2 | J65: =H65+I65 -> 10347652
A66: ='01_C&P'!A64 -> 46237 | B66: ='01_C&P'!B64 -> REVOQUE EXTERIOR (GRUESO FRATAZADO) CON HIDROFUGO. | C66: ='01_C&P'!C64 -> m² | D66: ='01_C&P'!D64 -> 284 | E66: ='01_C&P'!U64 -> 3803.7469 | F66: ='01_C&P'!V64 -> 57920.812 | G66: ='01_C&P'!W64 -> 61724.559 | H66: ='01_C&P'!X64 -> 1080264.1 | I66: ='01_C&P'!Y64 -> 16449511 | J66: =H66+I66 -> 17529775
A67: ='01_C&P'!A65 -> OBRA GRIS - SOBRE TERCER PISO
A68: ='01_C&P'!A66 -> 46025 | B68: ='01_C&P'!B66 -> COLUMNAS Y TABIQUES | C68: ='01_C&P'!C66 -> m³ | D68: ='01_C&P'!D66 -> 18 | E68: ='01_C&P'!U66 -> 517211.35 | F68: ='01_C&P'!V66 -> 871343.54 | G68: ='01_C&P'!W66 -> 1388554.9 | H68: ='01_C&P'!X66 -> 9309804.2 | I68: ='01_C&P'!Y66 -> 15684184 | J68: =H68+I68 -> 24993988
A69: ='01_C&P'!A67 -> 46056 | B69: ='01_C&P'!B67 -> VIGAS | C69: ='01_C&P'!C67 -> m³ | D69: ='01_C&P'!D67 -> 13 | E69: ='01_C&P'!U67 -> 631622.87 | F69: ='01_C&P'!V67 -> 1206475.7 | G69: ='01_C&P'!W67 -> 1838098.5 | H69: ='01_C&P'!X67 -> 8211097.4 | I69: ='01_C&P'!Y67 -> 15684184 | J69: =H69+I69 -> 23895281
A70: ='01_C&P'!A68 -> 46084 | B70: ='01_C&P'!B68 -> LOSA | C70: ='01_C&P'!C68 -> m³ | D70: ='01_C&P'!D68 -> 24 | E70: ='01_C&P'!U68 -> 381107.08 | F70: ='01_C&P'!V68 -> 667666.08 | G70: ='01_C&P'!W68 -> 1048773.2 | H70: ='01_C&P'!X68 -> 9146570 | I70: ='01_C&P'!Y68 -> 16023986 | J70: =H70+I70 -> 25170556
A71: ='01_C&P'!A69 -> 46115 | B71: ='01_C&P'!B69 -> MAMPOSTERIA. | C71: ='01_C&P'!C69 -> m² | D71: ='01_C&P'!D69 -> 320 | E71: ='01_C&P'!U69 -> 29083.526 | F71: ='01_C&P'!V69 -> 29274.144 | G71: ='01_C&P'!W69 -> 58357.67 | H71: ='01_C&P'!X69 -> 9306728.5 | I71: ='01_C&P'!Y69 -> 9367726.1 | J71: =H71+I71 -> 18674455
A72: ='01_C&P'!A70 -> 46145 | B72: ='01_C&P'!B70 -> CONTRAPISO . e=12cm | C72: ='01_C&P'!C70 -> m² | D72: ='01_C&P'!D70 -> 270 | E72: ='01_C&P'!U70 -> 18509.528 | F72: ='01_C&P'!V70 -> 28848.855 | G72: ='01_C&P'!W70 -> 47358.383 | H72: ='01_C&P'!X70 -> 4997572.5 | I72: ='01_C&P'!Y70 -> 7789190.9 | J72: =H72+I72 -> 12786763
A73: ='01_C&P'!A71 -> 46176 | B73: ='01_C&P'!B71 -> CARPETA . e=3cm | C73: ='01_C&P'!C71 -> m² | D73: ='01_C&P'!D71 -> 270 | E73: ='01_C&P'!U71 -> 4823.0741 | F73: ='01_C&P'!V71 -> 25914.201 | G73: ='01_C&P'!W71 -> 30737.275 | H73: ='01_C&P'!X71 -> 1302230 | I73: ='01_C&P'!Y71 -> 6996834.2 | J73: =H73+I73 -> 8299064.2
A74: ='01_C&P'!A72 -> 46206 | B74: ='01_C&P'!B72 -> REVOQUE INTERIOR. (GRUESO FRATAZADO) | C74: ='01_C&P'!C72 -> m² | D74: ='01_C&P'!D72 -> 244 | E74: ='01_C&P'!U72 -> 2908.3149 | F74: ='01_C&P'!V72 -> 39500.095 | G74: ='01_C&P'!W72 -> 42408.41 | H74: ='01_C&P'!X72 -> 709628.84 | I74: ='01_C&P'!Y72 -> 9638023.2 | J74: =H74+I74 -> 10347652
A75: ='01_C&P'!A73 -> 46237 | B75: ='01_C&P'!B73 -> REVOQUE EXTERIOR (GRUESO FRATAZADO) CON HIDROFUGO. | C75: ='01_C&P'!C73 -> m² | D75: ='01_C&P'!D73 -> 284 | E75: ='01_C&P'!U73 -> 3803.7469 | F75: ='01_C&P'!V73 -> 57920.812 | G75: ='01_C&P'!W73 -> 61724.559 | H75: ='01_C&P'!X73 -> 1080264.1 | I75: ='01_C&P'!Y73 -> 16449511 | J75: =H75+I75 -> 17529775
A76: ='01_C&P'!A74 -> OBRA GRIS - SOBRE CUARTO PISO
A77: ='01_C&P'!A75 -> 46025 | B77: ='01_C&P'!B75 -> COLUMNAS Y TABIQUES | C77: ='01_C&P'!C75 -> m³ | D77: ='01_C&P'!D75 -> 18 | E77: ='01_C&P'!U75 -> 517211.35 | F77: ='01_C&P'!V75 -> 871343.54 | G77: ='01_C&P'!W75 -> 1388554.9 | H77: ='01_C&P'!X75 -> 9309804.2 | I77: ='01_C&P'!Y75 -> 15684184 | J77: =H77+I77 -> 24993988
A78: ='01_C&P'!A76 -> 46056 | B78: ='01_C&P'!B76 -> VIGAS | C78: ='01_C&P'!C76 -> m³ | D78: ='01_C&P'!D76 -> 13 | E78: ='01_C&P'!U76 -> 631622.87 | F78: ='01_C&P'!V76 -> 1206475.7 | G78: ='01_C&P'!W76 -> 1838098.5 | H78: ='01_C&P'!X76 -> 8211097.4 | I78: ='01_C&P'!Y76 -> 15684184 | J78: =H78+I78 -> 23895281
A79: ='01_C&P'!A77 -> 46084 | B79: ='01_C&P'!B77 -> LOSA | C79: ='01_C&P'!C77 -> m³ | D79: ='01_C&P'!D77 -> 24 | E79: ='01_C&P'!U77 -> 381107.08 | F79: ='01_C&P'!V77 -> 667666.08 | G79: ='01_C&P'!W77 -> 1048773.2 | H79: ='01_C&P'!X77 -> 9146570 | I79: ='01_C&P'!Y77 -> 16023986 | J79: =H79+I79 -> 25170556
A80: ='01_C&P'!A78 -> 46115 | B80: ='01_C&P'!B78 -> MAMPOSTERIA. | C80: ='01_C&P'!C78 -> m² | D80: ='01_C&P'!D78 -> 320 | E80: ='01_C&P'!U78 -> 29083.526 | F80: ='01_C&P'!V78 -> 29274.144 | G80: ='01_C&P'!W78 -> 58357.67 | H80: ='01_C&P'!X78 -> 9306728.5 | I80: ='01_C&P'!Y78 -> 9367726.1 | J80: =H80+I80 -> 18674455
A81: ='01_C&P'!A79 -> 46145 | B81: ='01_C&P'!B79 -> CONTRAPISO . e=12cm | C81: ='01_C&P'!C79 -> m² | D81: ='01_C&P'!D79 -> 270 | E81: ='01_C&P'!U79 -> 18509.528 | F81: ='01_C&P'!V79 -> 28848.855 | G81: ='01_C&P'!W79 -> 47358.383 | H81: ='01_C&P'!X79 -> 4997572.5 | I81: ='01_C&P'!Y79 -> 7789190.9 | J81: =H81+I81 -> 12786763
A82: ='01_C&P'!A80 -> 46176 | B82: ='01_C&P'!B80 -> CARPETA . e=3cm | C82: ='01_C&P'!C80 -> m² | D82: ='01_C&P'!D80 -> 270 | E82: ='01_C&P'!U80 -> 4823.0741 | F82: ='01_C&P'!V80 -> 25914.201 | G82: ='01_C&P'!W80 -> 30737.275 | H82: ='01_C&P'!X80 -> 1302230 | I82: ='01_C&P'!Y80 -> 6996834.2 | J82: =H82+I82 -> 8299064.2
A83: ='01_C&P'!A81 -> 46206 | B83: ='01_C&P'!B81 -> REVOQUE INTERIOR. (GRUESO FRATAZADO) | C83: ='01_C&P'!C81 -> m² | D83: ='01_C&P'!D81 -> 244 | E83: ='01_C&P'!U81 -> 2908.3149 | F83: ='01_C&P'!V81 -> 39500.095 | G83: ='01_C&P'!W81 -> 42408.41 | H83: ='01_C&P'!X81 -> 709628.84 | I83: ='01_C&P'!Y81 -> 9638023.2 | J83: =H83+I83 -> 10347652
A84: ='01_C&P'!A82 -> 46237 | B84: ='01_C&P'!B82 -> REVOQUE EXTERIOR (GRUESO FRATAZADO) CON HIDROFUGO. | C84: ='01_C&P'!C82 -> m² | D84: ='01_C&P'!D82 -> 284 | E84: ='01_C&P'!U82 -> 3803.7469 | F84: ='01_C&P'!V82 -> 57920.812 | G84: ='01_C&P'!W82 -> 61724.559 | H84: ='01_C&P'!X82 -> 1080264.1 | I84: ='01_C&P'!Y82 -> 16449511 | J84: =H84+I84 -> 17529775
A85: ='01_C&P'!A83 -> OBRA GRIS - SOBRE QUINTO PISO
A86: ='01_C&P'!A84 -> 46025 | B86: ='01_C&P'!B84 -> COLUMNAS Y TABIQUES | C86: ='01_C&P'!C84 -> m³ | D86: ='01_C&P'!D84 -> 18 | E86: ='01_C&P'!U84 -> 517211.35 | F86: ='01_C&P'!V84 -> 871343.54 | G86: ='01_C&P'!W84 -> 1388554.9 | H86: ='01_C&P'!X84 -> 9309804.2 | I86: ='01_C&P'!Y84 -> 15684184 | J86: =H86+I86 -> 24993988
A87: ='01_C&P'!A85 -> 46056 | B87: ='01_C&P'!B85 -> VIGAS | C87: ='01_C&P'!C85 -> m³ | D87: ='01_C&P'!D85 -> 13 | E87: ='01_C&P'!U85 -> 631622.87 | F87: ='01_C&P'!V85 -> 1206475.7 | G87: ='01_C&P'!W85 -> 1838098.5 | H87: ='01_C&P'!X85 -> 8211097.4 | I87: ='01_C&P'!Y85 -> 15684184 | J87: =H87+I87 -> 23895281
A88: ='01_C&P'!A86 -> 46084 | B88: ='01_C&P'!B86 -> LOSA | C88: ='01_C&P'!C86 -> m³ | D88: ='01_C&P'!D86 -> 24 | E88: ='01_C&P'!U86 -> 381107.08 | F88: ='01_C&P'!V86 -> 667666.08 | G88: ='01_C&P'!W86 -> 1048773.2 | H88: ='01_C&P'!X86 -> 9146570 | I88: ='01_C&P'!Y86 -> 16023986 | J88: =H88+I88 -> 25170556
A89: ='01_C&P'!A87 -> 46115 | B89: ='01_C&P'!B87 -> MAMPOSTERIA. | C89: ='01_C&P'!C87 -> m² | D89: ='01_C&P'!D87 -> 320 | E89: ='01_C&P'!U87 -> 29083.526 | F89: ='01_C&P'!V87 -> 29274.144 | G89: ='01_C&P'!W87 -> 58357.67 | H89: ='01_C&P'!X87 -> 9306728.5 | I89: ='01_C&P'!Y87 -> 9367726.1 | J89: =H89+I89 -> 18674455
A90: ='01_C&P'!A88 -> 46145 | B90: ='01_C&P'!B88 -> CONTRAPISO . e=12cm | C90: ='01_C&P'!C88 -> m² | D90: ='01_C&P'!D88 -> 270 | E90: ='01_C&P'!U88 -> 18509.528 | F90: ='01_C&P'!V88 -> 28848.855 | G90: ='01_C&P'!W88 -> 47358.383 | H90: ='01_C&P'!X88 -> 4997572.5 | I90: ='01_C&P'!Y88 -> 7789190.9 | J90: =H90+I90 -> 12786763
A91: ='01_C&P'!A89 -> 46176 | B91: ='01_C&P'!B89 -> CARPETA . e=3cm | C91: ='01_C&P'!C89 -> m² | D91: ='01_C&P'!D89 -> 270 | E91: ='01_C&P'!U89 -> 4823.0741 | F91: ='01_C&P'!V89 -> 25914.201 | G91: ='01_C&P'!W89 -> 30737.275 | H91: ='01_C&P'!X89 -> 1302230 | I91: ='01_C&P'!Y89 -> 6996834.2 | J91: =H91+I91 -> 8299064.2
A92: ='01_C&P'!A90 -> 46206 | B92: ='01_C&P'!B90 -> REVOQUE INTERIOR. (GRUESO FRATAZADO) | C92: ='01_C&P'!C90 -> m² | D92: ='01_C&P'!D90 -> 244 | E92: ='01_C&P'!U90 -> 2908.3149 | F92: ='01_C&P'!V90 -> 39500.095 | G92: ='01_C&P'!W90 -> 42408.41 | H92: ='01_C&P'!X90 -> 709628.84 | I92: ='01_C&P'!Y90 -> 9638023.2 | J92: =H92+I92 -> 10347652
A93: ='01_C&P'!A91 -> 46237 | B93: ='01_C&P'!B91 -> REVOQUE EXTERIOR (GRUESO FRATAZADO) CON HIDROFUGO. | C93: ='01_C&P'!C91 -> m² | D93: ='01_C&P'!D91 -> 284 | E93: ='01_C&P'!U91 -> 3803.7469 | F93: ='01_C&P'!V91 -> 57920.812 | G93: ='01_C&P'!W91 -> 61724.559 | H93: ='01_C&P'!X91 -> 1080264.1 | I93: ='01_C&P'!Y91 -> 16449511 | J93: =H93+I93 -> 17529775
A94: ='01_C&P'!A92 -> OBRA GRIS - SOBRE SEXTO PISO
A95: ='01_C&P'!A93 -> 46025 | B95: ='01_C&P'!B93 -> COLUMNAS Y TABIQUES | C95: ='01_C&P'!C93 -> m³ | D95: ='01_C&P'!D93 -> 18 | E95: ='01_C&P'!U93 -> 517211.35 | F95: ='01_C&P'!V93 -> 871343.54 | G95: ='01_C&P'!W93 -> 1388554.9 | H95: ='01_C&P'!X93 -> 9309804.2 | I95: ='01_C&P'!Y93 -> 15684184 | J95: =H95+I95 -> 24993988
A96: ='01_C&P'!A94 -> 46056 | B96: ='01_C&P'!B94 -> VIGAS | C96: ='01_C&P'!C94 -> m³ | D96: ='01_C&P'!D94 -> 13 | E96: ='01_C&P'!U94 -> 631622.87 | F96: ='01_C&P'!V94 -> 1206475.7 | G96: ='01_C&P'!W94 -> 1838098.5 | H96: ='01_C&P'!X94 -> 8211097.4 | I96: ='01_C&P'!Y94 -> 15684184 | J96: =H96+I96 -> 23895281
A97: ='01_C&P'!A95 -> 46084 | B97: ='01_C&P'!B95 -> LOSA | C97: ='01_C&P'!C95 -> m³ | D97: ='01_C&P'!D95 -> 24 | E97: ='01_C&P'!U95 -> 381107.08 | F97: ='01_C&P'!V95 -> 667666.08 | G97: ='01_C&P'!W95 -> 1048773.2 | H97: ='01_C&P'!X95 -> 9146570 | I97: ='01_C&P'!Y95 -> 16023986 | J97: =H97+I97 -> 25170556
A98: ='01_C&P'!A96 -> 46115 | B98: ='01_C&P'!B96 -> MAMPOSTERIA. | C98: ='01_C&P'!C96 -> m² | D98: ='01_C&P'!D96 -> 320 | E98: ='01_C&P'!U96 -> 29083.526 | F98: ='01_C&P'!V96 -> 29274.144 | G98: ='01_C&P'!W96 -> 58357.67 | H98: ='01_C&P'!X96 -> 9306728.5 | I98: ='01_C&P'!Y96 -> 9367726.1 | J98: =H98+I98 -> 18674455
A99: ='01_C&P'!A97 -> 46145 | B99: ='01_C&P'!B97 -> CONTRAPISO . e=12cm | C99: ='01_C&P'!C97 -> m² | D99: ='01_C&P'!D97 -> 270 | E99: ='01_C&P'!U97 -> 18509.528 | F99: ='01_C&P'!V97 -> 28848.855 | G99: ='01_C&P'!W97 -> 47358.383 | H99: ='01_C&P'!X97 -> 4997572.5 | I99: ='01_C&P'!Y97 -> 7789190.9 | J99: =H99+I99 -> 12786763
A100: ='01_C&P'!A98 -> 46176 | B100: ='01_C&P'!B98 -> CARPETA . e=3cm | C100: ='01_C&P'!C98 -> m² | D100: ='01_C&P'!D98 -> 270 | E100: ='01_C&P'!U98 -> 4823.0741 | F100: ='01_C&P'!V98 -> 25914.201 | G100: ='01_C&P'!W98 -> 30737.275 | H100: ='01_C&P'!X98 -> 1302230 | I100: ='01_C&P'!Y98 -> 6996834.2 | J100: =H100+I100 -> 8299064.2
A101: ='01_C&P'!A99 -> 46206 | B101: ='01_C&P'!B99 -> REVOQUE INTERIOR. (GRUESO FRATAZADO) | C101: ='01_C&P'!C99 -> m² | D101: ='01_C&P'!D99 -> 244 | E101: ='01_C&P'!U99 -> 2908.3149 | F101: ='01_C&P'!V99 -> 39500.095 | G101: ='01_C&P'!W99 -> 42408.41 | H101: ='01_C&P'!X99 -> 709628.84 | I101: ='01_C&P'!Y99 -> 9638023.2 | J101: =H101+I101 -> 10347652
A102: ='01_C&P'!A100 -> 46237 | B102: ='01_C&P'!B100 -> REVOQUE EXTERIOR (GRUESO FRATAZADO) CON HIDROFUGO. | C102: ='01_C&P'!C100 -> m² | D102: ='01_C&P'!D100 -> 284 | E102: ='01_C&P'!U100 -> 3803.7469 | F102: ='01_C&P'!V100 -> 57920.812 | G102: ='01_C&P'!W100 -> 61724.559 | H102: ='01_C&P'!X100 -> 1080264.1 | I102: ='01_C&P'!Y100 -> 16449511 | J102: =H102+I102 -> 17529775
A103: ='01_C&P'!A101 -> OBRA GRIS - SOBRE SEPTIMO PISO | C103: ='01_C&P'!C101 | D103: ='01_C&P'!D101
...

Sheet 01_RESUMEN VENTA
B4: M2 | G4: MAT | H4: MO | I4: MAT + MO
B5: CUBIERTO | C5: S/CUBIERTO | D5: DESCUBIERTO | F5: TOTAL PESOS | G5: ='01_VENTA'!H132 -> 5.6636989e+08 | H5: ='01_VENTA'!I132 -> 1537402823 | I5: ='01_VENTA'!J132 -> 2103772717
B6: 1 | C6: 0.5 | D6: 0.25 | F6: TOTAL USD | G6: =G5/1450 -> 390599.93 | H6: =H5/1450 -> 1060277.8 | I6: =I5/1450 -> 1450877.7
A7: SUBSUELO | B7: 410 | C7: - | D7: - | F7: USD X M2 | G7: =G6/B23 -> 146.66288 | H7: =H6/B23 -> 398.11426 | I7: =I6/B23 -> 544.77715
A8: PLANTA BAJA | B8: 144 | C8: - | D8: 247
A9: P1 | B9: 231 | C9: 34 | D9: -
A10: P2 | B10: 231 | C10: 22 | D10: -
A11: P3 | B11: 231 | C11: 22 | D11: -
A12: P4 | B12: 231 | C12: 19 | D12: -
A13: P5 | B13: 231 | C13: 19 | D13: -
A14: P6 | B14: 231 | C14: 22 | D14: -
A15: P7 | B15: 231 | C15: 19 | D15: -
A16: P8 | B16: 231 | C16: 19 | D16: -
A17: AZOTEA ACC. | B17: 43 | C17: 30 | D17: =178-C17 -> 148
A18: AZOTEA INACC. | B18: - | C18: - | D18: 66
A20: SUBTOTAL | B20: =SUM(B7:B18) -> 2445 | C20: =SUM(C7:C18) -> 206 | D20: =SUM(D7:D18) -> 461
B21: =B20*B6 -> 2445 | C21: =C20*C6 -> 103 | D21: =D20*D6 -> 115.25
A23: TOTAL | B23: =B21+C21+D21 -> 2663.25

Sheet 01_RESUMEN MAT.
A1: ='01_C&P'!A1 -> EDIFICIO LAS HERAS
A3: ='2.1.'!A3 -> 45293 | B3: ='2.1.'!B3 -> COLUMNAS Y TABIQUES | H3: ='2.1.'!H3 -> 31 | I3: ='2.1.'!I3 -> m³
A5: MATERIALES
A6: Código | B6: Descripción | C6: Unidad | D6: Cantidad | F6: Desperdicio | G6: Cantidad + Desperdicio | H6: Precio Unitario | I6: Subtotal
A7: ='2.1.'!A7 -> H30 | B7: ='2.1.'!B7 -> Hormigon H30 | C7: ='2.1.'!C7 -> m3 | D7: ='2.1.'!D7 -> 31 | E7: ='2.1.'!E7 | F7: ='2.1.'!F7 -> 0.1 | G7: ='2.1.'!G7 -> 35 | H7: ='2.1.'!H7 -> 158000 | I7: ='2.1.'!I7 -> 5530000
A8: ='2.1.'!A8 -> HADN6 | B8: ='2.1.'!B8 -> Hierros ADN 420 Φ 6 | C8: ='2.1.'!C8 -> u | D8: ='2.1.'!D8 -> 266 | E8: ='2.1.'!E8 | F8: ='2.1.'!F8 -> 0.1 | G8: ='2.1.'!G8 -> 293 | H8: ='2.1.'!H8 -> 5250 | I8: ='2.1.'!I8 -> 1538250 | M8: =SUM(I8:I13) -> 6634136.1
A9: ='2.1.'!A9 -> HADN8 | B9: ='2.1.'!B9 -> Hierros ADN 420 Φ 8 | C9: ='2.1.'!C9 -> u | D9: ='2.1.'!D9 -> 50 | E9: ='2.1.'!E9 | F9: ='2.1.'!F9 -> 0.1 | G9: ='2.1.'!G9 -> 55 | H9: ='2.1.'!H9 -> 9050 | I9: ='2.1.'!I9 -> 497750
A10: ='2.1.'!A10 -> HADN10 | B10: ='2.1.'!B10 -> Hierros ADN 420Φ 10 | C10: ='2.1.'!C10 -> u | D10: ='2.1.'!D10 -> 15 | E10: ='2.1.'!E10 | F10: ='2.1.'!F10 -> 0.1 | G10: ='2.1.'!G10 -> 17 | H10: ='2.1.'!H10 -> 11237 | I10: ='2.1.'!I10 -> 191029
A11: ='2.1.'!A11 -> HADN12 | B11: ='2.1.'!B11 -> Hierros ADN 420 Φ 12 | C11: ='2.1.'!C11 -> u | D11: ='2.1.'!D11 -> 44 | E11: ='2.1.'!E11 | F11: ='2.1.'!F11 -> 0.1 | G11: ='2.1.'!G11 -> 49 | H11: ='2.1.'!H11 -> 20442.5 | I11: ='2.1.'!I11 -> 1001682.5
A12: ='2.1.'!A12 -> HADN16 | B12: ='2.1.'!B12 -> Hierros ADN 420 Φ 16 | C12: ='2.1.'!C12 -> u | D12: ='2.1.'!D12 -> 65 | E12: ='2.1.'!E12 | F12: ='2.1.'!F12 -> 0.1 | G12: ='2.1.'!G12 -> 72 | H12: ='2.1.'!H12 -> 36603.12 | I12: ='2.1.'!I12 -> 2635424.6
A13: ='2.1.'!A13 -> HADN20 | B13: ='2.1.'!B13 -> Hierros ADN 420 Φ 20 | C13: ='2.1.'!C13 -> U | D13: ='2.1.'!D13 -> 12 | E13: ='2.1.'!E13 | F13: ='2.1.'!F13 -> 0.1 | G13: ='2.1.'!G13 -> 14 | H13: ='2.1.'!H13 -> 55000 | I13: ='2.1.'!I13 -> 770000
A14: ='2.1.'!A14 -> F-MIR | B14: ='2.1.'!B14 -> Fenolico 18mm Miraluz 125 GR con film | C14: ='2.1.'!C14 -> u | D14: ='2.1.'!D14 -> 15.5 | E14: ='2.1.'!E14 | F14: ='2.1.'!F14 -> 0.25 | G14: ='2.1.'!G14 -> 20 | H14: ='2.1.'!H14 -> 55260 | I14: ='2.1.'!I14 -> 1105200
A15: ='2.1.'!A15 -> F-GR2 | B15: ='2.1.'!B15 -> Fenolico 18mm Grandis 2 Buenas cal 3/3 | C15: ='2.1.'!C15 -> u | D15: ='2.1.'!D15 -> 45.5 | E15: ='2.1.'!E15 | F15: ='2.1.'!F15 -> 0.25 | G15: ='2.1.'!G15 -> 57 | H15: ='2.1.'!H15 -> 45454 | I15: ='2.1.'!I15 -> 2590878
A16: ='2.1.'!A16 -> H-PL-TI | B16: ='2.1.'!B16 -> Bomba Pluma Traslado e Instalacion | C16: ='2.1.'!C16 -> u | D16: ='2.1.'!D16 -> 1 | E16: ='2.1.'!E16 | F16: ='2.1.'!F16 | G16: ='2.1.'!G16 -> 1 | H16: ='2.1.'!H16 -> 600000 | I16: ='2.1.'!I16 -> 600000
A17: ='2.1.'!A17 -> H-PL-m | B17: ='2.1.'!B17 -> Bomba Pluma m3 bombeable | C17: ='2.1.'!C17 -> m3 | D17: ='2.1.'!D17 -> 31 | E17: ='2.1.'!E17 | F17: ='2.1.'!F17 -> 0.1 | G17: ='2.1.'!G17 -> 35 | H17: ='2.1.'!H17 -> 6000 | I17: ='2.1.'!I17 -> 210000
A18: ='2.1.'!A18 | B18: ='2.1.'!B18 | C18: ='2.1.'!C18 | D18: ='2.1.'!D18 | E18: ='2.1.'!E18 | F18: ='2.1.'!F18 -> 0.1 | G18: ='2.1.'!G18 -> 0 | H18: ='2.1.'!H18 | I18: ='2.1.'!I18 -> 0
A20: TOTAL MATERIALES | I20: =SUM(I7:I18) -> 16670214
A23: ='2.2.'!A3 -> n | B23: ='2.2.'!B3 -> VIGAS | G23: ='2.2.'!G3 | H23: ='2.2.'!H3 -> 14 | I23: ='2.2.'!I3 -> m³
A25: ='2.2.'!A5 -> MATERIALES | B25: ='2.2.'!B5 | C25: ='2.2.'!C5 | D25: ='2.2.'!D5 | E25: ='2.2.'!E5 | F25: ='2.2.'!F5 | G25: ='2.2.'!G5 | H25: ='2.2.'!H5 | I25: ='2.2.'!I5
A26: ='2.2.'!A6 -> Código | B26: ='2.2.'!B6 -> Descripción | C26: ='2.2.'!C6 -> Unidad | D26: ='2.2.'!D6 -> Cantidad | F26: ='2.2.'!F6 -> Desperdicio | G26: ='2.2.'!G6 -> Cantidad + Desperdicio | H26: ='2.2.'!H6 -> Precio Unitario | I26: ='2.2.'!I6 -> Subtotal
A27: ='2.2.'!A7 -> H30 | B27: ='2.2.'!B7 -> Hormigon H30 | C27: ='2.2.'!C7 -> m3 | D27: ='2.2.'!D7 -> 14 | E27: ='2.2.'!E7 | F27: ='2.2.'!F7 -> 0.1 | G27: ='2.2.'!G7 -> 16 | H27: ='2.2.'!H7 -> 158000 | I27: ='2.2.'!I7 -> 2528000
A28: ='2.2.'!A8 -> HADN6 | B28: ='2.2.'!B8 -> Hierros ADN 420 Φ 6 | C28: ='2.2.'!C8 -> u | D28: ='2.2.'!D8 -> 123 | E28: ='2.2.'!E8 | F28: ='2.2.'!F8 -> 0.1 | G28: ='2.2.'!G8 -> 136 | H28: ='2.2.'!H8 -> 5250 | I28: ='2.2.'!I8 -> 714000 | M28: =SUM(I28:I33) -> 3492397.2
A29: ='2.2.'!A9 -> HADN8 | B29: ='2.2.'!B9 -> Hierros ADN 420 Φ 8 | C29: ='2.2.'!C9 -> u | D29: ='2.2.'!D9 -> 4 | E29: ='2.2.'!E9 | F29: ='2.2.'!F9 -> 0.1 | G29: ='2.2.'!G9 -> 5 | H29: ='2.2.'!H9 -> 9050 | I29: ='2.2.'!I9 -> 45250
A30: ='2.2.'!A10 -> HADN10 | B30: ='2.2.'!B10 -> Hierros ADN 420Φ 10 | C30: ='2.2.'!C10 -> u | D30: ='2.2.'!D10 -> 66 | E30: ='2.2.'!E10 | F30: ='2.2.'!F10 -> 0.1 | G30: ='2.2.'!G10 -> 73 | H30: ='2.2.'!H10 -> 11237 | I30: ='2.2.'!I10 -> 820301
A31: ='2.2.'!A11 -> HADN12 | B31: ='2.2.'!B11 -> Hierros ADN 420 Φ 12 | C31: ='2.2.'!C11 -> u | D31: ='2.2.'!D11 -> 34 | E31: ='2.2.'!E11 | F31: ='2.2.'!F11 -> 0.1 | G31: ='2.2.'!G11 -> 38 | H31: ='2.2.'!H11 -> 20442.5 | I31: ='2.2.'!I11 -> 776815
A32: ='2.2.'!A12 -> HADN16 | B32: ='2.2.'!B12 -> Hierros ADN 420 Φ 16 | C32: ='2.2.'!C12 -> u | D32: ='2.2.'!D12 -> 9 | E32: ='2.2.'!E12 | F32: ='2.2.'!F12 -> 0.1 | G32: ='2.2.'!G12 -> 10 | H32: ='2.2.'!H12 -> 36603.12 | I32: ='2.2.'!I12 -> 366031.2
A33: ='2.2.'!A13 -> HADN20 | B33: ='2.2.'!B13 -> Hierros ADN 420 Φ 20 | C33: ='2.2.'!C13 -> U | D33: ='2.2.'!D13 -> 12 | E33: ='2.2.'!E13 | F33: ='2.2.'!F13 -> 0.1 | G33: ='2.2.'!G13 -> 14 | H33: ='2.2.'!H13 -> 55000 | I33: ='2.2.'!I13 -> 770000
A34: ='2.2.'!A14 -> F-MIR | B34: ='2.2.'!B14 -> Fenolico 18mm Miraluz 125 GR con film | C34: ='2.2.'!C14 -> u | D34: ='2.2.'!D14 -> 0 | E34: ='2.2.'!E14 | F34: ='2.2.'!F14 -> 0.25 | G34: ='2.2.'!G14 -> 0 | H34: ='2.2.'!H14 -> 55260 | I34: ='2.2.'!I14 -> 0
A35: ='2.2.'!A15 -> F-GR2 | B35: ='2.2.'!B15 -> Fenolico 18mm Grandis 2 Buenas cal 3/3 | C35: ='2.2.'!C15 -> u | D35: ='2.2.'!D15 -> 31.5 | E35: ='2.2.'!E15 | F35: ='2.2.'!F15 -> 0.25 | G35: ='2.2.'!G15 -> 40 | H35: ='2.2.'!H15 -> 45454 | I35: ='2.2.'!I15 -> 1818160
A36: ='2.2.'!A16 | B36: ='2.2.'!B16 | C36: ='2.2.'!C16 | D36: ='2.2.'!D16 | E36: ='2.2.'!E16 | F36: ='2.2.'!F16 | G36: ='2.2.'!G16 -> 0 | H36: ='2.2.'!H16 | I36: ='2.2.'!I16
A37: ='2.2.'!A17 | B37: ='2.2.'!B17 | C37: ='2.2.'!C17 | D37: ='2.2.'!D17 | E37: ='2.2.'!E17 | F37: ='2.2.'!F17 | G37: ='2.2.'!G17 -> 0 | H37: ='2.2.'!H17 | I37: ='2.2.'!I17
A38: ='2.2.'!A18 | B38: ='2.2.'!B18 | C38: ='2.2.'!C18 | D38: ='2.2.'!D18 | E38: ='2.2.'!E18 | F38: ='2.2.'!F18 | G38: ='2.2.'!G18 -> 0 | H38: ='2.2.'!H18 | I38: ='2.2.'!I18
A39: ='2.2.'!A19 | B39: ='2.2.'!B19 | C39: ='2.2.'!C19 | D39: ='2.2.'!D19 | E39: ='2.2.'!E19 | F39: ='2.2.'!F19 | G39: ='2.2.'!G19 | H39: ='2.2.'!H19 | I39: ='2.2.'!I19
A40: ='2.2.'!A20 -> TOTAL MATERIALES | B40: ='2.2.'!B20 | C40: ='2.2.'!C20 | D40: ='2.2.'!D20 | E40: ='2.2.'!E20 | F40: ='2.2.'!F20 | G40: ='2.2.'!G20 | H40: ='2.2.'!H20 | I40: ='2.2.'!I20 -> 7838557.2
A43: ='2.3.'!A3 -> #REF! | B43: ='2.3.'!B3 -> #REF! | G43: ='2.3.'!G3 -> #REF! | H43: ='2.3.'!H3 -> #REF! | I43: ='2.3.'!I3 -> #REF!
A45: ='2.3.'!A5 -> #REF! | B45: ='2.3.'!B5 -> #REF! | C45: ='2.3.'!C5 -> #REF! | D45: ='2.3.'!D5 -> #REF! | E45: ='2.3.'!E5 -> #REF! | F45: ='2.3.'!F5 -> #REF! | G45: ='2.3.'!G5 -> #REF! | H45: ='2.3.'!H5 -> #REF! | I45: ='2.3.'!I5 -> #REF!
A46: ='2.3.'!A6 -> #REF! | B46: ='2.3.'!B6 -> #REF! | C46: ='2.3.'!C6 -> #REF! | D46: ='2.3.'!D6 -> #REF! | F46: ='2.3.'!F6 -> #REF! | G46: ='2.3.'!G6 -> #REF! | H46: ='2.3.'!H6 -> #REF! | I46: ='2.3.'!I6 -> #REF!
A47: ='2.3.'!A7 -> #REF! | B47: ='2.3.'!B7 -> #REF! | C47: ='2.3.'!C7 -> #REF! | D47: ='2.3.'!D7 -> #REF! | E47: ='2.3.'!E7 -> #REF! | F47: ='2.3.'!F7 -> #REF! | G47: ='2.3.'!G7 -> #REF! | H47: ='2.3.'!H7 -> #REF! | I47: ='2.3.'!I7 -> #REF!
A48: ='2.3.'!A8 -> #REF! | B48: ='2.3.'!B8 -> #REF! | C48: ='2.3.'!C8 -> #REF! | D48: ='2.3.'!D8 -> #REF! | E48: ='2.3.'!E8 -> #REF! | F48: ='2.3.'!F8 -> #REF! | G48: ='2.3.'!G8 -> #REF! | H48: ='2.3.'!H8 -> #REF! | I48: ='2.3.'!I8 -> #REF!
A49: ='2.3.'!A9 -> #REF! | B49: ='2.3.'!B9 -> #REF! | C49: ='2.3.'!C9 -> #REF! | D49: ='2.3.'!D9 -> #REF! | E49: ='2.3.'!E9 -> #REF! | F49: ='2.3.'!F9 -> #REF! | G49: ='2.3.'!G9 -> #REF! | H49: ='2.3.'!H9 -> #REF! | I49: ='2.3.'!I9 -> #REF!
A50: ='2.3.'!A10 -> #REF! | B50: ='2.3.'!B10 -> #REF! | C50: ='2.3.'!C10 -> #REF! | D50: ='2.3.'!D10 -> #REF! | E50: ='2.3.'!E10 -> #REF! | F50: ='2.3.'!F10 -> #REF! | G50: ='2.3.'!G10 -> #REF! | H50: ='2.3.'!H10 -> #REF! | I50: ='2.3.'!I10 -> #REF!
A51: ='2.3.'!A11 -> #REF! | B51: ='2.3.'!B11 -> #REF! | C51: ='2.3.'!C11 -> #REF! | D51: ='2.3.'!D11 -> #REF! | E51: ='2.3.'!E11 -> #REF! | F51: ='2.3.'!F11 -> #REF! | G51: ='2.3.'!G11 -> #REF! | H51: ='2.3.'!H11 -> #REF! | I51: ='2.3.'!I11 -> #REF!
A52: ='2.3.'!A12 -> #REF! | B52: ='2.3.'!B12 -> #REF! | C52: ='2.3.'!C12 -> #REF! | D52: ='2.3.'!D12 -> #REF! | E52: ='2.3.'!E12 -> #REF! | F52: ='2.3.'!F12 -> #REF! | G52: ='2.3.'!G12 -> #REF! | H52: ='2.3.'!H12 -> #REF! | I52: ='2.3.'!I12 -> #REF!
A53: ='2.3.'!A13 -> #REF! | B53: ='2.3.'!B13 -> #REF! | C53: ='2.3.'!C13 -> #REF! | D53: ='2.3.'!D13 -> #REF! | E53: ='2.3.'!E13 -> #REF! | F53: ='2.3.'!F13 -> #REF! | G53: ='2.3.'!G13 -> #REF! | H53: ='2.3.'!H13 -> #REF! | I53: ='2.3.'!I13 -> #REF!
A54: ='2.3.'!A14 -> #REF! | B54: ='2.3.'!B14 -> #REF! | C54: ='2.3.'!C14 -> #REF! | D54: ='2.3.'!D14 -> #REF! | E54: ='2.3.'!E14 -> #REF! | F54: ='2.3.'!F14 -> #REF! | G54: ='2.3.'!G14 -> #REF! | H54: ='2.3.'!H14 -> #REF! | I54: ='2.3.'!I14 -> #REF!
A55: ='2.3.'!A15 -> #REF! | B55: ='2.3.'!B15 -> #REF! | C55: ='2.3.'!C15 -> #REF! | D55: ='2.3.'!D15 -> #REF! | E55: ='2.3.'!E15 -> #REF! | F55: ='2.3.'!F15 -> #REF! | G55: ='2.3.'!G15 -> #REF! | H55: ='2.3.'!H15 -> #REF! | I55: ='2.3.'!I15 -> #REF!
A56: ='2.3.'!A16 -> #REF! | B56: ='2.3.'!B16 -> #REF! | C56: ='2.3.'!C16 -> #REF! | D56: ='2.3.'!D16 -> #REF! | E56: ='2.3.'!E16 -> #REF! | F56: ='2.3.'!F16 -> #REF! | G56: ='2.3.'!G16 -> #REF! | H56: ='2.3.'!H16 -> #REF! | I56: ='2.3.'!I16 -> #REF!
A57: ='2.3.'!A17 -> #REF! | B57: ='2.3.'!B17 -> #REF! | C57: ='2.3.'!C17 -> #REF! | D57: ='2.3.'!D17 -> #REF! | E57: ='2.3.'!E17 -> #REF! | F57: ='2.3.'!F17 -> #REF! | G57: ='2.3.'!G17 -> #REF! | H57: ='2.3.'!H17 -> #REF! | I57: ='2.3.'!I17 -> #REF!
A58: ='2.3.'!A18 -> #REF! | B58: ='2.3.'!B18 -> #REF! | C58: ='2.3.'!C18 -> #REF! | D58: ='2.3.'!D18 -> #REF! | E58: ='2.3.'!E18 -> #REF! | F58: ='2.3.'!F18 -> #REF! | G58: ='2.3.'!G18 -> #REF! | H58: ='2.3.'!H18 -> #REF! | I58: ='2.3.'!I18 -> #REF!
... A60: ='2.3.'!A20 -> #REF! | B60: ='2.3.'!B20 -> #REF! | C60: ='2.3.'!C20 -> #REF! | D60: ='2.3.'!D20 -> #REF! | E60: ='2.3.'!E20 -> #REF! | F60: ='2.3.'!F20 -> #REF! | G60: ='2.3.'!G20 -> #REF! | H60: ='2.3.'!H20 -> #REF! | I60: ='2.3.'!I20 -> #REF!
A63: ='2.4.'!A3 -> #REF! | B63: ='2.4.'!B3 -> #REF! | G63: ='2.4.'!G3 -> #REF! | H63: ='2.4.'!H3 -> #REF! | I63: ='2.4.'!I3 -> #REF!
A64: ='2.4.'!A4 -> #REF! | B64: ='2.4.'!B4 -> #REF! | C64: ='2.4.'!C4 -> #REF! | D64: ='2.4.'!D4 -> #REF! | E64: ='2.4.'!E4 -> #REF! | F64: ='2.4.'!F4 -> #REF! | G64: ='2.4.'!G4 -> #REF! | H64: ='2.4.'!H4 -> #REF! | I64: ='2.4.'!I4 -> #REF!
A65: ='2.4.'!A5 -> #REF! | B65: ='2.4.'!B5 -> #REF! | C65: ='2.4.'!C5 -> #REF! | D65: ='2.4.'!D5 -> #REF! | E65: ='2.4.'!E5 -> #REF! | F65: ='2.4.'!F5 -> #REF! | G65: ='2.4.'!G5 -> #REF! | H65: ='2.4.'!H5 -> #REF! | I65: ='2.4.'!I5 -> #REF!
A66: ='2.4.'!A6 -> #REF! | B66: ='2.4.'!B6 -> #REF! | C66: ='2.4.'!C6 -> #REF! | D66: ='2.4.'!D6 -> #REF! | F66: ='2.4.'!F6 -> #REF! | G66: ='2.4.'!G6 -> #REF! | H66: ='2.4.'!H6 -> #REF! | I66: ='2.4.'!I6 -> #REF!
A67: ='2.4.'!A7 -> #REF! | B67: ='2.4.'!B7 -> #REF! | C67: ='2.4.'!C7 -> #REF! | D67: ='2.4.'!D7 -> #REF! | E67: ='2.4.'!E7 -> #REF! | F67: ='2.4.'!F7 -> #REF! | G67: ='2.4.'!G7 -> #REF! | H67: ='2.4.'!H7 -> #REF! | I67: ='2.4.'!I7 -> #REF!
A68: ='2.4.'!A8 -> #REF! | B68: ='2.4.'!B8 -> #REF! | C68: ='2.4.'!C8 -> #REF! | D68: ='2.4.'!D8 -> #REF! | E68: ='2.4.'!E8 -> #REF! | F68: ='2.4.'!F8 -> #REF! | G68: ='2.4.'!G8 -> #REF! | H68: ='2.4.'!H8 -> #REF! | I68: ='2.4.'!I8 -> #REF!
A69: ='2.4.'!A9 -> #REF! | B69: ='2.4.'!B9 -> #REF! | C69: ='2.4.'!C9 -> #REF! | D69: ='2.4.'!D9 -> #REF! | E69: ='2.4.'!E9 -> #REF! | F69: ='2.4.'!F9 -> #REF! | G69: ='2.4.'!G9 -> #REF! | H69: ='2.4.'!H9 -> #REF! | I69: ='2.4.'!I9 -> #REF!
A70: ='2.4.'!A10 -> #REF! | B70: ='2.4.'!B10 -> #REF! | C70: ='2.4.'!C10 -> #REF! | D70: ='2.4.'!D10 -> #REF! | E70: ='2.4.'!E10 -> #REF! | F70: ='2.4.'!F10 -> #REF! | G70: ='2.4.'!G10 -> #REF! | H70: ='2.4.'!H10 -> #REF! | I70: ='2.4.'!I10 -> #REF!
A71: ='2.4.'!A11 -> #REF! | B71: ='2.4.'!B11 -> #REF! | C71: ='2.4.'!C11 -> #REF! | D71: ='2.4.'!D11 -> #REF! | E71: ='2.4.'!E11 -> #REF! | F71: ='2.4.'!F11 -> #REF! | G71: ='2.4.'!G11 -> #REF! | H71: ='2.4.'!H11 -> #REF! | I71: ='2.4.'!I11 -> #REF!
A72: ='2.4.'!A12 -> #REF! | B72: ='2.4.'!B12 -> #REF! | C72: ='2.4.'!C12 -> #REF! | D72: ='2.4.'!D12 -> #REF! | E72: ='2.4.'!E12 -> #REF! | F72: ='2.4.'!F12 -> #REF! | G72: ='2.4.'!G12 -> #REF! | H72: ='2.4.'!H12 -> #REF! | I72: ='2.4.'!I12 -> #REF!
A73: ='2.4.'!A13 -> #REF! | B73: ='2.4.'!B13 -> #REF! | C73: ='2.4.'!C13 -> #REF! | D73: ='2.4.'!D13 -> #REF! | E73: ='2.4.'!E13 -> #REF! | F73: ='2.4.'!F13 -> #REF! | G73: ='2.4.'!G13 -> #REF! | H73: ='2.4.'!H13 -> #REF! | I73: ='2.4.'!I13 -> #REF!
A74: ='2.4.'!A14 -> #REF! | B74: ='2.4.'!B14 -> #REF! | C74: ='2.4.'!C14 -> #REF! | D74: ='2.4.'!D14 -> #REF! | E74: ='2.4.'!E14 -> #REF! | F74: ='2.4.'!F14 -> #REF! | G74: ='2.4.'!G14 -> #REF! | H74: ='2.4.'!H14 -> #REF! | I74: ='2.4.'!I14 -> #REF!
A75: ='2.4.'!A15 -> #REF! | B75: ='2.4.'!B15 -> #REF! | C75: ='2.4.'!C15 -> #REF! | D75: ='2.4.'!D15 -> #REF! | E75: ='2.4.'!E15 -> #REF! | F75: ='2.4.'!F15 -> #REF! | G75: ='2.4.'!G15 -> #REF! | H75: ='2.4.'!H15 -> #REF! | I75: ='2.4.'!I15 -> #REF!
A76: ='2.4.'!A16 -> #REF! | B76: ='2.4.'!B16 -> #REF! | C76: ='2.4.'!C16 -> #REF! | D76: ='2.4.'!D16 -> #REF! | E76: ='2.4.'!E16 -> #REF! | F76: ='2.4.'!F16 -> #REF! | G76: ='2.4.'!G16 -> #REF! | H76: ='2.4.'!H16 -> #REF! | I76: ='2.4.'!I16 -> #REF!
A77: ='2.4.'!A17 -> #REF! | B77: ='2.4.'!B17 -> #REF! | C77: ='2.4.'!C17 -> #REF! | D77: ='2.4.'!D17 -> #REF! | E77: ='2.4.'!E17 -> #REF! | F77: ='2.4.'!F17 -> #REF! | G77: ='2.4.'!G17 -> #REF! | H77: ='2.4.'!H17 -> #REF! | I77: ='2.4.'!I17 -> #REF!
A78: ='2.4.'!A18 -> #REF! | B78: ='2.4.'!B18 -> #REF! | C78: ='2.4.'!C18 -> #REF! | D78: ='2.4.'!D18 -> #REF! | E78: ='2.4.'!E18 -> #REF! | F78: ='2.4.'!F18 -> #REF! | G78: ='2.4.'!G18 -> #REF! | H78: ='2.4.'!H18 -> #REF! | I78: ='2.4.'!I18 -> #REF!
... A80: ='2.4.'!A20 -> #REF! | B80: ='2.4.'!B20 -> #REF! | C80: ='2.4.'!C20 -> #REF! | D80: ='2.4.'!D20 -> #REF! | E80: ='2.4.'!E20 -> #REF! | F80: ='2.4.'!F20 -> #REF! | G80: ='2.4.'!G20 -> #REF! | H80: ='2.4.'!H20 -> #REF! | I80: ='2.4.'!I20 -> #REF!
A83: ='2.5.'!A3 -> #REF! | B83: ='2.5.'!B3 -> #REF! | G83: ='2.5.'!G3 -> #REF! | H83: ='2.5.'!H3 -> #REF! | I83: ='2.5.'!I3 -> #REF!
A84: ='2.5.'!A4 -> #REF! | B84: ='2.5.'!B4 -> #REF! | C84: ='2.5.'!C4 -> #REF! | D84: ='2.5.'!D4 -> #REF! | E84: ='2.5.'!E4 -> #REF! | F84: ='2.5.'!F4 -> #REF! | G84: ='2.5.'!G4 -> #REF! | H84: ='2.5.'!H4 -> #REF! | I84: ='2.5.'!I4 -> #REF!
A85: ='2.5.'!A5 -> #REF! | B85: ='2.5.'!B5 -> #REF! | C85: ='2.5.'!C5 -> #REF! | D85: ='2.5.'!D5 -> #REF! | E85: ='2.5.'!E5 -> #REF! | F85: ='2.5.'!F5 -> #REF! | G85: ='2.5.'!G5 -> #REF! | H85: ='2.5.'!H5 -> #REF! | I85: ='2.5.'!I5 -> #REF!
A86: ='2.5.'!A6 -> #REF! | B86: ='2.5.'!B6 -> #REF! | C86: ='2.5.'!C6 -> #REF! | D86: ='2.5.'!D6 -> #REF! | F86: ='2.5.'!F6 -> #REF! | G86: ='2.5.'!G6 -> #REF! | H86: ='2.5.'!H6 -> #REF! | I86: ='2.5.'!I6 -> #REF!
A87: ='2.5.'!A7 -> #REF! | B87: ='2.5.'!B7 -> #REF! | C87: ='2.5.'!C7 -> #REF! | D87: ='2.5.'!D7 -> #REF! | E87: ='2.5.'!E7 -> #REF! | F87: ='2.5.'!F7 -> #REF! | G87: ='2.5.'!G7 -> #REF! | H87: ='2.5.'!H7 -> #REF! | I87: ='2.5.'!I7 -> #REF!
A88: ='2.5.'!A8 -> #REF! | B88: ='2.5.'!B8 -> #REF! | C88: ='2.5.'!C8 -> #REF! | D88: ='2.5.'!D8 -> #REF! | E88: ='2.5.'!E8 -> #REF! | F88: ='2.5.'!F8 -> #REF! | G88: ='2.5.'!G8 -> #REF! | H88: ='2.5.'!H8 -> #REF! | I88: ='2.5.'!I8 -> #REF!
A89: ='2.5.'!A9 -> #REF! | B89: ='2.5.'!B9 -> #REF! | C89: ='2.5.'!C9 -> #REF! | D89: ='2.5.'!D9 -> #REF! | E89: ='2.5.'!E9 -> #REF! | F89: ='2.5.'!F9 -> #REF! | G89: ='2.5.'!G9 -> #REF! | H89: ='2.5.'!H9 -> #REF! | I89: ='2.5.'!I9 -> #REF!
A90: ='2.5.'!A10 -> #REF! | B90: ='2.5.'!B10 -> #REF! | C90: ='2.5.'!C10 -> #REF! | D90: ='2.5.'!D10 -> #REF! | E90: ='2.5.'!E10 -> #REF! | F90: ='2.5.'!F10 -> #REF! | G90: ='2.5.'!G10 -> #REF! | H90: ='2.5.'!H10 -> #REF! | I90: ='2.5.'!I10 -> #REF!
A91: ='2.5.'!A11 -> #REF! | B91: ='2.5.'!B11 -> #REF! | C91: ='2.5.'!C11 -> #REF! | D91: ='2.5.'!D11 -> #REF! | E91: ='2.5.'!E11 -> #REF! | F91: ='2.5.'!F11 -> #REF! | G91: ='2.5.'!G11 -> #REF! | H91: ='2.5.'!H11 -> #REF! | I91: ='2.5.'!I11 -> #REF!
A92: ='2.5.'!A12 -> #REF! | B92: ='2.5.'!B12 -> #REF! | C92: ='2.5.'!C12 -> #REF! | D92: ='2.5.'!D12 -> #REF! | E92: ='2.5.'!E12 -> #REF! | F92: ='2.5.'!F12 -> #REF! | G92: ='2.5.'!G12 -> #REF! | H92: ='2.5.'!H12 -> #REF! | I92: ='2.5.'!I12 -> #REF!
A93: ='2.5.'!A13 -> #REF! | B93: ='2.5.'!B13 -> #REF! | C93: ='2.5.'!C13 -> #REF! | D93: ='2.5.'!D13 -> #REF! | E93: ='2.5.'!E13 -> #REF! | F93: ='2.5.'!F13 -> #REF! | G93: ='2.5.'!G13 -> #REF! | H93: ='2.5.'!H13 -> #REF! | I93: ='2.5.'!I13 -> #REF!
A94: ='2.5.'!A14 -> #REF! | B94: ='2.5.'!B14 -> #REF! | C94: ='2.5.'!C14 -> #REF! | D94: ='2.5.'!D14 -> #REF! | E94: ='2.5.'!E14 -> #REF! | F94: ='2.5.'!F14 -> #REF! | G94: ='2.5.'!G14 -> #REF! | H94: ='2.5.'!H14 -> #REF! | I94: ='2.5.'!I14 -> #REF!
A95: ='2.5.'!A15 -> #REF! | B95: ='2.5.'!B15 -> #REF! | C95: ='2.5.'!C15 -> #REF! | D95: ='2.5.'!D15 -> #REF! | E95: ='2.5.'!E15 -> #REF! | F95: ='2.5.'!F15 -> #REF! | G95: ='2.5.'!G15 -> #REF! | H95: ='2.5.'!H15 -> #REF! | I95: ='2.5.'!I15 -> #REF!
A96: ='2.5.'!A16 -> #REF! | B96: ='2.5.'!B16 -> #REF! | C96: ='2.5.'!C16 -> #REF! | D96: ='2.5.'!D16 -> #REF! | E96: ='2.5.'!E16 -> #REF! | F96: ='2.5.'!F16 -> #REF! | G96: ='2.5.'!G16 -> #REF! | H96: ='2.5.'!H16 -> #REF! | I96: ='2.5.'!I16 -> #REF!
A97: ='2.5.'!A17 -> #REF! | B97: ='2.5.'!B17 -> #REF! | C97: ='2.5.'!C17 -> #REF! | D97: ='2.5.'!D17 -> #REF! | E97: ='2.5.'!E17 -> #REF! | F97: ='2.5.'!F17 -> #REF! | G97: ='2.5.'!G17 -> #REF! | H97: ='2.5.'!H17 -> #REF! | I97: ='2.5.'!I17 -> #REF!
A98: ='2.5.'!A18 -> #REF! | B98: ='2.5.'!B18 -> #REF! | C98: ='2.5.'!C18 -> #REF! | D98: ='2.5.'!D18 -> #REF! | E98: ='2.5.'!E18 -> #REF! | F98: ='2.5.'!F18 -> #REF! | G98: ='2.5.'!G18 -> #REF! | H98: ='2.5.'!H18 -> #REF! | I98: ='2.5.'!I18 -> #REF!
... A100: ='2.5.'!A20 -> #REF! | B100: ='2.5.'!B20 -> #REF! | C100: ='2.5.'!C20 -> #REF! | D100: ='2.5.'!D20 -> #REF! | E100: ='2.5.'!E20 -> #REF! | F100: ='2.5.'!F20 -> #REF! | G100: ='2.5.'!G20 -> #REF! | H100: ='2.5.'!H20 -> #REF! | I100: ='2.5.'!I20 -> #REF!
A103: ='2.6.'!A3 -> #REF! | B103: ='2.6.'!B3 -> #REF! | G103: ='2.6.'!G3 -> #REF! | H103: ='2.6.'!H3 -> #REF! | I103: ='2.6.'!I3 -> #REF!
A104: ='2.6.'!A4 -> #REF! | B104: ='2.6.'!B4 -> #REF! | C104: ='2.6.'!C4 -> #REF! | D104: ='2.6.'!D4 -> #REF! | E104: ='2.6.'!E4 -> #REF! | F104: ='2.6.'!F4 -> #REF! | G104: ='2.6.'!G4 -> #REF! | H104: ='2.6.'!H4 -> #REF! | I104: ='2.6.'!I4 -> #REF!
A105: ='2.6.'!A5 -> #REF! | B105: ='2.6.'!B5 -> #REF! | C105: ='2.6.'!C5 -> #REF! | D105: ='2.6.'!D5 -> #REF! | E105: ='2.6.'!E5 -> #REF! | F105: ='2.6.'!F5 -> #REF! | G105: ='2.6.'!G5 -> #REF! | H105: ='2.6.'!H5 -> #REF! | I105: ='2.6.'!I5 -> #REF!
A106: ='2.6.'!A6 -> #REF! | B106: ='2.6.'!B6 -> #REF! | C106: ='2.6.'!C6 -> #REF! | D106: ='2.6.'!D6 -> #REF! | F106: ='2.6.'!F6 -> #REF! | G106: ='2.6.'!G6 -> #REF! | H106: ='2.6.'!H6 -> #REF! | I106: ='2.6.'!I6 -> #REF!
A107: ='2.6.'!A7 -> #REF! | B107: ='2.6.'!B7 -> #REF! | C107: ='2.6.'!C7 -> #REF! | D107: ='2.6.'!D7 -> #REF! | E107: ='2.6.'!E7 -> #REF! | F107: ='2.6.'!F7 -> #REF! | G107: ='2.6.'!G7 -> #REF! | H107: ='2.6.'!H7 -> #REF! | I107: ='2.6.'!I7 -> #REF!
A108: ='2.6.'!A8 -> #REF! | B108: ='2.6.'!B8 -> #REF! | C108: ='2.6.'!C8 -> #REF! | D108: ='2.6.'!D8 -> #REF! | E108: ='2.6.'!E8 -> #REF! | F108: ='2.6.'!F8 -> #REF! | G108: ='2.6.'!G8 -> #REF! | H108: ='2.6.'!H8 -> #REF! | I108: ='2.6.'!I8 -> #REF!
A109: ='2.6.'!A9 -> #REF! | B109: ='2.6.'!B9 -> #REF! | C109: ='2.6.'!C9 -> #REF! | D109: ='2.6.'!D9 -> #REF! | E109: ='2.6.'!E9 -> #REF! | F109: ='2.6.'!F9 -> #REF! | G109: ='2.6.'!G9 -> #REF! | H109: ='2.6.'!H9 -> #REF! | I109: ='2.6.'!I9 -> #REF!
A110: ='2.6.'!A10 -> #REF! | B110: ='2.6.'!B10 -> #REF! | C110: ='2.6.'!C10 -> #REF! | D110: ='2.6.'!D10 -> #REF! | E110: ='2.6.'!E10 -> #REF! | F110: ='2.6.'!F10 -> #REF! | G110: ='2.6.'!G10 -> #REF! | H110: ='2.6.'!H10 -> #REF! | I110: ='2.6.'!I10 -> #REF!
A111: ='2.6.'!A11 -> #REF! | B111: ='2.6.'!B11 -> #REF! | C111: ='2.6.'!C11 -> #REF! | D111: ='2.6.'!D11 -> #REF! | E111: ='2.6.'!E11 -> #REF! | F111: ='2.6.'!F11 -> #REF! | G111: ='2.6.'!G11 -> #REF! | H111: ='2.6.'!H11 -> #REF! | I111: ='2.6.'!I11 -> #REF!
A112: ='2.6.'!A12 -> #REF! | B112: ='2.6.'!B12 -> #REF! | C112: ='2.6.'!C12 -> #REF! | D112: ='2.6.'!D12 -> #REF! | E112: ='2.6.'!E12 -> #REF! | F112: ='2.6.'!F12 -> #REF! | G112: ='2.6.'!G12 -> #REF! | H112: ='2.6.'!H12 -> #REF! | I112: ='2.6.'!I12 -> #REF!
A113: ='2.6.'!A13 -> #REF! | B113: ='2.6.'!B13 -> #REF! | C113: ='2.6.'!C13 -> #REF! | D113: ='2.6.'!D13 -> #REF! | E113: ='2.6.'!E13 -> #REF! | F113: ='2.6.'!F13 -> #REF! | G113: ='2.6.'!G13 -> #REF! | H113: ='2.6.'!H13 -> #REF! | I113: ='2.6.'!I13 -> #REF!
A114: ='2.6.'!A14 -> #REF! | B114: ='2.6.'!B14 -> #REF! | C114: ='2.6.'!C14 -> #REF! | D114: ='2.6.'!D14 -> #REF! | E114: ='2.6.'!E14 -> #REF! | F114: ='2.6.'!F14 -> #REF! | G114: ='2.6.'!G14 -> #REF! | H114: ='2.6.'!H14 -> #REF! | I114: ='2.6.'!I14 -> #REF!
A115: ='2.6.'!A15 -> #REF! | B115: ='2.6.'!B15 -> #REF! | C115: ='2.6.'!C15 -> #REF! | D115: ='2.6.'!D15 -> #REF! | E115: ='2.6.'!E15 -> #REF! | F115: ='2.6.'!F15 -> #REF! | G115: ='2.6.'!G15 -> #REF! | H115: ='2.6.'!H15 -> #REF! | I115: ='2.6.'!I15 -> #REF!
A116: ='2.6.'!A16 -> #REF! | B116: ='2.6.'!B16 -> #REF! | C116: ='2.6.'!C16 -> #REF! | D116: ='2.6.'!D16 -> #REF! | E116: ='2.6.'!E16 -> #REF! | F116: ='2.6.'!F16 -> #REF! | G116: ='2.6.'!G16 -> #REF! | H116: ='2.6.'!H16 -> #REF! | I116: ='2.6.'!I16 -> #REF!
A117: ='2.6.'!A17 -> #REF! | B117: ='2.6.'!B17 -> #REF! | C117: ='2.6.'!C17 -> #REF! | D117: ='2.6.'!D17 -> #REF! | E117: ='2.6.'!E17 -> #REF! | F117: ='2.6.'!F17 -> #REF! | G117: ='2.6.'!G17 -> #REF! | H117: ='2.6.'!H17 -> #REF! | I117: ='2.6.'!I17 -> #REF!
A118: ='2.6.'!A18 -> #REF! | B118: ='2.6.'!B18 -> #REF! | C118: ='2.6.'!C18 -> #REF! | D118: ='2.6.'!D18 -> #REF! | E118: ='2.6.'!E18 -> #REF! | F118: ='2.6.'!F18 -> #REF! | G118: ='2.6.'!G18 -> #REF! | H118: ='2.6.'!H18 -> #REF! | I118: ='2.6.'!I18 -> #REF!
...

Sheet 01_RESUMEN MAT M.O.
A1: ='01_C&P'!A1 -> EDIFICIO LAS HERAS
A3: ='2.1.'!A3 -> 45293 | B3: ='2.1.'!B3 -> COLUMNAS Y TABIQUES | G3: ='2.1.'!G3 | H3: ='2.1.'!H3 -> 31 | I3: ='2.1.'!I3 -> m³
A5: ='2.1.'!A53 -> MANO DE OBRA - MATERIALES | C5: ='2.1.'!C53 | D5: ='2.1.'!D53 | E5: ='2.1.'!E53 | F5: ='2.1.'!F53 | G5: ='2.1.'!G53 | H5: ='2.1.'!H53 | I5: ='2.1.'!I53
A6: ='2.1.'!A54 -> Código | B6: ='2.1.'!B54 -> Descripción | C6: ='2.1.'!C54 -> Unidad | D6: ='2.1.'!D54 -> Cantidad | E6: ='2.1.'!E54 | F6: ='2.1.'!F54 -> Desperdicio | G6: ='2.1.'!G54 -> Cantidad + Desperdicio | H6: ='2.1.'!H54 -> Precio Unitario | I6: ='2.1.'!I54 -> Subtotal
A7: ='2.1.'!A55 | B7: ='2.1.'!B55 | C7: ='2.1.'!C55 | D7: ='2.1.'!D55 | E7: ='2.1.'!E55 | F7: ='2.1.'!F55 -> 0.1 | G7: ='2.1.'!G55 -> 0 | H7: ='2.1.'!H55 | I7: ='2.1.'!I55 -> 0
A8: ='2.1.'!A56 | B8: ='2.1.'!B56 | C8: ='2.1.'!C56 | D8: ='2.1.'!D56 | E8: ='2.1.'!E56 | F8: ='2.1.'!F56 -> 0.1 | G8: ='2.1.'!G56 -> 0 | H8: ='2.1.'!H56 | I8: ='2.1.'!I56 -> 0
A9: ='2.1.'!A57 -> CL2 | B9: ='2.1.'!B57 -> Clavos 2" punta paris (k) | C9: ='2.1.'!C57 -> k | D9: ='2.1.'!D57 -> 10 | E9: ='2.1.'!E57 | F9: ='2.1.'!F57 -> 0.1 | G9: ='2.1.'!G57 -> 11 | H9: ='2.1.'!H57 -> 4500 | I9: ='2.1.'!I57 -> 49500
A10: =#REF! -> #REF! | B10: =#REF! -> #REF! | C10: ='2.1.'!C58 -> k | D10: ='2.1.'!D58 -> 1 | E10: ='2.1.'!E58 | F10: ='2.1.'!F58 -> 0.1 | G10: ='2.1.'!G58 -> 2 | H10: ='2.1.'!H58 -> 220000 | I10: ='2.1.'!I58 -> 440000
A11: ='2.1.'!A58 -> AL-50k | B11: ='2.1.'!B58 -> Alambre Fardo (50 k) | C11: ='2.1.'!C59 -> k | D11: ='2.1.'!D59 | E11: ='2.1.'!E59 | F11: ='2.1.'!F59 -> 0.1 | G11: ='2.1.'!G59 -> 0 | H11: ='2.1.'!H59 | I11: ='2.1.'!I59 -> 0
A12: ='2.1.'!A60 | B12: ='2.1.'!B60 | C12: ='2.1.'!C60 | D12: ='2.1.'!D60 | E12: ='2.1.'!E60 | F12: ='2.1.'!F60 | G12: ='2.1.'!G60 -> 0 | H12: ='2.1.'!H60 | I12: ='2.1.'!I60 -> 0
A13: ='2.1.'!A61 | B13: ='2.1.'!B61 | C13: ='2.1.'!C61 | D13: ='2.1.'!D61 | E13: ='2.1.'!E61 | F13: ='2.1.'!F61 | G13: ='2.1.'!G61 | H13: ='2.1.'!H61 | I13: ='2.1.'!I61
A14: ='2.1.'!A62 -> TOTAL | B14: ='2.1.'!B62 | C14: ='2.1.'!C62 | D14: ='2.1.'!D62 | E14: ='2.1.'!E62 | F14: ='2.1.'!F62 | G14: ='2.1.'!G62 | H14: ='2.1.'!H62 | I14: ='2.1.'!I62 -> 489500
A17: ='2.2.'!A3 -> n | B17: ='2.2.'!B3 -> VIGAS | G17: ='2.2.'!G3 | H17: ='2.2.'!H3 -> 14 | I17: ='2.2.'!I3 -> m³
A19: ='2.2.'!A53 -> MANO DE OBRA - MATERIALES | C19: ='2.2.'!C53 | D19: ='2.2.'!D53 | E19: ='2.2.'!E53 | F19: ='2.2.'!F53 | G19: ='2.2.'!G53 | H19: ='2.2.'!H53 | I19: ='2.2.'!I53
A20: ='2.2.'!A54 -> Código | B20: ='2.2.'!B54 -> Descripción | C20: ='2.2.'!C54 -> Unidad | D20: ='2.2.'!D54 -> Cantidad | E20: ='2.2.'!E54 | F20: ='2.2.'!F54 -> Desperdicio | G20: ='2.2.'!G54 -> Cantidad + Desperdicio | H20: ='2.2.'!H54 -> Precio Unitario | I20: ='2.2.'!I54 -> Subtotal
A21: ='2.2.'!A55 | B21: ='2.2.'!B55 | C21: ='2.2.'!C55 | D21: ='2.2.'!D55 | E21: ='2.2.'!E55 | F21: ='2.2.'!F55 -> 0.1 | G21: ='2.2.'!G55 -> 0 | H21: ='2.2.'!H55 | I21: ='2.2.'!I55 -> 0
A22: ='2.2.'!A56 | B22: ='2.2.'!B56 | C22: ='2.2.'!C56 | D22: ='2.2.'!D56 | E22: ='2.2.'!E56 | F22: ='2.2.'!F56 -> 0.1 | G22: ='2.2.'!G56 -> 0 | H22: ='2.2.'!H56 | I22: ='2.2.'!I56 -> 0
A23: ='2.2.'!A57 -> CL2 | B23: ='2.2.'!B57 -> Clavos 2" punta paris (k) | C23: ='2.2.'!C57 -> k | D23: ='2.2.'!D57 -> 10 | E23: ='2.2.'!E57 | F23: ='2.2.'!F57 -> 0.1 | G23: ='2.2.'!G57 -> 11 | H23: ='2.2.'!H57 -> 4500 | I23: ='2.2.'!I57 -> 49500
A24: ='2.2.'!A58 -> AL-50k | B24: ='2.2.'!B58 -> Alambre Fardo (50 k) | C24: ='2.2.'!C58 -> k | D24: ='2.2.'!D58 -> 1 | E24: ='2.2.'!E58 | F24: ='2.2.'!F58 | G24: ='2.2.'!G58 -> 1 | H24: ='2.2.'!H58 -> 220000 | I24: ='2.2.'!I58 -> 220000
A25: ='2.2.'!A59 | B25: ='2.2.'!B59 | C25: ='2.2.'!C59 | D25: ='2.2.'!D59 | E25: ='2.2.'!E59 | F25: ='2.2.'!F59 -> 0.1 | G25: ='2.2.'!G59 -> 0 | H25: ='2.2.'!H59 | I25: ='2.2.'!I59 -> 0
A26: ='2.2.'!A60 | B26: ='2.2.'!B60 | C26: ='2.2.'!C60 | D26: ='2.2.'!D60 | E26: ='2.2.'!E60 | F26: ='2.2.'!F60 -> 0.1 | G26: ='2.2.'!G60 -> 0 | H26: ='2.2.'!H60 | I26: ='2.2.'!I60 -> 0
A27: ='2.2.'!A61 | B27: ='2.2.'!B61 | C27: ='2.2.'!C61 | D27: ='2.2.'!D61 | E27: ='2.2.'!E61 | F27: ='2.2.'!F61 | G27: ='2.2.'!G61 | H27: ='2.2.'!H61 | I27: ='2.2.'!I61
A28: ='2.2.'!A62 -> TOTAL | B28: ='2.2.'!B62 | C28: ='2.2.'!C62 | D28: ='2.2.'!D62 | E28: ='2.2.'!E62 | F28: ='2.2.'!F62 | G28: ='2.2.'!G62 | H28: ='2.2.'!H62 | I28: ='2.2.'!I62 -> 269500
A31: ='2.3.'!A3 -> #REF! | B31: ='2.3.'!B3 -> #REF! | G31: ='2.3.'!G3 -> #REF! | H31: ='2.3.'!H3 -> #REF! | I31: ='2.3.'!I3 -> #REF!
A33: ='2.3.'!A53 -> #REF! | C33: ='2.3.'!C53 -> #REF! | D33: ='2.3.'!D53 -> #REF! | E33: ='2.3.'!E53 -> #REF! | F33: ='2.3.'!F53 -> #REF! | G33: ='2.3.'!G53 -> #REF! | H33: ='2.3.'!H53 -> #REF! | I33: ='2.3.'!I53 -> #REF!
A34: ='2.3.'!A54 -> #REF! | B34: ='2.3.'!B54 -> #REF! | C34: ='2.3.'!C54 -> #REF! | D34: ='2.3.'!D54 -> #REF! | E34: ='2.3.'!E54 -> #REF! | F34: ='2.3.'!F54 -> #REF! | G34: ='2.3.'!G54 -> #REF! | H34: ='2.3.'!H54 -> #REF! | I34: ='2.3.'!I54 -> #REF!
A35: ='2.3.'!A55 -> #REF! | B35: ='2.3.'!B55 -> #REF! | C35: ='2.3.'!C55 -> #REF! | D35: ='2.3.'!D55 -> #REF! | E35: ='2.3.'!E55 -> #REF! | F35: ='2.3.'!F55 -> #REF! | G35: ='2.3.'!G55 -> #REF! | H35: ='2.3.'!H55 -> #REF! | I35: ='2.3.'!I55 -> #REF!
A36: ='2.3.'!A56 -> #REF! | B36: ='2.3.'!B56 -> #REF! | C36: ='2.3.'!C56 -> #REF! | D36: ='2.3.'!D56 -> #REF! | E36: ='2.3.'!E56 -> #REF! | F36: ='2.3.'!F56 -> #REF! | G36: ='2.3.'!G56 -> #REF! | H36: ='2.3.'!H56 -> #REF! | I36: ='2.3.'!I56 -> #REF!
A37: ='2.3.'!A57 -> #REF! | B37: ='2.3.'!B57 -> #REF! | C37: ='2.3.'!C57 -> #REF! | D37: ='2.3.'!D57 -> #REF! | E37: ='2.3.'!E57 -> #REF! | F37: ='2.3.'!F57 -> #REF! | G37: ='2.3.'!G57 -> #REF! | H37: ='2.3.'!H57 -> #REF! | I37: ='2.3.'!I57 -> #REF!
A38: ='2.3.'!A58 -> #REF! | B38: ='2.3.'!B58 -> #REF! | C38: ='2.3.'!C58 -> #REF! | D38: ='2.3.'!D58 -> #REF! | E38: ='2.3.'!E58 -> #REF! | F38: ='2.3.'!F58 -> #REF! | G38: ='2.3.'!G58 -> #REF! | H38: ='2.3.'!H58 -> #REF! | I38: ='2.3.'!I58 -> #REF!
A39: ='2.3.'!A59 -> #REF! | B39: ='2.3.'!B59 -> #REF! | C39: ='2.3.'!C59 -> #REF! | D39: ='2.3.'!D59 -> #REF! | E39: ='2.3.'!E59 -> #REF! | F39: ='2.3.'!F59 -> #REF! | G39: ='2.3.'!G59 -> #REF! | H39: ='2.3.'!H59 -> #REF! | I39: ='2.3.'!I59 -> #REF!
A40: ='2.3.'!A60 -> #REF! | B40: ='2.3.'!B60 -> #REF! | C40: ='2.3.'!C60 -> #REF! | D40: ='2.3.'!D60 -> #REF! | E40: ='2.3.'!E60 -> #REF! | F40: ='2.3.'!F60 -> #REF! | G40: ='2.3.'!G60 -> #REF! | H40: ='2.3.'!H60 -> #REF! | I40: ='2.3.'!I60 -> #REF!
A41: ='2.3.'!A61 -> #REF! | B41: ='2.3.'!B61 -> #REF! | C41: ='2.3.'!C61 -> #REF! | D41: ='2.3.'!D61 -> #REF! | E41: ='2.3.'!E61 -> #REF! | F41: ='2.3.'!F61 -> #REF! | G41: ='2.3.'!G61 -> #REF! | H41: ='2.3.'!H61 -> #REF! | I41: ='2.3.'!I61 -> #REF!
A42: ='2.3.'!A62 -> #REF! | B42: ='2.3.'!B62 -> #REF! | C42: ='2.3.'!C62 -> #REF! | D42: ='2.3.'!D62 -> #REF! | E42: ='2.3.'!E62 -> #REF! | F42: ='2.3.'!F62 -> #REF! | G42: ='2.3.'!G62 -> #REF! | H42: ='2.3.'!H62 -> #REF! | I42: ='2.3.'!I62 -> #REF!
A45: ='2.4.'!A3 -> #REF! | B45: ='2.4.'!B3 -> #REF! | G45: ='2.4.'!G3 -> #REF! | H45: ='2.4.'!H3 -> #REF! | I45: ='2.4.'!I3 -> #REF!
A47: ='2.4.'!A53 -> #REF! | B47: ='2.4.'!B53 -> #REF! | C47: ='2.4.'!C53 -> #REF! | D47: ='2.4.'!D53 -> #REF! | E47: ='2.4.'!E53 -> #REF! | F47: ='2.4.'!F53 -> #REF! | G47: ='2.4.'!G53 -> #REF! | H47: ='2.4.'!H53 -> #REF! | I47: ='2.4.'!I53 -> #REF!
A48: ='2.4.'!A54 -> #REF! | B48: ='2.4.'!B54 -> #REF! | C48: ='2.4.'!C54 -> #REF! | D48: ='2.4.'!D54 -> #REF! | E48: ='2.4.'!E54 -> #REF! | F48: ='2.4.'!F54 -> #REF! | G48: ='2.4.'!G54 -> #REF! | H48: ='2.4.'!H54 -> #REF! | I48: ='2.4.'!I54 -> #REF!
A49: ='2.4.'!A55 -> #REF! | B49: ='2.4.'!B55 -> #REF! | C49: ='2.4.'!C55 -> #REF! | D49: ='2.4.'!D55 -> #REF! | E49: ='2.4.'!E55 -> #REF! | F49: ='2.4.'!F55 -> #REF! | G49: ='2.4.'!G55 -> #REF! | H49: ='2.4.'!H55 -> #REF! | I49: ='2.4.'!I55 -> #REF!
A50: ='2.4.'!A56 -> #REF! | B50: ='2.4.'!B56 -> #REF! | C50: ='2.4.'!C56 -> #REF! | D50: ='2.4.'!D56 -> #REF! | E50: ='2.4.'!E56 -> #REF! | F50: ='2.4.'!F56 -> #REF! | G50: ='2.4.'!G56 -> #REF! | H50: ='2.4.'!H56 -> #REF! | I50: ='2.4.'!I56 -> #REF!
A51: ='2.4.'!A57 -> #REF! | B51: ='2.4.'!B57 -> #REF! | C51: ='2.4.'!C57 -> #REF! | D51: ='2.4.'!D57 -> #REF! | E51: ='2.4.'!E57 -> #REF! | F51: ='2.4.'!F57 -> #REF! | G51: ='2.4.'!G57 -> #REF! | H51: ='2.4.'!H57 -> #REF! | I51: ='2.4.'!I57 -> #REF!
A52: ='2.4.'!A58 -> #REF! | B52: ='2.4.'!B58 -> #REF! | C52: ='2.4.'!C58 -> #REF! | D52: ='2.4.'!D58 -> #REF! | E52: ='2.4.'!E58 -> #REF! | F52: ='2.4.'!F58 -> #REF! | G52: ='2.4.'!G58 -> #REF! | H52: ='2.4.'!H58 -> #REF! | I52: ='2.4.'!I58 -> #REF!
A53: ='2.4.'!A59 -> #REF! | B53: ='2.4.'!B59 -> #REF! | C53: ='2.4.'!C59 -> #REF! | D53: ='2.4.'!D59 -> #REF! | E53: ='2.4.'!E59 -> #REF! | F53: ='2.4.'!F59 -> #REF! | G53: ='2.4.'!G59 -> #REF! | H53: ='2.4.'!H59 -> #REF! | I53: ='2.4.'!I59 -> #REF!
A54: ='2.4.'!A60 -> #REF! | B54: ='2.4.'!B60 -> #REF! | C54: ='2.4.'!C60 -> #REF! | D54: ='2.4.'!D60 -> #REF! | E54: ='2.4.'!E60 -> #REF! | F54: ='2.4.'!F60 -> #REF! | G54: ='2.4.'!G60 -> #REF! | H54: ='2.4.'!H60 -> #REF! | I54: ='2.4.'!I60 -> #REF!
A55: ='2.4.'!A61 -> #REF! | B55: ='2.4.'!B61 -> #REF! | C55: ='2.4.'!C61 -> #REF! | D55: ='2.4.'!D61 -> #REF! | E55: ='2.4.'!E61 -> #REF! | F55: ='2.4.'!F61 -> #REF! | G55: ='2.4.'!G61 -> #REF! | H55: ='2.4.'!H61 -> #REF! | I55: ='2.4.'!I61 -> #REF!
A56: ='2.4.'!A62 -> #REF! | B56: ='2.4.'!B62 -> #REF! | C56: ='2.4.'!C62 -> #REF! | D56: ='2.4.'!D62 -> #REF! | E56: ='2.4.'!E62 -> #REF! | F56: ='2.4.'!F62 -> #REF! | G56: ='2.4.'!G62 -> #REF! | H56: ='2.4.'!H62 -> #REF! | I56: ='2.4.'!I62 -> #REF!
A59: ='2.5.'!A3 -> #REF! | B59: ='2.5.'!B3 -> #REF! | G59: ='2.5.'!G3 -> #REF! | H59: ='2.5.'!H3 -> #REF! | I59: ='2.5.'!I3 -> #REF!
A61: ='2.5.'!A53 -> #REF! | B61: ='2.5.'!B53 -> #REF! | C61: ='2.5.'!C53 -> #REF! | D61: ='2.5.'!D53 -> #REF! | E61: ='2.5.'!E53 -> #REF! | F61: ='2.5.'!F53 -> #REF! | G61: ='2.5.'!G53 -> #REF! | H61: ='2.5.'!H53 -> #REF! | I61: ='2.5.'!I53 -> #REF!
A62: ='2.5.'!A54 -> #REF! | B62: ='2.5.'!B54 -> #REF! | C62: ='2.5.'!C54 -> #REF! | D62: ='2.5.'!D54 -> #REF! | E62: ='2.5.'!E54 -> #REF! | F62: ='2.5.'!F54 -> #REF! | G62: ='2.5.'!G54 -> #REF! | H62: ='2.5.'!H54 -> #REF! | I62: ='2.5.'!I54 -> #REF!
A63: ='2.5.'!A55 -> #REF! | B63: ='2.5.'!B55 -> #REF! | C63: ='2.5.'!C55 -> #REF! | D63: ='2.5.'!D55 -> #REF! | E63: ='2.5.'!E55 -> #REF! | F63: ='2.5.'!F55 -> #REF! | G63: ='2.5.'!G55 -> #REF! | H63: ='2.5.'!H55 -> #REF! | I63: ='2.5.'!I55 -> #REF!
A64: ='2.5.'!A56 -> #REF! | B64: ='2.5.'!B56 -> #REF! | C64: ='2.5.'!C56 -> #REF! | D64: ='2.5.'!D56 -> #REF! | E64: ='2.5.'!E56 -> #REF! | F64: ='2.5.'!F56 -> #REF! | G64: ='2.5.'!G56 -> #REF! | H64: ='2.5.'!H56 -> #REF! | I64: ='2.5.'!I56 -> #REF!
A65: ='2.5.'!A57 -> #REF! | B65: ='2.5.'!B57 -> #REF! | C65: ='2.5.'!C57 -> #REF! | D65: ='2.5.'!D57 -> #REF! | E65: ='2.5.'!E57 -> #REF! | F65: ='2.5.'!F57 -> #REF! | G65: ='2.5.'!G57 -> #REF! | H65: ='2.5.'!H57 -> #REF! | I65: ='2.5.'!I57 -> #REF!
A66: ='2.5.'!A58 -> #REF! | B66: ='2.5.'!B58 -> #REF! | C66: ='2.5.'!C58 -> #REF! | D66: ='2.5.'!D58 -> #REF! | E66: ='2.5.'!E58 -> #REF! | F66: ='2.5.'!F58 -> #REF! | G66: ='2.5.'!G58 -> #REF! | H66: ='2.5.'!H58 -> #REF! | I66: ='2.5.'!I58 -> #REF!
A67: ='2.5.'!A59 -> #REF! | B67: ='2.5.'!B59 -> #REF! | C67: ='2.5.'!C59 -> #REF! | D67: ='2.5.'!D59 -> #REF! | E67: ='2.5.'!E59 -> #REF! | F67: ='2.5.'!F59 -> #REF! | G67: ='2.5.'!G59 -> #REF! | H67: ='2.5.'!H59 -> #REF! | I67: ='2.5.'!I59 -> #REF!
A68: ='2.5.'!A60 -> #REF! | B68: ='2.5.'!B60 -> #REF! | C68: ='2.5.'!C60 -> #REF! | D68: ='2.5.'!D60 -> #REF! | E68: ='2.5.'!E60 -> #REF! | F68: ='2.5.'!F60 -> #REF! | G68: ='2.5.'!G60 -> #REF! | H68: ='2.5.'!H60 -> #REF! | I68: ='2.5.'!I60 -> #REF!
A69: ='2.5.'!A61 -> #REF! | B69: ='2.5.'!B61 -> #REF! | C69: ='2.5.'!C61 -> #REF! | D69: ='2.5.'!D61 -> #REF! | E69: ='2.5.'!E61 -> #REF! | F69: ='2.5.'!F61 -> #REF! | G69: ='2.5.'!G61 -> #REF! | H69: ='2.5.'!H61 -> #REF! | I69: ='2.5.'!I61 -> #REF!
A70: ='2.5.'!A62 -> #REF! | B70: ='2.5.'!B62 -> #REF! | C70: ='2.5.'!C62 -> #REF! | D70: ='2.5.'!D62 -> #REF! | E70: ='2.5.'!E62 -> #REF! | F70: ='2.5.'!F62 -> #REF! | G70: ='2.5.'!G62 -> #REF! | H70: ='2.5.'!H62 -> #REF! | I70: ='2.5.'!I62 -> #REF!
A73: ='2.6.'!A3 -> #REF! | B73: ='2.1.'!B73 | G73: ='2.1.'!G73 -> 0 | H73: ='2.1.'!H73 | I73: ='2.1.'!I73
A75: ='2.6.'!A53 -> #REF! | B75: ='2.6.'!B53 -> #REF! | C75: ='2.6.'!C53 -> #REF! | D75: ='2.6.'!D53 -> #REF! | E75: ='2.6.'!E53 -> #REF! | F75: ='2.6.'!F53 -> #REF! | G75: ='2.6.'!G53 -> #REF! | H75: ='2.6.'!H53 -> #REF! | I75: ='2.6.'!I53 -> #REF!
A76: ='2.6.'!A54 -> #REF! | B76: ='2.6.'!B54 -> #REF! | C76: ='2.6.'!C54 -> #REF! | D76: ='2.6.'!D54 -> #REF! | E76: ='2.6.'!E54 -> #REF! | F76: ='2.6.'!F54 -> #REF! | G76: ='2.6.'!G54 -> #REF! | H76: ='2.6.'!H54 -> #REF! | I76: ='2.6.'!I54 -> #REF!
A77: ='2.6.'!A55 -> #REF! | B77: ='2.6.'!B55 -> #REF! | C77: ='2.6.'!C55 -> #REF! | D77: ='2.6.'!D55 -> #REF! | E77: ='2.6.'!E55 -> #REF! | F77: ='2.6.'!F55 -> #REF! | G77: ='2.6.'!G55 -> #REF! | H77: ='2.6.'!H55 -> #REF! | I77: ='2.6.'!I55 -> #REF!
A78: ='2.6.'!A56 -> #REF! | B78: ='2.6.'!B56 -> #REF! | C78: ='2.6.'!C56 -> #REF! | D78: ='2.6.'!D56 -> #REF! | E78: ='2.6.'!E56 -> #REF! | F78: ='2.6.'!F56 -> #REF! | G78: ='2.6.'!G56 -> #REF! | H78: ='2.6.'!H56 -> #REF! | I78: ='2.6.'!I56 -> #REF!
A79: ='2.6.'!A57 -> #REF! | B79: ='2.6.'!B57 -> #REF! | C79: ='2.6.'!C57 -> #REF! | D79: ='2.6.'!D57 -> #REF! | E79: ='2.6.'!E57 -> #REF! | F79: ='2.6.'!F57 -> #REF! | G79: ='2.6.'!G57 -> #REF! | H79: ='2.6.'!H57 -> #REF! | I79: ='2.6.'!I57 -> #REF!
A80: ='2.6.'!A58 -> #REF! | B80: ='2.6.'!B58 -> #REF! | C80: ='2.6.'!C58 -> #REF! | D80: ='2.6.'!D58 -> #REF! | E80: ='2.6.'!E58 -> #REF! | F80: ='2.6.'!F58 -> #REF! | G80: ='2.6.'!G58 -> #REF! | H80: ='2.6.'!H58 -> #REF! | I80: ='2.6.'!I58 -> #REF!
A81: ='2.6.'!A59 -> #REF! | B81: ='2.6.'!B59 -> #REF! | C81: ='2.6.'!C59 -> #REF! | D81: ='2.6.'!D59 -> #REF! | E81: ='2.6.'!E59 -> #REF! | F81: ='2.6.'!F59 -> #REF! | G81: ='2.6.'!G59 -> #REF! | H81: ='2.6.'!H59 -> #REF! | I81: ='2.6.'!I59 -> #REF!
A82: ='2.6.'!A60 -> #REF! | B82: ='2.6.'!B60 -> #REF! | C82: ='2.6.'!C60 -> #REF! | D82: ='2.6.'!D60 -> #REF! | E82: ='2.6.'!E60 -> #REF! | F82: ='2.6.'!F60 -> #REF! | G82: ='2.6.'!G60 -> #REF! | H82: ='2.6.'!H60 -> #REF! | I82: ='2.6.'!I60 -> #REF!
A83: ='2.6.'!A61 -> #REF! | B83: ='2.6.'!B61 -> #REF! | C83: ='2.6.'!C61 -> #REF! | D83: ='2.6.'!D61 -> #REF! | E83: ='2.6.'!E61 -> #REF! | F83: ='2.6.'!F61 -> #REF! | G83: ='2.6.'!G61 -> #REF! | H83: ='2.6.'!H61 -> #REF! | I83: ='2.6.'!I61 -> #REF!
A84: ='2.6.'!A62 -> #REF! | B84: ='2.6.'!B62 -> #REF! | C84: ='2.6.'!C62 -> #REF! | D84: ='2.6.'!D62 -> #REF! | E84: ='2.6.'!E62 -> #REF! | F84: ='2.6.'!F62 -> #REF! | G84: ='2.6.'!G62 -> #REF! | H84: ='2.6.'!H62 -> #REF! | I84: ='2.6.'!I62 -> #REF!
A87: ='2.6'!A3 -> 46175 | B87: ='2.1.'!B87 | G87: ='2.1.'!G87 | H87: ='2.1.'!H87 | I87: ='2.1.'!I87
A89: ='2.6'!A53 -> MANO DE OBRA - MATERIALES | B89: ='2.6'!B53 | C89: ='2.6'!C53 | D89: ='2.6'!D53 | E89: ='2.6'!E53 | F89: ='2.6'!F53 | G89: ='2.6'!G53 | H89: ='2.6'!H53 | I89: ='2.6'!I53
A90: ='2.6'!A54 -> Código | B90: ='2.6'!B54 -> Descripción | C90: ='2.6'!C54 -> Unidad | D90: ='2.6'!D54 -> Cantidad | E90: ='2.6'!E54 | F90: ='2.6'!F54 -> Desperdicio | G90: ='2.6'!G54 -> Cantidad + Desperdicio | H90: ='2.6'!H54 -> Precio Unitario | I90: ='2.6'!I54 -> Subtotal
A91: ='2.6'!A55 | B91: ='2.6'!B55 | C91: ='2.6'!C55 | D91: ='2.6'!D55 | E91: ='2.6'!E55 | F91: ='2.6'!F55 | G91: ='2.6'!G55 -> 0 | H91: ='2.6'!H55 | I91: ='2.6'!I55 -> 0
A92: ='2.6'!A56 | B92: ='2.6'!B56 | C92: ='2.6'!C56 | D92: ='2.6'!D56 | E92: ='2.6'!E56 | F92: ='2.6'!F56 | G92: ='2.6'!G56 -> 0 | H92: ='2.6'!H56 | I92: ='2.6'!I56 -> 0
A93: ='2.6'!A57 | B93: ='2.6'!B57 | C93: ='2.6'!C57 | D93: ='2.6'!D57 | E93: ='2.6'!E57 | F93: ='2.6'!F57 | G93: ='2.6'!G57 -> 0 | H93: ='2.6'!H57 | I93: ='2.6'!I57
A94: ='2.6'!A58 | B94: ='2.6'!B58 | C94: ='2.6'!C58 | D94: ='2.6'!D58 | E94: ='2.6'!E58 | F94: ='2.6'!F58 | G94: ='2.6'!G58 -> 0 | H94: ='2.6'!H58 | I94: ='2.6'!I58
A95: ='2.6'!A59 | B95: ='2.6'!B59 | C95: ='2.6'!C59 | D95: ='2.6'!D59 | E95: ='2.6'!E59 | F95: ='2.6'!F59 | G95: ='2.6'!G59 -> 0 | H95: ='2.6'!H59 | I95: ='2.6'!I59
A96: ='2.6'!A60 | B96: ='2.6'!B60 | C96: ='2.6'!C60 | D96: ='2.6'!D60 | E96: ='2.6'!E60 | F96: ='2.6'!F60 | G96: ='2.6'!G60 -> 0 | H96: ='2.6'!H60 | I96: ='2.6'!I60
A97: ='2.6'!A61 | B97: ='2.6'!B61 | C97: ='2.6'!C61 | D97: ='2.6'!D61 | E97: ='2.6'!E61 | F97: ='2.6'!F61 | G97: ='2.6'!G61 | H97: ='2.6'!H61 | I97: ='2.6'!I61
A98: ='2.6'!A62 -> TOTAL | B98: ='2.6'!B62 | C98: ='2.6'!C62 | D98: ='2.6'!D62 | E98: ='2.6'!E62 | F98: ='2.6'!F62 | G98: ='2.6'!G62 | H98: ='2.6'!H62 | I98: ='2.6'!I62 -> 0
A101: ='2.7'!A3 -> 46205 | B101: ='2.1.'!B101 | G101: ='2.1.'!G101 | H101: ='2.1.'!H101 | I101: ='2.1.'!I101
A103: ='2.7'!A53 -> MANO DE OBRA - MATERIALES | B103: ='2.7'!B53 | C103: ='2.7'!C53 | D103: ='2.7'!D53 | E103: ='2.7'!E53 | F103: ='2.7'!F53 | G103: ='2.7'!G53 | H103: ='2.7'!H53 | I103: ='2.7'!I53
A104: ='2.7'!A54 -> Código | B104: ='2.7'!B54 -> Descripción | C104: ='2.7'!C54 -> Unidad | D104: ='2.7'!D54 -> Cantidad | E104: ='2.7'!E54 | F104: ='2.7'!F54 -> Desperdicio | G104: ='2.7'!G54 -> Cantidad + Desperdicio | H104: ='2.7'!H54 -> Precio Unitario | I104: ='2.7'!I54 -> Subtotal
A105: ='2.7'!A55 | B105: ='2.7'!B55 | C105: ='2.7'!C55 | D105: ='2.7'!D55 | E105: ='2.7'!E55 | F105: ='2.7'!F55 | G105: ='2.7'!G55 -> 0 | H105: ='2.7'!H55 | I105: ='2.7'!I55
A106: ='2.7'!A56 | B106: ='2.7'!B56 | C106: ='2.7'!C56 | D106: ='2.7'!D56 | E106: ='2.7'!E56 | F106: ='2.7'!F56 | G106: ='2.7'!G56 -> 0 | H106: ='2.7'!H56 | I106: ='2.7'!I56
A107: ='2.7'!A57 | B107: ='2.7'!B57 | C107: ='2.7'!C57 | D107: ='2.7'!D57 | E107: ='2.7'!E57 | F107: ='2.7'!F57 | G107: ='2.7'!G57 -> 0 | H107: ='2.7'!H57 | I107: ='2.7'!I57
A108: ='2.7'!A58 | B108: ='2.7'!B58 | C108: ='2.7'!C58 | D108: ='2.7'!D58 | E108: ='2.7'!E58 | F108: ='2.7'!F58 | G108: ='2.7'!G58 -> 0 | H108: ='2.7'!H58 | I108: ='2.7'!I58
A109: ='2.7'!A59 | B109: ='2.7'!B59 | C109: ='2.7'!C59 | D109: ='2.7'!D59 | E109: ='2.7'!E59 | F109: ='2.7'!F59 | G109: ='2.7'!G59 -> 0 | H109: ='2.7'!H59 | I109: ='2.7'!I59
A110: ='2.7'!A60 | B110: ='2.7'!B60 | C110: ='2.7'!C60 | D110: ='2.7'!D60 | E110: ='2.7'!E60 | F110: ='2.7'!F60 | G110: ='2.7'!G60 -> 0 | H110: ='2.7'!H60 | I110: ='2.7'!I60
A111: ='2.7'!A61 | B111: ='2.7'!B61 | C111: ='2.7'!C61 | D111: ='2.7'!D61 | E111: ='2.7'!E61 | F111: ='2.7'!F61 | G111: ='2.7'!G61 | H111: ='2.7'!H61 | I111: ='2.7'!I61
A112: ='2.7'!A62 -> TOTAL | B112: ='2.7'!B62 | C112: ='2.7'!C62 | D112: ='2.7'!D62 | E112: ='2.7'!E62 | F112: ='2.7'!F62 | G112: ='2.7'!G62 | H112: ='2.7'!H62 | I112: ='2.7'!I62 -> 0
A115: ='2.8'!A3 -> 46236 | B115: ='2.1.'!B115 | G115: ='2.1.'!G115 | H115: ='2.1.'!H115 | I115: ='2.1.'!I115
A117: ='2.8'!A53 -> MANO DE OBRA - MATERIALES | B117: ='2.8'!B53 | C117: ='2.8'!C53 | D117: ='2.8'!D53 | E117: ='2.8'!E53 | F117: ='2.8'!F53 | G117: ='2.8'!G53 | H117: ='2.8'!H53 | I117: ='2.8'!I53
A118: ='2.8'!A54 -> Código | B118: ='2.8'!B54 -> Descripción | C118: ='2.8'!C54 -> Unidad | D118: ='2.8'!D54 -> Cantidad | E118: ='2.8'!E54 | F118: ='2.8'!F54 -> Desperdicio | G118: ='2.8'!G54 -> Cantidad + Desperdicio | H118: ='2.8'!H54 -> Precio Unitario | I118: ='2.8'!I54 -> Subtotal
A119: ='2.8'!A55 | B119: ='2.8'!B55 | C119: ='2.8'!C55 | D119: ='2.8'!D55 | E119: ='2.8'!E55 | F119: ='2.8'!F55 | G119: ='2.8'!G55 -> 0 | H119: ='2.8'!H55 | I119: ='2.8'!I55 -> 0
A120: ='2.8'!A56 | B120: ='2.8'!B56 | C120: ='2.8'!C56 | D120: ='2.8'!D56 | E120: ='2.8'!E56 | F120: ='2.8'!F56 | G120: ='2.8'!G56 -> 0 | H120: ='2.8'!H56 | I120: ='2.8'!I56
A121: ='2.8'!A57 | B121: ='2.8'!B57 | C121: ='2.8'!C57 | D121: ='2.8'!D57 | E121: ='2.8'!E57 | F121: ='2.8'!F57 | G121: ='2.8'!G57 -> 0 | H121: ='2.8'!H57 | I121: ='2.8'!I57
A122: ='2.8'!A58 | B122: ='2.8'!B58 | C122: ='2.8'!C58 | D122: ='2.8'!D58 | E122: ='2.8'!E58 | F122: ='2.8'!F58 | G122: ='2.8'!G58 -> 0 | H122: ='2.8'!H58 | I122: ='2.8'!I58
A123: ='2.8'!A59 | B123: ='2.8'!B59 | C123: ='2.8'!C59 | D123: ='2.8'!D59 | E123: ='2.8'!E59 | F123: ='2.8'!F59 | G123: ='2.8'!G59 -> 0 | H123: ='2.8'!H59 | I123: ='2.8'!I59
A124: ='2.8'!A60 | B124: ='2.8'!B60 | C124: ='2.8'!C60 | D124: ='2.8'!D60 | E124: ='2.8'!E60 | F124: ='2.8'!F60 | G124: ='2.8'!G60 -> 0 | H124: ='2.8'!H60 | I124: ='2.8'!I60
A125: ='2.8'!A61 | B125: ='2.8'!B61 | C125: ='2.8'!C61 | D125: ='2.8'!D61 | E125: ='2.8'!E61 | F125: ='2.8'!F61 | G125: ='2.8'!G61 | H125: ='2.8'!H61 | I125: ='2.8'!I61
A126: ='2.8'!A62 -> TOTAL | B126: ='2.8'!B62 | C126: ='2.8'!C62 | D126: ='2.8'!D62 | E126: ='2.8'!E62 | F126: ='2.8'!F62 | G126: ='2.8'!G62 | H126: ='2.8'!H62 | I126: ='2.8'!I62 -> 0
...

Sheet 01_RESUMEN SERV. M.O.
A1: ='01_C&P'!A1 -> EDIFICIO LAS HERAS
A3: ='2.1.'!A3 -> 45293 | B3: ='2.1.'!B3 -> COLUMNAS Y TABIQUES | G3: ='2.1.'!G3 | H3: ='2.1.'!H3 -> 31 | I3: ='2.1.'!I3 -> m³
A5: ='2.1.'!A39 -> MANO DE OBRA - EQUIPOS | C5: ='2.1.'!C39 | D5: ='2.1.'!D39 | E5: ='2.1.'!E39 | F5: ='2.1.'!F39 | G5: ='2.1.'!G39 | H5: ='2.1.'!H39 | I5: ='2.1.'!I39
A6: ='2.1.'!A40 -> Código | B6: ='2.1.'!B40 -> Descripción | C6: ='2.1.'!C40 -> Unidad | D6: ='2.1.'!D40 -> Cantidad | E6: ='2.1.'!E40 -> Dias | F6: ='2.1.'!F40 -> Desperdicio | G6: ='2.1.'!G40 -> Cantidad + Desperdicio | H6: ='2.1.'!H40 -> Precio Unitario | I6: ='2.1.'!I40 -> Subtotal
A7: ='2.1.'!A41 | B7: ='2.1.'!B41 | C7: ='2.1.'!C41 | D7: ='2.1.'!D41 | E7: ='2.1.'!E41 | F7: ='2.1.'!F41 | G7: ='2.1.'!G41 -> 0 | H7: ='2.1.'!H41 | I7: ='2.1.'!I41 -> 0
A8: ='2.1.'!A42 | B8: ='2.1.'!B42 | C8: ='2.1.'!C42 | D8: ='2.1.'!D42 | E8: ='2.1.'!E42 | F8: ='2.1.'!F42 | G8: ='2.1.'!G42 -> 0 | H8: ='2.1.'!H42 | I8: ='2.1.'!I42 -> 0
A9: ='2.1.'!A43 | B9: ='2.1.'!B43 | C9: ='2.1.'!C43 | D9: ='2.1.'!D43 | E9: ='2.1.'!E43 | F9: ='2.1.'!F43 | G9: ='2.1.'!G43 -> 0 | H9: ='2.1.'!H43 | I9: ='2.1.'!I43 -> 0
A10: ='2.1.'!A44 | B10: ='2.1.'!B44 | C10: ='2.1.'!C44 | D10: ='2.1.'!D44 | E10: ='2.1.'!E44 | F10: ='2.1.'!F44 | G10: ='2.1.'!G44 -> 0 | H10: ='2.1.'!H44 | I10: ='2.1.'!I44 -> 0
A11: ='2.1.'!A45 | B11: ='2.1.'!B45 | C11: ='2.1.'!C45 | D11: ='2.1.'!D45 | E11: ='2.1.'!E45 | F11: ='2.1.'!F45 | G11: ='2.1.'!G45 -> 0 | H11: ='2.1.'!H45 | I11: ='2.1.'!I45
A12: ='2.1.'!A46 | B12: ='2.1.'!B46 | C12: ='2.1.'!C46 | D12: ='2.1.'!D46 | E12: ='2.1.'!E46 | F12: ='2.1.'!F46 | G12: ='2.1.'!G46 -> 0 | H12: ='2.1.'!H46 | I12: ='2.1.'!I46
A13: ='2.1.'!A47 | B13: ='2.1.'!B47 | C13: ='2.1.'!C47 | D13: ='2.1.'!D47 | E13: ='2.1.'!E47 | F13: ='2.1.'!F47 | G13: ='2.1.'!G47 | H13: ='2.1.'!H47 | I13: ='2.1.'!I47
A14: ='2.1.'!A48 -> TOTAL | B14: ='2.1.'!B48 | C14: ='2.1.'!C48 | D14: ='2.1.'!D48 | E14: ='2.1.'!E48 | F14: ='2.1.'!F48 | G14: ='2.1.'!G48 | H14: ='2.1.'!H48 | I14: ='2.1.'!I48 -> 0
A17: ='2.1.'!A67 -> MANO DE OBRA - SUBCONTRATOS | C17: ='2.1.'!C67 | D17: ='2.1.'!D67 | E17: ='2.1.'!E67 | F17: ='2.1.'!F67 | G17: ='2.1.'!G67 | H17: ='2.1.'!H67 | I17: ='2.1.'!I67
A18: ='2.1.'!A68 -> Código | B18: ='2.1.'!B68 -> Descripción | C18: ='2.1.'!C68 -> Unidad | D18: ='2.1.'!D68 -> Cantidad | E18: ='2.1.'!E68 -> Dias | F18: ='2.1.'!F68 -> Desperdicio | G18: ='2.1.'!G68 -> Cantidad + Desperdicio | H18: ='2.1.'!H68 -> Precio Unitario | I18: ='2.1.'!I68 -> Subtotal
A19: ='2.1.'!A69 | B19: ='2.1.'!B69 | C19: ='2.1.'!C69 | D19: ='2.1.'!D69 | E19: ='2.1.'!E69 | F19: ='2.1.'!F69 | G19: ='2.1.'!G69 -> 0 | H19: ='2.1.'!H69 | I19: ='2.1.'!I69
A20: ='2.1.'!A70 | B20: ='2.1.'!B70 | C20: ='2.1.'!C70 | D20: ='2.1.'!D70 | E20: ='2.1.'!E70 | F20: ='2.1.'!F70 | G20: ='2.1.'!G70 -> 0 | H20: ='2.1.'!H70 | I20: ='2.1.'!I70
A21: ='2.1.'!A71 | B21: ='2.1.'!B71 | C21: ='2.1.'!C71 | D21: ='2.1.'!D71 | E21: ='2.1.'!E71 | F21: ='2.1.'!F71 | G21: ='2.1.'!G71 -> 0 | H21: ='2.1.'!H71 | I21: ='2.1.'!I71
A22: ='2.1.'!A72 | B22: ='2.1.'!B72 | C22: ='2.1.'!C72 | D22: ='2.1.'!D72 | E22: ='2.1.'!E72 | F22: ='2.1.'!F72 | G22: ='2.1.'!G72 -> 0 | H22: ='2.1.'!H72 | I22: ='2.1.'!I72
A23: ='2.1.'!A73 | B23: ='2.1.'!B73 | C23: ='2.1.'!C73 | D23: ='2.1.'!D73 | E23: ='2.1.'!E73 | F23: ='2.1.'!F73 | G23: ='2.1.'!G73 -> 0 | H23: ='2.1.'!H73 | I23: ='2.1.'!I73
A24: ='2.1.'!A74 | B24: ='2.1.'!B74 | C24: ='2.1.'!C74 | D24: ='2.1.'!D74 | E24: ='2.1.'!E74 | F24: ='2.1.'!F74 | G24: ='2.1.'!G74 -> 0 | H24: ='2.1.'!H74 | I24: ='2.1.'!I74
A25: ='2.1.'!A75 | B25: ='2.1.'!B75 | C25: ='2.1.'!C75 | D25: ='2.1.'!D75 | E25: ='2.1.'!E75 | F25: ='2.1.'!F75 | G25: ='2.1.'!G75 | H25: ='2.1.'!H75 | I25: ='2.1.'!I75
A26: ='2.1.'!A76 -> TOTAL | B26: ='2.1.'!B76 | C26: ='2.1.'!C76 | D26: ='2.1.'!D76 | E26: ='2.1.'!E76 | F26: ='2.1.'!F76 | G26: ='2.1.'!G76 | H26: ='2.1.'!H76 | I26: ='2.1.'!I76 -> 0
A29: ='2.2.'!A3 -> n | B29: ='2.1.'!B29 -> Oficial | G29: ='2.1.'!G29 -> 45 | H29: ='2.1.'!H29 -> 90000 | I29: ='2.1.'!I29 -> 4050000
A31: ='2.2.'!A39 -> MANO DE OBRA - EQUIPOS | B31: ='2.2.'!B39 | C31: ='2.2.'!C39 | D31: ='2.2.'!D39 | E31: ='2.2.'!E39 | F31: ='2.2.'!F39 | G31: ='2.2.'!G39 | H31: ='2.2.'!H39 | I31: ='2.2.'!I39
A32: ='2.2.'!A40 -> Código | B32: ='2.2.'!B40 -> Descripción | C32: ='2.2.'!C40 -> Unidad | D32: ='2.2.'!D40 -> Cantidad | E32: ='2.2.'!E40 -> Dias | F32: ='2.2.'!F40 -> Desperdicio | G32: ='2.2.'!G40 -> Cantidad + Desperdicio | H32: ='2.2.'!H40 -> Precio Unitario | I32: ='2.2.'!I40 -> Subtotal
A33: ='2.2.'!A41 | B33: ='2.2.'!B41 | C33: ='2.2.'!C41 | D33: ='2.2.'!D41 | E33: ='2.2.'!E41 | F33: ='2.2.'!F41 | G33: ='2.2.'!G41 -> 0 | H33: ='2.2.'!H41 | I33: ='2.2.'!I41 -> 0
A34: ='2.2.'!A42 | B34: ='2.2.'!B42 | C34: ='2.2.'!C42 | D34: ='2.2.'!D42 | E34: ='2.2.'!E42 | F34: ='2.2.'!F42 | G34: ='2.2.'!G42 -> 0 | H34: ='2.2.'!H42 | I34: ='2.2.'!I42 -> 0
A35: ='2.2.'!A43 | B35: ='2.2.'!B43 | C35: ='2.2.'!C43 | D35: ='2.2.'!D43 | E35: ='2.2.'!E43 | F35: ='2.2.'!F43 | G35: ='2.2.'!G43 -> 0 | H35: ='2.2.'!H43 | I35: ='2.2.'!I43 -> 0
A36: ='2.2.'!A44 | B36: ='2.2.'!B44 | C36: ='2.2.'!C44 | D36: ='2.2.'!D44 | E36: ='2.2.'!E44 | F36: ='2.2.'!F44 | G36: ='2.2.'!G44 -> 0 | H36: ='2.2.'!H44 | I36: ='2.2.'!I44 -> 0
A37: ='2.2.'!A45 | B37: ='2.2.'!B45 | C37: ='2.2.'!C45 | D37: ='2.2.'!D45 | E37: ='2.2.'!E45 | F37: ='2.2.'!F45 | G37: ='2.2.'!G45 -> 0 | H37: ='2.2.'!H45 | I37: ='2.2.'!I45 -> 0
A38: ='2.2.'!A46 | B38: ='2.2.'!B46 | C38: ='2.2.'!C46 | D38: ='2.2.'!D46 | E38: ='2.2.'!E46 | F38: ='2.2.'!F46 | G38: ='2.2.'!G46 -> 0 | H38: ='2.2.'!H46 | I38: ='2.2.'!I46 -> 0
A39: ='2.2.'!A47 | B39: ='2.2.'!B47 | C39: ='2.2.'!C47 | D39: ='2.2.'!D47 | E39: ='2.2.'!E47 | F39: ='2.2.'!F47 | G39: ='2.2.'!G47 | H39: ='2.2.'!H47 | I39: ='2.2.'!I47
A40: ='2.2.'!A48 -> TOTAL | B40: ='2.2.'!B48 | C40: ='2.2.'!C48 | D40: ='2.2.'!D48 | E40: ='2.2.'!E48 | F40: ='2.2.'!F48 | G40: ='2.2.'!G48 | H40: ='2.2.'!H48 | I40: ='2.2.'!I48 -> 0
A43: ='2.2.'!A67 -> MANO DE OBRA - SUBCONTRATOS | B43: ='2.2.'!B67 | C43: ='2.2.'!C67 | D43: ='2.2.'!D67 | E43: ='2.2.'!E67 | F43: ='2.2.'!F67 | G43: ='2.2.'!G67 | H43: ='2.2.'!H67 | I43: ='2.2.'!I67
A44: ='2.2.'!A68 -> Código | B44: ='2.2.'!B68 -> Descripción | C44: ='2.2.'!C68 -> Unidad | D44: ='2.2.'!D68 -> Cantidad | E44: ='2.2.'!E68 -> Dias | F44: ='2.2.'!F68 -> Desperdicio | G44: ='2.2.'!G68 -> Cantidad + Desperdicio | H44: ='2.2.'!H68 -> Precio Unitario | I44: ='2.2.'!I68 -> Subtotal
A45: ='2.2.'!A69 | B45: ='2.2.'!B69 | C45: ='2.2.'!C69 | D45: ='2.2.'!D69 | E45: ='2.2.'!E69 | F45: ='2.2.'!F69 | G45: ='2.2.'!G69 -> 0 | H45: ='2.2.'!H69 | I45: ='2.2.'!I69
A46: ='2.2.'!A70 | B46: ='2.2.'!B70 | C46: ='2.2.'!C70 | D46: ='2.2.'!D70 | E46: ='2.2.'!E70 | F46: ='2.2.'!F70 | G46: ='2.2.'!G70 -> 0 | H46: ='2.2.'!H70 | I46: ='2.2.'!I70
A47: ='2.2.'!A71 | B47: ='2.2.'!B71 | C47: ='2.2.'!C71 | D47: ='2.2.'!D71 | E47: ='2.2.'!E71 | F47: ='2.2.'!F71 | G47: ='2.2.'!G71 -> 0 | H47: ='2.2.'!H71 | I47: ='2.2.'!I71
A48: ='2.2.'!A72 | B48: ='2.2.'!B72 | C48: ='2.2.'!C72 | D48: ='2.2.'!D72 | E48: ='2.2.'!E72 | F48: ='2.2.'!F72 | G48: ='2.2.'!G72 -> 0 | H48: ='2.2.'!H72 | I48: ='2.2.'!I72
A49: ='2.2.'!A73 | B49: ='2.2.'!B73 | C49: ='2.2.'!C73 | D49: ='2.2.'!D73 | E49: ='2.2.'!E73 | F49: ='2.2.'!F73 | G49: ='2.2.'!G73 -> 0 | H49: ='2.2.'!H73 | I49: ='2.2.'!I73
A50: ='2.2.'!A74 | B50: ='2.2.'!B74 | C50: ='2.2.'!C74 | D50: ='2.2.'!D74 | E50: ='2.2.'!E74 | F50: ='2.2.'!F74 | G50: ='2.2.'!G74 -> 0 | H50: ='2.2.'!H74 | I50: ='2.2.'!I74
A51: ='2.2.'!A75 | B51: ='2.2.'!B75 | C51: ='2.2.'!C75 | D51: ='2.2.'!D75 | E51: ='2.2.'!E75 | F51: ='2.2.'!F75 | G51: ='2.2.'!G75 | H51: ='2.2.'!H75 | I51: ='2.2.'!I75
A52: ='2.2.'!A76 -> TOTAL | B52: ='2.2.'!B76 | C52: ='2.2.'!C76 | D52: ='2.2.'!D76 | E52: ='2.2.'!E76 | F52: ='2.2.'!F76 | G52: ='2.2.'!G76 | H52: ='2.2.'!H76 | I52: ='2.2.'!I76 -> 0
A55: ='2.3.'!A3 -> #REF! | B55: ='2.1.'!B55 | G55: ='2.1.'!G55 -> 0 | H55: ='2.1.'!H55 | I55: ='2.1.'!I55 -> 0
A57: ='2.3.'!A39 -> #REF! | B57: ='2.3.'!B39 -> #REF! | C57: ='2.3.'!C39 -> #REF! | D57: ='2.3.'!D39 -> #REF! | E57: ='2.3.'!E39 -> #REF! | F57: ='2.3.'!F39 -> #REF! | G57: ='2.3.'!G39 -> #REF! | H57: ='2.3.'!H39 -> #REF! | I57: ='2.3.'!I39 -> #REF!
A58: ='2.3.'!A40 -> #REF! | B58: ='2.3.'!B40 -> #REF! | C58: ='2.3.'!C40 -> #REF! | D58: ='2.3.'!D40 -> #REF! | E58: ='2.3.'!E40 -> #REF! | F58: ='2.3.'!F40 -> #REF! | G58: ='2.3.'!G40 -> #REF! | H58: ='2.3.'!H40 -> #REF! | I58: ='2.3.'!I40 -> #REF!
A59: ='2.3.'!A41 -> #REF! | B59: ='2.3.'!B41 -> #REF! | C59: ='2.3.'!C41 -> #REF! | D59: ='2.3.'!D41 -> #REF! | E59: ='2.3.'!E41 -> #REF! | F59: ='2.3.'!F41 -> #REF! | G59: ='2.3.'!G41 -> #REF! | H59: ='2.3.'!H41 -> #REF! | I59: ='2.3.'!I41 -> #REF!
A60: ='2.3.'!A42 -> #REF! | B60: ='2.3.'!B42 -> #REF! | C60: ='2.3.'!C42 -> #REF! | D60: ='2.3.'!D42 -> #REF! | E60: ='2.3.'!E42 -> #REF! | F60: ='2.3.'!F42 -> #REF! | G60: ='2.3.'!G42 -> #REF! | H60: ='2.3.'!H42 -> #REF! | I60: ='2.3.'!I42 -> #REF!
A61: ='2.3.'!A43 -> #REF! | B61: ='2.3.'!B43 -> #REF! | C61: ='2.3.'!C43 -> #REF! | D61: ='2.3.'!D43 -> #REF! | E61: ='2.3.'!E43 -> #REF! | F61: ='2.3.'!F43 -> #REF! | G61: ='2.3.'!G43 -> #REF! | H61: ='2.3.'!H43 -> #REF! | I61: ='2.3.'!I43 -> #REF!
A62: ='2.3.'!A44 -> #REF! | B62: ='2.3.'!B44 -> #REF! | C62: ='2.3.'!C44 -> #REF! | D62: ='2.3.'!D44 -> #REF! | E62: ='2.3.'!E44 -> #REF! | F62: ='2.3.'!F44 -> #REF! | G62: ='2.3.'!G44 -> #REF! | H62: ='2.3.'!H44 -> #REF! | I62: ='2.3.'!I44 -> #REF!
A63: ='2.3.'!A45 -> #REF! | B63: ='2.3.'!B45 -> #REF! | C63: ='2.3.'!C45 -> #REF! | D63: ='2.3.'!D45 -> #REF! | E63: ='2.3.'!E45 -> #REF! | F63: ='2.3.'!F45 -> #REF! | G63: ='2.3.'!G45 -> #REF! | H63: ='2.3.'!H45 -> #REF! | I63: ='2.3.'!I45 -> #REF!
A64: ='2.3.'!A46 -> #REF! | B64: ='2.3.'!B46 -> #REF! | C64: ='2.3.'!C46 -> #REF! | D64: ='2.3.'!D46 -> #REF! | E64: ='2.3.'!E46 -> #REF! | F64: ='2.3.'!F46 -> #REF! | G64: ='2.3.'!G46 -> #REF! | H64: ='2.3.'!H46 -> #REF! | I64: ='2.3.'!I46 -> #REF!
A65: ='2.3.'!A47 -> #REF! | B65: ='2.3.'!B47 -> #REF! | C65: ='2.3.'!C47 -> #REF! | D65: ='2.3.'!D47 -> #REF! | E65: ='2.3.'!E47 -> #REF! | F65: ='2.3.'!F47 -> #REF! | G65: ='2.3.'!G47 -> #REF! | H65: ='2.3.'!H47 -> #REF! | I65: ='2.3.'!I47 -> #REF!
A66: ='2.3.'!A48 -> #REF! | B66: ='2.3.'!B48 -> #REF! | C66: ='2.3.'!C48 -> #REF! | D66: ='2.3.'!D48 -> #REF! | E66: ='2.3.'!E48 -> #REF! | F66: ='2.3.'!F48 -> #REF! | G66: ='2.3.'!G48 -> #REF! | H66: ='2.3.'!H48 -> #REF! | I66: ='2.3.'!I48 -> #REF!
A69: ='2.3.'!A67 -> #REF! | B69: ='2.3.'!B67 -> #REF! | C69: ='2.3.'!C67 -> #REF! | D69: ='2.3.'!D67 -> #REF! | E69: ='2.3.'!E67 -> #REF! | F69: ='2.3.'!F67 -> #REF! | G69: ='2.3.'!G67 -> #REF! | H69: ='2.3.'!H67 -> #REF! | I69: ='2.3.'!I67 -> #REF!
A70: ='2.3.'!A68 -> #REF! | B70: ='2.3.'!B68 -> #REF! | C70: ='2.3.'!C68 -> #REF! | D70: ='2.3.'!D68 -> #REF! | E70: ='2.3.'!E68 -> #REF! | F70: ='2.3.'!F68 -> #REF! | G70: ='2.3.'!G68 -> #REF! | H70: ='2.3.'!H68 -> #REF! | I70: ='2.3.'!I68 -> #REF!
A71: ='2.3.'!A69 -> #REF! | B71: ='2.3.'!B69 -> #REF! | C71: ='2.3.'!C69 -> #REF! | D71: ='2.3.'!D69 -> #REF! | E71: ='2.3.'!E69 -> #REF! | F71: ='2.3.'!F69 -> #REF! | G71: ='2.3.'!G69 -> #REF! | H71: ='2.3.'!H69 -> #REF! | I71: ='2.3.'!I69 -> #REF!
A72: ='2.3.'!A70 -> #REF! | B72: ='2.3.'!B70 -> #REF! | C72: ='2.3.'!C70 -> #REF! | D72: ='2.3.'!D70 -> #REF! | E72: ='2.3.'!E70 -> #REF! | F72: ='2.3.'!F70 -> #REF! | G72: ='2.3.'!G70 -> #REF! | H72: ='2.3.'!H70 -> #REF! | I72: ='2.3.'!I70 -> #REF!
A73: ='2.3.'!A71 -> #REF! | B73: ='2.3.'!B71 -> #REF! | C73: ='2.3.'!C71 -> #REF! | D73: ='2.3.'!D71 -> #REF! | E73: ='2.3.'!E71 -> #REF! | F73: ='2.3.'!F71 -> #REF! | G73: ='2.3.'!G71 -> #REF! | H73: ='2.3.'!H71 -> #REF! | I73: ='2.3.'!I71 -> #REF!
A74: ='2.3.'!A72 -> #REF! | B74: ='2.3.'!B72 -> #REF! | C74: ='2.3.'!C72 -> #REF! | D74: ='2.3.'!D72 -> #REF! | E74: ='2.3.'!E72 -> #REF! | F74: ='2.3.'!F72 -> #REF! | G74: ='2.3.'!G72 -> #REF! | H74: ='2.3.'!H72 -> #REF! | I74: ='2.3.'!I72 -> #REF!
A75: ='2.3.'!A73 -> #REF! | B75: ='2.3.'!B73 -> #REF! | C75: ='2.3.'!C73 -> #REF! | D75: ='2.3.'!D73 -> #REF! | E75: ='2.3.'!E73 -> #REF! | F75: ='2.3.'!F73 -> #REF! | G75: ='2.3.'!G73 -> #REF! | H75: ='2.3.'!H73 -> #REF! | I75: ='2.3.'!I73 -> #REF!
A76: ='2.3.'!A74 -> #REF! | B76: ='2.3.'!B74 -> #REF! | C76: ='2.3.'!C74 -> #REF! | D76: ='2.3.'!D74 -> #REF! | E76: ='2.3.'!E74 -> #REF! | F76: ='2.3.'!F74 -> #REF! | G76: ='2.3.'!G74 -> #REF! | H76: ='2.3.'!H74 -> #REF! | I76: ='2.3.'!I74 -> #REF!
A77: ='2.3.'!A75 -> #REF! | B77: ='2.3.'!B75 -> #REF! | C77: ='2.3.'!C75 -> #REF! | D77: ='2.3.'!D75 -> #REF! | E77: ='2.3.'!E75 -> #REF! | F77: ='2.3.'!F75 -> #REF! | G77: ='2.3.'!G75 -> #REF! | H77: ='2.3.'!H75 -> #REF! | I77: ='2.3.'!I75 -> #REF!
A78: ='2.3.'!A76 -> #REF! | B78: ='2.3.'!B76 -> #REF! | C78: ='2.3.'!C76 -> #REF! | D78: ='2.3.'!D76 -> #REF! | E78: ='2.3.'!E76 -> #REF! | F78: ='2.3.'!F76 -> #REF! | G78: ='2.3.'!G76 -> #REF! | H78: ='2.3.'!H76 -> #REF! | I78: ='2.3.'!I76 -> #REF!
A81: ='2.4.'!A3 -> #REF! | B81: ='2.1.'!B81 | G81: ='2.1.'!G81 | H81: ='2.1.'!H81 | I81: ='2.1.'!I81
A83: ='2.4.'!A39 -> #REF! | B83: ='2.4.'!B39 -> #REF! | C83: ='2.4.'!C39 -> #REF! | D83: ='2.4.'!D39 -> #REF! | E83: ='2.4.'!E39 -> #REF! | F83: ='2.4.'!F39 -> #REF! | G83: ='2.4.'!G39 -> #REF! | H83: ='2.4.'!H39 -> #REF! | I83: ='2.4.'!I39 -> #REF!
A84: ='2.4.'!A40 -> #REF! | B84: ='2.4.'!B40 -> #REF! | C84: ='2.4.'!C40 -> #REF! | D84: ='2.4.'!D40 -> #REF! | E84: ='2.4.'!E40 -> #REF! | F84: ='2.4.'!F40 -> #REF! | G84: ='2.4.'!G40 -> #REF! | H84: ='2.4.'!H40 -> #REF! | I84: ='2.4.'!I40 -> #REF!
A85: ='2.4.'!A41 -> #REF! | B85: ='2.4.'!B41 -> #REF! | C85: ='2.4.'!C41 -> #REF! | D85: ='2.4.'!D41 -> #REF! | E85: ='2.4.'!E41 -> #REF! | F85: ='2.4.'!F41 -> #REF! | G85: ='2.4.'!G41 -> #REF! | H85: ='2.4.'!H41 -> #REF! | I85: ='2.4.'!I41 -> #REF!
A86: ='2.4.'!A42 -> #REF! | B86: ='2.4.'!B42 -> #REF! | C86: ='2.4.'!C42 -> #REF! | D86: ='2.4.'!D42 -> #REF! | E86: ='2.4.'!E42 -> #REF! | F86: ='2.4.'!F42 -> #REF! | G86: ='2.4.'!G42 -> #REF! | H86: ='2.4.'!H42 -> #REF! | I86: ='2.4.'!I42 -> #REF!
A87: ='2.4.'!A43 -> #REF! | B87: ='2.4.'!B43 -> #REF! | C87: ='2.4.'!C43 -> #REF! | D87: ='2.4.'!D43 -> #REF! | E87: ='2.4.'!E43 -> #REF! | F87: ='2.4.'!F43 -> #REF! | G87: ='2.4.'!G43 -> #REF! | H87: ='2.4.'!H43 -> #REF! | I87: ='2.4.'!I43 -> #REF!
A88: ='2.4.'!A44 -> #REF! | B88: ='2.4.'!B44 -> #REF! | C88: ='2.4.'!C44 -> #REF! | D88: ='2.4.'!D44 -> #REF! | E88: ='2.4.'!E44 -> #REF! | F88: ='2.4.'!F44 -> #REF! | G88: ='2.4.'!G44 -> #REF! | H88: ='2.4.'!H44 -> #REF! | I88: ='2.4.'!I44 -> #REF!
A89: ='2.4.'!A45 -> #REF! | B89: ='2.4.'!B45 -> #REF! | C89: ='2.4.'!C45 -> #REF! | D89: ='2.4.'!D45 -> #REF! | E89: ='2.4.'!E45 -> #REF! | F89: ='2.4.'!F45 -> #REF! | G89: ='2.4.'!G45 -> #REF! | H89: ='2.4.'!H45 -> #REF! | I89: ='2.4.'!I45 -> #REF!
A90: ='2.4.'!A46 -> #REF! | B90: ='2.4.'!B46 -> #REF! | C90: ='2.4.'!C46 -> #REF! | D90: ='2.4.'!D46 -> #REF! | E90: ='2.4.'!E46 -> #REF! | F90: ='2.4.'!F46 -> #REF! | G90: ='2.4.'!G46 -> #REF! | H90: ='2.4.'!H46 -> #REF! | I90: ='2.4.'!I46 -> #REF!
A91: ='2.4.'!A47 -> #REF! | B91: ='2.4.'!B47 -> #REF! | C91: ='2.4.'!C47 -> #REF! | D91: ='2.4.'!D47 -> #REF! | E91: ='2.4.'!E47 -> #REF! | F91: ='2.4.'!F47 -> #REF! | G91: ='2.4.'!G47 -> #REF! | H91: ='2.4.'!H47 -> #REF! | I91: ='2.4.'!I47 -> #REF!
A92: ='2.4.'!A48 -> #REF! | B92: ='2.4.'!B48 -> #REF! | C92: ='2.4.'!C48 -> #REF! | D92: ='2.4.'!D48 -> #REF! | E92: ='2.4.'!E48 -> #REF! | F92: ='2.4.'!F48 -> #REF! | G92: ='2.4.'!G48 -> #REF! | H92: ='2.4.'!H48 -> #REF! | I92: ='2.4.'!I48 -> #REF!
A95: ='2.4.'!A67 -> #REF! | B95: ='2.4.'!B67 -> #REF! | C95: ='2.4.'!C67 -> #REF! | D95: ='2.4.'!D67 -> #REF! | E95: ='2.4.'!E67 -> #REF! | F95: ='2.4.'!F67 -> #REF! | G95: ='2.4.'!G67 -> #REF! | H95: ='2.4.'!H67 -> #REF! | I95: ='2.4.'!I67 -> #REF!
A96: ='2.4.'!A68 -> #REF! | B96: ='2.4.'!B68 -> #REF! | C96: ='2.4.'!C68 -> #REF! | D96: ='2.4.'!D68 -> #REF! | E96: ='2.4.'!E68 -> #REF! | F96: ='2.4.'!F68 -> #REF! | G96: ='2.4.'!G68 -> #REF! | H96: ='2.4.'!H68 -> #REF! | I96: ='2.4.'!I68 -> #REF!
A97: ='2.4.'!A69 -> #REF! | B97: ='2.4.'!B69 -> #REF! | C97: ='2.4.'!C69 -> #REF! | D97: ='2.4.'!D69 -> #REF! | E97: ='2.4.'!E69 -> #REF! | F97: ='2.4.'!F69 -> #REF! | G97: ='2.4.'!G69 -> #REF! | H97: ='2.4.'!H69 -> #REF! | I97: ='2.4.'!I69 -> #REF!
A98: ='2.4.'!A70 -> #REF! | B98: ='2.4.'!B70 -> #REF! | C98: ='2.4.'!C70 -> #REF! | D98: ='2.4.'!D70 -> #REF! | E98: ='2.4.'!E70 -> #REF! | F98: ='2.4.'!F70 -> #REF! | G98: ='2.4.'!G70 -> #REF! | H98: ='2.4.'!H70 -> #REF! | I98: ='2.4.'!I70 -> #REF!
A99: ='2.4.'!A71 -> #REF! | B99: ='2.4.'!B71 -> #REF! | C99: ='2.4.'!C71 -> #REF! | D99: ='2.4.'!D71 -> #REF! | E99: ='2.4.'!E71 -> #REF! | F99: ='2.4.'!F71 -> #REF! | G99: ='2.4.'!G71 -> #REF! | H99: ='2.4.'!H71 -> #REF! | I99: ='2.4.'!I71 -> #REF!
A100: ='2.4.'!A72 -> #REF! | B100: ='2.4.'!B72 -> #REF! | C100: ='2.4.'!C72 -> #REF! | D100: ='2.4.'!D72 -> #REF! | E100: ='2.4.'!E72 -> #REF! | F100: ='2.4.'!F72 -> #REF! | G100: ='2.4.'!G72 -> #REF! | H100: ='2.4.'!H72 -> #REF! | I100: ='2.4.'!I72 -> #REF!
A101: ='2.4.'!A73 -> #REF! | B101: ='2.4.'!B73 -> #REF! | C101: ='2.4.'!C73 -> #REF! | D101: ='2.4.'!D73 -> #REF! | E101: ='2.4.'!E73 -> #REF! | F101: ='2.4.'!F73 -> #REF! | G101: ='2.4.'!G73 -> #REF! | H101: ='2.4.'!H73 -> #REF! | I101: ='2.4.'!I73 -> #REF!
A102: ='2.4.'!A74 -> #REF! | B102: ='2.4.'!B74 -> #REF! | C102: ='2.4.'!C74 -> #REF! | D102: ='2.4.'!D74 -> #REF! | E102: ='2.4.'!E74 -> #REF! | F102: ='2.4.'!F74 -> #REF! | G102: ='2.4.'!G74 -> #REF! | H102: ='2.4.'!H74 -> #REF! | I102: ='2.4.'!I74 -> #REF!
A103: ='2.4.'!A75 -> #REF! | B103: ='2.4.'!B75 -> #REF! | C103: ='2.4.'!C75 -> #REF! | D103: ='2.4.'!D75 -> #REF! | E103: ='2.4.'!E75 -> #REF! | F103: ='2.4.'!F75 -> #REF! | G103: ='2.4.'!G75 -> #REF! | H103: ='2.4.'!H75 -> #REF! | I103: ='2.4.'!I75 -> #REF!
A104: ='2.4.'!A76 -> #REF! | B104: ='2.4.'!B76 -> #REF! | C104: ='2.4.'!C76 -> #REF! | D104: ='2.4.'!D76 -> #REF! | E104: ='2.4.'!E76 -> #REF! | F104: ='2.4.'!F76 -> #REF! | G104: ='2.4.'!G76 -> #REF! | H104: ='2.4.'!H76 -> #REF! | I104: ='2.4.'!I76 -> #REF!
A107: ='2.5.'!A3 -> #REF! | B107: ='2.1.'!B107 | G107: ='2.1.'!G107 | H107: ='2.1.'!H107 | I107: ='2.1.'!I107
A109: ='2.5.'!A39 -> #REF! | B109: ='2.5.'!B39 -> #REF! | C109: ='2.5.'!C39 -> #REF! | D109: ='2.5.'!D39 -> #REF! | E109: ='2.5.'!E39 -> #REF! | F109: ='2.5.'!F39 -> #REF! | G109: ='2.5.'!G39 -> #REF! | H109: ='2.5.'!H39 -> #REF! | I109: ='2.5.'!I39 -> #REF!
A110: ='2.5.'!A40 -> #REF! | B110: ='2.5.'!B40 -> #REF! | C110: ='2.5.'!C40 -> #REF! | D110: ='2.5.'!D40 -> #REF! | E110: ='2.5.'!E40 -> #REF! | F110: ='2.5.'!F40 -> #REF! | G110: ='2.5.'!G40 -> #REF! | H110: ='2.5.'!H40 -> #REF! | I110: ='2.5.'!I40 -> #REF!
A111: ='2.5.'!A41 -> #REF! | B111: ='2.5.'!B41 -> #REF! | C111: ='2.5.'!C41 -> #REF! | D111: ='2.5.'!D41 -> #REF! | E111: ='2.5.'!E41 -> #REF! | F111: ='2.5.'!F41 -> #REF! | G111: ='2.5.'!G41 -> #REF! | H111: ='2.5.'!H41 -> #REF! | I111: ='2.5.'!I41 -> #REF!
A112: ='2.5.'!A42 -> #REF! | B112: ='2.5.'!B42 -> #REF! | C112: ='2.5.'!C42 -> #REF! | D112: ='2.5.'!D42 -> #REF! | E112: ='2.5.'!E42 -> #REF! | F112: ='2.5.'!F42 -> #REF! | G112: ='2.5.'!G42 -> #REF! | H112: ='2.5.'!H42 -> #REF! | I112: ='2.5.'!I42 -> #REF!
A113: ='2.5.'!A43 -> #REF! | B113: ='2.5.'!B43 -> #REF! | C113: ='2.5.'!C43 -> #REF! | D113: ='2.5.'!D43 -> #REF! | E113: ='2.5.'!E43 -> #REF! | F113: ='2.5.'!F43 -> #REF! | G113: ='2.5.'!G43 -> #REF! | H113: ='2.5.'!H43 -> #REF! | I113: ='2.5.'!I43 -> #REF!
A114: ='2.5.'!A44 -> #REF! | B114: ='2.5.'!B44 -> #REF! | C114: ='2.5.'!C44 -> #REF! | D114: ='2.5.'!D44 -> #REF! | E114: ='2.5.'!E44 -> #REF! | F114: ='2.5.'!F44 -> #REF! | G114: ='2.5.'!G44 -> #REF! | H114: ='2.5.'!H44 -> #REF! | I114: ='2.5.'!I44 -> #REF!
A115: ='2.5.'!A45 -> #REF! | B115: ='2.5.'!B45 -> #REF! | C115: ='2.5.'!C45 -> #REF! | D115: ='2.5.'!D45 -> #REF! | E115: ='2.5.'!E45 -> #REF! | F115: ='2.5.'!F45 -> #REF! | G115: ='2.5.'!G45 -> #REF! | H115: ='2.5.'!H45 -> #REF! | I115: ='2.5.'!I45 -> #REF!
A116: ='2.5.'!A46 -> #REF! | B116: ='2.5.'!B46 -> #REF! | C116: ='2.5.'!C46 -> #REF! | D116: ='2.5.'!D46 -> #REF! | E116: ='2.5.'!E46 -> #REF! | F116: ='2.5.'!F46 -> #REF! | G116: ='2.5.'!G46 -> #REF! | H116: ='2.5.'!H46 -> #REF! | I116: ='2.5.'!I46 -> #REF!
A117: ='2.5.'!A47 -> #REF! | B117: ='2.5.'!B47 -> #REF! | C117: ='2.5.'!C47 -> #REF! | D117: ='2.5.'!D47 -> #REF! | E117: ='2.5.'!E47 -> #REF! | F117: ='2.5.'!F47 -> #REF! | G117: ='2.5.'!G47 -> #REF! | H117: ='2.5.'!H47 -> #REF! | I117: ='2.5.'!I47 -> #REF!
A118: ='2.5.'!A48 -> #REF! | B118: ='2.5.'!B48 -> #REF! | C118: ='2.5.'!C48 -> #REF! | D118: ='2.5.'!D48 -> #REF! | E118: ='2.5.'!E48 -> #REF! | F118: ='2.5.'!F48 -> #REF! | G118: ='2.5.'!G48 -> #REF! | H118: ='2.5.'!H48 -> #REF! | I118: ='2.5.'!I48 -> #REF!
A121: ='2.5.'!A67 -> #REF! | B121: ='2.5.'!B67 -> #REF! | C121: ='2.5.'!C67 -> #REF! | D121: ='2.5.'!D67 -> #REF! | E121: ='2.5.'!E67 -> #REF! | F121: ='2.5.'!F67 -> #REF! | G121: ='2.5.'!G67 -> #REF! | H121: ='2.5.'!H67 -> #REF! | I121: ='2.5.'!I67 -> #REF!
A122: ='2.5.'!A68 -> #REF! | B122: ='2.5.'!B68 -> #REF! | C122: ='2.5.'!C68 -> #REF! | D122: ='2.5.'!D68 -> #REF! | E122: ='2.5.'!E68 -> #REF! | F122: ='2.5.'!F68 -> #REF! | G122: ='2.5.'!G68 -> #REF! | H122: ='2.5.'!H68 -> #REF! | I122: ='2.5.'!I68 -> #REF!
A123: ='2.5.'!A69 -> #REF! | B123: ='2.5.'!B69 -> #REF! | C123: ='2.5.'!C69 -> #REF! | D123: ='2.5.'!D69 -> #REF! | E123: ='2.5.'!E69 -> #REF! | F123: ='2.5.'!F69 -> #REF! | G123: ='2.5.'!G69 -> #REF! | H123: ='2.5.'!H69 -> #REF! | I123: ='2.5.'!I69 -> #REF!
A124: ='2.5.'!A70 -> #REF! | B124: ='2.5.'!B70 -> #REF! | C124: ='2.5.'!C70 -> #REF! | D124: ='2.5.'!D70 -> #REF! | E124: ='2.5.'!E70 -> #REF! | F124: ='2.5.'!F70 -> #REF! | G124: ='2.5.'!G70 -> #REF! | H124: ='2.5.'!H70 -> #REF! | I124: ='2.5.'!I70 -> #REF!
...

Sheet ESTRUCTURA
A1: ='01_C&P'!A1 -> EDIFICIO LAS HERAS
A3: ='01_C&P'!A16 -> 0.8 | B3: =IF($A3=0,"",VLOOKUP($A3,'01_C&P'!$A$9:$D$192,2,FALSE)) -> ESTRUCTURA DE ENCOFRADO Y APUNTALAMIENTO PROVISORIO | H3: =IF($A3=0,"",VLOOKUP($A3,'01_C&P'!$A$9:$D$192,4,FALSE)) -> 1 | I3: =IF($A3=0,"",VLOOKUP($A3,'01_C&P'!$A$9:$D$192,3,FALSE)) -> gl
A5: MATERIALES
A6: Código | B6: Descripción | C6: Unidad | D6: Cantidad | F6: Desperdicio | G6: Cantidad + Desperdicio | H6: Precio Unitario | I6: Subtotal
B7: =IF($A7=0,"",VLOOKUP($A7,'00_Mat'!$A$4:$J$1135,2,FALSE)) | C7: =IF($A7=0,"",VLOOKUP($A7,'00_Mat'!$A$4:$J$1135,3,FALSE)) | D7: =H3 -> 1 | F7: 0.1 | G7: =ROUNDUP((D7+(D7*F7)),0) -> 2 | H7: =IF($A7=0,"",VLOOKUP($A7,'00_Mat'!$A$4:$J$1135,5,FALSE)) | I7: =G7*H7 -> 0
B8: =IF($A8=0,"",VLOOKUP($A8,'00_Mat'!$A$4:$J$1135,2,FALSE)) | C8: =IF($A8=0,"",VLOOKUP($A8,'00_Mat'!$A$4:$J$1135,3,FALSE)) | F8: 0.1 | G8: =ROUNDUP((D8+(D8*F8)),0) -> 0 | H8: =IF($A8=0,"",VLOOKUP($A8,'00_Mat'!$A$4:$J$1135,5,FALSE)) | I8: =G8*H8 -> 0
B9: =IF($A9=0,"",VLOOKUP($A9,'00_Mat'!$A$4:$J$1135,2,FALSE)) | C9: =IF($A9=0,"",VLOOKUP($A9,'00_Mat'!$A$4:$J$1135,3,FALSE)) | F9: 0.1 | G9: =ROUNDUP((D9+(D9*F9)),0) -> 0 | H9: =IF($A9=0,"",VLOOKUP($A9,'00_Mat'!$A$4:$J$1135,5,FALSE)) | I9: =G9*H9 -> 0
B10: =IF($A10=0,"",VLOOKUP($A10,'00_Mat'!$A$4:$J$1135,2,FALSE)) | C10: =IF($A10=0,"",VLOOKUP($A10,'00_Mat'!$A$4:$J$1135,3,FALSE)) | F10: 0.1 | G10: =ROUNDUP((D10+(D10*F10)),0) -> 0 | H10: =IF($A10=0,"",VLOOKUP($A10,'00_Mat'!$A$4:$J$1135,5,FALSE)) | I10: =G10*H10 -> 0
B11: =IF($A11=0,"",VLOOKUP($A11,'00_Mat'!$A$4:$J$1135,2,FALSE)) | C11: =IF($A11=0,"",VLOOKUP($A11,'00_Mat'!$A$4:$J$1135,3,FALSE)) | F11: 0.1 | G11: =ROUNDUP((D11+(D11*F11)),0) -> 0 | H11: =IF($A11=0,"",VLOOKUP($A11,'00_Mat'!$A$4:$J$1135,5,FALSE)) | I11: =G11*H11 -> 0
B12: =IF($A12=0,"",VLOOKUP($A12,'00_Mat'!$A$4:$J$1135,2,FALSE)) | C12: =IF($A12=0,"",VLOOKUP($A12,'00_Mat'!$A$4:$J$1135,3,FALSE)) | F12: 0.1 | G12: =ROUNDUP((D12+(D12*F12)),0) -> 0 | H12: =IF($A12=0,"",VLOOKUP($A12,'00_Mat'!$A$4:$J$1135,5,FALSE)) | I12: =G12*H12 -> 0
B13: =IF($A13=0,"",VLOOKUP($A13,'00_Mat'!$A$4:$J$1135,2,FALSE)) | C13: =IF($A13=0,"",VLOOKUP($A13,'00_Mat'!$A$4:$J$1135,3,FALSE)) | F13: 0.1 | G13: =ROUNDUP((D13+(D13*F13)),0) -> 0 | H13: =IF($A13=0,"",VLOOKUP($A13,'00_Mat'!$A$4:$J$1135,5,FALSE)) | I13: =G13*H13 -> 0
B14: =IF($A14=0,"",VLOOKUP($A14,'00_Mat'!$A$4:$J$1135,2,FALSE)) | C14: =IF($A14=0,"",VLOOKUP($A14,'00_Mat'!$A$4:$J$1135,3,FALSE)) | F14: 0.1 | G14: =ROUNDUP((D14+(D14*F14)),0) -> 0 | H14: =IF($A14=0,"",VLOOKUP($A14,'00_Mat'!$A$4:$J$1135,5,FALSE)) | I14: =G14*H14 -> 0
B15: =IF($A15=0,"",VLOOKUP($A15,'00_Mat'!$A$4:$J$1135,2,FALSE)) | C15: =IF($A15=0,"",VLOOKUP($A15,'00_Mat'!$A$4:$J$1135,3,FALSE)) | F15: 0.1 | G15: =ROUNDUP((D15+(D15*F15)),0) -> 0 | H15: =IF($A15=0,"",VLOOKUP($A15,'00_Mat'!$A$4:$J$1135,5,FALSE)) | I15: =G15*H15 -> 0
B16: =IF($A16=0,"",VLOOKUP($A16,'00_Mat'!$A$4:$J$1135,2,FALSE)) | C16: =IF($A16=0,"",VLOOKUP($A16,'00_Mat'!$A$4:$J$1135,3,FALSE)) | G16: =ROUNDUP((D16+(D16*F16)),0) -> 0 | H16: =IF($A16=0,"",VLOOKUP($A16,'00_Mat'!$A$4:$J$1135,5,FALSE)) | I16: =G16*H16 -> 0
B17: =IF($A17=0,"",VLOOKUP($A17,'00_Mat'!$A$4:$J$1135,2,FALSE)) | C17: =IF($A17=0,"",VLOOKUP($A17,'00_Mat'!$A$4:$J$1135,3,FALSE)) | G17: =ROUNDUP((D17+(D17*F17)),0) -> 0 | H17: =IF($A17=0,"",VLOOKUP($A17,'00_Mat'!$A$4:$J$1135,5,FALSE)) | I17: =G17*H17 -> 0
B18: =IF($A18=0,"",VLOOKUP($A18,'00_Mat'!$A$4:$J$1135,2,FALSE)) | C18: =IF($A18=0,"",VLOOKUP($A18,'00_Mat'!$A$4:$J$1135,3,FALSE)) | G18: =ROUNDUP((D18+(D18*F18)),0) -> 0 | H18: =IF($A18=0,"",VLOOKUP($A18,'00_Mat'!$A$4:$J$1135,5,FALSE))
A20: TOTAL MATERIALES | I20: =SUM(I7:I18) -> 0
A21: =$I$3 -> gl | I21: =$H$3 -> 1
A22: TOTAL x | B22: =A21 -> gl | I22: =I20/I21 -> 0
A25: MANO DE OBRA - PERSONAS
A26: Código | B26: Descripción | C26: Unidad | D26: Cantidad | E26: Dias | F26: Desperdicio | G26: Cantidad + Desperdicio | H26: Precio Unitario | I26: Subtotal
B27: =IF($A27=0,"",VLOOKUP($A27,'00_MO'!$A$4:$D$7,2,FALSE)) | C27: =IF($A27=0,"",VLOOKUP($A27,'00_MO'!$A$4:$D$7,3,FALSE)) | G27: =ROUNDUP(((D27*E27)*(1+F27)),0) -> 0 | H27: =IF($A27=0,"",VLOOKUP($A27,'00_MO'!$A$4:$D$7,4,FALSE)) | I27: =G27*H27 -> 0
B28: =IF($A28=0,"",VLOOKUP($A28,'00_MO'!$A$4:$D$7,2,FALSE)) | C28: =IF($A28=0,"",VLOOKUP($A28,'00_MO'!$A$4:$D$7,3,FALSE)) | G28: =ROUNDUP(((D28*E28)*(1+F28)),0) -> 0 | H28: =IF($A28=0,"",VLOOKUP($A28,'00_MO'!$A$4:$D$7,4,FALSE)) | I28: =G28*H28 -> 0
B29: =IF($A29=0,"",VLOOKUP($A29,'00_MO'!$A$4:$D$7,2,FALSE)) | C29: =IF($A29=0,"",VLOOKUP($A29,'00_MO'!$A$4:$D$7,3,FALSE)) | G29: =ROUNDUP(((D29*E29)*(1+F29)),0) -> 0 | H29: =IF($A29=0,"",VLOOKUP($A29,'00_MO'!$A$4:$D$7,4,FALSE)) | I29: =G29*H29 -> 0
B30: =IF($A30=0,"",VLOOKUP($A30,'00_MO'!$A$4:$D$7,2,FALSE)) | C30: =IF($A30=0,"",VLOOKUP($A30,'00_MO'!$A$4:$D$7,3,FALSE)) | G30: =ROUNDUP(((D30*E30)*(1+F30)),0) -> 0 | H30: =IF($A30=0,"",VLOOKUP($A30,'00_MO'!$A$4:$D$7,4,FALSE)) | I30: =G30*H30 -> 0
B31: =IF($A31=0,"",VLOOKUP($A31,'00_MO'!$A$4:$D$7,2,FALSE)) | C31: =IF($A31=0,"",VLOOKUP($A31,'00_MO'!$A$4:$D$7,3,FALSE)) | G31: =ROUNDUP(((D31*E31)*(1+F31)),0) -> 0 | H31: =IF($A31=0,"",VLOOKUP($A31,'00_MO'!$A$4:$D$7,4,FALSE))
B32: =IF($A32=0,"",VLOOKUP($A32,'00_MO'!$A$4:$D$7,2,FALSE)) | C32: =IF($A32=0,"",VLOOKUP($A32,'00_MO'!$A$4:$D$7,3,FALSE)) | G32: =ROUNDUP(((D32*E32)*(1+F32)),0) -> 0 | H32: =IF($A32=0,"",VLOOKUP($A32,'00_MO'!$A$4:$D$7,4,FALSE))
A34: TOTAL | I34: =SUM(I27:I32) -> 0
A35: =$I$3 -> gl | I35: =$H$3 -> 1
A36: TOTAL x | B36: =A35 -> gl | I36: =I34/I35 -> 0
A39: MANO DE OBRA - EQUIPOS
A40: Código | B40: Descripción | C40: Unidad | D40: Cantidad | E40: Dias | F40: Desperdicio | G40: Cantidad + Desperdicio | H40: Precio Unitario | I40: Subtotal
A41: F-P | B41: Puntal 3 x 3 x 3,66 m tirante saligna | C41: u | D41: 319.34426 | F41: 0.15 | G41: =ROUNDUP((D41+(D41*F41)),0) -> 368 | H41: 4731 | I41: =G41*H41 -> 1741008 | J41: tirante 3x3 | M41: COMPRANDOLOS
A42: F-TSAL | B42: Tabla saligna 1"x5" 3m | C42: u | D42: 1560 | F42: 0.15 | G42: =ROUNDUP((D42+(D42*F42)),0) -> 1794 | H42: 2900 | I42: =G42*H42 -> 5202600 | J42: tabla 1x4
B43: ALQUILER PUNTALES | D43: 1342 | F43: 0.2 | G43: =ROUNDUP((D43+(D43*F43)),0) -> 1611 | H43: =40*1450 -> 58000 | I43: =G43*H43 -> 93438000 | J43: PUNTALES
B44: COMPRA PERIS | D44: =80*2 -> 160 | F44: 0.15 | G44: =ROUNDUP((D44+(D44*F44)),0) -> 184 | H44: =(22*4.9)*1450 -> 156310 | I44: =G44*H44 -> 28761040 | J44: PERIS | K44: 80 x losa
B45: =IF($A45=0,"",VLOOKUP($A45,'00_Mat'!$A$4:$J$1135,2,FALSE)) | C45: =IF($A45=0,"",VLOOKUP($A45,'00_Mat'!$A$4:$J$1135,3,FALSE)) | F45: 0.1 | G45: =ROUNDUP((D45+(D45*F45)),0) -> 0 | I45: =G45*H45 -> 0
B46: =IF($A46=0,"",VLOOKUP($A46,'00_Mat'!$A$4:$J$1135,2,FALSE)) | C46: =IF($A46=0,"",VLOOKUP($A46,'00_Mat'!$A$4:$J$1135,3,FALSE)) | F46: 0.1 | G46: =ROUNDUP(((D46*E46)*(1+F46)),0) -> 0 | H46: =IF($A46=0,"",VLOOKUP($A46,'00_Mat'!$A$4:$J$1135,5,FALSE)) | I46: =G46*H46 -> 0
A48: TOTAL | I48: =SUM(I41:I46) -> 129142648
A49: =$I$3 -> gl | I49: =$H$3 -> 1
A50: TOTAL x | B50: =A49 -> gl | I50: =I48/I49 -> 129142648
A53: MANO DE OBRA - MATERIALES | N53: 1kg x 4col | O53: aprox son 30 col | P53: clavos
A54: Código | B54: Descripción | C54: Unidad | D54: Cantidad | F54: Desperdicio | G54: Cantidad + Desperdicio | H54: Precio Unitario | I54: Subtotal | M54: ALQUILANDOLOS
A55: F-P | B55: =IF($A55=0,"",VLOOKUP($A55,'00_Mat'!$A$4:$J$1135,2,FALSE)) -> Puntal 3 x 3 x 3,66 m tirante saligna | C55: =IF($A55=0,"",VLOOKUP($A55,'00_Mat'!$A$4:$J$1135,3,FALSE)) -> u | D55: =O70 -> 319.34426 | F55: 0.1 | G55: =ROUNDUP((D55+(D55*F55)),0) -> 352 | H55: =IF($A55=0,"",VLOOKUP($A55,'00_Mat'!$A$4:$J$1135,5,FALSE)) -> 4731 | I55: =G55*H55 -> 1665312 | J55: tirante 3x3
A56: F-TSAL | B56: =IF($A56=0,"",VLOOKUP($A56,'00_Mat'!$A$4:$J$1135,2,FALSE)) -> Tabla saligna 1"x5" 3m | C56: =IF($A56=0,"",VLOOKUP($A56,'00_Mat'!$A$4:$J$1135,3,FALSE)) -> u | D56: =O71 -> 1560 | F56: 0.1 | G56: =ROUNDUP((D56+(D56*F56)),0) -> 1716 | H56: =IF($A56=0,"",VLOOKUP($A56,'00_Mat'!$A$4:$J$1135,5,FALSE)) -> 2900 | I56: =G56*H56 -> 4976400 | J56: tabla 1x4
B57: ALQUILER PUNTALES | C57: =IF($A57=0,"",VLOOKUP($A57,'00_Mat'!$A$4:$J$1135,3,FALSE)) | D57: 1340 | G57: =ROUNDUP((D57+(D57*F57)),0) -> 1340 | H57: =10000*9 -> 90000 | I57: =G57*H57 -> 120600000 | J57: PUNTALES | L57: 10.000 X MES C/U | N57: OBRA DE 9 MESES
B58: COMPRA PERIS | C58: =IF($A58=0,"",VLOOKUP($A58,'00_Mat'!$A$4:$J$1135,3,FALSE)) | D58: 70 | F58: 0.1 | G58: =ROUNDUP((D58+(D58*F58)),0) -> 77 | H58: =IF($A58=0,"",VLOOKUP($A58,'00_Mat'!$A$4:$J$1135,5,FALSE)) | I58: =G58*H58 -> 0 | J58: PERIS
B59: =IF($A59=0,"",VLOOKUP($A59,'00_Mat'!$A$4:$J$1135,2,FALSE)) | C59: =IF($A59=0,"",VLOOKUP($A59,'00_Mat'!$A$4:$J$1135,3,FALSE)) | F59: 0.1 | G59: =ROUNDUP((D59+(D59*F59)),0) -> 0 | H59: =IF($A59=0,"",VLOOKUP($A59,'00_Mat'!$A$4:$J$1135,5,FALSE)) | I59: =G59*H59 -> 0
B60: =IF($A60=0,"",VLOOKUP($A60,'00_Mat'!$A$4:$J$1135,2,FALSE)) | C60: =IF($A60=0,"",VLOOKUP($A60,'00_Mat'!$A$4:$J$1135,3,FALSE)) | D60: 40 | F60: 0.1 | G60: =ROUNDUP(((D60*E60)*(1+F60)),0) -> 0 | H60: =IF($A60=0,"",VLOOKUP($A60,'00_Mat'!$A$4:$J$1135,5,FALSE)) | I60: =G60*H60 -> 0 | P60: https://www.mercadolibre.com.ar/viga-h20-alma-fenolico-p-encofrado-maderwil-500mtsx20cm-im/up/MLAU3006820611#polycard_client=search-desktop&search_layout=grid&position=37&type=product&tracking_id=96ec5412-75db-4875-9959-a13636106fa9&wid=MLA2012431448&sid=search
M61: COL | N61: PARA TRES 3 PISOS | O61: PARA 9 PISOS
A62: TOTAL | I62: =SUM(I55:I60) -> 127241712 | M62: TIRANTES (2 x col) | N62: =2*30 -> 60 | O62: =N62*3 -> 180
A63: =$I$3 -> gl | I63: =$H$3 -> 1 | M63: TABLAS (6 x col) | N63: =6*30 -> 180 | O63: =N63*3 -> 540
A64: TOTAL x | B64: =A63 -> gl | I64: =I62/I63 -> 127241712
M65: VIGAS | N65: PARA TRES 3 PISOS | O65: PARA 9 PISOS
M66: TIRANTES | N66: =170/3.66 -> 46.448087 | O66: =N66*3 -> 139.34426
A67: MANO DE OBRA - SUBCONTRATOS | M67: TABLAS | N67: =(170*6)/3 -> 340 | O67: =N67*3 -> 1020
A68: Código | B68: Descripción | C68: Unidad | D68: Cantidad | E68: Dias | F68: Desperdicio | G68: Cantidad + Desperdicio | H68: Precio Unitario | I68: Subtotal
B69: =IF($A69=0,"",VLOOKUP($A69,'00_Sub'!$A$4:$D$1007,2,FALSE)) | C69: =IF($A69=0,"",VLOOKUP($A69,'00_Sub'!$A$4:$D$1007,3,FALSE)) | G69: =ROUNDUP((D69+(D69*F69)),0) -> 0 | H69: =IF($A69=0,"",VLOOKUP($A69,'00_Sub'!$A$4:$D$1007,4,FALSE)) | M69: TOTAL
B70: =IF($A70=0,"",VLOOKUP($A70,'00_Sub'!$A$4:$D$1007,2,FALSE)) | C70: =IF($A70=0,"",VLOOKUP($A70,'00_Sub'!$A$4:$D$1007,3,FALSE)) | G70: =ROUNDUP((D70+(D70*F70)),0) -> 0 | H70: =IF($A70=0,"",VLOOKUP($A70,'00_Sub'!$A$4:$D$1007,4,FALSE)) | M70: TIRANTES | O70: =O62+O66 -> 319.34426
B71: =IF($A71=0,"",VLOOKUP($A71,'00_Sub'!$A$4:$D$1007,2,FALSE)) | C71: =IF($A71=0,"",VLOOKUP($A71,'00_Sub'!$A$4:$D$1007,3,FALSE)) | G71: =ROUNDUP((D71+(D71*F71)),0) -> 0 | H71: =IF($A71=0,"",VLOOKUP($A71,'00_Sub'!$A$4:$D$1007,4,FALSE)) | M71: TABLAS | O71: =O63+O67 -> 1560
B72: =IF($A72=0,"",VLOOKUP($A72,'00_Sub'!$A$4:$D$1007,2,FALSE)) | C72: =IF($A72=0,"",VLOOKUP($A72,'00_Sub'!$A$4:$D$1007,3,FALSE)) | G72: =ROUNDUP((D72+(D72*F72)),0) -> 0 | H72: =IF($A72=0,"",VLOOKUP($A72,'00_Sub'!$A$4:$D$1007,4,FALSE))
B73: =IF($A73=0,"",VLOOKUP($A73,'00_Sub'!$A$4:$D$1007,2,FALSE)) | C73: =IF($A73=0,"",VLOOKUP($A73,'00_Sub'!$A$4:$D$1007,3,FALSE)) | G73: =ROUNDUP((D73+(D73*F73)),0) -> 0 | H73: =IF($A73=0,"",VLOOKUP($A73,'00_Sub'!$A$4:$D$1007,4,FALSE))
B74: =IF($A74=0,"",VLOOKUP($A74,'00_Sub'!$A$4:$D$1007,2,FALSE)) | C74: =IF($A74=0,"",VLOOKUP($A74,'00_Sub'!$A$4:$D$1007,3,FALSE)) | G74: =ROUNDUP((D74+(D74*F74)),0) -> 0 | H74: =IF($A74=0,"",VLOOKUP($A74,'00_Sub'!$A$4:$D$1007,4,FALSE))
A76: TOTAL | I76: =SUM(I69:I74) -> 0
A77: =$I$3 -> gl | I77: =$H$3 -> 1
A78: TOTAL x | B78: =A77 -> gl | I78: =I76/I77 -> 0

Sheet 0.9
A1: ='01_C&P'!A1 -> EDIFICIO LAS HERAS
A3: ='01_C&P'!A18 -> 0.9 | B3: =IF($A3=0,"",VLOOKUP($A3,'01_C&P'!$A$9:$D$192,2,FALSE)) -> EXCAVACION BASES Y TRONCOS | H3: =IF($A3=0,"",VLOOKUP($A3,'01_C&P'!$A$9:$D$192,4,FALSE)) -> 366.36 | I3: =IF($A3=0,"",VLOOKUP($A3,'01_C&P'!$A$9:$D$192,3,FALSE)) -> m³ | M3: son 40 columnas + tabqiues
A5: MATERIALES
A6: Código | B6: Descripción | C6: Unidad | D6: Cantidad | F6: Desperdicio | G6: Cantidad + Desperdicio | H6: Precio Unitario | I6: Subtotal
B7: =IF($A7=0,"",VLOOKUP($A7,'00_Mat'!$A$4:$J$1135,2,FALSE)) | C7: =IF($A7=0,"",VLOOKUP($A7,'00_Mat'!$A$4:$J$1135,3,FALSE)) | D7: =H3 -> 366.36 | F7: 0.1 | G7: =ROUNDUP((D7+(D7*F7)),0) -> 403 | H7: =IF($A7=0,"",VLOOKUP($A7,'00_Mat'!$A$4:$J$1135,5,FALSE)) | I7: =G7*H7 -> 0 | J7: HORMIGON
B8: =IF($A8=0,"",VLOOKUP($A8,'00_Mat'!$A$4:$J$1135,2,FALSE)) | C8: =IF($A8=0,"",VLOOKUP($A8,'00_Mat'!$A$4:$J$1135,3,FALSE)) | D8: 206 | F8: 0.1 | G8: =ROUNDUP((D8+(D8*F8)),0) -> 227 | H8: =IF($A8=0,"",VLOOKUP($A8,'00_Mat'!$A$4:$J$1135,5,FALSE)) | I8: =G8*H8 -> 0 | J8: HIERROS
B9: =IF($A9=0,"",VLOOKUP($A9,'00_Mat'!$A$4:$J$1135,2,FALSE)) | C9: =IF($A9=0,"",VLOOKUP($A9,'00_Mat'!$A$4:$J$1135,3,FALSE)) | D9: 52 | F9: 0.1 | G9: =ROUNDUP((D9+(D9*F9)),0) -> 58 | H9: =IF($A9=0,"",VLOOKUP($A9,'00_Mat'!$A$4:$J$1135,5,FALSE)) | I9: =G9*H9 -> 0
B10: =IF($A10=0,"",VLOOKUP($A10,'00_Mat'!$A$4:$J$1135,2,FALSE)) | C10: =IF($A10=0,"",VLOOKUP($A10,'00_Mat'!$A$4:$J$1135,3,FALSE)) | D10: 9 | F10: 0.1 | G10: =ROUNDUP((D10+(D10*F10)),0) -> 10 | H10: =IF($A10=0,"",VLOOKUP($A10,'00_Mat'!$A$4:$J$1135,5,FALSE)) | I10: =G10*H10 -> 0
B11: =IF($A11=0,"",VLOOKUP($A11,'00_Mat'!$A$4:$J$1135,2,FALSE)) | C11: =IF($A11=0,"",VLOOKUP($A11,'00_Mat'!$A$4:$J$1135,3,FALSE)) | D11: 54 | F11: 0.1 | G11: =ROUNDUP((D11+(D11*F11)),0) -> 60 | H11: =IF($A11=0,"",VLOOKUP($A11,'00_Mat'!$A$4:$J$1135,5,FALSE)) | I11: =G11*H11 -> 0
B12: =IF($A12=0,"",VLOOKUP($A12,'00_Mat'!$A$4:$J$1135,2,FALSE)) | C12: =IF($A12=0,"",VLOOKUP($A12,'00_Mat'!$A$4:$J$1135,3,FALSE)) | D12: 37 | F12: 0.1 | G12: =ROUNDUP((D12+(D12*F12)),0) -> 41 | H12: =IF($A12=0,"",VLOOKUP($A12,'00_Mat'!$A$4:$J$1135,5,FALSE)) | I12: =G12*H12 -> 0
B13: =IF($A13=0,"",VLOOKUP($A13,'00_Mat'!$A$4:$J$1135,2,FALSE)) | C13: =IF($A13=0,"",VLOOKUP($A13,'00_Mat'!$A$4:$J$1135,3,FALSE)) | D13: 9 | F13: 0.1 | G13: =ROUNDUP((D13+(D13*F13)),0) -> 10 | H13: =IF($A13=0,"",VLOOKUP($A13,'00_Mat'!$A$4:$J$1135,5,FALSE)) | I13: =G13*H13 -> 0
B14: =IF($A14=0,"",VLOOKUP($A14,'00_Mat'!$A$4:$J$1135,2,FALSE)) | C14: =IF($A14=0,"",VLOOKUP($A14,'00_Mat'!$A$4:$J$1135,3,FALSE)) | D14: 0 | F14: 0.25 | G14: =ROUNDUP((D14+(D14*F14)),0) -> 0 | H14: =IF($A14=0,"",VLOOKUP($A14,'00_Mat'!$A$4:$J$1135,5,FALSE)) | I14: =G14*H14 -> 0 | J14: FENOLICOS VISTOS
B15: =IF($A15=0,"",VLOOKUP($A15,'00_Mat'!$A$4:$J$1135,2,FALSE)) | C15: =IF($A15=0,"",VLOOKUP($A15,'00_Mat'!$A$4:$J$1135,3,FALSE)) | D15: =92 -> 92 | F15: 0.2 | G15: =ROUNDUP((D15+(D15*F15)),0) -> 111 | H15: =IF($A15=0,"",VLOOKUP($A15,'00_Mat'!$A$4:$J$1135,5,FALSE)) | I15: =G15*H15 -> 0 | J15: FENOLICOS
B16: =IF($A16=0,"",VLOOKUP($A16,'00_Mat'!$A$4:$J$1135,2,FALSE)) | C16: =IF($A16=0,"",VLOOKUP($A16,'00_Mat'!$A$4:$J$1135,3,FALSE)) | D16: 1 | G16: =ROUNDUP((D16+(D16*F16)),0) -> 1 | H16: =IF($A16=0,"",VLOOKUP($A16,'00_Mat'!$A$4:$J$1135,5,FALSE)) | I16: =G16*H16 -> 0 | J16: BOMBA
B17: =IF($A17=0,"",VLOOKUP($A17,'00_Mat'!$A$4:$J$1135,2,FALSE)) | C17: =IF($A17=0,"",VLOOKUP($A17,'00_Mat'!$A$4:$J$1135,3,FALSE)) | D17: =D7 -> 366.36 | F17: 0.1 | G17: =ROUNDUP((D17+(D17*F17)),0) -> 403 | H17: =IF($A17=0,"",VLOOKUP($A17,'00_Mat'!$A$4:$J$1135,5,FALSE)) | I17: =G17*H17 -> 0 | J17: ADICIONAL X BOMBEO
B18: =IF($A18=0,"",VLOOKUP($A18,'00_Mat'!$A$4:$J$1135,2,FALSE)) | C18: =IF($A18=0,"",VLOOKUP($A18,'00_Mat'!$A$4:$J$1135,3,FALSE)) | F18: 0.1 | G18: =ROUNDUP((D18+(D18*F18)),0) -> 0 | H18: =IF($A18=0,"",VLOOKUP($A18,'00_Mat'!$A$4:$J$1135,5,FALSE)) | I18: =G18*H18 -> 0
A20: TOTAL MATERIALES | I20: =SUM(I7:I18) -> 0
A21: =$I$3 -> m³ | I21: =$H$3 -> 366.36
A22: TOTAL x | B22: =A21 -> m³ | I22: =I20/I21 -> 0
A25: MANO DE OBRA - PERSONAS
A26: Código | B26: Descripción | C26: Unidad | D26: Cantidad | E26: Dias | F26: Desperdicio | G26: Cantidad + Desperdicio | H26: Precio Unitario | I26: Subtotal
A27: MO-CA | B27: =IF($A27=0,"",VLOOKUP($A27,'00_MO'!$A$4:$D$7,2,FALSE)) -> Capataz | C27: =IF($A27=0,"",VLOOKUP($A27,'00_MO'!$A$4:$D$7,3,FALSE)) -> u | D27: 1 | E27: 0 | F27: 0.25 | G27: =ROUNDUP(((D27*E27)*(1+F27)),0) -> 0 | H27: =IF($A27=0,"",VLOOKUP($A27,'00_MO'!$A$4:$D$7,4,FALSE)) -> 120000 | I27: =G27*H27 -> 0
A28: MO-PU | B28: =IF($A28=0,"",VLOOKUP($A28,'00_MO'!$A$4:$D$7,2,FALSE)) -> Puntero | C28: =IF($A28=0,"",VLOOKUP($A28,'00_MO'!$A$4:$D$7,3,FALSE)) -> u | D28: 2 | F28: 0.25 | G28: =ROUNDUP(((D28*E28)*(1+F28)),0) -> 0 | H28: =IF($A28=0,"",VLOOKUP($A28,'00_MO'!$A$4:$D$7,4,FALSE)) -> 105000 | I28: =G28*H28 -> 0
A29: MO-OF | B29: =IF($A29=0,"",VLOOKUP($A29,'00_MO'!$A$4:$D$7,2,FALSE)) -> Oficial | C29: =IF($A29=0,"",VLOOKUP($A29,'00_MO'!$A$4:$D$7,3,FALSE)) -> u | D29: 3 | F29: 0.25 | G29: =ROUNDUP(((D29*E29)*(1+F29)),0) -> 0 | H29: =IF($A29=0,"",VLOOKUP($A29,'00_MO'!$A$4:$D$7,4,FALSE)) -> 90000 | I29: =G29*H29 -> 0
A30: MO-AY | B30: =IF($A30=0,"",VLOOKUP($A30,'00_MO'!$A$4:$D$7,2,FALSE)) -> Ayudante | C30: =IF($A30=0,"",VLOOKUP($A30,'00_MO'!$A$4:$D$7,3,FALSE)) -> u | D30: 3 | F30: 0.25 | G30: =ROUNDUP(((D30*E30)*(1+F30)),0) -> 0 | H30: =IF($A30=0,"",VLOOKUP($A30,'00_MO'!$A$4:$D$7,4,FALSE)) -> 60000 | I30: =G30*H30 -> 0
B31: =IF($A31=0,"",VLOOKUP($A31,'00_MO'!$A$4:$D$7,2,FALSE)) | C31: =IF($A31=0,"",VLOOKUP($A31,'00_MO'!$A$4:$D$7,3,FALSE)) | G31: =ROUNDUP(((D31*E31)*(1+F31)),0) -> 0 | H31: =IF($A31=0,"",VLOOKUP($A31,'00_MO'!$A$4:$D$7,4,FALSE)) | I31: =G31*H31 -> 0
B32: =IF($A32=0,"",VLOOKUP($A32,'00_MO'!$A$4:$D$7,2,FALSE)) | C32: =IF($A32=0,"",VLOOKUP($A32,'00_MO'!$A$4:$D$7,3,FALSE)) | G32: =ROUNDUP(((D32*E32)*(1+F32)),0) -> 0 | H32: =IF($A32=0,"",VLOOKUP($A32,'00_MO'!$A$4:$D$7,4,FALSE)) | I32: =G32*H32 -> 0
A34: TOTAL | I34: =SUM(I27:I32) -> 0
A35: =$I$3 -> m³ | I35: =$H$3 -> 366.36
A36: TOTAL x | B36: =A35 -> m³ | I36: =I34/I35 -> 0
A39: MANO DE OBRA - EQUIPOS
A40: Código | B40: Descripción | C40: Unidad | D40: Cantidad | E40: Dias | F40: Desperdicio | G40: Cantidad + Desperdicio | H40: Precio Unitario | I40: Subtotal
A41: MS-ER | B41: =IF($A41=0,"",VLOOKUP($A41,'00_Eq'!$A$4:$D$100,2,FALSE)) -> EXCAVACION Y RETIRO | C41: =IF($A41=0,"",VLOOKUP($A41,'00_Eq'!$A$4:$D$100,3,FALSE)) -> m3 | D41: =H3 -> 366.36 | E41: 1 | F41: 0.25 | G41: =ROUNDUP(((D41*E41)*(1+F41)),0) -> 458 | H41: =IF($A41=0,"",VLOOKUP($A41,'00_Eq'!$A$4:$D$100,4,FALSE)) -> 30000 | I41: =G41*H41 -> 13740000
B42: =IF($A42=0,"",VLOOKUP($A42,'00_Eq'!$A$4:$D$100,2,FALSE)) | C42: =IF($A42=0,"",VLOOKUP($A42,'00_Eq'!$A$4:$D$100,3,FALSE)) | G42: =ROUNDUP(((D42*E42)*(1+F42)),0) -> 0 | H42: =IF($A42=0,"",VLOOKUP($A42,'00_Eq'!$A$4:$D$100,4,FALSE)) | I42: =G42*H42 -> 0
B43: =IF($A43=0,"",VLOOKUP($A43,'00_Eq'!$A$4:$D$100,2,FALSE)) | C43: =IF($A43=0,"",VLOOKUP($A43,'00_Eq'!$A$4:$D$100,3,FALSE)) | G43: =ROUNDUP(((D43*E43)*(1+F43)),0) -> 0 | H43: =IF($A43=0,"",VLOOKUP($A43,'00_Eq'!$A$4:$D$100,4,FALSE)) | I43: =G43*H43 -> 0
B44: =IF($A44=0,"",VLOOKUP($A44,'00_Eq'!$A$4:$D$100,2,FALSE)) | C44: =IF($A44=0,"",VLOOKUP($A44,'00_Eq'!$A$4:$D$100,3,FALSE)) | G44: =ROUNDUP(((D44*E44)*(1+F44)),0) -> 0 | H44: =IF($A44=0,"",VLOOKUP($A44,'00_Eq'!$A$4:$D$100,4,FALSE)) | I44: =G44*H44 -> 0
B45: =IF($A45=0,"",VLOOKUP($A45,'00_Eq'!$A$4:$D$100,2,FALSE)) | C45: =IF($A45=0,"",VLOOKUP($A45,'00_Eq'!$A$4:$D$100,3,FALSE)) | G45: =ROUNDUP(((D45*E45)*(1+F45)),0) -> 0 | H45: =IF($A45=0,"",VLOOKUP($A45,'00_Eq'!$A$4:$D$100,4,FALSE))
B46: =IF($A46=0,"",VLOOKUP($A46,'00_Eq'!$A$4:$D$100,2,FALSE)) | C46: =IF($A46=0,"",VLOOKUP($A46,'00_Eq'!$A$4:$D$100,3,FALSE)) | G46: =ROUNDUP(((D46*E46)*(1+F46)),0) -> 0 | H46: =IF($A46=0,"",VLOOKUP($A46,'00_Eq'!$A$4:$D$100,4,FALSE))
A48: TOTAL | I48: =SUM(I41:I46) -> 13740000
A49: =$I$3 -> m³ | I49: =$H$3 -> 366.36
A50: TOTAL x | B50: =A49 -> m³ | I50: =I48/I49 -> 37504.094
A53: MANO DE OBRA - MATERIALES
A54: Código | B54: Descripción | C54: Unidad | D54: Cantidad | F54: Desperdicio | G54: Cantidad + Desperdicio | H54: Precio Unitario | I54: Subtotal
B55: =IF($A55=0,"",VLOOKUP($A55,'00_Mat'!$A$4:$J$1135,2,FALSE)) | C55: =IF($A55=0,"",VLOOKUP($A55,'00_Mat'!$A$4:$J$1135,3,FALSE)) | F55: 0.1 | G55: =ROUNDUP((D55+(D55*F55)),0) -> 0 | H55: =IF($A55=0,"",VLOOKUP($A55,'00_Mat'!$A$4:$J$1135,5,FALSE)) | I55: =G55*H55 -> 0
B56: =IF($A56=0,"",VLOOKUP($A56,'00_Mat'!$A$4:$J$1135,2,FALSE)) | C56: =IF($A56=0,"",VLOOKUP($A56,'00_Mat'!$A$4:$J$1135,3,FALSE)) | F56: 0.1 | G56: =ROUNDUP((D56+(D56*F56)),0) -> 0 | H56: =IF($A56=0,"",VLOOKUP($A56,'00_Mat'!$A$4:$J$1135,5,FALSE)) | I56: =G56*H56 -> 0
B57: =IF($A57=0,"",VLOOKUP($A57,'00_Mat'!$A$4:$J$1135,2,FALSE)) | C57: =IF($A57=0,"",VLOOKUP($A57,'00_Mat'!$A$4:$J$1135,3,FALSE)) | D57: 20 | F57: 0.1 | G57: =ROUNDUP((D57+(D57*F57)),0) -> 22 | H57: =IF($A57=0,"",VLOOKUP($A57,'00_Mat'!$A$4:$J$1135,5,FALSE)) | I57: =G57*H57 -> 0 | J57: clavos | L57: 1kg x 4col | M57: aprox son 30 col
B58: =IF($A58=0,"",VLOOKUP($A58,'00_Mat'!$A$4:$J$1135,2,FALSE)) | C58: =IF($A58=0,"",VLOOKUP($A58,'00_Mat'!$A$4:$J$1135,3,FALSE)) | D58: 2 | F58: 0.1 | G58: =ROUNDUP((D58+(D58*F58)),0) -> 3 | H58: =IF($A58=0,"",VLOOKUP($A58,'00_Mat'!$A$4:$J$1135,5,FALSE)) | I58: =G58*H58 -> 0 | J58: alambre
C59: =IF($A58=0,"",VLOOKUP($A58,'00_Mat'!$A$4:$J$1135,3,FALSE)) | F59: 0.1 | G59: =ROUNDUP((D59+(D59*F59)),0) -> 0 | H59: =IF($A59=0,"",VLOOKUP($A59,'00_Mat'!$A$4:$J$1135,5,FALSE)) | I59: =G59*H59 -> 0
B60: =IF($A60=0,"",VLOOKUP($A60,'00_Mat'!$A$4:$J$1135,2,FALSE)) | C60: =IF($A60=0,"",VLOOKUP($A60,'00_Mat'!$A$4:$J$1135,3,FALSE)) | G60: =ROUNDUP((D60+(D60*F60)),0) -> 0 | H60: =IF($A60=0,"",VLOOKUP($A60,'00_Mat'!$A$4:$J$1135,5,FALSE)) | I60: =G60*H60 -> 0
A62: TOTAL | I62: =SUM(I55:I60) -> 0
A63: =$I$3 -> m³ | I63: =$H$3 -> 366.36
A64: TOTAL x | B64: =A63 -> m³ | I64: =I62/I63 -> 0
A67: MANO DE OBRA - SUBCONTRATOS
A68: Código | B68: Descripción | C68: Unidad | D68: Cantidad | E68: Dias | F68: Desperdicio | G68: Cantidad + Desperdicio | H68: Precio Unitario | I68: Subtotal
B69: =IF($A69=0,"",VLOOKUP($A69,'00_Sub'!$A$4:$D$1007,2,FALSE)) | C69: =IF($A69=0,"",VLOOKUP($A69,'00_Sub'!$A$4:$D$1007,3,FALSE)) | G69: =ROUNDUP((D69+(D69*F69)),0) -> 0 | H69: =IF($A69=0,"",VLOOKUP($A69,'00_Sub'!$A$4:$D$1007,4,FALSE))
B70: =IF($A70=0,"",VLOOKUP($A70,'00_Sub'!$A$4:$D$1007,2,FALSE)) | C70: =IF($A70=0,"",VLOOKUP($A70,'00_Sub'!$A$4:$D$1007,3,FALSE)) | G70: =ROUNDUP((D70+(D70*F70)),0) -> 0 | H70: =IF($A70=0,"",VLOOKUP($A70,'00_Sub'!$A$4:$D$1007,4,FALSE))
B71: =IF($A71=0,"",VLOOKUP($A71,'00_Sub'!$A$4:$D$1007,2,FALSE)) | C71: =IF($A71=0,"",VLOOKUP($A71,'00_Sub'!$A$4:$D$1007,3,FALSE)) | G71: =ROUNDUP((D71+(D71*F71)),0) -> 0 | H71: =IF($A71=0,"",VLOOKUP($A71,'00_Sub'!$A$4:$D$1007,4,FALSE))
B72: =IF($A72=0,"",VLOOKUP($A72,'00_Sub'!$A$4:$D$1007,2,FALSE)) | C72: =IF($A72=0,"",VLOOKUP($A72,'00_Sub'!$A$4:$D$1007,3,FALSE)) | G72: =ROUNDUP((D72+(D72*F72)),0) -> 0 | H72: =IF($A72=0,"",VLOOKUP($A72,'00_Sub'!$A$4:$D$1007,4,FALSE))
B73: =IF($A73=0,"",VLOOKUP($A73,'00_Sub'!$A$4:$D$1007,2,FALSE)) | C73: =IF($A73=0,"",VLOOKUP($A73,'00_Sub'!$A$4:$D$1007,3,FALSE)) | G73: =ROUNDUP((D73+(D73*F73)),0) -> 0 | H73: =IF($A73=0,"",VLOOKUP($A73,'00_Sub'!$A$4:$D$1007,4,FALSE))
B74: =IF($A74=0,"",VLOOKUP($A74,'00_Sub'!$A$4:$D$1007,2,FALSE)) | C74: =IF($A74=0,"",VLOOKUP($A74,'00_Sub'!$A$4:$D$1007,3,FALSE)) | G74: =ROUNDUP((D74+(D74*F74)),0) -> 0 | H74: =IF($A74=0,"",VLOOKUP($A74,'00_Sub'!$A$4:$D$1007,4,FALSE))
A76: TOTAL | I76: =SUM(I69:I74) -> 0
A77: =$I$3 -> m³ | I77: =$H$3 -> 366.36
A78: TOTAL x | B78: =A77 -> m³ | I78: =I76/I77 -> 0

Sheet 0.10
A1: ='01_C&P'!A1 -> EDIFICIO LAS HERAS
A3: ='01_C&P'!A19 -> 0.10 | B3: =IF($A3=0,"",VLOOKUP($A3,'01_C&P'!$A$9:$D$192,2,FALSE)) -> EXCAVACION TENSORES | H3: =IF($A3=0,"",VLOOKUP($A3,'01_C&P'!$A$9:$D$192,4,FALSE)) -> 5.4 | I3: =IF($A3=0,"",VLOOKUP($A3,'01_C&P'!$A$9:$D$192,3,FALSE)) -> m³ | M3: son 40 columnas + tabqiues
A5: MATERIALES
A6: Código | B6: Descripción | C6: Unidad | D6: Cantidad | F6: Desperdicio | G6: Cantidad + Desperdicio | H6: Precio Unitario | I6: Subtotal
B7: =IF($A7=0,"",VLOOKUP($A7,'00_Mat'!$A$4:$J$1135,2,FALSE)) | C7: =IF($A7=0,"",VLOOKUP($A7,'00_Mat'!$A$4:$J$1135,3,FALSE)) | D7: =H3 -> 5.4 | F7: 0.1 | G7: =ROUNDUP((D7+(D7*F7)),0) -> 6 | H7: =IF($A7=0,"",VLOOKUP($A7,'00_Mat'!$A$4:$J$1135,5,FALSE)) | I7: =G7*H7 -> 0 | J7: HORMIGON
B8: =IF($A8=0,"",VLOOKUP($A8,'00_Mat'!$A$4:$J$1135,2,FALSE)) | C8: =IF($A8=0,"",VLOOKUP($A8,'00_Mat'!$A$4:$J$1135,3,FALSE)) | D8: 206 | F8: 0.1 | G8: =ROUNDUP((D8+(D8*F8)),0) -> 227 | H8: =IF($A8=0,"",VLOOKUP($A8,'00_Mat'!$A$4:$J$1135,5,FALSE)) | I8: =G8*H8 -> 0 | J8: HIERROS
B9: =IF($A9=0,"",VLOOKUP($A9,'00_Mat'!$A$4:$J$1135,2,FALSE)) | C9: =IF($A9=0,"",VLOOKUP($A9,'00_Mat'!$A$4:$J$1135,3,FALSE)) | D9: 52 | F9: 0.1 | G9: =ROUNDUP((D9+(D9*F9)),0) -> 58 | H9: =IF($A9=0,"",VLOOKUP($A9,'00_Mat'!$A$4:$J$1135,5,FALSE)) | I9: =G9*H9 -> 0
B10: =IF($A10=0,"",VLOOKUP($A10,'00_Mat'!$A$4:$J$1135,2,FALSE)) | C10: =IF($A10=0,"",VLOOKUP($A10,'00_Mat'!$A$4:$J$1135,3,FALSE)) | D10: 9 | F10: 0.1 | G10: =ROUNDUP((D10+(D10*F10)),0) -> 10 | H10: =IF($A10=0,"",VLOOKUP($A10,'00_Mat'!$A$4:$J$1135,5,FALSE)) | I10: =G10*H10 -> 0
B11: =IF($A11=0,"",VLOOKUP($A11,'00_Mat'!$A$4:$J$1135,2,FALSE)) | C11: =IF($A11=0,"",VLOOKUP($A11,'00_Mat'!$A$4:$J$1135,3,FALSE)) | D11: 54 | F11: 0.1 | G11: =ROUNDUP((D11+(D11*F11)),0) -> 60 | H11: =IF($A11=0,"",VLOOKUP($A11,'00_Mat'!$A$4:$J$1135,5,FALSE)) | I11: =G11*H11 -> 0
B12: =IF($A12=0,"",VLOOKUP($A12,'00_Mat'!$A$4:$J$1135,2,FALSE)) | C12: =IF($A12=0,"",VLOOKUP($A12,'00_Mat'!$A$4:$J$1135,3,FALSE)) | D12: 37 | F12: 0.1 | G12: =ROUNDUP((D12+(D12*F12)),0) -> 41 | H12: =IF($A12=0,"",VLOOKUP($A12,'00_Mat'!$A$4:$J$1135,5,FALSE)) | I12: =G12*H12 -> 0
B13: =IF($A13=0,"",VLOOKUP($A13,'00_Mat'!$A$4:$J$1135,2,FALSE)) | C13: =IF($A13=0,"",VLOOKUP($A13,'00_Mat'!$A$4:$J$1135,3,FALSE)) | D13: 9 | F13: 0.1 | G13: =ROUNDUP((D13+(D13*F13)),0) -> 10 | H13: =IF($A13=0,"",VLOOKUP($A13,'00_Mat'!$A$4:$J$1135,5,FALSE)) | I13: =G13*H13 -> 0
